Workbook

Sheet Executive Summary
A1: PRICING MODEL | EXECUTIVE SUMMARY
A2: Monte Carlo Simulation Outputs
A3: Candidate SKUs | B3: Total Gross Profit Impact | C3: Average Gross Profit Lift % | E3: Average Price Change | G3: LTV at Risk | J3: LTV Protection-Sacrifice Ratio
A4: =TEXT(COUNTA($A$13:$A$36), "0") -> 24 | B4: =IF(SUM($G$13:$G$36) > 0, "+ ", "- ") & TEXT(SUM($G$13:$G$36), "$0,00.00") -> + $5,575.32 | C4: {=IF(AVERAGE($H$13:$H$36) > 0, "+ ", "- ") & ROUND(AVERAGE(H13:H36 * 100),2) & "%"} -> + 12.33% | E4: =TEXT(AVERAGE($F$13:$F$36), "0.00%") -> 8.88% | G4: =TEXT(SUM(Model_Output[LTV Protected]) + SUM(Model_Output[LTV Sacrificed]), "$0,00.00") -> $29,113.56 | J4: =TEXT(AVERAGE($J$13:$J$36), "0.00%") -> 66.91%
A5: =COUNTIF($C$13:$C$36,"Raise") & " Raise | " & COUNTIF($C$13:$C$36, "Hold") & " Hold | " & COUNTIF($C$13:$C$36, "Reduce") & " Reduce" -> 20 Raise | 4 Hold | 0 Reduce | B5: ="on $"&TEXT(SUM(Model_Output[Current Gross Profit]),"#,##0.00")&" current GP" -> on $44,900.96 current GP | C5: ="GP Margin: " &TEXT(AVERAGE(Model_Output[Current Gross Profit Margin %]),"0.00%")&" → "&TEXT(AVERAGE(Model_Output[Projected Gross Profit Margin %]),"0.00%") -> GP Margin: 53.73% → 57.28% | E5: =IFERROR(TEXT(SUM(Model_Output[Adjusted Difference %]) / SUM(Model_Output[V1 Difference %]), "0.0%"), "0%") & " of V1 suggested" -> 59.9% of V1 suggested | G5: ="Across all " &TEXT(COUNTA($I$13:$I$36), "0") &" SKUs" -> Across all 24 SKUs | J5: =TEXT(SUM(Model_Output[LTV Protected]), "$0,00") & " protected" -> $11,671 protected
A11: ="SKU RESULTS SUMMARY - ALL "&TEXT(COUNTA(_xlfn.ANCHORARRAY($A$13)),"0") & " SKUs" -> SKU RESULTS SUMMARY - ALL 24 SKUs
A12: Product | B12: Category | C12: Action | D12: Current Price | E12: Adj. Price | F12: ∆ % | G12: GP Impact $ | H12: ∆ % | I12: LTV at Risk | J12: LTV Protection to Sacrifice Ratio (%)
A13: {=Model_Output[Product Name]} -> Wireless Earbuds | B13: =_xlfn.XLOOKUP($A13,Model_Output[Product Name], Model_Output[Category]) -> Electronics | C13: =_xlfn.XLOOKUP($A13,Model_Output[Product Name], Model_Output[Recommendation]) -> Raise | D13: =_xlfn.XLOOKUP($A13,Model_Output[Product Name], Model_Output[Current Price]) -> 76.53 | E13: =_xlfn.XLOOKUP($A13,Model_Output[Product Name], Model_Output[Adjusted Price]) -> 78.975794 | F13: =_xlfn.XLOOKUP($A13,Model_Output[Product Name], Model_Output[Adjusted Difference %]) -> 0.031958627 | G13: =_xlfn.XLOOKUP($A13,Model_Output[Product Name], Model_Output[Projected Gross Profit Impact $]) -> 50.71733 | H13: =_xlfn.XLOOKUP($A13,Model_Output[Product Name], Model_Output[Projected Gross Profit Lift %]) -> 0.08965728 | I13: =_xlfn.XLOOKUP($A13,Model_Output[Product Name], Model_Output[Total LTV at Risk]) -> 1112.0932 | J13: =_xlfn.XLOOKUP($A13,Model_Output[Product Name], Model_Output[LTV Protection-Adjusted Risk Ratio]) -> 0.66666667
A14: Bluetooth Speaker | B14: =_xlfn.XLOOKUP($A14,Model_Output[Product Name], Model_Output[Category]) -> Electronics | C14: =_xlfn.XLOOKUP($A14,Model_Output[Product Name], Model_Output[Recommendation]) -> Raise | D14: =_xlfn.XLOOKUP($A14,Model_Output[Product Name], Model_Output[Current Price]) -> 53.26 | E14: =_xlfn.XLOOKUP($A14,Model_Output[Product Name], Model_Output[Adjusted Price]) -> 55.842395 | F14: =_xlfn.XLOOKUP($A14,Model_Output[Product Name], Model_Output[Adjusted Difference %]) -> 0.048486577 | G14: =_xlfn.XLOOKUP($A14,Model_Output[Product Name], Model_Output[Projected Gross Profit Impact $]) -> 46.409406 | H14: =_xlfn.XLOOKUP($A14,Model_Output[Product Name], Model_Output[Projected Gross Profit Lift %]) -> 0.13297062 | I14: =_xlfn.XLOOKUP($A14,Model_Output[Product Name], Model_Output[Total LTV at Risk]) -> 1487.03 | J14: =_xlfn.XLOOKUP($A14,Model_Output[Product Name], Model_Output[LTV Protection-Adjusted Risk Ratio]) -> 0.66666667
A15: USB-C Hub | B15: =_xlfn.XLOOKUP($A15,Model_Output[Product Name], Model_Output[Category]) -> Electronics | C15: =_xlfn.XLOOKUP($A15,Model_Output[Product Name], Model_Output[Recommendation]) -> Hold | D15: =_xlfn.XLOOKUP($A15,Model_Output[Product Name], Model_Output[Current Price]) -> 18.39 | E15: =_xlfn.XLOOKUP($A15,Model_Output[Product Name], Model_Output[Adjusted Price]) -> 19.551373 | F15: =_xlfn.XLOOKUP($A15,Model_Output[Product Name], Model_Output[Adjusted Difference %]) -> 0.063152419 | G15: =_xlfn.XLOOKUP($A15,Model_Output[Product Name], Model_Output[Projected Gross Profit Impact $]) -> 14.894414 | H15: =_xlfn.XLOOKUP($A15,Model_Output[Product Name], Model_Output[Projected Gross Profit Lift %]) -> 0.086489831 | I15: =_xlfn.XLOOKUP($A15,Model_Output[Product Name], Model_Output[Total LTV at Risk]) -> 1216.0707 | J15: =_xlfn.XLOOKUP($A15,Model_Output[Product Name], Model_Output[LTV Protection-Adjusted Risk Ratio]) -> 0.66666667
A16: Mechanical Keyboard | B16: =_xlfn.XLOOKUP($A16,Model_Output[Product Name], Model_Output[Category]) -> Electronics | C16: =_xlfn.XLOOKUP($A16,Model_Output[Product Name], Model_Output[Recommendation]) -> Hold | D16: =_xlfn.XLOOKUP($A16,Model_Output[Product Name], Model_Output[Current Price]) -> 113.18 | E16: =_xlfn.XLOOKUP($A16,Model_Output[Product Name], Model_Output[Adjusted Price]) -> 118.51611 | F16: =_xlfn.XLOOKUP($A16,Model_Output[Product Name], Model_Output[Adjusted Difference %]) -> 0.047147087 | G16: =_xlfn.XLOOKUP($A16,Model_Output[Product Name], Model_Output[Projected Gross Profit Impact $]) -> 92.081155 | H16: =_xlfn.XLOOKUP($A16,Model_Output[Product Name], Model_Output[Projected Gross Profit Lift %]) -> 0.051728661 | I16: =_xlfn.XLOOKUP($A16,Model_Output[Product Name], Model_Output[Total LTV at Risk]) -> 1378.1368 | J16: =_xlfn.XLOOKUP($A16,Model_Output[Product Name], Model_Output[LTV Protection-Adjusted Risk Ratio]) -> 0.66666667
A17: Phone Stand | B17: =_xlfn.XLOOKUP($A17,Model_Output[Product Name], Model_Output[Category]) -> Electronics | C17: =_xlfn.XLOOKUP($A17,Model_Output[Product Name], Model_Output[Recommendation]) -> Raise | D17: =_xlfn.XLOOKUP($A17,Model_Output[Product Name], Model_Output[Current Price]) -> 177.91 | E17: =_xlfn.XLOOKUP($A17,Model_Output[Product Name], Model_Output[Adjusted Price]) -> 197.38145 | F17: =_xlfn.XLOOKUP($A17,Model_Output[Product Name], Model_Output[Adjusted Difference %]) -> 0.10944552 | G17: =_xlfn.XLOOKUP($A17,Model_Output[Product Name], Model_Output[Projected Gross Profit Impact $]) -> 505.71744 | H17: =_xlfn.XLOOKUP($A17,Model_Output[Product Name], Model_Output[Projected Gross Profit Lift %]) -> 0.1345308 | I17: =_xlfn.XLOOKUP($A17,Model_Output[Product Name], Model_Output[Total LTV at Risk]) -> 1987.1738 | J17: =_xlfn.XLOOKUP($A17,Model_Output[Product Name], Model_Output[LTV Protection-Adjusted Risk Ratio]) -> 0.66666667
A18: Slim Fit Jeans | B18: =_xlfn.XLOOKUP($A18,Model_Output[Product Name], Model_Output[Category]) -> Apparel | C18: =_xlfn.XLOOKUP($A18,Model_Output[Product Name], Model_Output[Recommendation]) -> Raise | D18: =_xlfn.XLOOKUP($A18,Model_Output[Product Name], Model_Output[Current Price]) -> 45.86 | E18: =_xlfn.XLOOKUP($A18,Model_Output[Product Name], Model_Output[Adjusted Price]) -> 52.899021 | F18: =_xlfn.XLOOKUP($A18,Model_Output[Product Name], Model_Output[Adjusted Difference %]) -> 0.15348934 | G18: =_xlfn.XLOOKUP($A18,Model_Output[Product Name], Model_Output[Projected Gross Profit Impact $]) -> 223.36266 | H18: =_xlfn.XLOOKUP($A18,Model_Output[Product Name], Model_Output[Projected Gross Profit Lift %]) -> 0.2533663 | I18: =_xlfn.XLOOKUP($A18,Model_Output[Product Name], Model_Output[Total LTV at Risk]) -> 1838.4437 | J18: =_xlfn.XLOOKUP($A18,Model_Output[Product Name], Model_Output[LTV Protection-Adjusted Risk Ratio]) -> 0.66666667
A19: Graphic Tee | B19: =_xlfn.XLOOKUP($A19,Model_Output[Product Name], Model_Output[Category]) -> Apparel | C19: =_xlfn.XLOOKUP($A19,Model_Output[Product Name], Model_Output[Recommendation]) -> Raise | D19: =_xlfn.XLOOKUP($A19,Model_Output[Product Name], Model_Output[Current Price]) -> 67.56 | E19: =_xlfn.XLOOKUP($A19,Model_Output[Product Name], Model_Output[Adjusted Price]) -> 71.933095 | F19: =_xlfn.XLOOKUP($A19,Model_Output[Product Name], Model_Output[Adjusted Difference %]) -> 0.064729063 | G19: =_xlfn.XLOOKUP($A19,Model_Output[Product Name], Model_Output[Projected Gross Profit Impact $]) -> 79.846973 | H19: =_xlfn.XLOOKUP($A19,Model_Output[Product Name], Model_Output[Projected Gross Profit Lift %]) -> 0.14905166 | I19: =_xlfn.XLOOKUP($A19,Model_Output[Product Name], Model_Output[Total LTV at Risk]) -> 1511.5432 | J19: =_xlfn.XLOOKUP($A19,Model_Output[Product Name], Model_Output[LTV Protection-Adjusted Risk Ratio]) -> 0.66666667
A20: Wool Sweater | B20: =_xlfn.XLOOKUP($A20,Model_Output[Product Name], Model_Output[Category]) -> Apparel | C20: =_xlfn.XLOOKUP($A20,Model_Output[Product Name], Model_Output[Recommendation]) -> Raise | D20: =_xlfn.XLOOKUP($A20,Model_Output[Product Name], Model_Output[Current Price]) -> 143.8 | E20: =_xlfn.XLOOKUP($A20,Model_Output[Product Name], Model_Output[Adjusted Price]) -> 163.17672 | F20: =_xlfn.XLOOKUP($A20,Model_Output[Product Name], Model_Output[Adjusted Difference %]) -> 0.13474768 | G20: =_xlfn.XLOOKUP($A20,Model_Output[Product Name], Model_Output[Projected Gross Profit Impact $]) -> 404.01265 | H20: =_xlfn.XLOOKUP($A20,Model_Output[Product Name], Model_Output[Projected Gross Profit Lift %]) -> 0.17062426 | I20: =_xlfn.XLOOKUP($A20,Model_Output[Product Name], Model_Output[Total LTV at Risk]) -> 1207.1798 | J20: =_xlfn.XLOOKUP($A20,Model_Output[Product Name], Model_Output[LTV Protection-Adjusted Risk Ratio]) -> 0.66666667
A21: Canvas Tote Bag | B21: =_xlfn.XLOOKUP($A21,Model_Output[Product Name], Model_Output[Category]) -> Apparel | C21: =_xlfn.XLOOKUP($A21,Model_Output[Product Name], Model_Output[Recommendation]) -> Raise | D21: =_xlfn.XLOOKUP($A21,Model_Output[Product Name], Model_Output[Current Price]) -> 160.35 | E21: =_xlfn.XLOOKUP($A21,Model_Output[Product Name], Model_Output[Adjusted Price]) -> 173.51239 | F21: =_xlfn.XLOOKUP($A21,Model_Output[Product Name], Model_Output[Adjusted Difference %]) -> 0.082085347 | G21: =_xlfn.XLOOKUP($A21,Model_Output[Product Name], Model_Output[Projected Gross Profit Impact $]) -> 354.41085 | H21: =_xlfn.XLOOKUP($A21,Model_Output[Product Name], Model_Output[Projected Gross Profit Lift %]) -> 0.11202487 | I21: =_xlfn.XLOOKUP($A21,Model_Output[Product Name], Model_Output[Total LTV at Risk]) -> 1437.421 | J21: =_xlfn.XLOOKUP($A21,Model_Output[Product Name], Model_Output[LTV Protection-Adjusted Risk Ratio]) -> 0.66666667
A22: Air Fryer | B22: =_xlfn.XLOOKUP($A22,Model_Output[Product Name], Model_Output[Category]) -> Home & Kitchen | C22: =_xlfn.XLOOKUP($A22,Model_Output[Product Name], Model_Output[Recommendation]) -> Raise | D22: =_xlfn.XLOOKUP($A22,Model_Output[Product Name], Model_Output[Current Price]) -> 98.51 | E22: =_xlfn.XLOOKUP($A22,Model_Output[Product Name], Model_Output[Adjusted Price]) -> 108.78291 | F22: =_xlfn.XLOOKUP($A22,Model_Output[Product Name], Model_Output[Adjusted Difference %]) -> 0.10428294 | G22: =_xlfn.XLOOKUP($A22,Model_Output[Product Name], Model_Output[Projected Gross Profit Impact $]) -> 273.24261 | H22: =_xlfn.XLOOKUP($A22,Model_Output[Product Name], Model_Output[Projected Gross Profit Lift %]) -> 0.18543026 | I22: =_xlfn.XLOOKUP($A22,Model_Output[Product Name], Model_Output[Total LTV at Risk]) -> 1821.0804 | J22: =_xlfn.XLOOKUP($A22,Model_Output[Product Name], Model_Output[LTV Protection-Adjusted Risk Ratio]) -> 0.66666667
A23: Dish Rack | B23: =_xlfn.XLOOKUP($A23,Model_Output[Product Name], Model_Output[Category]) -> Home & Kitchen | C23: =_xlfn.XLOOKUP($A23,Model_Output[Product Name], Model_Output[Recommendation]) -> Raise | D23: =_xlfn.XLOOKUP($A23,Model_Output[Product Name], Model_Output[Current Price]) -> 106.06 | E23: =_xlfn.XLOOKUP($A23,Model_Output[Product Name], Model_Output[Adjusted Price]) -> 117.99989 | F23: =_xlfn.XLOOKUP($A23,Model_Output[Product Name], Model_Output[Adjusted Difference %]) -> 0.11257677 | G23: =_xlfn.XLOOKUP($A23,Model_Output[Product Name], Model_Output[Projected Gross Profit Impact $]) -> 317.1168 | H23: =_xlfn.XLOOKUP($A23,Model_Output[Product Name], Model_Output[Projected Gross Profit Lift %]) -> 0.11193832 | I23: =_xlfn.XLOOKUP($A23,Model_Output[Product Name], Model_Output[Total LTV at Risk]) -> 1061.3752 | J23: =_xlfn.XLOOKUP($A23,Model_Output[Product Name], Model_Output[LTV Protection-Adjusted Risk Ratio]) -> 0.66666667
A24: Storage Bins | B24: =_xlfn.XLOOKUP($A24,Model_Output[Product Name], Model_Output[Category]) -> Home & Kitchen | C24: =_xlfn.XLOOKUP($A24,Model_Output[Product Name], Model_Output[Recommendation]) -> Raise | D24: =_xlfn.XLOOKUP($A24,Model_Output[Product Name], Model_Output[Current Price]) -> 34.48 | E24: =_xlfn.XLOOKUP($A24,Model_Output[Product Name], Model_Output[Adjusted Price]) -> 35.936897 | F24: =_xlfn.XLOOKUP($A24,Model_Output[Product Name], Model_Output[Adjusted Difference %]) -> 0.042253398 | G24: =_xlfn.XLOOKUP($A24,Model_Output[Product Name], Model_Output[Projected Gross Profit Impact $]) -> 22.319241 | H24: =_xlfn.XLOOKUP($A24,Model_Output[Product Name], Model_Output[Projected Gross Profit Lift %]) -> 0.077079849 | I24: =_xlfn.XLOOKUP($A24,Model_Output[Product Name], Model_Output[Total LTV at Risk]) -> 804.52718 | J24: =_xlfn.XLOOKUP($A24,Model_Output[Product Name], Model_Output[LTV Protection-Adjusted Risk Ratio]) -> 0.66666667
A25: Scented Candle | B25: =_xlfn.XLOOKUP($A25,Model_Output[Product Name], Model_Output[Category]) -> Home & Kitchen | C25: =_xlfn.XLOOKUP($A25,Model_Output[Product Name], Model_Output[Recommendation]) -> Raise | D25: =_xlfn.XLOOKUP($A25,Model_Output[Product Name], Model_Output[Current Price]) -> 148.11 | E25: =_xlfn.XLOOKUP($A25,Model_Output[Product Name], Model_Output[Adjusted Price]) -> 157.82484 | F25: =_xlfn.XLOOKUP($A25,Model_Output[Product Name], Model_Output[Adjusted Difference %]) -> 0.065592027 | G25: =_xlfn.XLOOKUP($A25,Model_Output[Product Name], Model_Output[Projected Gross Profit Impact $]) -> 199.83095 | H25: =_xlfn.XLOOKUP($A25,Model_Output[Product Name], Model_Output[Projected Gross Profit Lift %]) -> 0.094318164 | I25: =_xlfn.XLOOKUP($A25,Model_Output[Product Name], Model_Output[Total LTV at Risk]) -> 1774.9244 | J25: =_xlfn.XLOOKUP($A25,Model_Output[Product Name], Model_Output[LTV Protection-Adjusted Risk Ratio]) -> 0.72413793
... A36: Protein Shaker | B36: =_xlfn.XLOOKUP($A36,Model_Output[Product Name], Model_Output[Category]) -> Sports & Outdoors | C36: =_xlfn.XLOOKUP($A36,Model_Output[Product Name], Model_Output[Recommendation]) -> Raise | D36: =_xlfn.XLOOKUP($A36,Model_Output[Product Name], Model_Output[Current Price]) -> 99.75 | E36: =_xlfn.XLOOKUP($A36,Model_Output[Product Name], Model_Output[Adjusted Price]) -> 106.16045 | F36: =_xlfn.XLOOKUP($A36,Model_Output[Product Name], Model_Output[Adjusted Difference %]) -> 0.06426521 | G36: =_xlfn.XLOOKUP($A36,Model_Output[Product Name], Model_Output[Projected Gross Profit Impact $]) -> 158.49638 | H36: =_xlfn.XLOOKUP($A36,Model_Output[Product Name], Model_Output[Projected Gross Profit Lift %]) -> 0.075651706 | I36: =_xlfn.XLOOKUP($A36,Model_Output[Product Name], Model_Output[Total LTV at Risk]) -> 1533.9834 | J36: =_xlfn.XLOOKUP($A36,Model_Output[Product Name], Model_Output[LTV Protection-Adjusted Risk Ratio]) -> 0.66666667
A37: TOTALS | E37: =AVERAGE($E13:$E36) -> 122.64136 | F37: =AVERAGE($F13:$F36) -> 0.08875811 | G37: =SUM($G13:$G36) -> 5575.3186 | H37: =AVERAGE($H13:$H36) -> 0.12326403 | I37: =SUM($I13:$I36) -> 36380.521 | J37: =AVERAGE($J13:$J36) -> 0.6690613

Sheet Pricing Detail
A1: PRICING DETAIL - V1 vs ADJUSTED
A2: Info | D2: Competitive Signal | E2: V1 Model | I2: Churn-Adjusted Model | M2: Churn-Adjusted Trade-off
A3: Product | B3: Category | C3: Current Price | D3: Recommendation | E3: V1 Price | F3: V1 ∆% | G3: V1 GR Impact | H3: V1 GP Impact | I3: Adj. Price | J3: Adj. ∆% | K3: Adj. GR Impact | L3: Adj. GP Impact | M3: LTV at Risk | N3: LTV Protected | O3: LTV Sacrificed | P3: LTV Uncertain
A4: {='Executive Summary'!$A$13:$B$36} -> Wireless Earbuds | B4: Electronics | C4: {='Executive Summary'!$D$13:$D$36} -> 76.53 | D4: {='Executive Summary'!C13:C36} -> Raise | E4: =_xlfn.XLOOKUP($A4,Model_Output[Product Name], Model_Output[V1 Suggested Price]) -> 80.606323 | F4: =_xlfn.XLOOKUP($A4,Model_Output[Product Name], Model_Output[V1 Difference %]) -> 0.053264378 | G4: =_xlfn.XLOOKUP($A4,Model_Output[Product Name],Model_Output[V1 Gross Revenue Impact]) -> 17.225425 | H4: =_xlfn.XLOOKUP($A4,Model_Output[Product Name],Model_Output[V1 Gross Profit Impact $]) -> 70.185425 | I4: =_xlfn.XLOOKUP($A4,Model_Output[Product Name], Model_Output[Adjusted Price]) -> 78.975794 | J4: =_xlfn.XLOOKUP($A4,Model_Output[Product Name], Model_Output[Adjusted Difference %]) -> 0.031958627 | K4: =_xlfn.XLOOKUP($A4,Model_Output[Product Name], Model_Output[Adjusted Gross Revenue Impact]) -> 34.469053 | L4: =_xlfn.XLOOKUP($A4,Model_Output[Product Name], Model_Output[Projected Gross Profit Impact $]) -> 50.71733 | M4: =_xlfn.XLOOKUP($A4,Model_Output[Product Name], Model_Output[Total LTV at Risk]) -> 1112.0932 | N4: {=_xlfn.XLOOKUP($A4,Model_Output[Product Name], Model_Output[[LTV Protected]:[LTV Sacrificed]])} -> 358.09401 | O4: 537.14101 | P4: =$M4-($N4+$O4) -> 216.85817
A5: Bluetooth Speaker | B5: Electronics | C5: 53.26 | D5: Raise | E5: =_xlfn.XLOOKUP($A5,Model_Output[Product Name], Model_Output[V1 Suggested Price]) -> 57.563992 | F5: =_xlfn.XLOOKUP($A5,Model_Output[Product Name], Model_Output[V1 Difference %]) -> 0.080810961 | G5: =_xlfn.XLOOKUP($A5,Model_Output[Product Name],Model_Output[V1 Gross Revenue Impact]) -> 32.819836 | H5: =_xlfn.XLOOKUP($A5,Model_Output[Product Name],Model_Output[V1 Gross Profit Impact $]) -> 69.459836 | I5: =_xlfn.XLOOKUP($A5,Model_Output[Product Name], Model_Output[Adjusted Price]) -> 55.842395 | J5: =_xlfn.XLOOKUP($A5,Model_Output[Product Name], Model_Output[Adjusted Difference %]) -> 0.048486577 | K5: =_xlfn.XLOOKUP($A5,Model_Output[Product Name], Model_Output[Adjusted Gross Revenue Impact]) -> 31.486401 | L5: =_xlfn.XLOOKUP($A5,Model_Output[Product Name], Model_Output[Projected Gross Profit Impact $]) -> 46.409406 | M5: =_xlfn.XLOOKUP($A5,Model_Output[Product Name], Model_Output[Total LTV at Risk]) -> 1487.03 | N5: {=_xlfn.XLOOKUP($A5,Model_Output[Product Name], Model_Output[[LTV Protected]:[LTV Sacrificed]])} -> 449.41351 | O5: 674.12027 | P5: =$M5-($N5+$O5) -> 363.49622
A6: USB-C Hub | B6: Electronics | C6: 18.39 | D6: Hold | E6: =_xlfn.XLOOKUP($A6,Model_Output[Product Name], Model_Output[V1 Suggested Price]) -> 20.325622 | F6: =_xlfn.XLOOKUP($A6,Model_Output[Product Name], Model_Output[V1 Difference %]) -> 0.10525403 | G6: =_xlfn.XLOOKUP($A6,Model_Output[Product Name],Model_Output[V1 Gross Revenue Impact]) -> 12.579946 | H6: =_xlfn.XLOOKUP($A6,Model_Output[Product Name],Model_Output[V1 Gross Profit Impact $]) -> 20.839946 | I6: =_xlfn.XLOOKUP($A6,Model_Output[Product Name], Model_Output[Adjusted Price]) -> 19.551373 | J6: =_xlfn.XLOOKUP($A6,Model_Output[Product Name], Model_Output[Adjusted Difference %]) -> 0.063152419 | K6: =_xlfn.XLOOKUP($A6,Model_Output[Product Name], Model_Output[Adjusted Gross Revenue Impact]) -> 11.347269 | L6: =_xlfn.XLOOKUP($A6,Model_Output[Product Name], Model_Output[Projected Gross Profit Impact $]) -> 14.894414 | M6: =_xlfn.XLOOKUP($A6,Model_Output[Product Name], Model_Output[Total LTV at Risk]) -> 1216.0707 | N6: {=_xlfn.XLOOKUP($A6,Model_Output[Product Name], Model_Output[[LTV Protected]:[LTV Sacrificed]])} -> 375.63072 | O6: 563.44608 | P6: =$M6-($N6+$O6) -> 276.99388
A7: Mechanical Keyboard | B7: Electronics | C7: 113.18 | D7: Hold | E7: =_xlfn.XLOOKUP($A7,Model_Output[Product Name], Model_Output[V1 Suggested Price]) -> 122.07351 | F7: =_xlfn.XLOOKUP($A7,Model_Output[Product Name], Model_Output[V1 Difference %]) -> 0.078578479 | G7: =_xlfn.XLOOKUP($A7,Model_Output[Product Name],Model_Output[V1 Gross Revenue Impact]) -> 91.370781 | H7: =_xlfn.XLOOKUP($A7,Model_Output[Product Name],Model_Output[V1 Gross Profit Impact $]) -> 130.38078 | I7: =_xlfn.XLOOKUP($A7,Model_Output[Product Name], Model_Output[Adjusted Price]) -> 118.51611 | J7: =_xlfn.XLOOKUP($A7,Model_Output[Product Name], Model_Output[Adjusted Difference %]) -> 0.047147087 | K7: =_xlfn.XLOOKUP($A7,Model_Output[Product Name], Model_Output[Adjusted Gross Revenue Impact]) -> 74.424759 | L7: =_xlfn.XLOOKUP($A7,Model_Output[Product Name], Model_Output[Projected Gross Profit Impact $]) -> 92.081155 | M7: =_xlfn.XLOOKUP($A7,Model_Output[Product Name], Model_Output[Total LTV at Risk]) -> 1378.1368 | N7: {=_xlfn.XLOOKUP($A7,Model_Output[Product Name], Model_Output[[LTV Protected]:[LTV Sacrificed]])} -> 396.9034 | O7: 595.3551 | P7: =$M7-($N7+$O7) -> 385.87831
A8: Phone Stand | B8: Electronics | C8: 177.91 | D8: Raise | E8: =_xlfn.XLOOKUP($A8,Model_Output[Product Name], Model_Output[V1 Suggested Price]) -> 210.36242 | F8: =_xlfn.XLOOKUP($A8,Model_Output[Product Name], Model_Output[V1 Difference %]) -> 0.1824092 | G8: =_xlfn.XLOOKUP($A8,Model_Output[Product Name],Model_Output[V1 Gross Revenue Impact]) -> 2118.3199 | H8: =_xlfn.XLOOKUP($A8,Model_Output[Product Name],Model_Output[V1 Gross Profit Impact $]) -> 2338.7899 | I8: =_xlfn.XLOOKUP($A8,Model_Output[Product Name], Model_Output[Adjusted Price]) -> 197.38145 | J8: =_xlfn.XLOOKUP($A8,Model_Output[Product Name], Model_Output[Adjusted Difference %]) -> 0.10944552 | K8: =_xlfn.XLOOKUP($A8,Model_Output[Product Name], Model_Output[Adjusted Gross Revenue Impact]) -> 389.89606 | L8: =_xlfn.XLOOKUP($A8,Model_Output[Product Name], Model_Output[Projected Gross Profit Impact $]) -> 505.71744 | M8: =_xlfn.XLOOKUP($A8,Model_Output[Product Name], Model_Output[Total LTV at Risk]) -> 1987.1738 | N8: {=_xlfn.XLOOKUP($A8,Model_Output[Product Name], Model_Output[[LTV Protected]:[LTV Sacrificed]])} -> 688.8869 | O8: 1033.3304 | P8: =$M8-($N8+$O8) -> 264.9565
A9: Slim Fit Jeans | B9: Apparel | C9: 45.86 | D9: Raise | E9: =_xlfn.XLOOKUP($A9,Model_Output[Product Name], Model_Output[V1 Suggested Price]) -> 57.591702 | F9: =_xlfn.XLOOKUP($A9,Model_Output[Product Name], Model_Output[V1 Difference %]) -> 0.25581556 | G9: =_xlfn.XLOOKUP($A9,Model_Output[Product Name],Model_Output[V1 Gross Revenue Impact]) -> 713.86466 | H9: =_xlfn.XLOOKUP($A9,Model_Output[Product Name],Model_Output[V1 Gross Profit Impact $]) -> 813.34466 | I9: =_xlfn.XLOOKUP($A9,Model_Output[Product Name], Model_Output[Adjusted Price]) -> 52.899021 | J9: =_xlfn.XLOOKUP($A9,Model_Output[Product Name], Model_Output[Adjusted Difference %]) -> 0.15348934 | K9: =_xlfn.XLOOKUP($A9,Model_Output[Product Name], Model_Output[Adjusted Gross Revenue Impact]) -> 159.23236 | L9: =_xlfn.XLOOKUP($A9,Model_Output[Product Name], Model_Output[Projected Gross Profit Impact $]) -> 223.36266 | M9: =_xlfn.XLOOKUP($A9,Model_Output[Product Name], Model_Output[Total LTV at Risk]) -> 1838.4437 | N9: {=_xlfn.XLOOKUP($A9,Model_Output[Product Name], Model_Output[[LTV Protected]:[LTV Sacrificed]])} -> 666.16547 | O9: 999.2482 | P9: =$M9-($N9+$O9) -> 173.02999
A10: Graphic Tee | B10: Apparel | C10: 67.56 | D10: Raise | E10: =_xlfn.XLOOKUP($A10,Model_Output[Product Name], Model_Output[V1 Suggested Price]) -> 74.848492 | F10: =_xlfn.XLOOKUP($A10,Model_Output[Product Name], Model_Output[V1 Difference %]) -> 0.10788177 | G10: =_xlfn.XLOOKUP($A10,Model_Output[Product Name],Model_Output[V1 Gross Revenue Impact]) -> 85.498342 | H10: =_xlfn.XLOOKUP($A10,Model_Output[Product Name],Model_Output[V1 Gross Profit Impact $]) -> 128.70834 | I10: =_xlfn.XLOOKUP($A10,Model_Output[Product Name], Model_Output[Adjusted Price]) -> 71.933095 | J10: =_xlfn.XLOOKUP($A10,Model_Output[Product Name], Model_Output[Adjusted Difference %]) -> 0.064729063 | K10: =_xlfn.XLOOKUP($A10,Model_Output[Product Name], Model_Output[Adjusted Gross Revenue Impact]) -> 55.233876 | L10: =_xlfn.XLOOKUP($A10,Model_Output[Product Name], Model_Output[Projected Gross Profit Impact $]) -> 79.846973 | M10: =_xlfn.XLOOKUP($A10,Model_Output[Product Name], Model_Output[Total LTV at Risk]) -> 1511.5432 | N10: {=_xlfn.XLOOKUP($A10,Model_Output[Product Name], Model_Output[[LTV Protected]:[LTV Sacrificed]])} -> 429.27827 | O10: 643.91741 | P10: =$M10-($N10+$O10) -> 438.34753
A11: Wool Sweater | B11: Apparel | C11: 143.8 | D11: Raise | E11: =_xlfn.XLOOKUP($A11,Model_Output[Product Name], Model_Output[V1 Suggested Price]) -> 176.09453 | F11: =_xlfn.XLOOKUP($A11,Model_Output[Product Name], Model_Output[V1 Difference %]) -> 0.22457947 | G11: =_xlfn.XLOOKUP($A11,Model_Output[Product Name],Model_Output[V1 Gross Revenue Impact]) -> 408.25774 | H11: =_xlfn.XLOOKUP($A11,Model_Output[Product Name],Model_Output[V1 Gross Profit Impact $]) -> 594.70774 | I11: =_xlfn.XLOOKUP($A11,Model_Output[Product Name], Model_Output[Adjusted Price]) -> 163.17672 | J11: =_xlfn.XLOOKUP($A11,Model_Output[Product Name], Model_Output[Adjusted Difference %]) -> 0.13474768 | K11: =_xlfn.XLOOKUP($A11,Model_Output[Product Name], Model_Output[Adjusted Gross Revenue Impact]) -> 306.86765 | L11: =_xlfn.XLOOKUP($A11,Model_Output[Product Name], Model_Output[Projected Gross Profit Impact $]) -> 404.01265 | M11: =_xlfn.XLOOKUP($A11,Model_Output[Product Name], Model_Output[Total LTV at Risk]) -> 1207.1798 | N11: {=_xlfn.XLOOKUP($A11,Model_Output[Product Name], Model_Output[[LTV Protected]:[LTV Sacrificed]])} -> 422.51294 | O11: 633.76941 | P11: =$M11-($N11+$O11) -> 150.89748
A12: Canvas Tote Bag | B12: Apparel | C12: 160.35 | D12: Raise | E12: =_xlfn.XLOOKUP($A12,Model_Output[Product Name], Model_Output[V1 Suggested Price]) -> 182.28731 | F12: =_xlfn.XLOOKUP($A12,Model_Output[Product Name], Model_Output[V1 Difference %]) -> 0.13680891 | G12: =_xlfn.XLOOKUP($A12,Model_Output[Product Name],Model_Output[V1 Gross Revenue Impact]) -> 425.16851 | H12: =_xlfn.XLOOKUP($A12,Model_Output[Product Name],Model_Output[V1 Gross Profit Impact $]) -> 570.10851 | I12: =_xlfn.XLOOKUP($A12,Model_Output[Product Name], Model_Output[Adjusted Price]) -> 173.51239 | J12: =_xlfn.XLOOKUP($A12,Model_Output[Product Name], Model_Output[Adjusted Difference %]) -> 0.082085347 | K12: =_xlfn.XLOOKUP($A12,Model_Output[Product Name], Model_Output[Adjusted Gross Revenue Impact]) -> 268.7492 | L12: =_xlfn.XLOOKUP($A12,Model_Output[Product Name], Model_Output[Projected Gross Profit Impact $]) -> 354.41085 | M12: =_xlfn.XLOOKUP($A12,Model_Output[Product Name], Model_Output[Total LTV at Risk]) -> 1437.421 | N12: {=_xlfn.XLOOKUP($A12,Model_Output[Product Name], Model_Output[[LTV Protected]:[LTV Sacrificed]])} -> 457.57901 | O12: 686.36852 | P12: =$M12-($N12+$O12) -> 293.47345
A13: Air Fryer | B13: Home & Kitchen | C13: 98.51 | D13: Raise | E13: =_xlfn.XLOOKUP($A13,Model_Output[Product Name], Model_Output[V1 Suggested Price]) -> 115.63152 | F13: =_xlfn.XLOOKUP($A13,Model_Output[Product Name], Model_Output[V1 Difference %]) -> 0.17380489 | G13: =_xlfn.XLOOKUP($A13,Model_Output[Product Name],Model_Output[V1 Gross Revenue Impact]) -> 350.86864 | H13: =_xlfn.XLOOKUP($A13,Model_Output[Product Name],Model_Output[V1 Gross Profit Impact $]) -> 461.20864 | I13: =_xlfn.XLOOKUP($A13,Model_Output[Product Name], Model_Output[Adjusted Price]) -> 108.78291 | J13: =_xlfn.XLOOKUP($A13,Model_Output[Product Name], Model_Output[Adjusted Difference %]) -> 0.10428294 | K13: =_xlfn.XLOOKUP($A13,Model_Output[Product Name], Model_Output[Adjusted Gross Revenue Impact]) -> 194.99787 | L13: =_xlfn.XLOOKUP($A13,Model_Output[Product Name], Model_Output[Projected Gross Profit Impact $]) -> 273.24261 | M13: =_xlfn.XLOOKUP($A13,Model_Output[Product Name], Model_Output[Total LTV at Risk]) -> 1821.0804 | N13: {=_xlfn.XLOOKUP($A13,Model_Output[Product Name], Model_Output[[LTV Protected]:[LTV Sacrificed]])} -> 591.15071 | O13: 886.72606 | P13: =$M13-($N13+$O13) -> 343.20361
A14: Dish Rack | B14: Home & Kitchen | C14: 106.06 | D14: Raise | E14: =_xlfn.XLOOKUP($A14,Model_Output[Product Name], Model_Output[V1 Suggested Price]) -> 125.95982 | F14: =_xlfn.XLOOKUP($A14,Model_Output[Product Name], Model_Output[V1 Difference %]) -> 0.18762795 | G14: =_xlfn.XLOOKUP($A14,Model_Output[Product Name],Model_Output[V1 Gross Revenue Impact]) -> 398.21354 | H14: =_xlfn.XLOOKUP($A14,Model_Output[Product Name],Model_Output[V1 Gross Profit Impact $]) -> 498.47354 | I14: =_xlfn.XLOOKUP($A14,Model_Output[Product Name], Model_Output[Adjusted Price]) -> 117.99989 | J14: =_xlfn.XLOOKUP($A14,Model_Output[Product Name], Model_Output[Adjusted Difference %]) -> 0.11257677 | K14: =_xlfn.XLOOKUP($A14,Model_Output[Product Name], Model_Output[Adjusted Gross Revenue Impact]) -> 258.42467 | L14: =_xlfn.XLOOKUP($A14,Model_Output[Product Name], Model_Output[Projected Gross Profit Impact $]) -> 317.1168 | M14: =_xlfn.XLOOKUP($A14,Model_Output[Product Name], Model_Output[Total LTV at Risk]) -> 1061.3752 | N14: {=_xlfn.XLOOKUP($A14,Model_Output[Product Name], Model_Output[[LTV Protected]:[LTV Sacrificed]])} -> 385.63297 | O14: 578.44946 | P14: =$M14-($N14+$O14) -> 97.292722
A15: Storage Bins | B15: Home & Kitchen | C15: 34.48 | D15: Raise | E15: =_xlfn.XLOOKUP($A15,Model_Output[Product Name], Model_Output[V1 Suggested Price]) -> 36.908162 | F15: =_xlfn.XLOOKUP($A15,Model_Output[Product Name], Model_Output[V1 Difference %]) -> 0.070422329 | G15: =_xlfn.XLOOKUP($A15,Model_Output[Product Name],Model_Output[V1 Gross Revenue Impact]) -> 9.2269146 | H15: =_xlfn.XLOOKUP($A15,Model_Output[Product Name],Model_Output[V1 Gross Profit Impact $]) -> 28.466915 | I15: =_xlfn.XLOOKUP($A15,Model_Output[Product Name], Model_Output[Adjusted Price]) -> 35.936897 | J15: =_xlfn.XLOOKUP($A15,Model_Output[Product Name], Model_Output[Adjusted Difference %]) -> 0.042253398 | K15: =_xlfn.XLOOKUP($A15,Model_Output[Product Name], Model_Output[Adjusted Gross Revenue Impact]) -> 16.14078 | L15: =_xlfn.XLOOKUP($A15,Model_Output[Product Name], Model_Output[Projected Gross Profit Impact $]) -> 22.319241 | M15: =_xlfn.XLOOKUP($A15,Model_Output[Product Name], Model_Output[Total LTV at Risk]) -> 804.52718 | N15: {=_xlfn.XLOOKUP($A15,Model_Output[Product Name], Model_Output[[LTV Protected]:[LTV Sacrificed]])} -> 255.15005 | O15: 382.72507 | P15: =$M15-($N15+$O15) -> 166.65206
A16: Scented Candle | B16: Home & Kitchen | C16: 148.11 | D16: Raise | E16: =_xlfn.XLOOKUP($A16,Model_Output[Product Name], Model_Output[V1 Suggested Price]) -> 164.85972 | F16: =_xlfn.XLOOKUP($A16,Model_Output[Product Name], Model_Output[V1 Difference %]) -> 0.1130897 | G16: =_xlfn.XLOOKUP($A16,Model_Output[Product Name],Model_Output[V1 Gross Revenue Impact]) -> 917.56261 | H16: =_xlfn.XLOOKUP($A16,Model_Output[Product Name],Model_Output[V1 Gross Profit Impact $]) -> 987.20261 | I16: =_xlfn.XLOOKUP($A16,Model_Output[Product Name], Model_Output[Adjusted Price]) -> 157.82484 | J16: =_xlfn.XLOOKUP($A16,Model_Output[Product Name], Model_Output[Adjusted Difference %]) -> 0.065592027 | K16: =_xlfn.XLOOKUP($A16,Model_Output[Product Name], Model_Output[Adjusted Gross Revenue Impact]) -> 150.4984 | L16: =_xlfn.XLOOKUP($A16,Model_Output[Product Name], Model_Output[Projected Gross Profit Impact $]) -> 199.83095 | M16: =_xlfn.XLOOKUP($A16,Model_Output[Product Name], Model_Output[Total LTV at Risk]) -> 1774.9244 | N16: {=_xlfn.XLOOKUP($A16,Model_Output[Product Name], Model_Output[[LTV Protected]:[LTV Sacrificed]])} -> 543.57058 | O16: 750.64509 | P16: =$M16-($N16+$O16) -> 480.70868
... A27: Protein Shaker | B27: Sports & Outdoors | C27: 99.75 | D27: Raise | E27: =_xlfn.XLOOKUP($A27,Model_Output[Product Name], Model_Output[V1 Suggested Price]) -> 110.43409 | F27: =_xlfn.XLOOKUP($A27,Model_Output[Product Name], Model_Output[V1 Difference %]) -> 0.10710868 | G27: =_xlfn.XLOOKUP($A27,Model_Output[Product Name],Model_Output[V1 Gross Revenue Impact]) -> 597.24501 | H27: =_xlfn.XLOOKUP($A27,Model_Output[Product Name],Model_Output[V1 Gross Profit Impact $]) -> 635.37501 | I27: =_xlfn.XLOOKUP($A27,Model_Output[Product Name], Model_Output[Adjusted Price]) -> 106.16045 | J27: =_xlfn.XLOOKUP($A27,Model_Output[Product Name], Model_Output[Adjusted Difference %]) -> 0.06426521 | K27: =_xlfn.XLOOKUP($A27,Model_Output[Product Name], Model_Output[Adjusted Gross Revenue Impact]) -> 125.1705 | L27: =_xlfn.XLOOKUP($A27,Model_Output[Product Name], Model_Output[Projected Gross Profit Impact $]) -> 158.49638 | M27: =_xlfn.XLOOKUP($A27,Model_Output[Product Name], Model_Output[Total LTV at Risk]) -> 1533.9834 | N27: {=_xlfn.XLOOKUP($A27,Model_Output[Product Name], Model_Output[[LTV Protected]:[LTV Sacrificed]])} -> 474.35487 | O27: 711.53231 | P27: =$M27-($N27+$O27) -> 348.09624
A28: TOTALS | F28: =AVERAGE(F$4:F$27) -> 0.14808725 | G28: =SUM($G$4:$G$27) -> 12361.137 | H28: =SUM(H4:H27) -> 14551.067 | J28: =AVERAGE(J$4:J$27) -> 0.08875811 | K28: =SUM(K4:K27) -> 4290.1698 | L28: =SUM(L4:L27) -> 5575.3186 | M28: =SUM(M$4:M$27) -> 36380.521 | N28: =SUM(N$4:N$27) -> 11671.306 | O28: =SUM(O$4:O$27) -> 17442.249 | P28: =SUM(P$4:P$27) -> 7266.9656

Sheet Product Churn Profile
A1: CHURN RISK PROFILE | BUYER-BASED ANALYSIS PER SKU
A2: Info | C2: V1-Based Churn Projection | M2: Churn-Adjusted Trade-off
A3: Product | B3: Category | C3: Dominant Churn Tier | D3: Average Churn Score | E3: Projected Churn Rate (V1-based) | F3: % Critical | G3: % High | H3: % Medium | I3: % Low | J3: Total Buyers | K3: Total Buyer LTV | L3: LTV at Risk | M3: LTV Protected | N3: LTV Sacrificed | O3: LTV Protection-Sacrifice %
A4: {=_xlfn.ANCHORARRAY('Executive Summary'!A13)} -> Wireless Earbuds | B4: {='Executive Summary'!B13:B36} -> Electronics | C4: =_xlfn.XLOOKUP($A4,Model_Output[Product Name], Model_Output[Dominant Tier]) -> Critical | D4: =_xlfn.XLOOKUP($A4,Model_Output[Product Name], Model_Output[Average Churn Score]) -> 70.505262 | E4: =_xlfn.XLOOKUP($A4,Model_Output[Product Name], Model_Output[Average Projected Churn Rate]) -> 0.3181247 | F4: {=_xlfn.XLOOKUP($A4,Model_Output[Product Name], Model_Output[[% Critical]:[%Low]])} -> 0.5 | G4: 0.3 | H4: 0.2 | I4: 0 | J4: =_xlfn.XLOOKUP($A4,Model_Output[Product Name], Model_Output[Total Buyers]) -> 10 | K4: {=_xlfn.XLOOKUP($A4,Model_Output[Product Name], Model_Output[[Total Buyer LTV]:[Total LTV at Risk]])} -> 3841.99 | L4: 1112.0932 | M4: {=_xlfn.XLOOKUP($A4,Model_Output[Product Name], Model_Output[[LTV Protected]:[LTV Protection-Adjusted Risk Ratio]])} -> 358.09401 | N4: 537.14101 | O4: 0.66666667
A5: Bluetooth Speaker | B5: Electronics | C5: =_xlfn.XLOOKUP($A5,Model_Output[Product Name], Model_Output[Dominant Tier]) -> High | D5: =_xlfn.XLOOKUP($A5,Model_Output[Product Name], Model_Output[Average Churn Score]) -> 66.806056 | E5: =_xlfn.XLOOKUP($A5,Model_Output[Product Name], Model_Output[Average Projected Churn Rate]) -> 0.26336465 | F5: {=_xlfn.XLOOKUP($A5,Model_Output[Product Name], Model_Output[[% Critical]:[%Low]])} -> 0.33333333 | G5: 0.44444444 | H5: 0.22222222 | I5: 0 | J5: =_xlfn.XLOOKUP($A5,Model_Output[Product Name], Model_Output[Total Buyers]) -> 9 | K5: {=_xlfn.XLOOKUP($A5,Model_Output[Product Name], Model_Output[[Total Buyer LTV]:[Total LTV at Risk]])} -> 5045.98 | L5: 1487.03 | M5: {=_xlfn.XLOOKUP($A5,Model_Output[Product Name], Model_Output[[LTV Protected]:[LTV Protection-Adjusted Risk Ratio]])} -> 449.41351 | N5: 674.12027 | O5: 0.66666667
A6: USB-C Hub | B6: Electronics | C6: =_xlfn.XLOOKUP($A6,Model_Output[Product Name], Model_Output[Dominant Tier]) -> Critical | D6: =_xlfn.XLOOKUP($A6,Model_Output[Product Name], Model_Output[Average Churn Score]) -> 68.467577 | E6: =_xlfn.XLOOKUP($A6,Model_Output[Product Name], Model_Output[Average Projected Churn Rate]) -> 0.2519532 | F6: {=_xlfn.XLOOKUP($A6,Model_Output[Product Name], Model_Output[[% Critical]:[%Low]])} -> 0.55555556 | G6: 0.11111111 | H6: 0.33333333 | I6: 0 | J6: =_xlfn.XLOOKUP($A6,Model_Output[Product Name], Model_Output[Total Buyers]) -> 9 | K6: {=_xlfn.XLOOKUP($A6,Model_Output[Product Name], Model_Output[[Total Buyer LTV]:[Total LTV at Risk]])} -> 6058.75 | L6: 1216.0707 | M6: {=_xlfn.XLOOKUP($A6,Model_Output[Product Name], Model_Output[[LTV Protected]:[LTV Protection-Adjusted Risk Ratio]])} -> 375.63072 | N6: 563.44608 | O6: 0.66666667
A7: Mechanical Keyboard | B7: Electronics | C7: =_xlfn.XLOOKUP($A7,Model_Output[Product Name], Model_Output[Dominant Tier]) -> Critical | D7: =_xlfn.XLOOKUP($A7,Model_Output[Product Name], Model_Output[Average Churn Score]) -> 63.379342 | E7: =_xlfn.XLOOKUP($A7,Model_Output[Product Name], Model_Output[Average Projected Churn Rate]) -> 0.1953265 | F7: {=_xlfn.XLOOKUP($A7,Model_Output[Product Name], Model_Output[[% Critical]:[%Low]])} -> 0.4 | G7: 0.3 | H7: 0.2 | I7: 0.1 | J7: =_xlfn.XLOOKUP($A7,Model_Output[Product Name], Model_Output[Total Buyers]) -> 10 | K7: {=_xlfn.XLOOKUP($A7,Model_Output[Product Name], Model_Output[[Total Buyer LTV]:[Total LTV at Risk]])} -> 8331.72 | L7: 1378.1368 | M7: {=_xlfn.XLOOKUP($A7,Model_Output[Product Name], Model_Output[[LTV Protected]:[LTV Protection-Adjusted Risk Ratio]])} -> 396.9034 | N7: 595.3551 | O7: 0.66666667
A8: Phone Stand | B8: Electronics | C8: =_xlfn.XLOOKUP($A8,Model_Output[Product Name], Model_Output[Dominant Tier]) -> Critical | D8: =_xlfn.XLOOKUP($A8,Model_Output[Product Name], Model_Output[Average Churn Score]) -> 72.583716 | E8: =_xlfn.XLOOKUP($A8,Model_Output[Product Name], Model_Output[Average Projected Churn Rate]) -> 0.2476082 | F8: {=_xlfn.XLOOKUP($A8,Model_Output[Product Name], Model_Output[[% Critical]:[%Low]])} -> 0.58333333 | G8: 0.33333333 | H8: 0.083333333 | I8: 0 | J8: =_xlfn.XLOOKUP($A8,Model_Output[Product Name], Model_Output[Total Buyers]) -> 12 | K8: {=_xlfn.XLOOKUP($A8,Model_Output[Product Name], Model_Output[[Total Buyer LTV]:[Total LTV at Risk]])} -> 9553.98 | L8: 1987.1738 | M8: {=_xlfn.XLOOKUP($A8,Model_Output[Product Name], Model_Output[[LTV Protected]:[LTV Protection-Adjusted Risk Ratio]])} -> 688.8869 | N8: 1033.3304 | O8: 0.66666667
A9: Slim Fit Jeans | B9: Apparel | C9: =_xlfn.XLOOKUP($A9,Model_Output[Product Name], Model_Output[Dominant Tier]) -> Critical | D9: =_xlfn.XLOOKUP($A9,Model_Output[Product Name], Model_Output[Average Churn Score]) -> 81.368043 | E9: =_xlfn.XLOOKUP($A9,Model_Output[Product Name], Model_Output[Average Projected Churn Rate]) -> 0.36473224 | F9: {=_xlfn.XLOOKUP($A9,Model_Output[Product Name], Model_Output[[% Critical]:[%Low]])} -> 0.70588235 | G9: 0.23529412 | H9: 0.058823529 | I9: 0 | J9: =_xlfn.XLOOKUP($A9,Model_Output[Product Name], Model_Output[Total Buyers]) -> 17 | K9: {=_xlfn.XLOOKUP($A9,Model_Output[Product Name], Model_Output[[Total Buyer LTV]:[Total LTV at Risk]])} -> 5696.89 | L9: 1838.4437 | M9: {=_xlfn.XLOOKUP($A9,Model_Output[Product Name], Model_Output[[LTV Protected]:[LTV Protection-Adjusted Risk Ratio]])} -> 666.16547 | N9: 999.2482 | O9: 0.66666667
A10: Graphic Tee | B10: Apparel | C10: =_xlfn.XLOOKUP($A10,Model_Output[Product Name], Model_Output[Dominant Tier]) -> Critical | D10: =_xlfn.XLOOKUP($A10,Model_Output[Product Name], Model_Output[Average Churn Score]) -> 66.15144 | E10: =_xlfn.XLOOKUP($A10,Model_Output[Product Name], Model_Output[Average Projected Churn Rate]) -> 0.25273448 | F10: {=_xlfn.XLOOKUP($A10,Model_Output[Product Name], Model_Output[[% Critical]:[%Low]])} -> 0.4 | G10: 0.2 | H10: 0.4 | I10: 0 | J10: =_xlfn.XLOOKUP($A10,Model_Output[Product Name], Model_Output[Total Buyers]) -> 10 | K10: {=_xlfn.XLOOKUP($A10,Model_Output[Product Name], Model_Output[[Total Buyer LTV]:[Total LTV at Risk]])} -> 5893.09 | L10: 1511.5432 | M10: {=_xlfn.XLOOKUP($A10,Model_Output[Product Name], Model_Output[[LTV Protected]:[LTV Protection-Adjusted Risk Ratio]])} -> 429.27827 | N10: 643.91741 | O10: 0.66666667
A11: Wool Sweater | B11: Apparel | C11: =_xlfn.XLOOKUP($A11,Model_Output[Product Name], Model_Output[Dominant Tier]) -> Critical | D11: =_xlfn.XLOOKUP($A11,Model_Output[Product Name], Model_Output[Average Churn Score]) -> 75.767552 | E11: =_xlfn.XLOOKUP($A11,Model_Output[Product Name], Model_Output[Average Projected Churn Rate]) -> 0.28614482 | F11: {=_xlfn.XLOOKUP($A11,Model_Output[Product Name], Model_Output[[% Critical]:[%Low]])} -> 0.5 | G11: 0.5 | H11: 0 | I11: 0 | J11: =_xlfn.XLOOKUP($A11,Model_Output[Product Name], Model_Output[Total Buyers]) -> 10 | K11: {=_xlfn.XLOOKUP($A11,Model_Output[Product Name], Model_Output[[Total Buyer LTV]:[Total LTV at Risk]])} -> 4045.53 | L11: 1207.1798 | M11: {=_xlfn.XLOOKUP($A11,Model_Output[Product Name], Model_Output[[LTV Protected]:[LTV Protection-Adjusted Risk Ratio]])} -> 422.51294 | N11: 633.76941 | O11: 0.66666667
A12: Canvas Tote Bag | B12: Apparel | C12: =_xlfn.XLOOKUP($A12,Model_Output[Product Name], Model_Output[Dominant Tier]) -> Critical | D12: =_xlfn.XLOOKUP($A12,Model_Output[Product Name], Model_Output[Average Churn Score]) -> 69.769541 | E12: =_xlfn.XLOOKUP($A12,Model_Output[Product Name], Model_Output[Average Projected Churn Rate]) -> 0.28227914 | F12: {=_xlfn.XLOOKUP($A12,Model_Output[Product Name], Model_Output[[% Critical]:[%Low]])} -> 0.41666667 | G12: 0.41666667 | H12: 0.16666667 | I12: 0 | J12: =_xlfn.XLOOKUP($A12,Model_Output[Product Name], Model_Output[Total Buyers]) -> 12 | K12: {=_xlfn.XLOOKUP($A12,Model_Output[Product Name], Model_Output[[Total Buyer LTV]:[Total LTV at Risk]])} -> 5455.85 | L12: 1437.421 | M12: {=_xlfn.XLOOKUP($A12,Model_Output[Product Name], Model_Output[[LTV Protected]:[LTV Protection-Adjusted Risk Ratio]])} -> 457.57901 | N12: 686.36852 | O12: 0.66666667
A13: Air Fryer | B13: Home & Kitchen | C13: =_xlfn.XLOOKUP($A13,Model_Output[Product Name], Model_Output[Dominant Tier]) -> Critical | D13: =_xlfn.XLOOKUP($A13,Model_Output[Product Name], Model_Output[Average Churn Score]) -> 67.896641 | E13: =_xlfn.XLOOKUP($A13,Model_Output[Product Name], Model_Output[Average Projected Churn Rate]) -> 0.2190319 | F13: {=_xlfn.XLOOKUP($A13,Model_Output[Product Name], Model_Output[[% Critical]:[%Low]])} -> 0.46153846 | G13: 0.38461538 | H13: 0.15384615 | I13: 0 | J13: =_xlfn.XLOOKUP($A13,Model_Output[Product Name], Model_Output[Total Buyers]) -> 13 | K13: {=_xlfn.XLOOKUP($A13,Model_Output[Product Name], Model_Output[[Total Buyer LTV]:[Total LTV at Risk]])} -> 7864.87 | L13: 1821.0804 | M13: {=_xlfn.XLOOKUP($A13,Model_Output[Product Name], Model_Output[[LTV Protected]:[LTV Protection-Adjusted Risk Ratio]])} -> 591.15071 | N13: 886.72606 | O13: 0.66666667
A14: Dish Rack | B14: Home & Kitchen | C14: =_xlfn.XLOOKUP($A14,Model_Output[Product Name], Model_Output[Dominant Tier]) -> Critical | D14: =_xlfn.XLOOKUP($A14,Model_Output[Product Name], Model_Output[Average Churn Score]) -> 83.640694 | E14: =_xlfn.XLOOKUP($A14,Model_Output[Product Name], Model_Output[Average Projected Churn Rate]) -> 0.39945616 | F14: {=_xlfn.XLOOKUP($A14,Model_Output[Product Name], Model_Output[[% Critical]:[%Low]])} -> 0.75 | G14: 0.16666667 | H14: 0.083333333 | I14: 0 | J14: =_xlfn.XLOOKUP($A14,Model_Output[Product Name], Model_Output[Total Buyers]) -> 12 | K14: {=_xlfn.XLOOKUP($A14,Model_Output[Product Name], Model_Output[[Total Buyer LTV]:[Total LTV at Risk]])} -> 3203.34 | L14: 1061.3752 | M14: {=_xlfn.XLOOKUP($A14,Model_Output[Product Name], Model_Output[[LTV Protected]:[LTV Protection-Adjusted Risk Ratio]])} -> 385.63297 | N14: 578.44946 | O14: 0.66666667
A15: Storage Bins | B15: Home & Kitchen | C15: =_xlfn.XLOOKUP($A15,Model_Output[Product Name], Model_Output[Dominant Tier]) -> Critical | D15: =_xlfn.XLOOKUP($A15,Model_Output[Product Name], Model_Output[Average Churn Score]) -> 73.558325 | E15: =_xlfn.XLOOKUP($A15,Model_Output[Product Name], Model_Output[Average Projected Churn Rate]) -> 0.22727842 | F15: {=_xlfn.XLOOKUP($A15,Model_Output[Product Name], Model_Output[[% Critical]:[%Low]])} -> 0.57142857 | G15: 0.14285714 | H15: 0.28571429 | I15: 0 | J15: =_xlfn.XLOOKUP($A15,Model_Output[Product Name], Model_Output[Total Buyers]) -> 7 | K15: {=_xlfn.XLOOKUP($A15,Model_Output[Product Name], Model_Output[[Total Buyer LTV]:[Total LTV at Risk]])} -> 2703.13 | L15: 804.52718 | M15: {=_xlfn.XLOOKUP($A15,Model_Output[Product Name], Model_Output[[LTV Protected]:[LTV Protection-Adjusted Risk Ratio]])} -> 255.15005 | N15: 382.72507 | O15: 0.66666667
A16: Scented Candle | B16: Home & Kitchen | C16: =_xlfn.XLOOKUP($A16,Model_Output[Product Name], Model_Output[Dominant Tier]) -> Critical | D16: =_xlfn.XLOOKUP($A16,Model_Output[Product Name], Model_Output[Average Churn Score]) -> 67.01174 | E16: =_xlfn.XLOOKUP($A16,Model_Output[Product Name], Model_Output[Average Projected Churn Rate]) -> 0.25894827 | F16: {=_xlfn.XLOOKUP($A16,Model_Output[Product Name], Model_Output[[% Critical]:[%Low]])} -> 0.5 | G16: 0.083333333 | H16: 0.41666667 | I16: 0 | J16: =_xlfn.XLOOKUP($A16,Model_Output[Product Name], Model_Output[Total Buyers]) -> 12 | K16: {=_xlfn.XLOOKUP($A16,Model_Output[Product Name], Model_Output[[Total Buyer LTV]:[Total LTV at Risk]])} -> 7071.97 | L16: 1774.9244 | M16: {=_xlfn.XLOOKUP($A16,Model_Output[Product Name], Model_Output[[LTV Protected]:[LTV Protection-Adjusted Risk Ratio]])} -> 543.57058 | N16: 750.64509 | O16: 0.72413793
... A27: Protein Shaker | B27: Sports & Outdoors | C27: =_xlfn.XLOOKUP($A27,Model_Output[Product Name], Model_Output[Dominant Tier]) -> High | D27: =_xlfn.XLOOKUP($A27,Model_Output[Product Name], Model_Output[Average Churn Score]) -> 62.63275 | E27: =_xlfn.XLOOKUP($A27,Model_Output[Product Name], Model_Output[Average Projected Churn Rate]) -> 0.23171703 | F27: {=_xlfn.XLOOKUP($A27,Model_Output[Product Name], Model_Output[[% Critical]:[%Low]])} -> 0.30769231 | G27: 0.53846154 | H27: 0.15384615 | I27: 0 | J27: =_xlfn.XLOOKUP($A27,Model_Output[Product Name], Model_Output[Total Buyers]) -> 13 | K27: {=_xlfn.XLOOKUP($A27,Model_Output[Product Name], Model_Output[[Total Buyer LTV]:[Total LTV at Risk]])} -> 6043.77 | L27: 1533.9834 | M27: {=_xlfn.XLOOKUP($A27,Model_Output[Product Name], Model_Output[[LTV Protected]:[LTV Protection-Adjusted Risk Ratio]])} -> 474.35487 | N27: 711.53231 | O27: 0.66666667
A28: TOTALS | D28: =AVERAGE($D$4:$D$27) -> 70.599508 | E28: =AVERAGE($E$4:$E$27) -> 0.26524813 | J28: =SUM($J$4:$J$27) -> 280 | K28: =SUM(K$4:K$27) -> 146514 | L28: =SUM(L$4:L$27) -> 36380.521 | M28: =SUM(M$4:M$27) -> 11671.306 | N28: =SUM(N$4:N$27) -> 17442.249 | O28: =AVERAGE($O$4:$O$27) -> 0.6690613

Sheet Model Output
A1: SKU | B1: Product Name | C1: Category | D1: Recommendation | E1: Current Price | F1: Current Cost Per Unit | G1: Current Volume | H1: Current Gross Revenue | I1: Current COGS | J1: Current Gross Profit | K1: Current Gross Profit Margin % | L1: V1 Suggested Price | M1: V1 Difference $ | N1: V1 Difference % | O1: V1 Gross Revenue Impact | P1: V1 Gross Profit Impact $ | Q1: Total Buyers | R1: Average Churn Score | S1: Average Projected Churn Rate | T1: Total Buyer LTV | U1: Total LTV at Risk | V1: % Critical | W1: % High | X1: % Medium | Y1: %Low | Z1: Dominant Tier | AA1: Adjusted Price | AB1: Adjusted Difference $ | AC1: Adjusted Difference % | AD1: Adjusted Volume Change % | AE1: Adjusted Volume | AF1: Adjusted Projected Gross Revenue | AG1: Adjusted Gross Revenue Impact | AH1: Adjusted Gross Revenue Lift | AI1: Adjusted COGS | AJ1: Adjusted COGS Impact | AK1: Adjusted COGS Lift | AL1: Adjusted Gross Profit | AM1: Projected Gross Profit Impact $ | AN1: Projected Gross Profit Lift % | AO1: Projected Gross Profit Margin % | AP1: Project Gross Profit Margin Impact % | AQ1: Projected Gross Profit Margin Lift | AR1: LTV Protected | AS1: LTV Sacrificed | AT1: LTV Protection-Adjusted Risk Ratio
A2: SKU-1000 | B2: Wireless Earbuds | C2: Electronics | D2: Raise | E2: 76.53 | F2: 52.96 | G2: 24 | H2: 1836.72 | I2: 1271.04 | J2: 565.68 | K2: 0.3079838 | L2: 80.606323 | M2: 4.0763228 | N2: 0.053264378 | O2: 17.225425 | P2: 70.185425 | Q2: 10 | R2: 70.505262 | S2: 0.3181247 | T2: 3841.99 | U2: 1112.0932 | V2: 0.5 | W2: 0.3 | X2: 0.2 | Y2: 0 | Z2: Critical | AA2: 78.975794 | AB2: 2.4457937 | AC2: 0.031958627 | AD2: -0.012783451 | AE2: 24.012783 | AF2: 1871.1891 | AG2: 34.469053 | AH2: 0.018766635 | AI2: 1271.717 | AJ2: 0.67701155 | AK2: 0.00053264378 | AL2: 616.39733 | AM2: 50.71733 | AN2: 0.08965728 | AO2: 0.32941478 | AP2: 0.021430983 | AQ2: 0.021430983 | AR2: 358.09401 | AS2: 537.14101 | AT2: 0.66666667
A3: SKU-1001 | B3: Bluetooth Speaker | C3: Electronics | D3: Raise | E3: 53.26 | F3: 36.64 | G3: 21 | H3: 1118.46 | I3: 769.44 | J3: 349.02 | K3: 0.31205407 | L3: 57.563992 | M3: 4.3039918 | N3: 0.080810961 | O3: 32.819836 | P3: 69.459836 | Q3: 9 | R3: 66.806056 | S3: 0.26336465 | T3: 5045.98 | U3: 1487.03 | V3: 0.33333333 | W3: 0.44444444 | X3: 0.22222222 | Y3: 0 | Z3: High | AA3: 55.842395 | AB3: 2.5823951 | AC3: 0.048486577 | AD3: -0.019394631 | AE3: 21.019395 | AF3: 1149.9464 | AG3: 31.486401 | AH3: 0.028151567 | AI3: 1113.1871 | AJ3: 343.74714 | AK3: 0.44674977 | AL3: 395.42941 | AM3: 46.409406 | AN3: 0.13297062 | AO3: 0.34386768 | AP3: 0.03181361 | AQ3: 0.03181361 | AR3: 449.41351 | AS3: 674.12027 | AT3: 0.66666667
A4: SKU-1004 | B4: USB-C Hub | C4: Electronics | D4: Hold | E4: 18.39 | F4: 8.26 | G4: 17 | H4: 312.63 | I4: 140.42 | J4: 172.21 | K4: 0.55084285 | L4: 20.325622 | M4: 1.9356217 | N4: 0.10525403 | O4: 12.579946 | P4: 20.839946 | Q4: 9 | R4: 68.467577 | S4: 0.2519532 | T4: 6058.75 | U4: 1216.0707 | V4: 0.55555556 | W4: 0.11111111 | X4: 0.33333333 | Y4: 0 | Z4: Critical | AA4: 19.551373 | AB4: 1.161373 | AC4: 0.063152419 | AD4: -0.025260968 | AE4: 17.025261 | AF4: 323.97727 | AG4: 11.347269 | AH4: 0.03629616 | AI4: 901.65782 | AJ4: 761.23782 | AK4: 5.4211496 | AL4: 187.10441 | AM4: 14.894414 | AN4: 0.086489831 | AO4: 0.57752328 | AP4: 0.026680427 | AQ4: 0.026680427 | AR4: 375.63072 | AS4: 563.44608 | AT4: 0.66666667
A5: SKU-1006 | B5: Mechanical Keyboard | C5: Electronics | D5: Hold | E5: 113.18 | F5: 39.01 | G5: 24 | H5: 2716.32 | I5: 936.24 | J5: 1780.08 | K5: 0.6553278 | L5: 122.07351 | M5: 8.8935122 | N5: 0.078578479 | O5: 91.370781 | P5: 130.38078 | Q5: 10 | R5: 63.379342 | S5: 0.1953265 | T5: 8331.72 | U5: 1378.1368 | V5: 0.4 | W5: 0.3 | X5: 0.2 | Y5: 0.1 | Z5: Critical | AA5: 118.51611 | AB5: 5.3361073 | AC5: 0.047147087 | AD5: -0.018858835 | AE5: 24.018859 | AF5: 2790.7448 | AG5: 74.424759 | AH5: 0.027399113 | AI5: 1272.0388 | AJ5: 335.79876 | AK5: 0.3586674 | AL5: 1872.1612 | AM5: 92.081155 | AN5: 0.051728661 | AO5: 0.67084643 | AP5: 0.015518632 | AQ5: 0.015518632 | AR5: 396.9034 | AS5: 595.3551 | AT5: 0.66666667
A6: SKU-1009 | B6: Phone Stand | C6: Electronics | D6: Raise | E6: 177.91 | F6: 73.49 | G6: 36 | H6: 6404.76 | I6: 2645.64 | J6: 3759.12 | K6: 0.58692597 | L6: 210.36242 | M6: 32.452421 | N6: 0.1824092 | O6: 2118.3199 | P6: 2338.7899 | Q6: 12 | R6: 72.583716 | S6: 0.2476082 | T6: 9553.98 | U6: 1987.1738 | V6: 0.58333333 | W6: 0.33333333 | X6: 0.083333333 | Y6: 0 | Z6: Critical | AA6: 197.38145 | AB6: 19.471452 | AC6: 0.10944552 | AD6: -0.043778208 | AE6: 36.043778 | AF6: 6794.6561 | AG6: 389.89606 | AH6: 0.060875983 | AI6: 1908.8785 | AJ6: -736.76151 | AK6: -0.27848139 | AL6: 4264.8374 | AM6: 505.71744 | AN6: 0.1345308 | AO6: 0.62767525 | AP6: 0.040749276 | AQ6: 0.040749276 | AR6: 688.8869 | AS6: 1033.3304 | AT6: 0.66666667
A7: SKU-1010 | B7: Slim Fit Jeans | C7: Apparel | D7: Raise | E7: 45.86 | F7: 24.87 | G7: 42 | H7: 1926.12 | I7: 1044.54 | J7: 881.58 | K7: 0.45769734 | L7: 57.591702 | M7: 11.731702 | N7: 0.25581556 | O7: 713.86466 | P7: 813.34466 | Q7: 17 | R7: 81.368043 | S7: 0.36473224 | T7: 5696.89 | U7: 1838.4437 | V7: 0.70588235 | W7: 0.23529412 | X7: 0.058823529 | Y7: 0 | Z7: Critical | AA7: 52.899021 | AB7: 7.0390209 | AC7: 0.15348934 | AD7: -0.061395734 | AE7: 42.061396 | AF7: 2085.3524 | AG7: 159.23236 | AH7: 0.082670011 | AI7: 2227.5715 | AJ7: 1183.0315 | AK7: 1.1325861 | AL7: 1104.9427 | AM7: 223.36266 | AN7: 0.2533663 | AO7: 0.52985897 | AP7: 0.072161634 | AQ7: 0.072161634 | AR7: 666.16547 | AS7: 999.2482 | AT7: 0.66666667
A8: SKU-1011 | B8: Graphic Tee | C8: Apparel | D8: Raise | E8: 67.56 | F8: 43.21 | G8: 22 | H8: 1486.32 | I8: 950.62 | J8: 535.7 | K8: 0.36042037 | L8: 74.848492 | M8: 7.2884925 | N8: 0.10788177 | O8: 85.498342 | P8: 128.70834 | Q8: 10 | R8: 66.15144 | S8: 0.25273448 | T8: 5893.09 | U8: 1511.5432 | V8: 0.4 | W8: 0.2 | X8: 0.4 | Y8: 0 | Z8: Critical | AA8: 71.933095 | AB8: 4.3730955 | AC8: 0.064729063 | AD8: -0.025891625 | AE8: 22.025892 | AF8: 1541.5539 | AG8: 55.233876 | AH8: 0.037161497 | AI8: 1166.4912 | AJ8: 215.87122 | AK8: 0.22708466 | AL8: 615.54697 | AM8: 79.846973 | AN8: 0.14905166 | AO8: 0.39930293 | AP8: 0.038882559 | AQ8: 0.038882559 | AR8: 429.27827 | AS8: 643.91741 | AT8: 0.66666667
A9: SKU-1014 | B9: Wool Sweater | C9: Apparel | D9: Raise | E9: 143.8 | F9: 62.15 | G9: 29 | H9: 4170.2 | I9: 1802.35 | J9: 2367.85 | K9: 0.5678025 | L9: 176.09453 | M9: 32.294528 | N9: 0.22457947 | O9: 408.25774 | P9: 594.70774 | Q9: 10 | R9: 75.767552 | S9: 0.28614482 | T9: 4045.53 | U9: 1207.1798 | V9: 0.5 | W9: 0.5 | X9: 0 | Y9: 0 | Z9: Critical | AA9: 163.17672 | AB9: 19.376717 | AC9: 0.13474768 | AD9: -0.053899074 | AE9: 29.053899 | AF9: 4477.0677 | AG9: 306.86765 | AH9: 0.073585836 | AI9: 1538.6945 | AJ9: -263.65551 | AK9: -0.1462843 | AL9: 2771.8626 | AM9: 404.01265 | AN9: 0.17062426 | AO9: 0.61912458 | AP9: 0.051322081 | AQ9: 0.051322081 | AR9: 422.51294 | AS9: 633.76941 | AT9: 0.66666667
A10: SKU-1019 | B10: Canvas Tote Bag | C10: Apparel | D10: Raise | E10: 160.35 | F10: 72.47 | G10: 36 | H10: 5772.6 | I10: 2608.92 | J10: 3163.68 | K10: 0.54805114 | L10: 182.28731 | M10: 21.937309 | N10: 0.13680891 | O10: 425.16851 | P10: 570.10851 | Q10: 12 | R10: 69.769541 | S10: 0.28227914 | T10: 5455.85 | U10: 1437.421 | V10: 0.41666667 | W10: 0.41666667 | X10: 0.16666667 | Y10: 0 | Z10: Critical | AA10: 173.51239 | AB10: 13.162385 | AC10: 0.082085347 | AD10: -0.032834139 | AE10: 36.032834 | AF10: 6041.3492 | AG10: 268.7492 | AH10: 0.046556007 | AI10: 1908.2989 | AJ10: -700.6211 | AK10: -0.26854833 | AL10: 3518.0908 | AM10: 354.41085 | AN10: 0.11202487 | AO10: 0.58233529 | AP10: 0.034284153 | AQ10: 0.034284153 | AR10: 457.57901 | AS10: 686.36852 | AT10: 0.66666667
A11: SKU-1021 | B11: Air Fryer | C11: Home & Kitchen | D11: Raise | E11: 98.51 | F11: 55.17 | G11: 34 | H11: 3349.34 | I11: 1875.78 | J11: 1473.56 | K11: 0.43995533 | L11: 115.63152 | M11: 17.12152 | N11: 0.17380489 | O11: 350.86864 | P11: 461.20864 | Q11: 13 | R11: 67.896641 | S11: 0.2190319 | T11: 7864.87 | U11: 1821.0804 | V11: 0.46153846 | W11: 0.38461538 | X11: 0.15384615 | Y11: 0 | Z11: Critical | AA11: 108.78291 | AB11: 10.272912 | AC11: 0.10428294 | AD11: -0.041713175 | AE11: 34.041713 | AF11: 3544.3379 | AG11: 194.99787 | AH11: 0.05821979 | AI11: 1802.8491 | AJ11: -72.93087 | AK11: -0.03888029 | AL11: 1746.8026 | AM11: 273.24261 | AN11: 0.18543026 | AO11: 0.49284314 | AP11: 0.052887807 | AQ11: 0.052887807 | AR11: 591.15071 | AS11: 886.72606 | AT11: 0.66666667
A12: SKU-1026 | B12: Dish Rack | C12: Home & Kitchen | D12: Raise | E12: 106.06 | F12: 33.42 | G12: 39 | H12: 4136.34 | I12: 1303.38 | J12: 2832.96 | K12: 0.68489534 | L12: 125.95982 | M12: 19.899821 | N12: 0.18762795 | O12: 398.21354 | P12: 498.47354 | Q12: 12 | R12: 83.640694 | S12: 0.39945616 | T12: 3203.34 | U12: 1061.3752 | V12: 0.75 | W12: 0.16666667 | X12: 0.083333333 | Y12: 0 | Z12: Critical | AA12: 117.99989 | AB12: 11.939892 | AC12: 0.11257677 | AD12: -0.045030708 | AE12: 39.045031 | AF12: 4394.7647 | AG12: 258.42467 | AH12: 0.062476651 | AI12: 2067.8248 | AJ12: 764.44483 | AK12: 0.58650956 | AL12: 3150.0768 | AM12: 317.1168 | AN12: 0.11193832 | AO12: 0.7167794 | AP12: 0.03188406 | AQ12: 0.03188406 | AR12: 385.63297 | AS12: 578.44946 | AT12: 0.66666667
A13: SKU-1027 | B13: Storage Bins | C13: Home & Kitchen | D13: Raise | E13: 34.48 | F13: 19.24 | G13: 19 | H13: 655.12 | I13: 365.56 | J13: 289.56 | K13: 0.44199536 | L13: 36.908162 | M13: 2.4281619 | N13: 0.070422329 | O13: 9.2269146 | P13: 28.466915 | Q13: 7 | R13: 73.558325 | S13: 0.22727842 | T13: 2703.13 | U13: 804.52718 | V13: 0.57142857 | W13: 0.14285714 | X13: 0.28571429 | Y13: 0 | Z13: Critical | AA13: 35.936897 | AB13: 1.4568972 | AC13: 0.042253398 | AD13: -0.016901359 | AE13: 19.016901 | AF13: 671.26078 | AG13: 16.14078 | AH13: 0.024637899 | AI13: 1007.1351 | AJ13: 641.5751 | AK13: 1.7550473 | AL13: 311.87924 | AM13: 22.319241 | AN13: 0.077079849 | AO13: 0.46461711 | AP13: 0.022621746 | AQ13: 0.022621746 | AR13: 255.15005 | AS13: 382.72507 | AT13: 0.66666667
... A25: SKU-1049 | B25: Protein Shaker | C25: Sports & Outdoors | D25: Raise | E25: 99.75 | F25: 38.13 | G25: 34 | H25: 3391.5 | I25: 1296.42 | J25: 2095.08 | K25: 0.61774436 | L25: 110.43409 | M25: 10.684091 | N25: 0.10710868 | O25: 597.24501 | P25: 635.37501 | Q25: 13 | R25: 62.63275 | S25: 0.23171703 | T25: 6043.77 | U25: 1533.9834 | V25: 0.30769231 | W25: 0.53846154 | X25: 0.15384615 | Y25: 0 | Z25: High | AA25: 106.16045 | AB25: 6.4104547 | AC25: 0.06426521 | AD25: -0.025706084 | AE25: 34.025706 | AF25: 3516.6705 | AG25: 125.1705 | AH25: 0.036907119 | AI25: 1802.0014 | AJ25: 505.58139 | AK25: 0.38998272 | AL25: 2253.5764 | AM25: 158.49638 | AN25: 0.075651706 | AO25: 0.64082671 | AP25: 0.023082347 | AQ25: 0.023082347 | AR25: 474.35487 | AS25: 711.53231 | AT25: 0.66666667

Sheet Path
A1: FilePath
A2: {=LEFT(CELL("filename",A1),SEARCH("[",CELL("filename",A1))-1)} -> C:\Users\Shamel\Documents\Projects\pricing_analysis\
