Workbook

Sheet Best Outcomes
A1: SKU | B1: Recommendation | C1: Candidate Type | D1: Current Price | E1: Winning Scenario | F1: Evaluation Score | G1: Adjusted Price | H1: Adjusted Difference $ | I1: Adjusted Difference % | J1: Adjusted Gross Revenue | K1: Gross Revenue Impact $ | L1: Gross Revenue Lift % | M1: Adjusted Gross Profit | N1: Gross Profit Impact $ | O1: Gross Profit Lift % | P1: Gross Profit Margin % | Q1: Gross Profit Margin Lift % | R1: LTV Protected | S1: LTV Sacrificed | T1: LTV Protection-Risk Ratio
A2: {=INDEX(Model_Input[SKU], ROW()-1)} -> SKU-1000 | B2: {=INDEX(Engine!$F$2:$F$2201, Helpers!$B7)} -> Raise | C2: {=INDEX(Engine!$G$2:$G$2201, Helpers!$B7)} -> Full | D2: {=INDEX(Engine!$H$2:$H$2201, Helpers!$B7)} -> 76.53 | E2: =IF(Helpers!$F7 >= 0.05, "Reprice", "Hold") -> Reprice | F2: =Helpers!$C7 -> 0.12635537 | G2: =IF($E2="Hold", $D2, Helpers!$D7) -> 78.975794 | H2: =$G2-$D2 -> 2.4457937 | I2: =IFERROR($H2/$D2, 0) -> 0.031958627 | J2: {=IF($E2="Hold", INDEX(Engine!$K$2:$K$2201, Helpers!$B7), INDEX(Engine!$X$2:$X$2201, Helpers!$B7))} -> 1871.1891 | K2: {=$J2 - INDEX(Engine!$K$2:$K$2201, Helpers!$B7)} -> 34.469053 | L2: =IF($E2="Hold", 0, Helpers!$E7) -> 0.018766635 | M2: {=IF($E2="Hold", INDEX(Engine!$L$2:$L$2201, Helpers!$B7), INDEX(Engine!$Y$2:$Y$2201, Helpers!$B7))} -> 616.39733 | N2: {=$M2 - INDEX(Engine!$L$2:$L$2201, Helpers!$B7)} -> 50.71733 | O2: =IF($E2="Hold", 0, Helpers!$F7) -> 0.08965728 | P2: =IFERROR($M2/$J2, 0) -> 0.32941478 | Q2: {=$P2 - INDEX(Engine!$M$2:$M$2201, Helpers!$B7)} -> 0.021430983 | R2: {=IF($E2="Hold", INDEX(Engine!$R$2:$R$2201, Helpers!$B7), INDEX(Engine!$AF$2:$AF$2201, Helpers!$B7))} -> 358.09401 | S2: {=INDEX(Engine!$R$2:$R$2201, Helpers!$B7) - $R2} -> 537.14101 | T2: =IFERROR($R2/$S2, 0) -> 0.66666667
A3: {=INDEX(Model_Input[SKU], ROW()-1)} -> SKU-1001 | B3: {=INDEX(Engine!$F$2:$F$2201, Helpers!$B8)} -> Raise | C3: {=INDEX(Engine!$G$2:$G$2201, Helpers!$B8)} -> Full | D3: {=INDEX(Engine!$H$2:$H$2201, Helpers!$B8)} -> 53.26 | E3: =IF(Helpers!$F8 >= 0.05, "Reprice", "Hold") -> Reprice | F3: =Helpers!$C8 -> 0.18771631 | G3: =IF($E3="Hold", $D3, Helpers!$D8) -> 55.842395 | H3: =$G3-$D3 -> 2.5823951 | I3: =IFERROR($H3/$D3, 0) -> 0.048486577 | J3: {=IF($E3="Hold", INDEX(Engine!$K$2:$K$2201, Helpers!$B8), INDEX(Engine!$X$2:$X$2201, Helpers!$B8))} -> 1149.9464 | K3: {=$J3 - INDEX(Engine!$K$2:$K$2201, Helpers!$B8)} -> 31.486401 | L3: =IF($E3="Hold", 0, Helpers!$E8) -> 0.028151567 | M3: {=IF($E3="Hold", INDEX(Engine!$L$2:$L$2201, Helpers!$B8), INDEX(Engine!$Y$2:$Y$2201, Helpers!$B8))} -> 395.42941 | N3: {=$M3 - INDEX(Engine!$L$2:$L$2201, Helpers!$B8)} -> 46.409406 | O3: =IF($E3="Hold", 0, Helpers!$F8) -> 0.13297062 | P3: =IFERROR($M3/$J3, 0) -> 0.34386768 | Q3: {=$P3 - INDEX(Engine!$M$2:$M$2201, Helpers!$B8)} -> 0.03181361 | R3: {=IF($E3="Hold", INDEX(Engine!$R$2:$R$2201, Helpers!$B8), INDEX(Engine!$AF$2:$AF$2201, Helpers!$B8))} -> 449.41351 | S3: {=INDEX(Engine!$R$2:$R$2201, Helpers!$B8) - $R3} -> 674.12027 | T3: =IFERROR($R3/$S3, 0) -> 0.66666667
A4: {=INDEX(Model_Input[SKU], ROW()-1)} -> SKU-1004 | B4: {=INDEX(Engine!$F$2:$F$2201, Helpers!$B9)} -> Hold | C4: {=INDEX(Engine!$G$2:$G$2201, Helpers!$B9)} -> Full | D4: {=INDEX(Engine!$H$2:$H$2201, Helpers!$B9)} -> 18.39 | E4: =IF(Helpers!$F9 >= 0.05, "Reprice", "Hold") -> Reprice | F4: =Helpers!$C9 -> 0.14008396 | G4: =IF($E4="Hold", $D4, Helpers!$D9) -> 19.551373 | H4: =$G4-$D4 -> 1.161373 | I4: =IFERROR($H4/$D4, 0) -> 0.063152419 | J4: {=IF($E4="Hold", INDEX(Engine!$K$2:$K$2201, Helpers!$B9), INDEX(Engine!$X$2:$X$2201, Helpers!$B9))} -> 323.97727 | K4: {=$J4 - INDEX(Engine!$K$2:$K$2201, Helpers!$B9)} -> 11.347269 | L4: =IF($E4="Hold", 0, Helpers!$E9) -> 0.03629616 | M4: {=IF($E4="Hold", INDEX(Engine!$L$2:$L$2201, Helpers!$B9), INDEX(Engine!$Y$2:$Y$2201, Helpers!$B9))} -> 187.10441 | N4: {=$M4 - INDEX(Engine!$L$2:$L$2201, Helpers!$B9)} -> 14.894414 | O4: =IF($E4="Hold", 0, Helpers!$F9) -> 0.086489831 | P4: =IFERROR($M4/$J4, 0) -> 0.57752328 | Q4: {=$P4 - INDEX(Engine!$M$2:$M$2201, Helpers!$B9)} -> 0.026680427 | R4: {=IF($E4="Hold", INDEX(Engine!$R$2:$R$2201, Helpers!$B9), INDEX(Engine!$AF$2:$AF$2201, Helpers!$B9))} -> 375.63072 | S4: {=INDEX(Engine!$R$2:$R$2201, Helpers!$B9) - $R4} -> 563.44608 | T4: =IFERROR($R4/$S4, 0) -> 0.66666667
A5: {=INDEX(Model_Input[SKU], ROW()-1)} -> SKU-1005 | B5: {=INDEX(Engine!$F$2:$F$2201, Helpers!$B10)} -> Raise | C5: {=INDEX(Engine!$G$2:$G$2201, Helpers!$B10)} -> Full | D5: {=INDEX(Engine!$H$2:$H$2201, Helpers!$B10)} -> 29.62 | E5: =IF(Helpers!$F10 >= 0.05, "Reprice", "Hold") -> Hold | F5: =Helpers!$C10 -> 0 | G5: =IF($E5="Hold", $D5, Helpers!$D10) -> 29.62 | H5: =$G5-$D5 -> 0 | I5: =IFERROR($H5/$D5, 0) -> 0 | J5: {=IF($E5="Hold", INDEX(Engine!$K$2:$K$2201, Helpers!$B10), INDEX(Engine!$X$2:$X$2201, Helpers!$B10))} -> 1362.52 | K5: {=$J5 - INDEX(Engine!$K$2:$K$2201, Helpers!$B10)} -> 0 | L5: =IF($E5="Hold", 0, Helpers!$E10) -> 0 | M5: {=IF($E5="Hold", INDEX(Engine!$L$2:$L$2201, Helpers!$B10), INDEX(Engine!$Y$2:$Y$2201, Helpers!$B10))} -> 469.2 | N5: {=$M5 - INDEX(Engine!$L$2:$L$2201, Helpers!$B10)} -> 0 | O5: =IF($E5="Hold", 0, Helpers!$F10) -> 0 | P5: =IFERROR($M5/$J5, 0) -> 0.34436192 | Q5: {=$P5 - INDEX(Engine!$M$2:$M$2201, Helpers!$B10)} -> 0 | R5: {=IF($E5="Hold", INDEX(Engine!$R$2:$R$2201, Helpers!$B10), INDEX(Engine!$AF$2:$AF$2201, Helpers!$B10))} -> 927.1195 | S5: {=INDEX(Engine!$R$2:$R$2201, Helpers!$B10) - $R5} -> 0 | T5: =IFERROR($R5/$S5, 0) -> 0
A6: {=INDEX(Model_Input[SKU], ROW()-1)} -> SKU-1006 | B6: {=INDEX(Engine!$F$2:$F$2201, Helpers!$B11)} -> Hold | C6: {=INDEX(Engine!$G$2:$G$2201, Helpers!$B11)} -> Full | D6: {=INDEX(Engine!$H$2:$H$2201, Helpers!$B11)} -> 113.18 | E6: =IF(Helpers!$F11 >= 0.05, "Reprice", "Hold") -> Reprice | F6: =Helpers!$C11 -> 0.089473506 | G6: =IF($E6="Hold", $D6, Helpers!$D11) -> 118.51611 | H6: =$G6-$D6 -> 5.3361073 | I6: =IFERROR($H6/$D6, 0) -> 0.047147087 | J6: {=IF($E6="Hold", INDEX(Engine!$K$2:$K$2201, Helpers!$B11), INDEX(Engine!$X$2:$X$2201, Helpers!$B11))} -> 2790.7448 | K6: {=$J6 - INDEX(Engine!$K$2:$K$2201, Helpers!$B11)} -> 74.424759 | L6: =IF($E6="Hold", 0, Helpers!$E11) -> 0.027399113 | M6: {=IF($E6="Hold", INDEX(Engine!$L$2:$L$2201, Helpers!$B11), INDEX(Engine!$Y$2:$Y$2201, Helpers!$B11))} -> 1872.1612 | N6: {=$M6 - INDEX(Engine!$L$2:$L$2201, Helpers!$B11)} -> 92.081155 | O6: =IF($E6="Hold", 0, Helpers!$F11) -> 0.051728661 | P6: =IFERROR($M6/$J6, 0) -> 0.67084643 | Q6: {=$P6 - INDEX(Engine!$M$2:$M$2201, Helpers!$B11)} -> 0.015518632 | R6: {=IF($E6="Hold", INDEX(Engine!$R$2:$R$2201, Helpers!$B11), INDEX(Engine!$AF$2:$AF$2201, Helpers!$B11))} -> 396.9034 | S6: {=INDEX(Engine!$R$2:$R$2201, Helpers!$B11) - $R6} -> 595.3551 | T6: =IFERROR($R6/$S6, 0) -> 0.66666667
A7: {=INDEX(Model_Input[SKU], ROW()-1)} -> SKU-1009 | B7: {=INDEX(Engine!$F$2:$F$2201, Helpers!$B12)} -> Raise | C7: {=INDEX(Engine!$G$2:$G$2201, Helpers!$B12)} -> Full | D7: {=INDEX(Engine!$H$2:$H$2201, Helpers!$B12)} -> 177.91 | E7: =IF(Helpers!$F12 >= 0.05, "Reprice", "Hold") -> Reprice | F7: =Helpers!$C12 -> 0.22231295 | G7: =IF($E7="Hold", $D7, Helpers!$D12) -> 197.38145 | H7: =$G7-$D7 -> 19.471452 | I7: =IFERROR($H7/$D7, 0) -> 0.10944552 | J7: {=IF($E7="Hold", INDEX(Engine!$K$2:$K$2201, Helpers!$B12), INDEX(Engine!$X$2:$X$2201, Helpers!$B12))} -> 6794.6561 | K7: {=$J7 - INDEX(Engine!$K$2:$K$2201, Helpers!$B12)} -> 389.89606 | L7: =IF($E7="Hold", 0, Helpers!$E12) -> 0.060875983 | M7: {=IF($E7="Hold", INDEX(Engine!$L$2:$L$2201, Helpers!$B12), INDEX(Engine!$Y$2:$Y$2201, Helpers!$B12))} -> 4264.8374 | N7: {=$M7 - INDEX(Engine!$L$2:$L$2201, Helpers!$B12)} -> 505.71744 | O7: =IF($E7="Hold", 0, Helpers!$F12) -> 0.1345308 | P7: =IFERROR($M7/$J7, 0) -> 0.62767525 | Q7: {=$P7 - INDEX(Engine!$M$2:$M$2201, Helpers!$B12)} -> 0.040749276 | R7: {=IF($E7="Hold", INDEX(Engine!$R$2:$R$2201, Helpers!$B12), INDEX(Engine!$AF$2:$AF$2201, Helpers!$B12))} -> 688.8869 | S7: {=INDEX(Engine!$R$2:$R$2201, Helpers!$B12) - $R7} -> 1033.3304 | T7: =IFERROR($R7/$S7, 0) -> 0.66666667
A8: {=INDEX(Model_Input[SKU], ROW()-1)} -> SKU-1010 | B8: {=INDEX(Engine!$F$2:$F$2201, Helpers!$B13)} -> Raise | C8: {=INDEX(Engine!$G$2:$G$2201, Helpers!$B13)} -> Full | D8: {=INDEX(Engine!$H$2:$H$2201, Helpers!$B13)} -> 45.86 | E8: =IF(Helpers!$F13 >= 0.05, "Reprice", "Hold") -> Reprice | F8: =Helpers!$C13 -> 0.38670957 | G8: =IF($E8="Hold", $D8, Helpers!$D13) -> 52.899021 | H8: =$G8-$D8 -> 7.0390209 | I8: =IFERROR($H8/$D8, 0) -> 0.15348934 | J8: {=IF($E8="Hold", INDEX(Engine!$K$2:$K$2201, Helpers!$B13), INDEX(Engine!$X$2:$X$2201, Helpers!$B13))} -> 2085.3524 | K8: {=$J8 - INDEX(Engine!$K$2:$K$2201, Helpers!$B13)} -> 159.23236 | L8: =IF($E8="Hold", 0, Helpers!$E13) -> 0.082670011 | M8: {=IF($E8="Hold", INDEX(Engine!$L$2:$L$2201, Helpers!$B13), INDEX(Engine!$Y$2:$Y$2201, Helpers!$B13))} -> 1104.9427 | N8: {=$M8 - INDEX(Engine!$L$2:$L$2201, Helpers!$B13)} -> 223.36266 | O8: =IF($E8="Hold", 0, Helpers!$F13) -> 0.2533663 | P8: =IFERROR($M8/$J8, 0) -> 0.52985897 | Q8: {=$P8 - INDEX(Engine!$M$2:$M$2201, Helpers!$B13)} -> 0.072161634 | R8: {=IF($E8="Hold", INDEX(Engine!$R$2:$R$2201, Helpers!$B13), INDEX(Engine!$AF$2:$AF$2201, Helpers!$B13))} -> 666.16547 | S8: {=INDEX(Engine!$R$2:$R$2201, Helpers!$B13) - $R8} -> 999.2482 | T8: =IFERROR($R8/$S8, 0) -> 0.66666667
A9: {=INDEX(Model_Input[SKU], ROW()-1)} -> SKU-1011 | B9: {=INDEX(Engine!$F$2:$F$2201, Helpers!$B14)} -> Raise | C9: {=INDEX(Engine!$G$2:$G$2201, Helpers!$B14)} -> Full | D9: {=INDEX(Engine!$H$2:$H$2201, Helpers!$B14)} -> 67.56 | E9: =IF(Helpers!$F14 >= 0.05, "Reprice", "Hold") -> Reprice | F9: =Helpers!$C14 -> 0.21602349 | G9: =IF($E9="Hold", $D9, Helpers!$D14) -> 71.933095 | H9: =$G9-$D9 -> 4.3730955 | I9: =IFERROR($H9/$D9, 0) -> 0.064729063 | J9: {=IF($E9="Hold", INDEX(Engine!$K$2:$K$2201, Helpers!$B14), INDEX(Engine!$X$2:$X$2201, Helpers!$B14))} -> 1541.5539 | K9: {=$J9 - INDEX(Engine!$K$2:$K$2201, Helpers!$B14)} -> 55.233876 | L9: =IF($E9="Hold", 0, Helpers!$E14) -> 0.037161497 | M9: {=IF($E9="Hold", INDEX(Engine!$L$2:$L$2201, Helpers!$B14), INDEX(Engine!$Y$2:$Y$2201, Helpers!$B14))} -> 615.54697 | N9: {=$M9 - INDEX(Engine!$L$2:$L$2201, Helpers!$B14)} -> 79.846973 | O9: =IF($E9="Hold", 0, Helpers!$F14) -> 0.14905166 | P9: =IFERROR($M9/$J9, 0) -> 0.39930293 | Q9: {=$P9 - INDEX(Engine!$M$2:$M$2201, Helpers!$B14)} -> 0.038882559 | R9: {=IF($E9="Hold", INDEX(Engine!$R$2:$R$2201, Helpers!$B14), INDEX(Engine!$AF$2:$AF$2201, Helpers!$B14))} -> 429.27827 | S9: {=INDEX(Engine!$R$2:$R$2201, Helpers!$B14) - $R9} -> 643.91741 | T9: =IFERROR($R9/$S9, 0) -> 0.66666667
A10: {=INDEX(Model_Input[SKU], ROW()-1)} -> SKU-1012 | B10: {=INDEX(Engine!$F$2:$F$2201, Helpers!$B15)} -> Raise | C10: {=INDEX(Engine!$G$2:$G$2201, Helpers!$B15)} -> Full | D10: {=INDEX(Engine!$H$2:$H$2201, Helpers!$B15)} -> 20.37 | E10: =IF(Helpers!$F15 >= 0.05, "Reprice", "Hold") -> Hold | F10: =Helpers!$C15 -> 0 | G10: =IF($E10="Hold", $D10, Helpers!$D15) -> 20.37 | H10: =$G10-$D10 -> 0 | I10: =IFERROR($H10/$D10, 0) -> 0 | J10: {=IF($E10="Hold", INDEX(Engine!$K$2:$K$2201, Helpers!$B15), INDEX(Engine!$X$2:$X$2201, Helpers!$B15))} -> 305.55 | K10: {=$J10 - INDEX(Engine!$K$2:$K$2201, Helpers!$B15)} -> 0 | L10: =IF($E10="Hold", 0, Helpers!$E15) -> 0 | M10: {=IF($E10="Hold", INDEX(Engine!$L$2:$L$2201, Helpers!$B15), INDEX(Engine!$Y$2:$Y$2201, Helpers!$B15))} -> 159.15 | N10: {=$M10 - INDEX(Engine!$L$2:$L$2201, Helpers!$B15)} -> 0 | O10: =IF($E10="Hold", 0, Helpers!$F15) -> 0 | P10: =IFERROR($M10/$J10, 0) -> 0.52086402 | Q10: {=$P10 - INDEX(Engine!$M$2:$M$2201, Helpers!$B15)} -> 0 | R10: {=IF($E10="Hold", INDEX(Engine!$R$2:$R$2201, Helpers!$B15), INDEX(Engine!$AF$2:$AF$2201, Helpers!$B15))} -> 311.63259 | S10: {=INDEX(Engine!$R$2:$R$2201, Helpers!$B15) - $R10} -> 0 | T10: =IFERROR($R10/$S10, 0) -> 0
A11: {=INDEX(Model_Input[SKU], ROW()-1)} -> SKU-1013 | B11: {=INDEX(Engine!$F$2:$F$2201, Helpers!$B16)} -> Raise | C11: {=INDEX(Engine!$G$2:$G$2201, Helpers!$B16)} -> Constrained | D11: {=INDEX(Engine!$H$2:$H$2201, Helpers!$B16)} -> 84.95 | E11: =IF(Helpers!$F16 >= 0.05, "Reprice", "Hold") -> Hold | F11: =Helpers!$C16 -> 0 | G11: =IF($E11="Hold", $D11, Helpers!$D16) -> 84.95 | H11: =$G11-$D11 -> 0 | I11: =IFERROR($H11/$D11, 0) -> 0 | J11: {=IF($E11="Hold", INDEX(Engine!$K$2:$K$2201, Helpers!$B16), INDEX(Engine!$X$2:$X$2201, Helpers!$B16))} -> 3058.2 | K11: {=$J11 - INDEX(Engine!$K$2:$K$2201, Helpers!$B16)} -> 0 | L11: =IF($E11="Hold", 0, Helpers!$E16) -> 0 | M11: {=IF($E11="Hold", INDEX(Engine!$L$2:$L$2201, Helpers!$B16), INDEX(Engine!$Y$2:$Y$2201, Helpers!$B16))} -> 1147.68 | N11: {=$M11 - INDEX(Engine!$L$2:$L$2201, Helpers!$B16)} -> 0 | O11: =IF($E11="Hold", 0, Helpers!$F16) -> 0 | P11: =IFERROR($M11/$J11, 0) -> 0.37527958 | Q11: {=$P11 - INDEX(Engine!$M$2:$M$2201, Helpers!$B16)} -> 0 | R11: {=IF($E11="Hold", INDEX(Engine!$R$2:$R$2201, Helpers!$B16), INDEX(Engine!$AF$2:$AF$2201, Helpers!$B16))} -> 894.15433 | S11: {=INDEX(Engine!$R$2:$R$2201, Helpers!$B16) - $R11} -> 0 | T11: =IFERROR($R11/$S11, 0) -> 0
A12: {=INDEX(Model_Input[SKU], ROW()-1)} -> SKU-1014 | B12: {=INDEX(Engine!$F$2:$F$2201, Helpers!$B17)} -> Raise | C12: {=INDEX(Engine!$G$2:$G$2201, Helpers!$B17)} -> Full | D12: {=INDEX(Engine!$H$2:$H$2201, Helpers!$B17)} -> 143.8 | E12: =IF(Helpers!$F17 >= 0.05, "Reprice", "Hold") -> Reprice | F12: =Helpers!$C17 -> 0.27833494 | G12: =IF($E12="Hold", $D12, Helpers!$D17) -> 163.17672 | H12: =$G12-$D12 -> 19.376717 | I12: =IFERROR($H12/$D12, 0) -> 0.13474768 | J12: {=IF($E12="Hold", INDEX(Engine!$K$2:$K$2201, Helpers!$B17), INDEX(Engine!$X$2:$X$2201, Helpers!$B17))} -> 4477.0677 | K12: {=$J12 - INDEX(Engine!$K$2:$K$2201, Helpers!$B17)} -> 306.86765 | L12: =IF($E12="Hold", 0, Helpers!$E17) -> 0.073585836 | M12: {=IF($E12="Hold", INDEX(Engine!$L$2:$L$2201, Helpers!$B17), INDEX(Engine!$Y$2:$Y$2201, Helpers!$B17))} -> 2771.8626 | N12: {=$M12 - INDEX(Engine!$L$2:$L$2201, Helpers!$B17)} -> 404.01265 | O12: =IF($E12="Hold", 0, Helpers!$F17) -> 0.17062426 | P12: =IFERROR($M12/$J12, 0) -> 0.61912458 | Q12: {=$P12 - INDEX(Engine!$M$2:$M$2201, Helpers!$B17)} -> 0.051322081 | R12: {=IF($E12="Hold", INDEX(Engine!$R$2:$R$2201, Helpers!$B17), INDEX(Engine!$AF$2:$AF$2201, Helpers!$B17))} -> 422.51294 | S12: {=INDEX(Engine!$R$2:$R$2201, Helpers!$B17) - $R12} -> 633.76941 | T12: =IFERROR($R12/$S12, 0) -> 0.66666667
A13: {=INDEX(Model_Input[SKU], ROW()-1)} -> SKU-1017 | B13: {=INDEX(Engine!$F$2:$F$2201, Helpers!$B18)} -> Raise | C13: {=INDEX(Engine!$G$2:$G$2201, Helpers!$B18)} -> Full | D13: {=INDEX(Engine!$H$2:$H$2201, Helpers!$B18)} -> 63.19 | E13: =IF(Helpers!$F18 >= 0.05, "Reprice", "Hold") -> Hold | F13: =Helpers!$C18 -> 0.032641382 | G13: =IF($E13="Hold", $D13, Helpers!$D18) -> 63.19 | H13: =$G13-$D13 -> 0 | I13: =IFERROR($H13/$D13, 0) -> 0 | J13: {=IF($E13="Hold", INDEX(Engine!$K$2:$K$2201, Helpers!$B18), INDEX(Engine!$X$2:$X$2201, Helpers!$B18))} -> 1200.61 | K13: {=$J13 - INDEX(Engine!$K$2:$K$2201, Helpers!$B18)} -> 0 | L13: =IF($E13="Hold", 0, Helpers!$E18) -> 0 | M13: {=IF($E13="Hold", INDEX(Engine!$L$2:$L$2201, Helpers!$B18), INDEX(Engine!$Y$2:$Y$2201, Helpers!$B18))} -> 413.06 | N13: {=$M13 - INDEX(Engine!$L$2:$L$2201, Helpers!$B18)} -> 0 | O13: =IF($E13="Hold", 0, Helpers!$F18) -> 0 | P13: =IFERROR($M13/$J13, 0) -> 0.34404178 | Q13: {=$P13 - INDEX(Engine!$M$2:$M$2201, Helpers!$B18)} -> 0 | R13: {=IF($E13="Hold", INDEX(Engine!$R$2:$R$2201, Helpers!$B18), INDEX(Engine!$AF$2:$AF$2201, Helpers!$B18))} -> 858.15236 | S13: {=INDEX(Engine!$R$2:$R$2201, Helpers!$B18) - $R13} -> 0 | T13: =IFERROR($R13/$S13, 0) -> 0
... A43: {=INDEX(Model_Input[SKU], ROW()-1)} -> SKU-1049 | B43: {=INDEX(Engine!$F$2:$F$2201, Helpers!$B48)} -> Raise | C43: {=INDEX(Engine!$G$2:$G$2201, Helpers!$B48)} -> Full | D43: {=INDEX(Engine!$H$2:$H$2201, Helpers!$B48)} -> 99.75 | E43: =IF(Helpers!$F48 >= 0.05, "Reprice", "Hold") -> Reprice | F43: =Helpers!$C48 -> 0.12768917 | G43: =IF($E43="Hold", $D43, Helpers!$D48) -> 106.16045 | H43: =$G43-$D43 -> 6.4104547 | I43: =IFERROR($H43/$D43, 0) -> 0.06426521 | J43: {=IF($E43="Hold", INDEX(Engine!$K$2:$K$2201, Helpers!$B48), INDEX(Engine!$X$2:$X$2201, Helpers!$B48))} -> 3516.6705 | K43: {=$J43 - INDEX(Engine!$K$2:$K$2201, Helpers!$B48)} -> 125.1705 | L43: =IF($E43="Hold", 0, Helpers!$E48) -> 0.036907119 | M43: {=IF($E43="Hold", INDEX(Engine!$L$2:$L$2201, Helpers!$B48), INDEX(Engine!$Y$2:$Y$2201, Helpers!$B48))} -> 2253.5764 | N43: {=$M43 - INDEX(Engine!$L$2:$L$2201, Helpers!$B48)} -> 158.49638 | O43: =IF($E43="Hold", 0, Helpers!$F48) -> 0.075651706 | P43: =IFERROR($M43/$J43, 0) -> 0.64082671 | Q43: {=$P43 - INDEX(Engine!$M$2:$M$2201, Helpers!$B48)} -> 0.023082347 | R43: {=IF($E43="Hold", INDEX(Engine!$R$2:$R$2201, Helpers!$B48), INDEX(Engine!$AF$2:$AF$2201, Helpers!$B48))} -> 474.35487 | S43: {=INDEX(Engine!$R$2:$R$2201, Helpers!$B48) - $R43} -> 711.53231 | T43: =IFERROR($R43/$S43, 0) -> 0.66666667

Sheet Scenario Results
A1: Selected Scenario | B1: 2 | C1: {=INDEX(Model_Scenarios[SCENARIOS], $B$1)} -> Conservative
A3: SKU | B3: Recommendation | C3: Candidate Type | D3: Current Price | E3: Current Cost/Unit | F3: Current Volume | G3: Current GR | H3: Current GP | I3: Current GP Margin % | J3: V1 Price | K3: LTV Risk | L3: Scenario Name | M3: Best Score | N3: Adjusted Price | O3: Adjusted Difference $ | P3: Adjusted Difference % | Q3: Elasticity | R3: Adjusted Volume Change % | S3: Adjusted Volume | T3: Adjusted GR | U3: Adjusted GR Impact | V3: Adjusted GR Lift | W3: Adjusted COGS | X3: Adjusted COGS Impact | Y3: Adjusted COGS Lift | Z3: Adjusted GP | AA3: GP Impact $ | AB3: GP Lift % | AC3: Adjusted GP Margin % | AD3: GP Margin Impact % | AE3: GP Margin Lift | AF3: Price Aggressiveness | AG3: LTV Protected | AH3: LTV Sacrificed | AI3: LTV Protection-Risk Ratio
A4: {=INDEX(Model_Input[SKU], ROW()-3)} -> SKU-1000 | B4: {=INDEX(Model_Input[Tie-Breaking Recommendation], ROW()-3)} -> Raise | C4: {=INDEX(Model_Input[Candidate Type], ROW()-3)} -> Full | D4: {=INDEX(Model_Input[Current Price], ROW()-3)} -> 76.53 | E4: {=INDEX(Model_Input[Current Cost Per Unit], ROW()-3)} -> 52.96 | F4: {=INDEX(Model_Input[Current Volume], ROW()-3)} -> 24 | G4: {=INDEX(Model_Input[Current Gross Revenue], ROW()-3)} -> 1836.72 | H4: {=INDEX(Model_Input[Current Gross Profit], ROW()-3)} -> 565.68 | I4: {=INDEX(Model_Input[Current Gross Profit Margin %], ROW()-3)} -> 0.3079838 | J4: {=INDEX(Model_Input[V1 Suggested Price], ROW()-3)} -> 80.606323 | K4: {=INDEX(Model_Input[Total LTV at Risk], ROW()-3)} -> 1112.0932 | L4: =$C$1 -> Conservative | M4: =_xlfn.MAXIFS(CHOOSE($B$1, Engine!$AZ$2:$AZ$2201, Engine!$BA$2:$BA$2201, Engine!$BB$2:$BB$2201, Engine!$BC$2:$BC$2201, Engine!$BD$2:$BD$2201), Engine!$E$2:$E$2201, $A4) -> 5.4060316 | N4: {=INDEX(Engine!$T$2:$T$2201, MATCH(1, (Engine!$E$2:$E$2201=$A4) * (CHOOSE($B$1, Engine!$AZ$2:$AZ$2201, Engine!$BA$2:$BA$2201, Engine!$BB$2:$BB$2201, Engine!$BC$2:$BC$2201, Engine!$BD$2:$BD$2201)=$M4), 0))} -> 80.524796 | O4: =$N4-$D4 -> 3.9947964 | P4: =IFERROR($O4/$D4, 0) -> 0.05219909 | Q4: =IF($B4="Reduce", INDEX(Model_Assumptions[Values], 2), INDEX(Model_Assumptions[Values], 1)) -> -0.4 | R4: =$P4*$Q4 -> -0.020879636 | S4: =$F4*(1+$R4) -> 23.498889 | T4: =$S4*$N4 -> 1892.2432 | U4: =$T4-$G4 -> 55.52323 | V4: =IFERROR($U4/$G4, 0) -> 0.030229556 | W4: =$S4*$E4 -> 1244.5011 | X4: =$W4-($F4*$E4) -> -26.538853 | Y4: =IFERROR($X4/($F4*$E4), 0) -> -0.020879636 | Z4: =$T4-$W4 -> 647.74208 | AA4: =$Z4-$H4 -> 82.062083 | AB4: =IFERROR($AA4/$H4, 0) -> 0.14506803 | AC4: =IFERROR($Z4/$T4, 0) -> 0.34231439 | AD4: =$AC4-$I4 -> 0.034330591 | AE4: =$AD4 -> 0.034330591 | AF4: =IFERROR(($N4-$D4)/($J4-$D4), 0) -> 0.98 | AG4: =$K4*(1-$AF4) -> 22.241864 | AH4: =$K4-$AG4 -> 1089.8513 | AI4: =IFERROR($AG4/$AH4, 0) -> 0.020408163
A5: {=INDEX(Model_Input[SKU], ROW()-3)} -> SKU-1001 | B5: {=INDEX(Model_Input[Tie-Breaking Recommendation], ROW()-3)} -> Raise | C5: {=INDEX(Model_Input[Candidate Type], ROW()-3)} -> Full | D5: {=INDEX(Model_Input[Current Price], ROW()-3)} -> 53.26 | E5: {=INDEX(Model_Input[Current Cost Per Unit], ROW()-3)} -> 36.64 | F5: {=INDEX(Model_Input[Current Volume], ROW()-3)} -> 21 | G5: {=INDEX(Model_Input[Current Gross Revenue], ROW()-3)} -> 1118.46 | H5: {=INDEX(Model_Input[Current Gross Profit], ROW()-3)} -> 349.02 | I5: {=INDEX(Model_Input[Current Gross Profit Margin %], ROW()-3)} -> 0.31205407 | J5: {=INDEX(Model_Input[V1 Suggested Price], ROW()-3)} -> 57.563992 | K5: {=INDEX(Model_Input[Total LTV at Risk], ROW()-3)} -> 1487.03 | L5: =$C$1 -> Conservative | M5: =_xlfn.MAXIFS(CHOOSE($B$1, Engine!$AZ$2:$AZ$2201, Engine!$BA$2:$BA$2201, Engine!$BB$2:$BB$2201, Engine!$BC$2:$BC$2201, Engine!$BD$2:$BD$2201), Engine!$E$2:$E$2201, $A5) -> 3.9413985 | N5: {=INDEX(Engine!$T$2:$T$2201, MATCH(1, (Engine!$E$2:$E$2201=$A5) * (CHOOSE($B$1, Engine!$AZ$2:$AZ$2201, Engine!$BA$2:$BA$2201, Engine!$BB$2:$BB$2201, Engine!$BC$2:$BC$2201, Engine!$BD$2:$BD$2201)=$M5), 0))} -> 57.477912 | O5: =$N5-$D5 -> 4.217912 | P5: =IFERROR($O5/$D5, 0) -> 0.079194742 | Q5: =IF($B5="Reduce", INDEX(Model_Assumptions[Values], 2), INDEX(Model_Assumptions[Values], 1)) -> -0.4 | R5: =$P5*$Q5 -> -0.031677897 | S5: =$F5*(1+$R5) -> 20.334764 | T5: =$S5*$N5 -> 1168.7998 | U5: =$T5-$G5 -> 50.339785 | V5: =IFERROR($U5/$G5, 0) -> 0.045008122 | W5: =$S5*$E5 -> 745.06576 | X5: =$W5-($F5*$E5) -> -24.374241 | Y5: =IFERROR($X5/($F5*$E5), 0) -> -0.031677897 | Z5: =$T5-$W5 -> 423.73403 | AA5: =$Z5-$H5 -> 74.714025 | AB5: =IFERROR($AA5/$H5, 0) -> 0.21406803 | AC5: =IFERROR($Z5/$T5, 0) -> 0.36253773 | AD5: =$AC5-$I5 -> 0.05048366 | AE5: =$AD5 -> 0.05048366 | AF5: =IFERROR(($N5-$D5)/($J5-$D5), 0) -> 0.98 | AG5: =$K5*(1-$AF5) -> 29.7406 | AH5: =$K5-$AG5 -> 1457.2894 | AI5: =IFERROR($AG5/$AH5, 0) -> 0.020408163
A6: {=INDEX(Model_Input[SKU], ROW()-3)} -> SKU-1004 | B6: {=INDEX(Model_Input[Tie-Breaking Recommendation], ROW()-3)} -> Hold | C6: {=INDEX(Model_Input[Candidate Type], ROW()-3)} -> Full | D6: {=INDEX(Model_Input[Current Price], ROW()-3)} -> 18.39 | E6: {=INDEX(Model_Input[Current Cost Per Unit], ROW()-3)} -> 8.26 | F6: {=INDEX(Model_Input[Current Volume], ROW()-3)} -> 17 | G6: {=INDEX(Model_Input[Current Gross Revenue], ROW()-3)} -> 312.63 | H6: {=INDEX(Model_Input[Current Gross Profit], ROW()-3)} -> 172.21 | I6: {=INDEX(Model_Input[Current Gross Profit Margin %], ROW()-3)} -> 0.55084285 | J6: {=INDEX(Model_Input[V1 Suggested Price], ROW()-3)} -> 20.325622 | K6: {=INDEX(Model_Input[Total LTV at Risk], ROW()-3)} -> 1216.0707 | L6: =$C$1 -> Conservative | M6: =_xlfn.MAXIFS(CHOOSE($B$1, Engine!$AZ$2:$AZ$2201, Engine!$BA$2:$BA$2201, Engine!$BB$2:$BB$2201, Engine!$BC$2:$BC$2201, Engine!$BD$2:$BD$2201), Engine!$E$2:$E$2201, $A6) -> 3.9620157 | N6: {=INDEX(Engine!$T$2:$T$2201, MATCH(1, (Engine!$E$2:$E$2201=$A6) * (CHOOSE($B$1, Engine!$AZ$2:$AZ$2201, Engine!$BA$2:$BA$2201, Engine!$BB$2:$BB$2201, Engine!$BC$2:$BC$2201, Engine!$BD$2:$BD$2201)=$M6), 0))} -> 20.286909 | O6: =$N6-$D6 -> 1.8969092 | P6: =IFERROR($O6/$D6, 0) -> 0.10314895 | Q6: =IF($B6="Reduce", INDEX(Model_Assumptions[Values], 2), INDEX(Model_Assumptions[Values], 1)) -> -0.4 | R6: =$P6*$Q6 -> -0.041259581 | S6: =$F6*(1+$R6) -> 16.298587 | T6: =$S6*$N6 -> 330.64796 | U6: =$T6-$G6 -> 18.017958 | V6: =IFERROR($U6/$G6, 0) -> 0.057633488 | W6: =$S6*$E6 -> 134.62633 | X6: =$W6-($F6*$E6) -> -5.7936703 | Y6: =IFERROR($X6/($F6*$E6), 0) -> -0.041259581 | Z6: =$T6-$W6 -> 196.02163 | AA6: =$Z6-$H6 -> 23.811628 | AB6: =IFERROR($AA6/$H6, 0) -> 0.13827088 | AC6: =IFERROR($Z6/$T6, 0) -> 0.59284089 | AD6: =$AC6-$I6 -> 0.041998036 | AE6: =$AD6 -> 0.041998036 | AF6: =IFERROR(($N6-$D6)/($J6-$D6), 0) -> 0.98 | AG6: =$K6*(1-$AF6) -> 24.321413 | AH6: =$K6-$AG6 -> 1191.7493 | AI6: =IFERROR($AG6/$AH6, 0) -> 0.020408163
A7: {=INDEX(Model_Input[SKU], ROW()-3)} -> SKU-1005 | B7: {=INDEX(Model_Input[Tie-Breaking Recommendation], ROW()-3)} -> Raise | C7: {=INDEX(Model_Input[Candidate Type], ROW()-3)} -> Full | D7: {=INDEX(Model_Input[Current Price], ROW()-3)} -> 29.62 | E7: {=INDEX(Model_Input[Current Cost Per Unit], ROW()-3)} -> 19.42 | F7: {=INDEX(Model_Input[Current Volume], ROW()-3)} -> 46 | G7: {=INDEX(Model_Input[Current Gross Revenue], ROW()-3)} -> 1362.52 | H7: {=INDEX(Model_Input[Current Gross Profit], ROW()-3)} -> 469.2 | I7: {=INDEX(Model_Input[Current Gross Profit Margin %], ROW()-3)} -> 0.34436192 | J7: {=INDEX(Model_Input[V1 Suggested Price], ROW()-3)} -> 28.258195 | K7: {=INDEX(Model_Input[Total LTV at Risk], ROW()-3)} -> 1171.8239 | L7: =$C$1 -> Conservative | M7: =_xlfn.MAXIFS(CHOOSE($B$1, Engine!$AZ$2:$AZ$2201, Engine!$BA$2:$BA$2201, Engine!$BB$2:$BB$2201, Engine!$BC$2:$BC$2201, Engine!$BD$2:$BD$2201), Engine!$E$2:$E$2201, $A7) -> 5.3284842 | N7: {=INDEX(Engine!$T$2:$T$2201, MATCH(1, (Engine!$E$2:$E$2201=$A7) * (CHOOSE($B$1, Engine!$AZ$2:$AZ$2201, Engine!$BA$2:$BA$2201, Engine!$BB$2:$BB$2201, Engine!$BC$2:$BC$2201, Engine!$BD$2:$BD$2201)=$M7), 0))} -> 29.62 | O7: =$N7-$D7 -> 0 | P7: =IFERROR($O7/$D7, 0) -> 0 | Q7: =IF($B7="Reduce", INDEX(Model_Assumptions[Values], 2), INDEX(Model_Assumptions[Values], 1)) -> -0.4 | R7: =$P7*$Q7 -> 0 | S7: =$F7*(1+$R7) -> 46 | T7: =$S7*$N7 -> 1362.52 | U7: =$T7-$G7 -> 0 | V7: =IFERROR($U7/$G7, 0) -> 0 | W7: =$S7*$E7 -> 893.32 | X7: =$W7-($F7*$E7) -> 0 | Y7: =IFERROR($X7/($F7*$E7), 0) -> 0 | Z7: =$T7-$W7 -> 469.2 | AA7: =$Z7-$H7 -> 0 | AB7: =IFERROR($AA7/$H7, 0) -> 0 | AC7: =IFERROR($Z7/$T7, 0) -> 0.34436192 | AD7: =$AC7-$I7 -> 0 | AE7: =$AD7 -> 0 | AF7: =IFERROR(($N7-$D7)/($J7-$D7), 0) -> 0 | AG7: =$K7*(1-$AF7) -> 1171.8239 | AH7: =$K7-$AG7 -> 0 | AI7: =IFERROR($AG7/$AH7, 0) -> 0
A8: {=INDEX(Model_Input[SKU], ROW()-3)} -> SKU-1006 | B8: {=INDEX(Model_Input[Tie-Breaking Recommendation], ROW()-3)} -> Hold | C8: {=INDEX(Model_Input[Candidate Type], ROW()-3)} -> Full | D8: {=INDEX(Model_Input[Current Price], ROW()-3)} -> 113.18 | E8: {=INDEX(Model_Input[Current Cost Per Unit], ROW()-3)} -> 39.01 | F8: {=INDEX(Model_Input[Current Volume], ROW()-3)} -> 24 | G8: {=INDEX(Model_Input[Current Gross Revenue], ROW()-3)} -> 2716.32 | H8: {=INDEX(Model_Input[Current Gross Profit], ROW()-3)} -> 1780.08 | I8: {=INDEX(Model_Input[Current Gross Profit Margin %], ROW()-3)} -> 0.6553278 | J8: {=INDEX(Model_Input[V1 Suggested Price], ROW()-3)} -> 122.07351 | K8: {=INDEX(Model_Input[Total LTV at Risk], ROW()-3)} -> 1378.1368 | L8: =$C$1 -> Conservative | M8: =_xlfn.MAXIFS(CHOOSE($B$1, Engine!$AZ$2:$AZ$2201, Engine!$BA$2:$BA$2201, Engine!$BB$2:$BB$2201, Engine!$BC$2:$BC$2201, Engine!$BD$2:$BD$2201), Engine!$E$2:$E$2201, $A8) -> 4.0560621 | N8: {=INDEX(Engine!$T$2:$T$2201, MATCH(1, (Engine!$E$2:$E$2201=$A8) * (CHOOSE($B$1, Engine!$AZ$2:$AZ$2201, Engine!$BA$2:$BA$2201, Engine!$BB$2:$BB$2201, Engine!$BC$2:$BC$2201, Engine!$BD$2:$BD$2201)=$M8), 0))} -> 121.89564 | O8: =$N8-$D8 -> 8.715642 | P8: =IFERROR($O8/$D8, 0) -> 0.077006909 | Q8: =IF($B8="Reduce", INDEX(Model_Assumptions[Values], 2), INDEX(Model_Assumptions[Values], 1)) -> -0.4 | R8: =$P8*$Q8 -> -0.030802764 | S8: =$F8*(1+$R8) -> 23.260734 | T8: =$S8*$N8 -> 2835.3821 | U8: =$T8-$G8 -> 119.06206 | V8: =IFERROR($U8/$G8, 0) -> 0.04383212 | W8: =$S8*$E8 -> 907.40122 | X8: =$W8-($F8*$E8) -> -28.83878 | Y8: =IFERROR($X8/($F8*$E8), 0) -> -0.030802764 | Z8: =$T8-$W8 -> 1927.9808 | AA8: =$Z8-$H8 -> 147.90084 | AB8: =IFERROR($AA8/$H8, 0) -> 0.083086627 | AC8: =IFERROR($Z8/$T8, 0) -> 0.67997215 | AD8: =$AC8-$I8 -> 0.024644355 | AE8: =$AD8 -> 0.024644355 | AF8: =IFERROR(($N8-$D8)/($J8-$D8), 0) -> 0.98 | AG8: =$K8*(1-$AF8) -> 27.562736 | AH8: =$K8-$AG8 -> 1350.5741 | AI8: =IFERROR($AG8/$AH8, 0) -> 0.020408163
A9: {=INDEX(Model_Input[SKU], ROW()-3)} -> SKU-1009 | B9: {=INDEX(Model_Input[Tie-Breaking Recommendation], ROW()-3)} -> Raise | C9: {=INDEX(Model_Input[Candidate Type], ROW()-3)} -> Full | D9: {=INDEX(Model_Input[Current Price], ROW()-3)} -> 177.91 | E9: {=INDEX(Model_Input[Current Cost Per Unit], ROW()-3)} -> 73.49 | F9: {=INDEX(Model_Input[Current Volume], ROW()-3)} -> 36 | G9: {=INDEX(Model_Input[Current Gross Revenue], ROW()-3)} -> 6404.76 | H9: {=INDEX(Model_Input[Current Gross Profit], ROW()-3)} -> 3759.12 | I9: {=INDEX(Model_Input[Current Gross Profit Margin %], ROW()-3)} -> 0.58692597 | J9: {=INDEX(Model_Input[V1 Suggested Price], ROW()-3)} -> 210.36242 | K9: {=INDEX(Model_Input[Total LTV at Risk], ROW()-3)} -> 1987.1738 | L9: =$C$1 -> Conservative | M9: =_xlfn.MAXIFS(CHOOSE($B$1, Engine!$AZ$2:$AZ$2201, Engine!$BA$2:$BA$2201, Engine!$BB$2:$BB$2201, Engine!$BC$2:$BC$2201, Engine!$BD$2:$BD$2201), Engine!$E$2:$E$2201, $A9) -> 2.2574333 | N9: {=INDEX(Engine!$T$2:$T$2201, MATCH(1, (Engine!$E$2:$E$2201=$A9) * (CHOOSE($B$1, Engine!$AZ$2:$AZ$2201, Engine!$BA$2:$BA$2201, Engine!$BB$2:$BB$2201, Engine!$BC$2:$BC$2201, Engine!$BD$2:$BD$2201)=$M9), 0))} -> 201.92479 | O9: =$N9-$D9 -> 24.014791 | P9: =IFERROR($O9/$D9, 0) -> 0.13498281 | Q9: =IF($B9="Reduce", INDEX(Model_Assumptions[Values], 2), INDEX(Model_Assumptions[Values], 1)) -> -0.4 | R9: =$P9*$Q9 -> -0.053993123 | S9: =$F9*(1+$R9) -> 34.056248 | T9: =$S9*$N9 -> 6876.8007 | U9: =$T9-$G9 -> 472.04068 | V9: =IFERROR($U9/$G9, 0) -> 0.073701541 | W9: =$S9*$E9 -> 2502.7936 | X9: =$W9-($F9*$E9) -> -142.84637 | Y9: =IFERROR($X9/($F9*$E9), 0) -> -0.053993123 | Z9: =$T9-$W9 -> 4374.007 | AA9: =$Z9-$H9 -> 614.88705 | AB9: =IFERROR($AA9/$H9, 0) -> 0.16357207 | AC9: =IFERROR($Z9/$T9, 0) -> 0.63605261 | AD9: =$AC9-$I9 -> 0.04912664 | AE9: =$AD9 -> 0.04912664 | AF9: =IFERROR(($N9-$D9)/($J9-$D9), 0) -> 0.74 | AG9: =$K9*(1-$AF9) -> 516.66518 | AH9: =$K9-$AG9 -> 1470.5086 | AI9: =IFERROR($AG9/$AH9, 0) -> 0.35135135
A10: {=INDEX(Model_Input[SKU], ROW()-3)} -> SKU-1010 | B10: {=INDEX(Model_Input[Tie-Breaking Recommendation], ROW()-3)} -> Raise | C10: {=INDEX(Model_Input[Candidate Type], ROW()-3)} -> Full | D10: {=INDEX(Model_Input[Current Price], ROW()-3)} -> 45.86 | E10: {=INDEX(Model_Input[Current Cost Per Unit], ROW()-3)} -> 24.87 | F10: {=INDEX(Model_Input[Current Volume], ROW()-3)} -> 42 | G10: {=INDEX(Model_Input[Current Gross Revenue], ROW()-3)} -> 1926.12 | H10: {=INDEX(Model_Input[Current Gross Profit], ROW()-3)} -> 881.58 | I10: {=INDEX(Model_Input[Current Gross Profit Margin %], ROW()-3)} -> 0.45769734 | J10: {=INDEX(Model_Input[V1 Suggested Price], ROW()-3)} -> 57.591702 | K10: {=INDEX(Model_Input[Total LTV at Risk], ROW()-3)} -> 1838.4437 | L10: =$C$1 -> Conservative | M10: =_xlfn.MAXIFS(CHOOSE($B$1, Engine!$AZ$2:$AZ$2201, Engine!$BA$2:$BA$2201, Engine!$BB$2:$BB$2201, Engine!$BC$2:$BC$2201, Engine!$BD$2:$BD$2201), Engine!$E$2:$E$2201, $A10) -> 2.3527087 | N10: {=INDEX(Engine!$T$2:$T$2201, MATCH(1, (Engine!$E$2:$E$2201=$A10) * (CHOOSE($B$1, Engine!$AZ$2:$AZ$2201, Engine!$BA$2:$BA$2201, Engine!$BB$2:$BB$2201, Engine!$BC$2:$BC$2201, Engine!$BD$2:$BD$2201)=$M10), 0))} -> 50.552681 | O10: =$N10-$D10 -> 4.6926806 | P10: =IFERROR($O10/$D10, 0) -> 0.10232622 | Q10: =IF($B10="Reduce", INDEX(Model_Assumptions[Values], 2), INDEX(Model_Assumptions[Values], 1)) -> -0.4 | R10: =$P10*$Q10 -> -0.04093049 | S10: =$F10*(1+$R10) -> 40.280919 | T10: =$S10*$N10 -> 2036.3085 | U10: =$T10-$G10 -> 110.18846 | V10: =IFERROR($U10/$G10, 0) -> 0.057207472 | W10: =$S10*$E10 -> 1001.7865 | X10: =$W10-($F10*$E10) -> -42.753534 | Y10: =IFERROR($X10/($F10*$E10), 0) -> -0.04093049 | Z10: =$T10-$W10 -> 1034.522 | AA10: =$Z10-$H10 -> 152.94199 | AB10: =IFERROR($AA10/$H10, 0) -> 0.17348623 | AC10: =IFERROR($Z10/$T10, 0) -> 0.50803796 | AD10: =$AC10-$I10 -> 0.050340618 | AE10: =$AD10 -> 0.050340618 | AF10: =IFERROR(($N10-$D10)/($J10-$D10), 0) -> 0.4 | AG10: =$K10*(1-$AF10) -> 1103.0662 | AH10: =$K10-$AG10 -> 735.37746 | AI10: =IFERROR($AG10/$AH10, 0) -> 1.5
A11: {=INDEX(Model_Input[SKU], ROW()-3)} -> SKU-1011 | B11: {=INDEX(Model_Input[Tie-Breaking Recommendation], ROW()-3)} -> Raise | C11: {=INDEX(Model_Input[Candidate Type], ROW()-3)} -> Full | D11: {=INDEX(Model_Input[Current Price], ROW()-3)} -> 67.56 | E11: {=INDEX(Model_Input[Current Cost Per Unit], ROW()-3)} -> 43.21 | F11: {=INDEX(Model_Input[Current Volume], ROW()-3)} -> 22 | G11: {=INDEX(Model_Input[Current Gross Revenue], ROW()-3)} -> 1486.32 | H11: {=INDEX(Model_Input[Current Gross Profit], ROW()-3)} -> 535.7 | I11: {=INDEX(Model_Input[Current Gross Profit Margin %], ROW()-3)} -> 0.36042037 | J11: {=INDEX(Model_Input[V1 Suggested Price], ROW()-3)} -> 74.848492 | K11: {=INDEX(Model_Input[Total LTV at Risk], ROW()-3)} -> 1511.5432 | L11: =$C$1 -> Conservative | M11: =_xlfn.MAXIFS(CHOOSE($B$1, Engine!$AZ$2:$AZ$2201, Engine!$BA$2:$BA$2201, Engine!$BB$2:$BB$2201, Engine!$BC$2:$BC$2201, Engine!$BD$2:$BD$2201), Engine!$E$2:$E$2201, $A11) -> 3.3544814 | N11: {=INDEX(Engine!$T$2:$T$2201, MATCH(1, (Engine!$E$2:$E$2201=$A11) * (CHOOSE($B$1, Engine!$AZ$2:$AZ$2201, Engine!$BA$2:$BA$2201, Engine!$BB$2:$BB$2201, Engine!$BC$2:$BC$2201, Engine!$BD$2:$BD$2201)=$M11), 0))} -> 74.702723 | O11: =$N11-$D11 -> 7.1427226 | P11: =IFERROR($O11/$D11, 0) -> 0.10572414 | Q11: =IF($B11="Reduce", INDEX(Model_Assumptions[Values], 2), INDEX(Model_Assumptions[Values], 1)) -> -0.4 | R11: =$P11*$Q11 -> -0.042289654 | S11: =$F11*(1+$R11) -> 21.069628 | T11: =$S11*$N11 -> 1573.9585 | U11: =$T11-$G11 -> 87.638547 | V11: =IFERROR($U11/$G11, 0) -> 0.058963444 | W11: =$S11*$E11 -> 910.41861 | X11: =$W11-($F11*$E11) -> -40.201391 | Y11: =IFERROR($X11/($F11*$E11), 0) -> -0.042289654 | Z11: =$T11-$W11 -> 663.53994 | AA11: =$Z11-$H11 -> 127.83994 | AB11: =IFERROR($AA11/$H11, 0) -> 0.23864091 | AC11: =IFERROR($Z11/$T11, 0) -> 0.42157396 | AD11: =$AC11-$I11 -> 0.061153593 | AE11: =$AD11 -> 0.061153593 | AF11: =IFERROR(($N11-$D11)/($J11-$D11), 0) -> 0.98 | AG11: =$K11*(1-$AF11) -> 30.230864 | AH11: =$K11-$AG11 -> 1481.3123 | AI11: =IFERROR($AG11/$AH11, 0) -> 0.020408163
A12: {=INDEX(Model_Input[SKU], ROW()-3)} -> SKU-1012 | B12: {=INDEX(Model_Input[Tie-Breaking Recommendation], ROW()-3)} -> Raise | C12: {=INDEX(Model_Input[Candidate Type], ROW()-3)} -> Full | D12: {=INDEX(Model_Input[Current Price], ROW()-3)} -> 20.37 | E12: {=INDEX(Model_Input[Current Cost Per Unit], ROW()-3)} -> 9.76 | F12: {=INDEX(Model_Input[Current Volume], ROW()-3)} -> 15 | G12: {=INDEX(Model_Input[Current Gross Revenue], ROW()-3)} -> 305.55 | H12: {=INDEX(Model_Input[Current Gross Profit], ROW()-3)} -> 159.15 | I12: {=INDEX(Model_Input[Current Gross Profit Margin %], ROW()-3)} -> 0.52086402 | J12: {=INDEX(Model_Input[V1 Suggested Price], ROW()-3)} -> 20.226862 | K12: {=INDEX(Model_Input[Total LTV at Risk], ROW()-3)} -> 464.13364 | L12: =$C$1 -> Conservative | M12: =_xlfn.MAXIFS(CHOOSE($B$1, Engine!$AZ$2:$AZ$2201, Engine!$BA$2:$BA$2201, Engine!$BB$2:$BB$2201, Engine!$BC$2:$BC$2201, Engine!$BD$2:$BD$2201), Engine!$E$2:$E$2201, $A12) -> 5.3473478 | N12: {=INDEX(Engine!$T$2:$T$2201, MATCH(1, (Engine!$E$2:$E$2201=$A12) * (CHOOSE($B$1, Engine!$AZ$2:$AZ$2201, Engine!$BA$2:$BA$2201, Engine!$BB$2:$BB$2201, Engine!$BC$2:$BC$2201, Engine!$BD$2:$BD$2201)=$M12), 0))} -> 20.37 | O12: =$N12-$D12 -> 0 | P12: =IFERROR($O12/$D12, 0) -> 0 | Q12: =IF($B12="Reduce", INDEX(Model_Assumptions[Values], 2), INDEX(Model_Assumptions[Values], 1)) -> -0.4 | R12: =$P12*$Q12 -> 0 | S12: =$F12*(1+$R12) -> 15 | T12: =$S12*$N12 -> 305.55 | U12: =$T12-$G12 -> 0 | V12: =IFERROR($U12/$G12, 0) -> 0 | W12: =$S12*$E12 -> 146.4 | X12: =$W12-($F12*$E12) -> 0 | Y12: =IFERROR($X12/($F12*$E12), 0) -> 0 | Z12: =$T12-$W12 -> 159.15 | AA12: =$Z12-$H12 -> 0 | AB12: =IFERROR($AA12/$H12, 0) -> 0 | AC12: =IFERROR($Z12/$T12, 0) -> 0.52086402 | AD12: =$AC12-$I12 -> 0 | AE12: =$AD12 -> 0 | AF12: =IFERROR(($N12-$D12)/($J12-$D12), 0) -> 0 | AG12: =$K12*(1-$AF12) -> 464.13364 | AH12: =$K12-$AG12 -> 0 | AI12: =IFERROR($AG12/$AH12, 0) -> 0
A13: {=INDEX(Model_Input[SKU], ROW()-3)} -> SKU-1013 | B13: {=INDEX(Model_Input[Tie-Breaking Recommendation], ROW()-3)} -> Raise | C13: {=INDEX(Model_Input[Candidate Type], ROW()-3)} -> Constrained | D13: {=INDEX(Model_Input[Current Price], ROW()-3)} -> 84.95 | E13: {=INDEX(Model_Input[Current Cost Per Unit], ROW()-3)} -> 53.07 | F13: {=INDEX(Model_Input[Current Volume], ROW()-3)} -> 36 | G13: {=INDEX(Model_Input[Current Gross Revenue], ROW()-3)} -> 3058.2 | H13: {=INDEX(Model_Input[Current Gross Profit], ROW()-3)} -> 1147.68 | I13: {=INDEX(Model_Input[Current Gross Profit Margin %], ROW()-3)} -> 0.37527958 | J13: {=INDEX(Model_Input[V1 Suggested Price], ROW()-3)} -> 84.95 | K13: {=INDEX(Model_Input[Total LTV at Risk], ROW()-3)} -> 1153.7475 | L13: =$C$1 -> Conservative | M13: =_xlfn.MAXIFS(CHOOSE($B$1, Engine!$AZ$2:$AZ$2201, Engine!$BA$2:$BA$2201, Engine!$BB$2:$BB$2201, Engine!$BC$2:$BC$2201, Engine!$BD$2:$BD$2201), Engine!$E$2:$E$2201, $A13) -> 2.8045227 | N13: {=INDEX(Engine!$T$2:$T$2201, MATCH(1, (Engine!$E$2:$E$2201=$A13) * (CHOOSE($B$1, Engine!$AZ$2:$AZ$2201, Engine!$BA$2:$BA$2201, Engine!$BB$2:$BB$2201, Engine!$BC$2:$BC$2201, Engine!$BD$2:$BD$2201)=$M13), 0))} -> 84.95 | O13: =$N13-$D13 -> 0 | P13: =IFERROR($O13/$D13, 0) -> 0 | Q13: =IF($B13="Reduce", INDEX(Model_Assumptions[Values], 2), INDEX(Model_Assumptions[Values], 1)) -> -0.4 | R13: =$P13*$Q13 -> 0 | S13: =$F13*(1+$R13) -> 36 | T13: =$S13*$N13 -> 3058.2 | U13: =$T13-$G13 -> 0 | V13: =IFERROR($U13/$G13, 0) -> 0 | W13: =$S13*$E13 -> 1910.52 | X13: =$W13-($F13*$E13) -> 0 | Y13: =IFERROR($X13/($F13*$E13), 0) -> 0 | Z13: =$T13-$W13 -> 1147.68 | AA13: =$Z13-$H13 -> 0 | AB13: =IFERROR($AA13/$H13, 0) -> 0 | AC13: =IFERROR($Z13/$T13, 0) -> 0.37527958 | AD13: =$AC13-$I13 -> 0 | AE13: =$AD13 -> 0 | AF13: =IFERROR(($N13-$D13)/($J13-$D13), 0) -> 0 | AG13: =$K13*(1-$AF13) -> 1153.7475 | AH13: =$K13-$AG13 -> 0 | AI13: =IFERROR($AG13/$AH13, 0) -> 0
A14: {=INDEX(Model_Input[SKU], ROW()-3)} -> SKU-1014 | B14: {=INDEX(Model_Input[Tie-Breaking Recommendation], ROW()-3)} -> Raise | C14: {=INDEX(Model_Input[Candidate Type], ROW()-3)} -> Full | D14: {=INDEX(Model_Input[Current Price], ROW()-3)} -> 143.8 | E14: {=INDEX(Model_Input[Current Cost Per Unit], ROW()-3)} -> 62.15 | F14: {=INDEX(Model_Input[Current Volume], ROW()-3)} -> 29 | G14: {=INDEX(Model_Input[Current Gross Revenue], ROW()-3)} -> 4170.2 | H14: {=INDEX(Model_Input[Current Gross Profit], ROW()-3)} -> 2367.85 | I14: {=INDEX(Model_Input[Current Gross Profit Margin %], ROW()-3)} -> 0.5678025 | J14: {=INDEX(Model_Input[V1 Suggested Price], ROW()-3)} -> 176.09453 | K14: {=INDEX(Model_Input[Total LTV at Risk], ROW()-3)} -> 1207.1798 | L14: =$C$1 -> Conservative | M14: =_xlfn.MAXIFS(CHOOSE($B$1, Engine!$AZ$2:$AZ$2201, Engine!$BA$2:$BA$2201, Engine!$BB$2:$BB$2201, Engine!$BC$2:$BC$2201, Engine!$BD$2:$BD$2201), Engine!$E$2:$E$2201, $A14) -> 3.3829177 | N14: {=INDEX(Engine!$T$2:$T$2201, MATCH(1, (Engine!$E$2:$E$2201=$A14) * (CHOOSE($B$1, Engine!$AZ$2:$AZ$2201, Engine!$BA$2:$BA$2201, Engine!$BB$2:$BB$2201, Engine!$BC$2:$BC$2201, Engine!$BD$2:$BD$2201)=$M14), 0))} -> 175.44864 | O14: =$N14-$D14 -> 31.648638 | P14: =IFERROR($O14/$D14, 0) -> 0.22008789 | Q14: =IF($B14="Reduce", INDEX(Model_Assumptions[Values], 2), INDEX(Model_Assumptions[Values], 1)) -> -0.4 | R14: =$P14*$Q14 -> -0.088035154 | S14: =$F14*(1+$R14) -> 26.446981 | T14: =$S14*$N14 -> 4640.0867 | U14: =$T14-$G14 -> 469.88671 | V14: =IFERROR($U14/$G14, 0) -> 0.11267726 | W14: =$S14*$E14 -> 1643.6798 | X14: =$W14-($F14*$E14) -> -158.67016 | Y14: =IFERROR($X14/($F14*$E14), 0) -> -0.088035154 | Z14: =$T14-$W14 -> 2996.4069 | AA14: =$Z14-$H14 -> 628.55687 | AB14: =IFERROR($AA14/$H14, 0) -> 0.26545468 | AC14: =IFERROR($Z14/$T14, 0) -> 0.64576528 | AD14: =$AC14-$I14 -> 0.077962772 | AE14: =$AD14 -> 0.077962772 | AF14: =IFERROR(($N14-$D14)/($J14-$D14), 0) -> 0.98 | AG14: =$K14*(1-$AF14) -> 24.143596 | AH14: =$K14-$AG14 -> 1183.0362 | AI14: =IFERROR($AG14/$AH14, 0) -> 0.020408163
A15: {=INDEX(Model_Input[SKU], ROW()-3)} -> SKU-1017 | B15: {=INDEX(Model_Input[Tie-Breaking Recommendation], ROW()-3)} -> Raise | C15: {=INDEX(Model_Input[Candidate Type], ROW()-3)} -> Full | D15: {=INDEX(Model_Input[Current Price], ROW()-3)} -> 63.19 | E15: {=INDEX(Model_Input[Current Cost Per Unit], ROW()-3)} -> 41.45 | F15: {=INDEX(Model_Input[Current Volume], ROW()-3)} -> 19 | G15: {=INDEX(Model_Input[Current Gross Revenue], ROW()-3)} -> 1200.61 | H15: {=INDEX(Model_Input[Current Gross Profit], ROW()-3)} -> 413.06 | I15: {=INDEX(Model_Input[Current Gross Profit Margin %], ROW()-3)} -> 0.34404178 | J15: {=INDEX(Model_Input[V1 Suggested Price], ROW()-3)} -> 64.147136 | K15: {=INDEX(Model_Input[Total LTV at Risk], ROW()-3)} -> 1170.2078 | L15: =$C$1 -> Conservative | M15: =_xlfn.MAXIFS(CHOOSE($B$1, Engine!$AZ$2:$AZ$2201, Engine!$BA$2:$BA$2201, Engine!$BB$2:$BB$2201, Engine!$BC$2:$BC$2201, Engine!$BD$2:$BD$2201), Engine!$E$2:$E$2201, $A15) -> 2.3147725 | N15: {=INDEX(Engine!$T$2:$T$2201, MATCH(1, (Engine!$E$2:$E$2201=$A15) * (CHOOSE($B$1, Engine!$AZ$2:$AZ$2201, Engine!$BA$2:$BA$2201, Engine!$BB$2:$BB$2201, Engine!$BC$2:$BC$2201, Engine!$BD$2:$BD$2201)=$M15), 0))} -> 64.127993 | O15: =$N15-$D15 -> 0.9379932 | P15: =IFERROR($O15/$D15, 0) -> 0.014844013 | Q15: =IF($B15="Reduce", INDEX(Model_Assumptions[Values], 2), INDEX(Model_Assumptions[Values], 1)) -> -0.4 | R15: =$P15*$Q15 -> -0.0059376053 | S15: =$F15*(1+$R15) -> 18.887185 | T15: =$S15*$N15 -> 1211.1973 | U15: =$T15-$G15 -> 10.587303 | V15: =IFERROR($U15/$G15, 0) -> 0.0088182701 | W15: =$S15*$E15 -> 782.87384 | X15: =$W15-($F15*$E15) -> -4.6761611 | Y15: =IFERROR($X15/($F15*$E15), 0) -> -0.0059376053 | Z15: =$T15-$W15 -> 428.32346 | AA15: =$Z15-$H15 -> 15.263464 | AB15: =IFERROR($AA15/$H15, 0) -> 0.036952173 | AC15: =IFERROR($Z15/$T15, 0) -> 0.35363641 | AD15: =$AC15-$I15 -> 0.0095946298 | AE15: =$AD15 -> 0.0095946298 | AF15: =IFERROR(($N15-$D15)/($J15-$D15), 0) -> 0.98 | AG15: =$K15*(1-$AF15) -> 23.404155 | AH15: =$K15-$AG15 -> 1146.8036 | AI15: =IFERROR($AG15/$AH15, 0) -> 0.020408163
... A45: {=INDEX(Model_Input[SKU], ROW()-3)} -> SKU-1049 | B45: {=INDEX(Model_Input[Tie-Breaking Recommendation], ROW()-3)} -> Raise | C45: {=INDEX(Model_Input[Candidate Type], ROW()-3)} -> Full | D45: {=INDEX(Model_Input[Current Price], ROW()-3)} -> 99.75 | E45: {=INDEX(Model_Input[Current Cost Per Unit], ROW()-3)} -> 38.13 | F45: {=INDEX(Model_Input[Current Volume], ROW()-3)} -> 34 | G45: {=INDEX(Model_Input[Current Gross Revenue], ROW()-3)} -> 3391.5 | H45: {=INDEX(Model_Input[Current Gross Profit], ROW()-3)} -> 2095.08 | I45: {=INDEX(Model_Input[Current Gross Profit Margin %], ROW()-3)} -> 0.61774436 | J45: {=INDEX(Model_Input[V1 Suggested Price], ROW()-3)} -> 110.43409 | K45: {=INDEX(Model_Input[Total LTV at Risk], ROW()-3)} -> 1533.9834 | L45: =$C$1 -> Conservative | M45: =_xlfn.MAXIFS(CHOOSE($B$1, Engine!$AZ$2:$AZ$2201, Engine!$BA$2:$BA$2201, Engine!$BB$2:$BB$2201, Engine!$BC$2:$BC$2201, Engine!$BD$2:$BD$2201), Engine!$E$2:$E$2201, $A45) -> 2.4263733 | N45: {=INDEX(Engine!$T$2:$T$2201, MATCH(1, (Engine!$E$2:$E$2201=$A45) * (CHOOSE($B$1, Engine!$AZ$2:$AZ$2201, Engine!$BA$2:$BA$2201, Engine!$BB$2:$BB$2201, Engine!$BC$2:$BC$2201, Engine!$BD$2:$BD$2201)=$M45), 0))} -> 110.22041 | O45: =$N45-$D45 -> 10.470409 | P45: =IFERROR($O45/$D45, 0) -> 0.10496651 | Q45: =IF($B45="Reduce", INDEX(Model_Assumptions[Values], 2), INDEX(Model_Assumptions[Values], 1)) -> -0.4 | R45: =$P45*$Q45 -> -0.041986604 | S45: =$F45*(1+$R45) -> 32.572455 | T45: =$S45*$N45 -> 3590.1494 | U45: =$T45-$G45 -> 198.64938 | V45: =IFERROR($U45/$G45, 0) -> 0.058572719 | W45: =$S45*$E45 -> 1241.9877 | X45: =$W45-($F45*$E45) -> -54.432273 | Y45: =IFERROR($X45/($F45*$E45), 0) -> -0.041986604 | Z45: =$T45-$W45 -> 2348.1616 | AA45: =$Z45-$H45 -> 253.08165 | AB45: =IFERROR($AA45/$H45, 0) -> 0.12079808 | AC45: =IFERROR($Z45/$T45, 0) -> 0.65405681 | AD45: =$AC45-$I45 -> 0.036312449 | AE45: =$AD45 -> 0.036312449 | AF45: =IFERROR(($N45-$D45)/($J45-$D45), 0) -> 0.98 | AG45: =$K45*(1-$AF45) -> 30.679668 | AH45: =$K45-$AG45 -> 1503.3037 | AI45: =IFERROR($AG45/$AH45, 0) -> 0.020408163
P48: =MIN(P4:P47) -> 0
P49: =MAX(P4:P47) -> 0.24971705

Sheet Helpers
A1: SELECTION ASSUMPTIONS | B1: Values
A2: Best Outcome GR Weight | B2: 1
A3: Best Outcome GP Weight | B3: 1.2
A4: Minimum Viable LTV Protection % | B4: 0.4
A6: SKU | B6: Best Row | C6: Best Combined Score | D6: Best Test Price | E6: GR Lift % at Best | F6: GP Lift % at Best | G6: LTV Protection % at Best
A7: {=INDEX(Model_Input[SKU], ROW()-6)} -> SKU-1000 | B7: {=_xlfn.LET( _xlpm.sku, $A7, _xlpm.matches, (Engine!$E$2:$E$2201=_xlpm.sku), _xlpm.gr_lift, IFERROR(IF(_xlpm.matches, Engine!$Z$2:$Z$2201 / Engine!$K$2:$K$2201, -999), -999), _xlpm.gp_lift, IFERROR(IF(_xlpm.matches, Engine!$AA$2:$AA$2201 / Engine!$L$2:$L$2201, -999), -999), _xlpm.ltv_prot, IFERROR(IF(_xlpm.matches, Engine!$AF$2:$AF$2201 / Engine!$R$2:$R$2201, 0), 0), _xlpm.combined, IF(_xlpm.ltv_prot >= INDEX(Selection_Assumptions[Values],3), INDEX(Selection_Assumptions[Values],1)*_xlpm.gr_lift + INDEX(Selection_Assumptions[Values],2)*_xlpm.gp_lift, -999), MATCH(MAX(_xlpm.combined), IF(_xlpm.matches, _xlpm.combined), 0) )} -> 31 | C7: {=_xlfn.LET( _xlpm.sku, $A7, _xlpm.matches, (Engine!$E$2:$E$2201=_xlpm.sku), _xlpm.gr_lift, IFERROR(IF(_xlpm.matches, Engine!$Z$2:$Z$2201 / Engine!$K$2:$K$2201, -999), -999), _xlpm.gp_lift, IFERROR(IF(_xlpm.matches, Engine!$AA$2:$AA$2201 / Engine!$L$2:$L$2201, -999), -999), _xlpm.ltv_prot, IFERROR(IF(_xlpm.matches, Engine!$AF$2:$AF$2201 / Engine!$R$2:$R$2201, 0), 0), _xlpm.combined, IF(_xlpm.ltv_prot >= INDEX(Selection_Assumptions[Values],3), INDEX(Selection_Assumptions[Values],1)*_xlpm.gr_lift + INDEX(Selection_Assumptions[Values],2)*_xlpm.gp_lift, -999), MAX(_xlpm.combined) )} -> 0.12635537 | D7: {=INDEX(Engine!$T$2:$T$2201, $B7)} -> 78.975794 | E7: {=IFERROR(INDEX(Engine!$Z$2:$Z$2201, $B7) / INDEX(Engine!$K$2:$K$2201, $B7), 0)} -> 0.018766635 | F7: {=IFERROR(INDEX(Engine!$AA$2:$AA$2201, $B7) / INDEX(Engine!$L$2:$L$2201, $B7), 0)} -> 0.08965728 | G7: {=IFERROR(INDEX(Engine!$AF$2:$AF$2201, $B7) / INDEX(Engine!$R$2:$R$2201, $B7), 0)} -> 0.4
A8: {=INDEX(Model_Input[SKU], ROW()-6)} -> SKU-1001 | B8: {=_xlfn.LET( _xlpm.sku, $A8, _xlpm.matches, (Engine!$E$2:$E$2201=_xlpm.sku), _xlpm.gr_lift, IFERROR(IF(_xlpm.matches, Engine!$Z$2:$Z$2201 / Engine!$K$2:$K$2201, -999), -999), _xlpm.gp_lift, IFERROR(IF(_xlpm.matches, Engine!$AA$2:$AA$2201 / Engine!$L$2:$L$2201, -999), -999), _xlpm.ltv_prot, IFERROR(IF(_xlpm.matches, Engine!$AF$2:$AF$2201 / Engine!$R$2:$R$2201, 0), 0), _xlpm.combined, IF(_xlpm.ltv_prot >= INDEX(Selection_Assumptions[Values],3), INDEX(Selection_Assumptions[Values],1)*_xlpm.gr_lift + INDEX(Selection_Assumptions[Values],2)*_xlpm.gp_lift, -999), MATCH(MAX(_xlpm.combined), IF(_xlpm.matches, _xlpm.combined), 0) )} -> 81 | C8: {=_xlfn.LET( _xlpm.sku, $A8, _xlpm.matches, (Engine!$E$2:$E$2201=_xlpm.sku), _xlpm.gr_lift, IFERROR(IF(_xlpm.matches, Engine!$Z$2:$Z$2201 / Engine!$K$2:$K$2201, -999), -999), _xlpm.gp_lift, IFERROR(IF(_xlpm.matches, Engine!$AA$2:$AA$2201 / Engine!$L$2:$L$2201, -999), -999), _xlpm.ltv_prot, IFERROR(IF(_xlpm.matches, Engine!$AF$2:$AF$2201 / Engine!$R$2:$R$2201, 0), 0), _xlpm.combined, IF(_xlpm.ltv_prot >= INDEX(Selection_Assumptions[Values],3), INDEX(Selection_Assumptions[Values],1)*_xlpm.gr_lift + INDEX(Selection_Assumptions[Values],2)*_xlpm.gp_lift, -999), MAX(_xlpm.combined) )} -> 0.18771631 | D8: {=INDEX(Engine!$T$2:$T$2201, $B8)} -> 55.842395 | E8: {=IFERROR(INDEX(Engine!$Z$2:$Z$2201, $B8) / INDEX(Engine!$K$2:$K$2201, $B8), 0)} -> 0.028151567 | F8: {=IFERROR(INDEX(Engine!$AA$2:$AA$2201, $B8) / INDEX(Engine!$L$2:$L$2201, $B8), 0)} -> 0.13297062 | G8: {=IFERROR(INDEX(Engine!$AF$2:$AF$2201, $B8) / INDEX(Engine!$R$2:$R$2201, $B8), 0)} -> 0.4
A9: {=INDEX(Model_Input[SKU], ROW()-6)} -> SKU-1004 | B9: {=_xlfn.LET( _xlpm.sku, $A9, _xlpm.matches, (Engine!$E$2:$E$2201=_xlpm.sku), _xlpm.gr_lift, IFERROR(IF(_xlpm.matches, Engine!$Z$2:$Z$2201 / Engine!$K$2:$K$2201, -999), -999), _xlpm.gp_lift, IFERROR(IF(_xlpm.matches, Engine!$AA$2:$AA$2201 / Engine!$L$2:$L$2201, -999), -999), _xlpm.ltv_prot, IFERROR(IF(_xlpm.matches, Engine!$AF$2:$AF$2201 / Engine!$R$2:$R$2201, 0), 0), _xlpm.combined, IF(_xlpm.ltv_prot >= INDEX(Selection_Assumptions[Values],3), INDEX(Selection_Assumptions[Values],1)*_xlpm.gr_lift + INDEX(Selection_Assumptions[Values],2)*_xlpm.gp_lift, -999), MATCH(MAX(_xlpm.combined), IF(_xlpm.matches, _xlpm.combined), 0) )} -> 131 | C9: {=_xlfn.LET( _xlpm.sku, $A9, _xlpm.matches, (Engine!$E$2:$E$2201=_xlpm.sku), _xlpm.gr_lift, IFERROR(IF(_xlpm.matches, Engine!$Z$2:$Z$2201 / Engine!$K$2:$K$2201, -999), -999), _xlpm.gp_lift, IFERROR(IF(_xlpm.matches, Engine!$AA$2:$AA$2201 / Engine!$L$2:$L$2201, -999), -999), _xlpm.ltv_prot, IFERROR(IF(_xlpm.matches, Engine!$AF$2:$AF$2201 / Engine!$R$2:$R$2201, 0), 0), _xlpm.combined, IF(_xlpm.ltv_prot >= INDEX(Selection_Assumptions[Values],3), INDEX(Selection_Assumptions[Values],1)*_xlpm.gr_lift + INDEX(Selection_Assumptions[Values],2)*_xlpm.gp_lift, -999), MAX(_xlpm.combined) )} -> 0.14008396 | D9: {=INDEX(Engine!$T$2:$T$2201, $B9)} -> 19.551373 | E9: {=IFERROR(INDEX(Engine!$Z$2:$Z$2201, $B9) / INDEX(Engine!$K$2:$K$2201, $B9), 0)} -> 0.03629616 | F9: {=IFERROR(INDEX(Engine!$AA$2:$AA$2201, $B9) / INDEX(Engine!$L$2:$L$2201, $B9), 0)} -> 0.086489831 | G9: {=IFERROR(INDEX(Engine!$AF$2:$AF$2201, $B9) / INDEX(Engine!$R$2:$R$2201, $B9), 0)} -> 0.4
A10: {=INDEX(Model_Input[SKU], ROW()-6)} -> SKU-1005 | B10: {=_xlfn.LET( _xlpm.sku, $A10, _xlpm.matches, (Engine!$E$2:$E$2201=_xlpm.sku), _xlpm.gr_lift, IFERROR(IF(_xlpm.matches, Engine!$Z$2:$Z$2201 / Engine!$K$2:$K$2201, -999), -999), _xlpm.gp_lift, IFERROR(IF(_xlpm.matches, Engine!$AA$2:$AA$2201 / Engine!$L$2:$L$2201, -999), -999), _xlpm.ltv_prot, IFERROR(IF(_xlpm.matches, Engine!$AF$2:$AF$2201 / Engine!$R$2:$R$2201, 0), 0), _xlpm.combined, IF(_xlpm.ltv_prot >= INDEX(Selection_Assumptions[Values],3), INDEX(Selection_Assumptions[Values],1)*_xlpm.gr_lift + INDEX(Selection_Assumptions[Values],2)*_xlpm.gp_lift, -999), MATCH(MAX(_xlpm.combined), IF(_xlpm.matches, _xlpm.combined), 0) )} -> 151 | C10: {=_xlfn.LET( _xlpm.sku, $A10, _xlpm.matches, (Engine!$E$2:$E$2201=_xlpm.sku), _xlpm.gr_lift, IFERROR(IF(_xlpm.matches, Engine!$Z$2:$Z$2201 / Engine!$K$2:$K$2201, -999), -999), _xlpm.gp_lift, IFERROR(IF(_xlpm.matches, Engine!$AA$2:$AA$2201 / Engine!$L$2:$L$2201, -999), -999), _xlpm.ltv_prot, IFERROR(IF(_xlpm.matches, Engine!$AF$2:$AF$2201 / Engine!$R$2:$R$2201, 0), 0), _xlpm.combined, IF(_xlpm.ltv_prot >= INDEX(Selection_Assumptions[Values],3), INDEX(Selection_Assumptions[Values],1)*_xlpm.gr_lift + INDEX(Selection_Assumptions[Values],2)*_xlpm.gp_lift, -999), MAX(_xlpm.combined) )} -> 0 | D10: {=INDEX(Engine!$T$2:$T$2201, $B10)} -> 29.62 | E10: {=IFERROR(INDEX(Engine!$Z$2:$Z$2201, $B10) / INDEX(Engine!$K$2:$K$2201, $B10), 0)} -> 0 | F10: {=IFERROR(INDEX(Engine!$AA$2:$AA$2201, $B10) / INDEX(Engine!$L$2:$L$2201, $B10), 0)} -> 0 | G10: {=IFERROR(INDEX(Engine!$AF$2:$AF$2201, $B10) / INDEX(Engine!$R$2:$R$2201, $B10), 0)} -> 1
A11: {=INDEX(Model_Input[SKU], ROW()-6)} -> SKU-1006 | B11: {=_xlfn.LET( _xlpm.sku, $A11, _xlpm.matches, (Engine!$E$2:$E$2201=_xlpm.sku), _xlpm.gr_lift, IFERROR(IF(_xlpm.matches, Engine!$Z$2:$Z$2201 / Engine!$K$2:$K$2201, -999), -999), _xlpm.gp_lift, IFERROR(IF(_xlpm.matches, Engine!$AA$2:$AA$2201 / Engine!$L$2:$L$2201, -999), -999), _xlpm.ltv_prot, IFERROR(IF(_xlpm.matches, Engine!$AF$2:$AF$2201 / Engine!$R$2:$R$2201, 0), 0), _xlpm.combined, IF(_xlpm.ltv_prot >= INDEX(Selection_Assumptions[Values],3), INDEX(Selection_Assumptions[Values],1)*_xlpm.gr_lift + INDEX(Selection_Assumptions[Values],2)*_xlpm.gp_lift, -999), MATCH(MAX(_xlpm.combined), IF(_xlpm.matches, _xlpm.combined), 0) )} -> 231 | C11: {=_xlfn.LET( _xlpm.sku, $A11, _xlpm.matches, (Engine!$E$2:$E$2201=_xlpm.sku), _xlpm.gr_lift, IFERROR(IF(_xlpm.matches, Engine!$Z$2:$Z$2201 / Engine!$K$2:$K$2201, -999), -999), _xlpm.gp_lift, IFERROR(IF(_xlpm.matches, Engine!$AA$2:$AA$2201 / Engine!$L$2:$L$2201, -999), -999), _xlpm.ltv_prot, IFERROR(IF(_xlpm.matches, Engine!$AF$2:$AF$2201 / Engine!$R$2:$R$2201, 0), 0), _xlpm.combined, IF(_xlpm.ltv_prot >= INDEX(Selection_Assumptions[Values],3), INDEX(Selection_Assumptions[Values],1)*_xlpm.gr_lift + INDEX(Selection_Assumptions[Values],2)*_xlpm.gp_lift, -999), MAX(_xlpm.combined) )} -> 0.089473506 | D11: {=INDEX(Engine!$T$2:$T$2201, $B11)} -> 118.51611 | E11: {=IFERROR(INDEX(Engine!$Z$2:$Z$2201, $B11) / INDEX(Engine!$K$2:$K$2201, $B11), 0)} -> 0.027399113 | F11: {=IFERROR(INDEX(Engine!$AA$2:$AA$2201, $B11) / INDEX(Engine!$L$2:$L$2201, $B11), 0)} -> 0.051728661 | G11: {=IFERROR(INDEX(Engine!$AF$2:$AF$2201, $B11) / INDEX(Engine!$R$2:$R$2201, $B11), 0)} -> 0.4
A12: {=INDEX(Model_Input[SKU], ROW()-6)} -> SKU-1009 | B12: {=_xlfn.LET( _xlpm.sku, $A12, _xlpm.matches, (Engine!$E$2:$E$2201=_xlpm.sku), _xlpm.gr_lift, IFERROR(IF(_xlpm.matches, Engine!$Z$2:$Z$2201 / Engine!$K$2:$K$2201, -999), -999), _xlpm.gp_lift, IFERROR(IF(_xlpm.matches, Engine!$AA$2:$AA$2201 / Engine!$L$2:$L$2201, -999), -999), _xlpm.ltv_prot, IFERROR(IF(_xlpm.matches, Engine!$AF$2:$AF$2201 / Engine!$R$2:$R$2201, 0), 0), _xlpm.combined, IF(_xlpm.ltv_prot >= INDEX(Selection_Assumptions[Values],3), INDEX(Selection_Assumptions[Values],1)*_xlpm.gr_lift + INDEX(Selection_Assumptions[Values],2)*_xlpm.gp_lift, -999), MATCH(MAX(_xlpm.combined), IF(_xlpm.matches, _xlpm.combined), 0) )} -> 281 | C12: {=_xlfn.LET( _xlpm.sku, $A12, _xlpm.matches, (Engine!$E$2:$E$2201=_xlpm.sku), _xlpm.gr_lift, IFERROR(IF(_xlpm.matches, Engine!$Z$2:$Z$2201 / Engine!$K$2:$K$2201, -999), -999), _xlpm.gp_lift, IFERROR(IF(_xlpm.matches, Engine!$AA$2:$AA$2201 / Engine!$L$2:$L$2201, -999), -999), _xlpm.ltv_prot, IFERROR(IF(_xlpm.matches, Engine!$AF$2:$AF$2201 / Engine!$R$2:$R$2201, 0), 0), _xlpm.combined, IF(_xlpm.ltv_prot >= INDEX(Selection_Assumptions[Values],3), INDEX(Selection_Assumptions[Values],1)*_xlpm.gr_lift + INDEX(Selection_Assumptions[Values],2)*_xlpm.gp_lift, -999), MAX(_xlpm.combined) )} -> 0.22231295 | D12: {=INDEX(Engine!$T$2:$T$2201, $B12)} -> 197.38145 | E12: {=IFERROR(INDEX(Engine!$Z$2:$Z$2201, $B12) / INDEX(Engine!$K$2:$K$2201, $B12), 0)} -> 0.060875983 | F12: {=IFERROR(INDEX(Engine!$AA$2:$AA$2201, $B12) / INDEX(Engine!$L$2:$L$2201, $B12), 0)} -> 0.1345308 | G12: {=IFERROR(INDEX(Engine!$AF$2:$AF$2201, $B12) / INDEX(Engine!$R$2:$R$2201, $B12), 0)} -> 0.4
A13: {=INDEX(Model_Input[SKU], ROW()-6)} -> SKU-1010 | B13: {=_xlfn.LET( _xlpm.sku, $A13, _xlpm.matches, (Engine!$E$2:$E$2201=_xlpm.sku), _xlpm.gr_lift, IFERROR(IF(_xlpm.matches, Engine!$Z$2:$Z$2201 / Engine!$K$2:$K$2201, -999), -999), _xlpm.gp_lift, IFERROR(IF(_xlpm.matches, Engine!$AA$2:$AA$2201 / Engine!$L$2:$L$2201, -999), -999), _xlpm.ltv_prot, IFERROR(IF(_xlpm.matches, Engine!$AF$2:$AF$2201 / Engine!$R$2:$R$2201, 0), 0), _xlpm.combined, IF(_xlpm.ltv_prot >= INDEX(Selection_Assumptions[Values],3), INDEX(Selection_Assumptions[Values],1)*_xlpm.gr_lift + INDEX(Selection_Assumptions[Values],2)*_xlpm.gp_lift, -999), MATCH(MAX(_xlpm.combined), IF(_xlpm.matches, _xlpm.combined), 0) )} -> 331 | C13: {=_xlfn.LET( _xlpm.sku, $A13, _xlpm.matches, (Engine!$E$2:$E$2201=_xlpm.sku), _xlpm.gr_lift, IFERROR(IF(_xlpm.matches, Engine!$Z$2:$Z$2201 / Engine!$K$2:$K$2201, -999), -999), _xlpm.gp_lift, IFERROR(IF(_xlpm.matches, Engine!$AA$2:$AA$2201 / Engine!$L$2:$L$2201, -999), -999), _xlpm.ltv_prot, IFERROR(IF(_xlpm.matches, Engine!$AF$2:$AF$2201 / Engine!$R$2:$R$2201, 0), 0), _xlpm.combined, IF(_xlpm.ltv_prot >= INDEX(Selection_Assumptions[Values],3), INDEX(Selection_Assumptions[Values],1)*_xlpm.gr_lift + INDEX(Selection_Assumptions[Values],2)*_xlpm.gp_lift, -999), MAX(_xlpm.combined) )} -> 0.38670957 | D13: {=INDEX(Engine!$T$2:$T$2201, $B13)} -> 52.899021 | E13: {=IFERROR(INDEX(Engine!$Z$2:$Z$2201, $B13) / INDEX(Engine!$K$2:$K$2201, $B13), 0)} -> 0.082670011 | F13: {=IFERROR(INDEX(Engine!$AA$2:$AA$2201, $B13) / INDEX(Engine!$L$2:$L$2201, $B13), 0)} -> 0.2533663 | G13: {=IFERROR(INDEX(Engine!$AF$2:$AF$2201, $B13) / INDEX(Engine!$R$2:$R$2201, $B13), 0)} -> 0.4
A14: {=INDEX(Model_Input[SKU], ROW()-6)} -> SKU-1011 | B14: {=_xlfn.LET( _xlpm.sku, $A14, _xlpm.matches, (Engine!$E$2:$E$2201=_xlpm.sku), _xlpm.gr_lift, IFERROR(IF(_xlpm.matches, Engine!$Z$2:$Z$2201 / Engine!$K$2:$K$2201, -999), -999), _xlpm.gp_lift, IFERROR(IF(_xlpm.matches, Engine!$AA$2:$AA$2201 / Engine!$L$2:$L$2201, -999), -999), _xlpm.ltv_prot, IFERROR(IF(_xlpm.matches, Engine!$AF$2:$AF$2201 / Engine!$R$2:$R$2201, 0), 0), _xlpm.combined, IF(_xlpm.ltv_prot >= INDEX(Selection_Assumptions[Values],3), INDEX(Selection_Assumptions[Values],1)*_xlpm.gr_lift + INDEX(Selection_Assumptions[Values],2)*_xlpm.gp_lift, -999), MATCH(MAX(_xlpm.combined), IF(_xlpm.matches, _xlpm.combined), 0) )} -> 381 | C14: {=_xlfn.LET( _xlpm.sku, $A14, _xlpm.matches, (Engine!$E$2:$E$2201=_xlpm.sku), _xlpm.gr_lift, IFERROR(IF(_xlpm.matches, Engine!$Z$2:$Z$2201 / Engine!$K$2:$K$2201, -999), -999), _xlpm.gp_lift, IFERROR(IF(_xlpm.matches, Engine!$AA$2:$AA$2201 / Engine!$L$2:$L$2201, -999), -999), _xlpm.ltv_prot, IFERROR(IF(_xlpm.matches, Engine!$AF$2:$AF$2201 / Engine!$R$2:$R$2201, 0), 0), _xlpm.combined, IF(_xlpm.ltv_prot >= INDEX(Selection_Assumptions[Values],3), INDEX(Selection_Assumptions[Values],1)*_xlpm.gr_lift + INDEX(Selection_Assumptions[Values],2)*_xlpm.gp_lift, -999), MAX(_xlpm.combined) )} -> 0.21602349 | D14: {=INDEX(Engine!$T$2:$T$2201, $B14)} -> 71.933095 | E14: {=IFERROR(INDEX(Engine!$Z$2:$Z$2201, $B14) / INDEX(Engine!$K$2:$K$2201, $B14), 0)} -> 0.037161497 | F14: {=IFERROR(INDEX(Engine!$AA$2:$AA$2201, $B14) / INDEX(Engine!$L$2:$L$2201, $B14), 0)} -> 0.14905166 | G14: {=IFERROR(INDEX(Engine!$AF$2:$AF$2201, $B14) / INDEX(Engine!$R$2:$R$2201, $B14), 0)} -> 0.4
A15: {=INDEX(Model_Input[SKU], ROW()-6)} -> SKU-1012 | B15: {=_xlfn.LET( _xlpm.sku, $A15, _xlpm.matches, (Engine!$E$2:$E$2201=_xlpm.sku), _xlpm.gr_lift, IFERROR(IF(_xlpm.matches, Engine!$Z$2:$Z$2201 / Engine!$K$2:$K$2201, -999), -999), _xlpm.gp_lift, IFERROR(IF(_xlpm.matches, Engine!$AA$2:$AA$2201 / Engine!$L$2:$L$2201, -999), -999), _xlpm.ltv_prot, IFERROR(IF(_xlpm.matches, Engine!$AF$2:$AF$2201 / Engine!$R$2:$R$2201, 0), 0), _xlpm.combined, IF(_xlpm.ltv_prot >= INDEX(Selection_Assumptions[Values],3), INDEX(Selection_Assumptions[Values],1)*_xlpm.gr_lift + INDEX(Selection_Assumptions[Values],2)*_xlpm.gp_lift, -999), MATCH(MAX(_xlpm.combined), IF(_xlpm.matches, _xlpm.combined), 0) )} -> 401 | C15: {=_xlfn.LET( _xlpm.sku, $A15, _xlpm.matches, (Engine!$E$2:$E$2201=_xlpm.sku), _xlpm.gr_lift, IFERROR(IF(_xlpm.matches, Engine!$Z$2:$Z$2201 / Engine!$K$2:$K$2201, -999), -999), _xlpm.gp_lift, IFERROR(IF(_xlpm.matches, Engine!$AA$2:$AA$2201 / Engine!$L$2:$L$2201, -999), -999), _xlpm.ltv_prot, IFERROR(IF(_xlpm.matches, Engine!$AF$2:$AF$2201 / Engine!$R$2:$R$2201, 0), 0), _xlpm.combined, IF(_xlpm.ltv_prot >= INDEX(Selection_Assumptions[Values],3), INDEX(Selection_Assumptions[Values],1)*_xlpm.gr_lift + INDEX(Selection_Assumptions[Values],2)*_xlpm.gp_lift, -999), MAX(_xlpm.combined) )} -> 0 | D15: {=INDEX(Engine!$T$2:$T$2201, $B15)} -> 20.37 | E15: {=IFERROR(INDEX(Engine!$Z$2:$Z$2201, $B15) / INDEX(Engine!$K$2:$K$2201, $B15), 0)} -> 0 | F15: {=IFERROR(INDEX(Engine!$AA$2:$AA$2201, $B15) / INDEX(Engine!$L$2:$L$2201, $B15), 0)} -> 0 | G15: {=IFERROR(INDEX(Engine!$AF$2:$AF$2201, $B15) / INDEX(Engine!$R$2:$R$2201, $B15), 0)} -> 1
A16: {=INDEX(Model_Input[SKU], ROW()-6)} -> SKU-1013 | B16: {=_xlfn.LET( _xlpm.sku, $A16, _xlpm.matches, (Engine!$E$2:$E$2201=_xlpm.sku), _xlpm.gr_lift, IFERROR(IF(_xlpm.matches, Engine!$Z$2:$Z$2201 / Engine!$K$2:$K$2201, -999), -999), _xlpm.gp_lift, IFERROR(IF(_xlpm.matches, Engine!$AA$2:$AA$2201 / Engine!$L$2:$L$2201, -999), -999), _xlpm.ltv_prot, IFERROR(IF(_xlpm.matches, Engine!$AF$2:$AF$2201 / Engine!$R$2:$R$2201, 0), 0), _xlpm.combined, IF(_xlpm.ltv_prot >= INDEX(Selection_Assumptions[Values],3), INDEX(Selection_Assumptions[Values],1)*_xlpm.gr_lift + INDEX(Selection_Assumptions[Values],2)*_xlpm.gp_lift, -999), MATCH(MAX(_xlpm.combined), IF(_xlpm.matches, _xlpm.combined), 0) )} -> 451 | C16: {=_xlfn.LET( _xlpm.sku, $A16, _xlpm.matches, (Engine!$E$2:$E$2201=_xlpm.sku), _xlpm.gr_lift, IFERROR(IF(_xlpm.matches, Engine!$Z$2:$Z$2201 / Engine!$K$2:$K$2201, -999), -999), _xlpm.gp_lift, IFERROR(IF(_xlpm.matches, Engine!$AA$2:$AA$2201 / Engine!$L$2:$L$2201, -999), -999), _xlpm.ltv_prot, IFERROR(IF(_xlpm.matches, Engine!$AF$2:$AF$2201 / Engine!$R$2:$R$2201, 0), 0), _xlpm.combined, IF(_xlpm.ltv_prot >= INDEX(Selection_Assumptions[Values],3), INDEX(Selection_Assumptions[Values],1)*_xlpm.gr_lift + INDEX(Selection_Assumptions[Values],2)*_xlpm.gp_lift, -999), MAX(_xlpm.combined) )} -> 0 | D16: {=INDEX(Engine!$T$2:$T$2201, $B16)} -> 84.95 | E16: {=IFERROR(INDEX(Engine!$Z$2:$Z$2201, $B16) / INDEX(Engine!$K$2:$K$2201, $B16), 0)} -> 0 | F16: {=IFERROR(INDEX(Engine!$AA$2:$AA$2201, $B16) / INDEX(Engine!$L$2:$L$2201, $B16), 0)} -> 0 | G16: {=IFERROR(INDEX(Engine!$AF$2:$AF$2201, $B16) / INDEX(Engine!$R$2:$R$2201, $B16), 0)} -> 1
A17: {=INDEX(Model_Input[SKU], ROW()-6)} -> SKU-1014 | B17: {=_xlfn.LET( _xlpm.sku, $A17, _xlpm.matches, (Engine!$E$2:$E$2201=_xlpm.sku), _xlpm.gr_lift, IFERROR(IF(_xlpm.matches, Engine!$Z$2:$Z$2201 / Engine!$K$2:$K$2201, -999), -999), _xlpm.gp_lift, IFERROR(IF(_xlpm.matches, Engine!$AA$2:$AA$2201 / Engine!$L$2:$L$2201, -999), -999), _xlpm.ltv_prot, IFERROR(IF(_xlpm.matches, Engine!$AF$2:$AF$2201 / Engine!$R$2:$R$2201, 0), 0), _xlpm.combined, IF(_xlpm.ltv_prot >= INDEX(Selection_Assumptions[Values],3), INDEX(Selection_Assumptions[Values],1)*_xlpm.gr_lift + INDEX(Selection_Assumptions[Values],2)*_xlpm.gp_lift, -999), MATCH(MAX(_xlpm.combined), IF(_xlpm.matches, _xlpm.combined), 0) )} -> 531 | C17: {=_xlfn.LET( _xlpm.sku, $A17, _xlpm.matches, (Engine!$E$2:$E$2201=_xlpm.sku), _xlpm.gr_lift, IFERROR(IF(_xlpm.matches, Engine!$Z$2:$Z$2201 / Engine!$K$2:$K$2201, -999), -999), _xlpm.gp_lift, IFERROR(IF(_xlpm.matches, Engine!$AA$2:$AA$2201 / Engine!$L$2:$L$2201, -999), -999), _xlpm.ltv_prot, IFERROR(IF(_xlpm.matches, Engine!$AF$2:$AF$2201 / Engine!$R$2:$R$2201, 0), 0), _xlpm.combined, IF(_xlpm.ltv_prot >= INDEX(Selection_Assumptions[Values],3), INDEX(Selection_Assumptions[Values],1)*_xlpm.gr_lift + INDEX(Selection_Assumptions[Values],2)*_xlpm.gp_lift, -999), MAX(_xlpm.combined) )} -> 0.27833494 | D17: {=INDEX(Engine!$T$2:$T$2201, $B17)} -> 163.17672 | E17: {=IFERROR(INDEX(Engine!$Z$2:$Z$2201, $B17) / INDEX(Engine!$K$2:$K$2201, $B17), 0)} -> 0.073585836 | F17: {=IFERROR(INDEX(Engine!$AA$2:$AA$2201, $B17) / INDEX(Engine!$L$2:$L$2201, $B17), 0)} -> 0.17062426 | G17: {=IFERROR(INDEX(Engine!$AF$2:$AF$2201, $B17) / INDEX(Engine!$R$2:$R$2201, $B17), 0)} -> 0.4
A18: {=INDEX(Model_Input[SKU], ROW()-6)} -> SKU-1017 | B18: {=_xlfn.LET( _xlpm.sku, $A18, _xlpm.matches, (Engine!$E$2:$E$2201=_xlpm.sku), _xlpm.gr_lift, IFERROR(IF(_xlpm.matches, Engine!$Z$2:$Z$2201 / Engine!$K$2:$K$2201, -999), -999), _xlpm.gp_lift, IFERROR(IF(_xlpm.matches, Engine!$AA$2:$AA$2201 / Engine!$L$2:$L$2201, -999), -999), _xlpm.ltv_prot, IFERROR(IF(_xlpm.matches, Engine!$AF$2:$AF$2201 / Engine!$R$2:$R$2201, 0), 0), _xlpm.combined, IF(_xlpm.ltv_prot >= INDEX(Selection_Assumptions[Values],3), INDEX(Selection_Assumptions[Values],1)*_xlpm.gr_lift + INDEX(Selection_Assumptions[Values],2)*_xlpm.gp_lift, -999), MATCH(MAX(_xlpm.combined), IF(_xlpm.matches, _xlpm.combined), 0) )} -> 581 | C18: {=_xlfn.LET( _xlpm.sku, $A18, _xlpm.matches, (Engine!$E$2:$E$2201=_xlpm.sku), _xlpm.gr_lift, IFERROR(IF(_xlpm.matches, Engine!$Z$2:$Z$2201 / Engine!$K$2:$K$2201, -999), -999), _xlpm.gp_lift, IFERROR(IF(_xlpm.matches, Engine!$AA$2:$AA$2201 / Engine!$L$2:$L$2201, -999), -999), _xlpm.ltv_prot, IFERROR(IF(_xlpm.matches, Engine!$AF$2:$AF$2201 / Engine!$R$2:$R$2201, 0), 0), _xlpm.combined, IF(_xlpm.ltv_prot >= INDEX(Selection_Assumptions[Values],3), INDEX(Selection_Assumptions[Values],1)*_xlpm.gr_lift + INDEX(Selection_Assumptions[Values],2)*_xlpm.gp_lift, -999), MAX(_xlpm.combined) )} -> 0.032641382 | D18: {=INDEX(Engine!$T$2:$T$2201, $B18)} -> 63.764282 | E18: {=IFERROR(INDEX(Engine!$Z$2:$Z$2201, $B18) / INDEX(Engine!$K$2:$K$2201, $B18), 0)} -> 0.0054198649 | F18: {=IFERROR(INDEX(Engine!$AA$2:$AA$2201, $B18) / INDEX(Engine!$L$2:$L$2201, $B18), 0)} -> 0.022684597 | G18: {=IFERROR(INDEX(Engine!$AF$2:$AF$2201, $B18) / INDEX(Engine!$R$2:$R$2201, $B18), 0)} -> 0.4
... A48: {=INDEX(Model_Input[SKU], ROW()-6)} -> SKU-1049 | B48: {=_xlfn.LET( _xlpm.sku, $A48, _xlpm.matches, (Engine!$E$2:$E$2201=_xlpm.sku), _xlpm.gr_lift, IFERROR(IF(_xlpm.matches, Engine!$Z$2:$Z$2201 / Engine!$K$2:$K$2201, -999), -999), _xlpm.gp_lift, IFERROR(IF(_xlpm.matches, Engine!$AA$2:$AA$2201 / Engine!$L$2:$L$2201, -999), -999), _xlpm.ltv_prot, IFERROR(IF(_xlpm.matches, Engine!$AF$2:$AF$2201 / Engine!$R$2:$R$2201, 0), 0), _xlpm.combined, IF(_xlpm.ltv_prot >= INDEX(Selection_Assumptions[Values],3), INDEX(Selection_Assumptions[Values],1)*_xlpm.gr_lift + INDEX(Selection_Assumptions[Values],2)*_xlpm.gp_lift, -999), MATCH(MAX(_xlpm.combined), IF(_xlpm.matches, _xlpm.combined), 0) )} -> 2081 | C48: {=_xlfn.LET( _xlpm.sku, $A48, _xlpm.matches, (Engine!$E$2:$E$2201=_xlpm.sku), _xlpm.gr_lift, IFERROR(IF(_xlpm.matches, Engine!$Z$2:$Z$2201 / Engine!$K$2:$K$2201, -999), -999), _xlpm.gp_lift, IFERROR(IF(_xlpm.matches, Engine!$AA$2:$AA$2201 / Engine!$L$2:$L$2201, -999), -999), _xlpm.ltv_prot, IFERROR(IF(_xlpm.matches, Engine!$AF$2:$AF$2201 / Engine!$R$2:$R$2201, 0), 0), _xlpm.combined, IF(_xlpm.ltv_prot >= INDEX(Selection_Assumptions[Values],3), INDEX(Selection_Assumptions[Values],1)*_xlpm.gr_lift + INDEX(Selection_Assumptions[Values],2)*_xlpm.gp_lift, -999), MAX(_xlpm.combined) )} -> 0.12768917 | D48: {=INDEX(Engine!$T$2:$T$2201, $B48)} -> 106.16045 | E48: {=IFERROR(INDEX(Engine!$Z$2:$Z$2201, $B48) / INDEX(Engine!$K$2:$K$2201, $B48), 0)} -> 0.036907119 | F48: {=IFERROR(INDEX(Engine!$AA$2:$AA$2201, $B48) / INDEX(Engine!$L$2:$L$2201, $B48), 0)} -> 0.075651706 | G48: {=IFERROR(INDEX(Engine!$AF$2:$AF$2201, $B48) / INDEX(Engine!$R$2:$R$2201, $B48), 0)} -> 0.4

Sheet Engine
A1: Row Index | B1: SKU Index | C1: Step # | D1: Step % | E1: SKU | F1: Recommendation | G1: Candidate Type | H1: Current Price | I1: Current Cost/Unit | J1: Current Volume | K1: Current GR | L1: Current GP | M1: Current GP Margin % | N1: V1 Price | O1: V1 GR Impact | P1: V1 GP Impact | Q1: Total LTV at Risk | R1: Risk-Adjusted LTV at Risk | S1: Effective Max % | T1: Test Price | U1: Price Change % | V1: Elasticity | W1: New Volume | X1: New GR | Y1: New GP | Z1: New GR Impact | AA1: New GP Impact | AB1: New GP Margin % | AC1: GP Margin Lift % | AD1: GR Margin Lift % | AE1: Price Aggressiveness | AF1: LTV Protected | AG1: Norm GR | AH1: Norm GP | AI1: Norm LTV | AJ1: Raw Penalty LTV | AK1: Raw Penalty GR Margin | AL1: Raw Penalty GP Margin | AM1: Raw Penalty Margin Floor | AN1: Mean Penalty LTV | AO1: Stdev Penalty LTV | AP1: Z-Score Penalty LTV | AQ1: Mean Penalty GR Margin | AR1: Stdev Penalty GR Margin | AS1: Z-Score Penalty GR Margin | AT1: Mean Penalty GP Margin | AU1: Stdev Penalty GP Margin | AV1: Z-Score Penalty GP Margin | AW1: Mean Penalty Floor | AX1: Stdev Penalty Floor | AY1: Z-Score Penalty Floor | AZ1: Score S1 (Aggressive Conservative) | BA1: Score S2 (Conservative) | BB1: Score S3 (Balanced) | BC1: Score S4 (Growth) | BD1: Score S5 (Aggressive Growth)
A2: {=_xlfn.SEQUENCE(COUNTA(Model_Input[SKU]) * 50)} -> 1 | B2: {=INT((_xlfn.ANCHORARRAY(A2)-1)/50)+1} -> 1 | C2: {=MOD(_xlfn.ANCHORARRAY($A2)-1,50)+1} -> 1 | D2: {=(_xlfn.ANCHORARRAY($C2)-1)*'Model Assumptions'!$B$9} -> 0 | E2: {=IFERROR(INDEX(Model_Input[SKU],_xlfn.ANCHORARRAY( $B2)), "")} -> SKU-1000 | F2: {=INDEX(Model_Input[Tie-Breaking Recommendation],_xlfn.ANCHORARRAY( Engine!$B2))} -> Raise | G2: {=INDEX(Model_Input[Candidate Type],_xlfn.ANCHORARRAY( Engine!$B2))} -> Full | H2: {=INDEX(Model_Input[Current Price],_xlfn.ANCHORARRAY(Engine!$B2))} -> 76.53 | I2: {=INDEX(Model_Input[Current Cost Per Unit],_xlfn.ANCHORARRAY(Engine!$B2))} -> 52.96 | J2: {=INDEX(Model_Input[Current Volume],_xlfn.ANCHORARRAY(Engine!$B2))} -> 24 | K2: {=INDEX(Model_Input[Current Gross Revenue],_xlfn.ANCHORARRAY(Engine!$B2))} -> 1836.72 | L2: {=INDEX(Model_Input[Current Gross Profit],_xlfn.ANCHORARRAY(Engine!$B2))} -> 565.68 | M2: {=INDEX(Model_Input[Current Gross Profit Margin %],_xlfn.ANCHORARRAY(Engine!$B2))} -> 0.3079838 | N2: {=INDEX(Model_Input[V1 Suggested Price],_xlfn.ANCHORARRAY(Engine!$B2))} -> 80.606323 | O2: {=INDEX(Model_Input[V1 Gross Revenue Impact],_xlfn.ANCHORARRAY(Engine!$B2))} -> 17.225425 | P2: {=INDEX(Model_Input[V1 Gross Profit Impact $],_xlfn.ANCHORARRAY(Engine!$B2))} -> 70.185425 | Q2: {=INDEX(Model_Input[Total LTV at Risk],_xlfn.ANCHORARRAY(Engine!$B2))} -> 1112.0932 | R2: {=_xlfn.LET( _xlpm.sku_idx,_xlfn.ANCHORARRAY( $B2), _xlpm.ltv,_xlfn.ANCHORARRAY( $Q2), _xlpm.pct_crit, INDEX(Model_Input[% Critical], _xlpm.sku_idx), _xlpm.pct_high, INDEX(Model_Input[% High], _xlpm.sku_idx), _xlpm.pct_med, INDEX(Model_Input[% Medium], _xlpm.sku_idx), _xlpm.pct_low, INDEX(Model_Input[%Low], _xlpm.sku_idx), _xlpm.ltv * (_xlpm.pct_crit * 1 + _xlpm.pct_high * 0.75 + _xlpm.pct_med * 0.4 + _xlpm.pct_low * 0.15) )} -> 895.23502 | S2: {=IF(_xlfn.ANCHORARRAY($G2)="Constrained", 0.5, 1)} -> 1 | T2: =$H2 + MIN($D2, $S2) * ($N2 - $H2) -> 76.53 | U2: =IFERROR(($T2-$H2)/$H2, 0) -> 0 | V2: =IF($F2="Reduce", INDEX(Model_Assumptions[Values], 2), INDEX(Model_Assumptions[Values], 1)) -> -0.4 | W2: =$J2 * (1 + ($U2 * $V2)) -> 24 | X2: =$W2*$T2 -> 1836.72 | Y2: =$X2-($W2*$I2) -> 565.68 | Z2: =$X2-$K2 -> 0 | AA2: =$Y2-$L2 -> 0 | AB2: =IFERROR($Y2/$X2,0) -> 0.3079838 | AC2: =$AB2-$M2 -> 0 | AD2: =IFERROR(($X2-($W2*$I2))/$X2, 0) - IFERROR(($K2-($J2*$I2))/$K2, 0) -> 0 | AE2: =IFERROR(($T2-$H2)/($N2-$H2), 0) -> 0 | AF2: =$R2 * (1 - $AE2) -> 895.23502 | AG2: =IFERROR($Z2/$O2, 0) -> 0 | AH2: =IFERROR($AA2/$P2, 0) -> 0 | AI2: =IFERROR($AF2/$R2, 0) -> 1 | AJ2: =MAX(0, $R2 - $AA2) * INDEX(Model_Assumptions[Values], 7) -> 1790.47 | AK2: =MAX(0, INDEX(Model_Assumptions[Values], 4) - $AD2) -> 0.05 | AL2: =MAX(0, INDEX(Model_Assumptions[Values], 5) - $AC2) -> 0.02 | AM2: =INDEX(Model_Assumptions[Values], 6) * MAX(0, INDEX(Model_Assumptions[Values], 3) - $AB2)^2 -> 0 | AN2: =AVERAGEIF($E$2:$E$2201, $E2, $AJ$2:$AJ$2201) -> 1707.7543 | AO2: {=IFERROR(STDEV(IF($E$2:$E$2201=$E2, $AJ$2:$AJ$2201)), 0)} -> 48.827543 | AP2: =IF($AO2=0, 0, ($AJ2-$AN2)/$AO2) -> 1.6940386 | AQ2: =AVERAGEIF($E$2:$E$2201, $E2, $AK$2:$AK$2201) -> 0.032549534 | AR2: {=IFERROR(STDEV(IF($E$2:$E$2201=$E2, $AK$2:$AK$2201)), 0)} -> 0.010211698 | AS2: =IF($AR2=0, 0, ($AK2-$AQ2)/$AR2) -> 1.7088701 | AT2: =AVERAGEIF($E$2:$E$2201, $E2, $AL$2:$AL$2201) -> 0.0057333065 | AU2: {=IFERROR(STDEV(IF($E$2:$E$2201=$E2, $AL$2:$AL$2201)), 0)} -> 0.0067452578 | AV2: =IF($AU2=0, 0, ($AL2-$AT2)/$AU2) -> 2.1150702 | AW2: =AVERAGEIF($E$2:$E$2201, $E2, $AM$2:$AM$2201) -> 0 | AX2: {=IFERROR(STDEV(IF($E$2:$E$2201=$E2, $AM$2:$AM$2201)), 0)} -> 0 | AY2: =IF($AU2=0, 0, ($AL2-$AT2)/$AU2) -> 2.1150702 | AZ2: =INDEX(Model_Assumptions[Values],9)*((INDEX(Model_Scenarios[GR Weight],1)*$AG2)+(INDEX(Model_Scenarios[GP Weight],1)*$AH2)+(INDEX(Model_Scenarios[LTV Weight],1)*$AI2))-(INDEX(Model_Scenarios[LTV Weight],1)*$AP2)-(INDEX(Model_Scenarios[GP Weight],1)*($AS2+$AV2+$AY2)) -> 2.0508681 | BA2: =INDEX(Model_Assumptions[Values],9)*((INDEX(Model_Scenarios[GR Weight],2)*$AG2)+(INDEX(Model_Scenarios[GP Weight],2)*$AH2)+(INDEX(Model_Scenarios[LTV Weight],2)*$AI2))-(INDEX(Model_Scenarios[LTV Weight],2)*$AP2)-(INDEX(Model_Scenarios[GP Weight],2)*($AS2+$AV2+$AY2)) -> 0.96107282 | BB2: =INDEX(Model_Assumptions[Values],9)*((INDEX(Model_Scenarios[GR Weight],3)*$AG2)+(INDEX(Model_Scenarios[GP Weight],3)*$AH2)+(INDEX(Model_Scenarios[LTV Weight],3)*$AI2))-(INDEX(Model_Scenarios[LTV Weight],3)*$AP2)-(INDEX(Model_Scenarios[GP Weight],3)*($AS2+$AV2+$AY2)) -> -0.75626909 | BC2: =INDEX(Model_Assumptions[Values],9)*((INDEX(Model_Scenarios[GR Weight],4)*$AG2)+(INDEX(Model_Scenarios[GP Weight],4)*$AH2)+(INDEX(Model_Scenarios[LTV Weight],4)*$AI2))-(INDEX(Model_Scenarios[LTV Weight],4)*$AP2)-(INDEX(Model_Scenarios[GP Weight],4)*($AS2+$AV2+$AY2)) -> -1.0868652 | BD2: =INDEX(Model_Assumptions[Values],9)*((INDEX(Model_Scenarios[GR Weight],5)*$AG2)+(INDEX(Model_Scenarios[GP Weight],5)*$AH2)+(INDEX(Model_Scenarios[LTV Weight],5)*$AI2))-(INDEX(Model_Scenarios[LTV Weight],5)*$AP2)-(INDEX(Model_Scenarios[GP Weight],5)*($AS2+$AV2+$AY2)) -> -2.4399654
A3: 2 | B3: 1 | C3: 2 | D3: 0.02 | E3: SKU-1000 | F3: Raise | G3: Full | H3: 76.53 | I3: 52.96 | J3: 24 | K3: 1836.72 | L3: 565.68 | M3: 0.3079838 | N3: 80.606323 | O3: 17.225425 | P3: 70.185425 | Q3: 1112.0932 | R3: 895.23502 | S3: 1 | T3: =$H3 + MIN($D3, $S3) * ($N3 - $H3) -> 76.611526 | U3: =IFERROR(($T3-$H3)/$H3, 0) -> 0.0010652876 | V3: =IF($F3="Reduce", INDEX(Model_Assumptions[Values], 2), INDEX(Model_Assumptions[Values], 1)) -> -0.4 | W3: =$J3 * (1 + ($U3 * $V3)) -> 23.989773 | X3: =$W3*$T3 -> 1837.8931 | Y3: =$X3-($W3*$I3) -> 567.39476 | Z3: =$X3-$K3 -> 1.1731472 | AA3: =$Y3-$L3 -> 1.7147565 | AB3: =IFERROR($Y3/$X3,0) -> 0.30872021 | AC3: =$AB3-$M3 -> 0.00073641176 | AD3: =IFERROR(($X3-($W3*$I3))/$X3, 0) - IFERROR(($K3-($J3*$I3))/$K3, 0) -> 0.00073641176 | AE3: =IFERROR(($T3-$H3)/($N3-$H3), 0) -> 0.02 | AF3: =$R3 * (1 - $AE3) -> 877.33032 | AG3: =IFERROR($Z3/$O3, 0) -> 0.068105559 | AH3: =IFERROR($AA3/$P3, 0) -> 0.024431803 | AI3: =IFERROR($AF3/$R3, 0) -> 0.98 | AJ3: =MAX(0, $R3 - $AA3) * INDEX(Model_Assumptions[Values], 7) -> 1787.0405 | AK3: =MAX(0, INDEX(Model_Assumptions[Values], 4) - $AD3) -> 0.049263588 | AL3: =MAX(0, INDEX(Model_Assumptions[Values], 5) - $AC3) -> 0.019263588 | AM3: =INDEX(Model_Assumptions[Values], 6) * MAX(0, INDEX(Model_Assumptions[Values], 3) - $AB3)^2 -> 0 | AN3: =AVERAGEIF($E$2:$E$2201, $E3, $AJ$2:$AJ$2201) -> 1707.7543 | AO3: {=IFERROR(STDEV(IF($E$2:$E$2201=$E3, $AJ$2:$AJ$2201)), 0)} -> 48.827543 | AP3: =IF($AO3=0, 0, ($AJ3-$AN3)/$AO3) -> 1.6238014 | AQ3: =AVERAGEIF($E$2:$E$2201, $E3, $AK$2:$AK$2201) -> 0.032549534 | AR3: {=IFERROR(STDEV(IF($E$2:$E$2201=$E3, $AK$2:$AK$2201)), 0)} -> 0.010211698 | AS3: =IF($AR3=0, 0, ($AK3-$AQ3)/$AR3) -> 1.6367556 | AT3: =AVERAGEIF($E$2:$E$2201, $E3, $AL$2:$AL$2201) -> 0.0057333065 | AU3: {=IFERROR(STDEV(IF($E$2:$E$2201=$E3, $AL$2:$AL$2201)), 0)} -> 0.0067452578 | AV3: =IF($AU3=0, 0, ($AL3-$AT3)/$AU3) -> 2.0058954 | AW3: =AVERAGEIF($E$2:$E$2201, $E3, $AM$2:$AM$2201) -> 0 | AX3: {=IFERROR(STDEV(IF($E$2:$E$2201=$E3, $AM$2:$AM$2201)), 0)} -> 0 | AY3: =IF($AU3=0, 0, ($AL3-$AT3)/$AU3) -> 2.0058954 | AZ3: =INDEX(Model_Assumptions[Values],9)*((INDEX(Model_Scenarios[GR Weight],1)*$AG3)+(INDEX(Model_Scenarios[GP Weight],1)*$AH3)+(INDEX(Model_Scenarios[LTV Weight],1)*$AI3))-(INDEX(Model_Scenarios[LTV Weight],1)*$AP3)-(INDEX(Model_Scenarios[GP Weight],1)*($AS3+$AV3+$AY3)) -> 2.102373 | BA3: =INDEX(Model_Assumptions[Values],9)*((INDEX(Model_Scenarios[GR Weight],2)*$AG3)+(INDEX(Model_Scenarios[GP Weight],2)*$AH3)+(INDEX(Model_Scenarios[LTV Weight],2)*$AI3))-(INDEX(Model_Scenarios[LTV Weight],2)*$AP3)-(INDEX(Model_Scenarios[GP Weight],2)*($AS3+$AV3+$AY3)) -> 1.0753308 | BB3: =INDEX(Model_Assumptions[Values],9)*((INDEX(Model_Scenarios[GR Weight],3)*$AG3)+(INDEX(Model_Scenarios[GP Weight],3)*$AH3)+(INDEX(Model_Scenarios[LTV Weight],3)*$AI3))-(INDEX(Model_Scenarios[LTV Weight],3)*$AP3)-(INDEX(Model_Scenarios[GP Weight],3)*($AS3+$AV3+$AY3)) -> -0.53862418 | BC3: =INDEX(Model_Assumptions[Values],9)*((INDEX(Model_Scenarios[GR Weight],4)*$AG3)+(INDEX(Model_Scenarios[GP Weight],4)*$AH3)+(INDEX(Model_Scenarios[LTV Weight],4)*$AI3))-(INDEX(Model_Scenarios[LTV Weight],4)*$AP3)-(INDEX(Model_Scenarios[GP Weight],4)*($AS3+$AV3+$AY3)) -> -0.83219127 | BD3: =INDEX(Model_Assumptions[Values],9)*((INDEX(Model_Scenarios[GR Weight],5)*$AG3)+(INDEX(Model_Scenarios[GP Weight],5)*$AH3)+(INDEX(Model_Scenarios[LTV Weight],5)*$AI3))-(INDEX(Model_Scenarios[LTV Weight],5)*$AP3)-(INDEX(Model_Scenarios[GP Weight],5)*($AS3+$AV3+$AY3)) -> -2.1523578
A4: 3 | B4: 1 | C4: 3 | D4: 0.04 | E4: SKU-1000 | F4: Raise | G4: Full | H4: 76.53 | I4: 52.96 | J4: 24 | K4: 1836.72 | L4: 565.68 | M4: 0.3079838 | N4: 80.606323 | O4: 17.225425 | P4: 70.185425 | Q4: 1112.0932 | R4: 895.23502 | S4: 1 | T4: =$H4 + MIN($D4, $S4) * ($N4 - $H4) -> 76.693053 | U4: =IFERROR(($T4-$H4)/$H4, 0) -> 0.0021305751 | V4: =IF($F4="Reduce", INDEX(Model_Assumptions[Values], 2), INDEX(Model_Assumptions[Values], 1)) -> -0.4 | W4: =$J4 * (1 + ($U4 * $V4)) -> 23.979546 | X4: =$W4*$T4 -> 1839.0646 | Y4: =$X4-($W4*$I4) -> 569.10785 | Z4: =$X4-$K4 -> 2.3446269 | AA4: =$Y4-$L4 -> 3.4278454 | AB4: =IFERROR($Y4/$X4,0) -> 0.30945506 | AC4: =$AB4-$M4 -> 0.0014712579 | AD4: =IFERROR(($X4-($W4*$I4))/$X4, 0) - IFERROR(($K4-($J4*$I4))/$K4, 0) -> 0.0014712579 | AE4: =IFERROR(($T4-$H4)/($N4-$H4), 0) -> 0.04 | AF4: =$R4 * (1 - $AE4) -> 859.42562 | AG4: =IFERROR($Z4/$O4, 0) -> 0.13611431 | AH4: =IFERROR($AA4/$P4, 0) -> 0.048839847 | AI4: =IFERROR($AF4/$R4, 0) -> 0.96 | AJ4: =MAX(0, $R4 - $AA4) * INDEX(Model_Assumptions[Values], 7) -> 1783.6144 | AK4: =MAX(0, INDEX(Model_Assumptions[Values], 4) - $AD4) -> 0.048528742 | AL4: =MAX(0, INDEX(Model_Assumptions[Values], 5) - $AC4) -> 0.018528742 | AM4: =INDEX(Model_Assumptions[Values], 6) * MAX(0, INDEX(Model_Assumptions[Values], 3) - $AB4)^2 -> 0 | AN4: =AVERAGEIF($E$2:$E$2201, $E4, $AJ$2:$AJ$2201) -> 1707.7543 | AO4: {=IFERROR(STDEV(IF($E$2:$E$2201=$E4, $AJ$2:$AJ$2201)), 0)} -> 48.827543 | AP4: =IF($AO4=0, 0, ($AJ4-$AN4)/$AO4) -> 1.5536324 | AQ4: =AVERAGEIF($E$2:$E$2201, $E4, $AK$2:$AK$2201) -> 0.032549534 | AR4: {=IFERROR(STDEV(IF($E$2:$E$2201=$E4, $AK$2:$AK$2201)), 0)} -> 0.010211698 | AS4: =IF($AR4=0, 0, ($AK4-$AQ4)/$AR4) -> 1.5647944 | AT4: =AVERAGEIF($E$2:$E$2201, $E4, $AL$2:$AL$2201) -> 0.0057333065 | AU4: {=IFERROR(STDEV(IF($E$2:$E$2201=$E4, $AL$2:$AL$2201)), 0)} -> 0.0067452578 | AV4: =IF($AU4=0, 0, ($AL4-$AT4)/$AU4) -> 1.8969528 | AW4: =AVERAGEIF($E$2:$E$2201, $E4, $AM$2:$AM$2201) -> 0 | AX4: {=IFERROR(STDEV(IF($E$2:$E$2201=$E4, $AM$2:$AM$2201)), 0)} -> 0 | AY4: =IF($AU4=0, 0, ($AL4-$AT4)/$AU4) -> 1.8969528 | AZ4: =INDEX(Model_Assumptions[Values],9)*((INDEX(Model_Scenarios[GR Weight],1)*$AG4)+(INDEX(Model_Scenarios[GP Weight],1)*$AH4)+(INDEX(Model_Scenarios[LTV Weight],1)*$AI4))-(INDEX(Model_Scenarios[LTV Weight],1)*$AP4)-(INDEX(Model_Scenarios[GP Weight],1)*($AS4+$AV4+$AY4)) -> 2.1537012 | BA4: =INDEX(Model_Assumptions[Values],9)*((INDEX(Model_Scenarios[GR Weight],2)*$AG4)+(INDEX(Model_Scenarios[GP Weight],2)*$AH4)+(INDEX(Model_Scenarios[LTV Weight],2)*$AI4))-(INDEX(Model_Scenarios[LTV Weight],2)*$AP4)-(INDEX(Model_Scenarios[GP Weight],2)*($AS4+$AV4+$AY4)) -> 1.1893245 | BB4: =INDEX(Model_Assumptions[Values],9)*((INDEX(Model_Scenarios[GR Weight],3)*$AG4)+(INDEX(Model_Scenarios[GP Weight],3)*$AH4)+(INDEX(Model_Scenarios[LTV Weight],3)*$AI4))-(INDEX(Model_Scenarios[LTV Weight],3)*$AP4)-(INDEX(Model_Scenarios[GP Weight],3)*($AS4+$AV4+$AY4)) -> -0.32138532 | BC4: =INDEX(Model_Assumptions[Values],9)*((INDEX(Model_Scenarios[GR Weight],4)*$AG4)+(INDEX(Model_Scenarios[GP Weight],4)*$AH4)+(INDEX(Model_Scenarios[LTV Weight],4)*$AI4))-(INDEX(Model_Scenarios[LTV Weight],4)*$AP4)-(INDEX(Model_Scenarios[GP Weight],4)*($AS4+$AV4+$AY4)) -> -0.57796492 | BD4: =INDEX(Model_Assumptions[Values],9)*((INDEX(Model_Scenarios[GR Weight],5)*$AG4)+(INDEX(Model_Scenarios[GP Weight],5)*$AH4)+(INDEX(Model_Scenarios[LTV Weight],5)*$AI4))-(INDEX(Model_Scenarios[LTV Weight],5)*$AP4)-(INDEX(Model_Scenarios[GP Weight],5)*($AS4+$AV4+$AY4)) -> -1.8652692
A5: 4 | B5: 1 | C5: 4 | D5: 0.06 | E5: SKU-1000 | F5: Raise | G5: Full | H5: 76.53 | I5: 52.96 | J5: 24 | K5: 1836.72 | L5: 565.68 | M5: 0.3079838 | N5: 80.606323 | O5: 17.225425 | P5: 70.185425 | Q5: 1112.0932 | R5: 895.23502 | S5: 1 | T5: =$H5 + MIN($D5, $S5) * ($N5 - $H5) -> 76.774579 | U5: =IFERROR(($T5-$H5)/$H5, 0) -> 0.0031958627 | V5: =IF($F5="Reduce", INDEX(Model_Assumptions[Values], 2), INDEX(Model_Assumptions[Values], 1)) -> -0.4 | W5: =$J5 * (1 + ($U5 * $V5)) -> 23.96932 | X5: =$W5*$T5 -> 1840.2344 | Y5: =$X5-($W5*$I5) -> 570.81927 | Z5: =$X5-$K5 -> 3.5144392 | AA5: =$Y5-$L5 -> 5.1392669 | AB5: =IFERROR($Y5/$X5,0) -> 0.31018834 | AC5: =$AB5-$M5 -> 0.0022045433 | AD5: =IFERROR(($X5-($W5*$I5))/$X5, 0) - IFERROR(($K5-($J5*$I5))/$K5, 0) -> 0.0022045433 | AE5: =IFERROR(($T5-$H5)/($N5-$H5), 0) -> 0.06 | AF5: =$R5 * (1 - $AE5) -> 841.52092 | AG5: =IFERROR($Z5/$O5, 0) -> 0.20402626 | AH5: =IFERROR($AA5/$P5, 0) -> 0.073224133 | AI5: =IFERROR($AF5/$R5, 0) -> 0.94 | AJ5: =MAX(0, $R5 - $AA5) * INDEX(Model_Assumptions[Values], 7) -> 1780.1915 | AK5: =MAX(0, INDEX(Model_Assumptions[Values], 4) - $AD5) -> 0.047795457 | AL5: =MAX(0, INDEX(Model_Assumptions[Values], 5) - $AC5) -> 0.017795457 | AM5: =INDEX(Model_Assumptions[Values], 6) * MAX(0, INDEX(Model_Assumptions[Values], 3) - $AB5)^2 -> 0 | AN5: =AVERAGEIF($E$2:$E$2201, $E5, $AJ$2:$AJ$2201) -> 1707.7543 | AO5: {=IFERROR(STDEV(IF($E$2:$E$2201=$E5, $AJ$2:$AJ$2201)), 0)} -> 48.827543 | AP5: =IF($AO5=0, 0, ($AJ5-$AN5)/$AO5) -> 1.4835317 | AQ5: =AVERAGEIF($E$2:$E$2201, $E5, $AK$2:$AK$2201) -> 0.032549534 | AR5: {=IFERROR(STDEV(IF($E$2:$E$2201=$E5, $AK$2:$AK$2201)), 0)} -> 0.010211698 | AS5: =IF($AR5=0, 0, ($AK5-$AQ5)/$AR5) -> 1.492986 | AT5: =AVERAGEIF($E$2:$E$2201, $E5, $AL$2:$AL$2201) -> 0.0057333065 | AU5: {=IFERROR(STDEV(IF($E$2:$E$2201=$E5, $AL$2:$AL$2201)), 0)} -> 0.0067452578 | AV5: =IF($AU5=0, 0, ($AL5-$AT5)/$AU5) -> 1.7882415 | AW5: =AVERAGEIF($E$2:$E$2201, $E5, $AM$2:$AM$2201) -> 0 | AX5: {=IFERROR(STDEV(IF($E$2:$E$2201=$E5, $AM$2:$AM$2201)), 0)} -> 0 | AY5: =IF($AU5=0, 0, ($AL5-$AT5)/$AU5) -> 1.7882415 | AZ5: =INDEX(Model_Assumptions[Values],9)*((INDEX(Model_Scenarios[GR Weight],1)*$AG5)+(INDEX(Model_Scenarios[GP Weight],1)*$AH5)+(INDEX(Model_Scenarios[LTV Weight],1)*$AI5))-(INDEX(Model_Scenarios[LTV Weight],1)*$AP5)-(INDEX(Model_Scenarios[GP Weight],1)*($AS5+$AV5+$AY5)) -> 2.2048529 | BA5: =INDEX(Model_Assumptions[Values],9)*((INDEX(Model_Scenarios[GR Weight],2)*$AG5)+(INDEX(Model_Scenarios[GP Weight],2)*$AH5)+(INDEX(Model_Scenarios[LTV Weight],2)*$AI5))-(INDEX(Model_Scenarios[LTV Weight],2)*$AP5)-(INDEX(Model_Scenarios[GP Weight],2)*($AS5+$AV5+$AY5)) -> 1.3030544 | BB5: =INDEX(Model_Assumptions[Values],9)*((INDEX(Model_Scenarios[GR Weight],3)*$AG5)+(INDEX(Model_Scenarios[GP Weight],3)*$AH5)+(INDEX(Model_Scenarios[LTV Weight],3)*$AI5))-(INDEX(Model_Scenarios[LTV Weight],3)*$AP5)-(INDEX(Model_Scenarios[GP Weight],3)*($AS5+$AV5+$AY5)) -> -0.1045518 | BC5: =INDEX(Model_Assumptions[Values],9)*((INDEX(Model_Scenarios[GR Weight],4)*$AG5)+(INDEX(Model_Scenarios[GP Weight],4)*$AH5)+(INDEX(Model_Scenarios[LTV Weight],4)*$AI5))-(INDEX(Model_Scenarios[LTV Weight],4)*$AP5)-(INDEX(Model_Scenarios[GP Weight],4)*($AS5+$AV5+$AY5)) -> -0.3241855 | BD5: =INDEX(Model_Assumptions[Values],9)*((INDEX(Model_Scenarios[GR Weight],5)*$AG5)+(INDEX(Model_Scenarios[GP Weight],5)*$AH5)+(INDEX(Model_Scenarios[LTV Weight],5)*$AI5))-(INDEX(Model_Scenarios[LTV Weight],5)*$AP5)-(INDEX(Model_Scenarios[GP Weight],5)*($AS5+$AV5+$AY5)) -> -1.5786983
A6: 5 | B6: 1 | C6: 5 | D6: 0.08 | E6: SKU-1000 | F6: Raise | G6: Full | H6: 76.53 | I6: 52.96 | J6: 24 | K6: 1836.72 | L6: 565.68 | M6: 0.3079838 | N6: 80.606323 | O6: 17.225425 | P6: 70.185425 | Q6: 1112.0932 | R6: 895.23502 | S6: 1 | T6: =$H6 + MIN($D6, $S6) * ($N6 - $H6) -> 76.856106 | U6: =IFERROR(($T6-$H6)/$H6, 0) -> 0.0042611502 | V6: =IF($F6="Reduce", INDEX(Model_Assumptions[Values], 2), INDEX(Model_Assumptions[Values], 1)) -> -0.4 | W6: =$J6 * (1 + ($U6 * $V6)) -> 23.959093 | X6: =$W6*$T6 -> 1841.4026 | Y6: =$X6-($W6*$I6) -> 572.52902 | Z6: =$X6-$K6 -> 4.6825839 | AA6: =$Y6-$L6 -> 6.8490208 | AB6: =IFERROR($Y6/$X6,0) -> 0.31092007 | AC6: =$AB6-$M6 -> 0.0029362731 | AD6: =IFERROR(($X6-($W6*$I6))/$X6, 0) - IFERROR(($K6-($J6*$I6))/$K6, 0) -> 0.0029362731 | AE6: =IFERROR(($T6-$H6)/($N6-$H6), 0) -> 0.08 | AF6: =$R6 * (1 - $AE6) -> 823.61622 | AG6: =IFERROR($Z6/$O6, 0) -> 0.27184141 | AH6: =IFERROR($AA6/$P6, 0) -> 0.09758466 | AI6: =IFERROR($AF6/$R6, 0) -> 0.92 | AJ6: =MAX(0, $R6 - $AA6) * INDEX(Model_Assumptions[Values], 7) -> 1776.772 | AK6: =MAX(0, INDEX(Model_Assumptions[Values], 4) - $AD6) -> 0.047063727 | AL6: =MAX(0, INDEX(Model_Assumptions[Values], 5) - $AC6) -> 0.017063727 | AM6: =INDEX(Model_Assumptions[Values], 6) * MAX(0, INDEX(Model_Assumptions[Values], 3) - $AB6)^2 -> 0 | AN6: =AVERAGEIF($E$2:$E$2201, $E6, $AJ$2:$AJ$2201) -> 1707.7543 | AO6: {=IFERROR(STDEV(IF($E$2:$E$2201=$E6, $AJ$2:$AJ$2201)), 0)} -> 48.827543 | AP6: =IF($AO6=0, 0, ($AJ6-$AN6)/$AO6) -> 1.4134994 | AQ6: =AVERAGEIF($E$2:$E$2201, $E6, $AK$2:$AK$2201) -> 0.032549534 | AR6: {=IFERROR(STDEV(IF($E$2:$E$2201=$E6, $AK$2:$AK$2201)), 0)} -> 0.010211698 | AS6: =IF($AR6=0, 0, ($AK6-$AQ6)/$AR6) -> 1.42133 | AT6: =AVERAGEIF($E$2:$E$2201, $E6, $AL$2:$AL$2201) -> 0.0057333065 | AU6: {=IFERROR(STDEV(IF($E$2:$E$2201=$E6, $AL$2:$AL$2201)), 0)} -> 0.0067452578 | AV6: =IF($AU6=0, 0, ($AL6-$AT6)/$AU6) -> 1.6797609 | AW6: =AVERAGEIF($E$2:$E$2201, $E6, $AM$2:$AM$2201) -> 0 | AX6: {=IFERROR(STDEV(IF($E$2:$E$2201=$E6, $AM$2:$AM$2201)), 0)} -> 0 | AY6: =IF($AU6=0, 0, ($AL6-$AT6)/$AU6) -> 1.6797609 | AZ6: =INDEX(Model_Assumptions[Values],9)*((INDEX(Model_Scenarios[GR Weight],1)*$AG6)+(INDEX(Model_Scenarios[GP Weight],1)*$AH6)+(INDEX(Model_Scenarios[LTV Weight],1)*$AI6))-(INDEX(Model_Scenarios[LTV Weight],1)*$AP6)-(INDEX(Model_Scenarios[GP Weight],1)*($AS6+$AV6+$AY6)) -> 2.2558283 | BA6: =INDEX(Model_Assumptions[Values],9)*((INDEX(Model_Scenarios[GR Weight],2)*$AG6)+(INDEX(Model_Scenarios[GP Weight],2)*$AH6)+(INDEX(Model_Scenarios[LTV Weight],2)*$AI6))-(INDEX(Model_Scenarios[LTV Weight],2)*$AP6)-(INDEX(Model_Scenarios[GP Weight],2)*($AS6+$AV6+$AY6)) -> 1.4165208 | BB6: =INDEX(Model_Assumptions[Values],9)*((INDEX(Model_Scenarios[GR Weight],3)*$AG6)+(INDEX(Model_Scenarios[GP Weight],3)*$AH6)+(INDEX(Model_Scenarios[LTV Weight],3)*$AI6))-(INDEX(Model_Scenarios[LTV Weight],3)*$AP6)-(INDEX(Model_Scenarios[GP Weight],3)*($AS6+$AV6+$AY6)) -> 0.11187704 | BC6: =INDEX(Model_Assumptions[Values],9)*((INDEX(Model_Scenarios[GR Weight],4)*$AG6)+(INDEX(Model_Scenarios[GP Weight],4)*$AH6)+(INDEX(Model_Scenarios[LTV Weight],4)*$AI6))-(INDEX(Model_Scenarios[LTV Weight],4)*$AP6)-(INDEX(Model_Scenarios[GP Weight],4)*($AS6+$AV6+$AY6)) -> -0.070852318 | BD6: =INDEX(Model_Assumptions[Values],9)*((INDEX(Model_Scenarios[GR Weight],5)*$AG6)+(INDEX(Model_Scenarios[GP Weight],5)*$AH6)+(INDEX(Model_Scenarios[LTV Weight],5)*$AI6))-(INDEX(Model_Scenarios[LTV Weight],5)*$AP6)-(INDEX(Model_Scenarios[GP Weight],5)*($AS6+$AV6+$AY6)) -> -1.2926441
A7: 6 | B7: 1 | C7: 6 | D7: 0.1 | E7: SKU-1000 | F7: Raise | G7: Full | H7: 76.53 | I7: 52.96 | J7: 24 | K7: 1836.72 | L7: 565.68 | M7: 0.3079838 | N7: 80.606323 | O7: 17.225425 | P7: 70.185425 | Q7: 1112.0932 | R7: 895.23502 | S7: 1 | T7: =$H7 + MIN($D7, $S7) * ($N7 - $H7) -> 76.937632 | U7: =IFERROR(($T7-$H7)/$H7, 0) -> 0.0053264378 | V7: =IF($F7="Reduce", INDEX(Model_Assumptions[Values], 2), INDEX(Model_Assumptions[Values], 1)) -> -0.4 | W7: =$J7 * (1 + ($U7 * $V7)) -> 23.948866 | X7: =$W7*$T7 -> 1842.5691 | Y7: =$X7-($W7*$I7) -> 574.23711 | Z7: =$X7-$K7 -> 5.8490611 | AA7: =$Y7-$L7 -> 8.5571073 | AB7: =IFERROR($Y7/$X7,0) -> 0.31165025 | AC7: =$AB7-$M7 -> 0.0036664521 | AD7: =IFERROR(($X7-($W7*$I7))/$X7, 0) - IFERROR(($K7-($J7*$I7))/$K7, 0) -> 0.0036664521 | AE7: =IFERROR(($T7-$H7)/($N7-$H7), 0) -> 0.1 | AF7: =$R7 * (1 - $AE7) -> 805.71152 | AG7: =IFERROR($Z7/$O7, 0) -> 0.33955975 | AH7: =IFERROR($AA7/$P7, 0) -> 0.12192143 | AI7: =IFERROR($AF7/$R7, 0) -> 0.9 | AJ7: =MAX(0, $R7 - $AA7) * INDEX(Model_Assumptions[Values], 7) -> 1773.3558 | AK7: =MAX(0, INDEX(Model_Assumptions[Values], 4) - $AD7) -> 0.046333548 | AL7: =MAX(0, INDEX(Model_Assumptions[Values], 5) - $AC7) -> 0.016333548 | AM7: =INDEX(Model_Assumptions[Values], 6) * MAX(0, INDEX(Model_Assumptions[Values], 3) - $AB7)^2 -> 0 | AN7: =AVERAGEIF($E$2:$E$2201, $E7, $AJ$2:$AJ$2201) -> 1707.7543 | AO7: {=IFERROR(STDEV(IF($E$2:$E$2201=$E7, $AJ$2:$AJ$2201)), 0)} -> 48.827543 | AP7: =IF($AO7=0, 0, ($AJ7-$AN7)/$AO7) -> 1.3435353 | AQ7: =AVERAGEIF($E$2:$E$2201, $E7, $AK$2:$AK$2201) -> 0.032549534 | AR7: {=IFERROR(STDEV(IF($E$2:$E$2201=$E7, $AK$2:$AK$2201)), 0)} -> 0.010211698 | AS7: =IF($AR7=0, 0, ($AK7-$AQ7)/$AR7) -> 1.3498258 | AT7: =AVERAGEIF($E$2:$E$2201, $E7, $AL$2:$AL$2201) -> 0.0057333065 | AU7: {=IFERROR(STDEV(IF($E$2:$E$2201=$E7, $AL$2:$AL$2201)), 0)} -> 0.0067452578 | AV7: =IF($AU7=0, 0, ($AL7-$AT7)/$AU7) -> 1.5715102 | AW7: =AVERAGEIF($E$2:$E$2201, $E7, $AM$2:$AM$2201) -> 0 | AX7: {=IFERROR(STDEV(IF($E$2:$E$2201=$E7, $AM$2:$AM$2201)), 0)} -> 0 | AY7: =IF($AU7=0, 0, ($AL7-$AT7)/$AU7) -> 1.5715102 | AZ7: =INDEX(Model_Assumptions[Values],9)*((INDEX(Model_Scenarios[GR Weight],1)*$AG7)+(INDEX(Model_Scenarios[GP Weight],1)*$AH7)+(INDEX(Model_Scenarios[LTV Weight],1)*$AI7))-(INDEX(Model_Scenarios[LTV Weight],1)*$AP7)-(INDEX(Model_Scenarios[GP Weight],1)*($AS7+$AV7+$AY7)) -> 2.3066277 | BA7: =INDEX(Model_Assumptions[Values],9)*((INDEX(Model_Scenarios[GR Weight],2)*$AG7)+(INDEX(Model_Scenarios[GP Weight],2)*$AH7)+(INDEX(Model_Scenarios[LTV Weight],2)*$AI7))-(INDEX(Model_Scenarios[LTV Weight],2)*$AP7)-(INDEX(Model_Scenarios[GP Weight],2)*($AS7+$AV7+$AY7)) -> 1.529724 | BB7: =INDEX(Model_Assumptions[Values],9)*((INDEX(Model_Scenarios[GR Weight],3)*$AG7)+(INDEX(Model_Scenarios[GP Weight],3)*$AH7)+(INDEX(Model_Scenarios[LTV Weight],3)*$AI7))-(INDEX(Model_Scenarios[LTV Weight],3)*$AP7)-(INDEX(Model_Scenarios[GP Weight],3)*($AS7+$AV7+$AY7)) -> 0.3279019 | BC7: =INDEX(Model_Assumptions[Values],9)*((INDEX(Model_Scenarios[GR Weight],4)*$AG7)+(INDEX(Model_Scenarios[GP Weight],4)*$AH7)+(INDEX(Model_Scenarios[LTV Weight],4)*$AI7))-(INDEX(Model_Scenarios[LTV Weight],4)*$AP7)-(INDEX(Model_Scenarios[GP Weight],4)*($AS7+$AV7+$AY7)) -> 0.1820353 | BD7: =INDEX(Model_Assumptions[Values],9)*((INDEX(Model_Scenarios[GR Weight],5)*$AG7)+(INDEX(Model_Scenarios[GP Weight],5)*$AH7)+(INDEX(Model_Scenarios[LTV Weight],5)*$AI7))-(INDEX(Model_Scenarios[LTV Weight],5)*$AP7)-(INDEX(Model_Scenarios[GP Weight],5)*($AS7+$AV7+$AY7)) -> -1.0071055
A8: 7 | B8: 1 | C8: 7 | D8: 0.12 | E8: SKU-1000 | F8: Raise | G8: Full | H8: 76.53 | I8: 52.96 | J8: 24 | K8: 1836.72 | L8: 565.68 | M8: 0.3079838 | N8: 80.606323 | O8: 17.225425 | P8: 70.185425 | Q8: 1112.0932 | R8: 895.23502 | S8: 1 | T8: =$H8 + MIN($D8, $S8) * ($N8 - $H8) -> 77.019159 | U8: =IFERROR(($T8-$H8)/$H8, 0) -> 0.0063917253 | V8: =IF($F8="Reduce", INDEX(Model_Assumptions[Values], 2), INDEX(Model_Assumptions[Values], 1)) -> -0.4 | W8: =$J8 * (1 + ($U8 * $V8)) -> 23.938639 | X8: =$W8*$T8 -> 1843.7339 | Y8: =$X8-($W8*$I8) -> 575.94353 | Z8: =$X8-$K8 -> 7.0138708 | AA8: =$Y8-$L8 -> 10.263526 | AB8: =IFERROR($Y8/$X8,0) -> 0.31237888 | AC8: =$AB8-$M8 -> 0.0043950853 | AD8: =IFERROR(($X8-($W8*$I8))/$X8, 0) - IFERROR(($K8-($J8*$I8))/$K8, 0) -> 0.0043950853 | AE8: =IFERROR(($T8-$H8)/($N8-$H8), 0) -> 0.12 | AF8: =$R8 * (1 - $AE8) -> 787.80682 | AG8: =IFERROR($Z8/$O8, 0) -> 0.40718129 | AH8: =IFERROR($AA8/$P8, 0) -> 0.14623444 | AI8: =IFERROR($AF8/$R8, 0) -> 0.88 | AJ8: =MAX(0, $R8 - $AA8) * INDEX(Model_Assumptions[Values], 7) -> 1769.943 | AK8: =MAX(0, INDEX(Model_Assumptions[Values], 4) - $AD8) -> 0.045604915 | AL8: =MAX(0, INDEX(Model_Assumptions[Values], 5) - $AC8) -> 0.015604915 | AM8: =INDEX(Model_Assumptions[Values], 6) * MAX(0, INDEX(Model_Assumptions[Values], 3) - $AB8)^2 -> 0 | AN8: =AVERAGEIF($E$2:$E$2201, $E8, $AJ$2:$AJ$2201) -> 1707.7543 | AO8: {=IFERROR(STDEV(IF($E$2:$E$2201=$E8, $AJ$2:$AJ$2201)), 0)} -> 48.827543 | AP8: =IF($AO8=0, 0, ($AJ8-$AN8)/$AO8) -> 1.2736396 | AQ8: =AVERAGEIF($E$2:$E$2201, $E8, $AK$2:$AK$2201) -> 0.032549534 | AR8: {=IFERROR(STDEV(IF($E$2:$E$2201=$E8, $AK$2:$AK$2201)), 0)} -> 0.010211698 | AS8: =IF($AR8=0, 0, ($AK8-$AQ8)/$AR8) -> 1.278473 | AT8: =AVERAGEIF($E$2:$E$2201, $E8, $AL$2:$AL$2201) -> 0.0057333065 | AU8: {=IFERROR(STDEV(IF($E$2:$E$2201=$E8, $AL$2:$AL$2201)), 0)} -> 0.0067452578 | AV8: =IF($AU8=0, 0, ($AL8-$AT8)/$AU8) -> 1.4634886 | AW8: =AVERAGEIF($E$2:$E$2201, $E8, $AM$2:$AM$2201) -> 0 | AX8: {=IFERROR(STDEV(IF($E$2:$E$2201=$E8, $AM$2:$AM$2201)), 0)} -> 0 | AY8: =IF($AU8=0, 0, ($AL8-$AT8)/$AU8) -> 1.4634886 | AZ8: =INDEX(Model_Assumptions[Values],9)*((INDEX(Model_Scenarios[GR Weight],1)*$AG8)+(INDEX(Model_Scenarios[GP Weight],1)*$AH8)+(INDEX(Model_Scenarios[LTV Weight],1)*$AI8))-(INDEX(Model_Scenarios[LTV Weight],1)*$AP8)-(INDEX(Model_Scenarios[GP Weight],1)*($AS8+$AV8+$AY8)) -> 2.3572512 | BA8: =INDEX(Model_Assumptions[Values],9)*((INDEX(Model_Scenarios[GR Weight],2)*$AG8)+(INDEX(Model_Scenarios[GP Weight],2)*$AH8)+(INDEX(Model_Scenarios[LTV Weight],2)*$AI8))-(INDEX(Model_Scenarios[LTV Weight],2)*$AP8)-(INDEX(Model_Scenarios[GP Weight],2)*($AS8+$AV8+$AY8)) -> 1.6426646 | BB8: =INDEX(Model_Assumptions[Values],9)*((INDEX(Model_Scenarios[GR Weight],3)*$AG8)+(INDEX(Model_Scenarios[GP Weight],3)*$AH8)+(INDEX(Model_Scenarios[LTV Weight],3)*$AI8))-(INDEX(Model_Scenarios[LTV Weight],3)*$AP8)-(INDEX(Model_Scenarios[GP Weight],3)*($AS8+$AV8+$AY8)) -> 0.54352345 | BC8: =INDEX(Model_Assumptions[Values],9)*((INDEX(Model_Scenarios[GR Weight],4)*$AG8)+(INDEX(Model_Scenarios[GP Weight],4)*$AH8)+(INDEX(Model_Scenarios[LTV Weight],4)*$AI8))-(INDEX(Model_Scenarios[LTV Weight],4)*$AP8)-(INDEX(Model_Scenarios[GP Weight],4)*($AS8+$AV8+$AY8)) -> 0.43447805 | BD8: =INDEX(Model_Assumptions[Values],9)*((INDEX(Model_Scenarios[GR Weight],5)*$AG8)+(INDEX(Model_Scenarios[GP Weight],5)*$AH8)+(INDEX(Model_Scenarios[LTV Weight],5)*$AI8))-(INDEX(Model_Scenarios[LTV Weight],5)*$AP8)-(INDEX(Model_Scenarios[GP Weight],5)*($AS8+$AV8+$AY8)) -> -0.72208156
A9: 8 | B9: 1 | C9: 8 | D9: 0.14 | E9: SKU-1000 | F9: Raise | G9: Full | H9: 76.53 | I9: 52.96 | J9: 24 | K9: 1836.72 | L9: 565.68 | M9: 0.3079838 | N9: 80.606323 | O9: 17.225425 | P9: 70.185425 | Q9: 1112.0932 | R9: 895.23502 | S9: 1 | T9: =$H9 + MIN($D9, $S9) * ($N9 - $H9) -> 77.100685 | U9: =IFERROR(($T9-$H9)/$H9, 0) -> 0.0074570129 | V9: =IF($F9="Reduce", INDEX(Model_Assumptions[Values], 2), INDEX(Model_Assumptions[Values], 1)) -> -0.4 | W9: =$J9 * (1 + ($U9 * $V9)) -> 23.928413 | X9: =$W9*$T9 -> 1844.897 | Y9: =$X9-($W9*$I9) -> 577.64828 | Z9: =$X9-$K9 -> 8.177013 | AA9: =$Y9-$L9 -> 11.968278 | AB9: =IFERROR($Y9/$X9,0) -> 0.31310597 | AC9: =$AB9-$M9 -> 0.0051221776 | AD9: =IFERROR(($X9-($W9*$I9))/$X9, 0) - IFERROR(($K9-($J9*$I9))/$K9, 0) -> 0.0051221776 | AE9: =IFERROR(($T9-$H9)/($N9-$H9), 0) -> 0.14 | AF9: =$R9 * (1 - $AE9) -> 769.90212 | AG9: =IFERROR($Z9/$O9, 0) -> 0.47470602 | AH9: =IFERROR($AA9/$P9, 0) -> 0.17052369 | AI9: =IFERROR($AF9/$R9, 0) -> 0.86 | AJ9: =MAX(0, $R9 - $AA9) * INDEX(Model_Assumptions[Values], 7) -> 1766.5335 | AK9: =MAX(0, INDEX(Model_Assumptions[Values], 4) - $AD9) -> 0.044877822 | AL9: =MAX(0, INDEX(Model_Assumptions[Values], 5) - $AC9) -> 0.014877822 | AM9: =INDEX(Model_Assumptions[Values], 6) * MAX(0, INDEX(Model_Assumptions[Values], 3) - $AB9)^2 -> 0 | AN9: =AVERAGEIF($E$2:$E$2201, $E9, $AJ$2:$AJ$2201) -> 1707.7543 | AO9: {=IFERROR(STDEV(IF($E$2:$E$2201=$E9, $AJ$2:$AJ$2201)), 0)} -> 48.827543 | AP9: =IF($AO9=0, 0, ($AJ9-$AN9)/$AO9) -> 1.2038121 | AQ9: =AVERAGEIF($E$2:$E$2201, $E9, $AK$2:$AK$2201) -> 0.032549534 | AR9: {=IFERROR(STDEV(IF($E$2:$E$2201=$E9, $AK$2:$AK$2201)), 0)} -> 0.010211698 | AS9: =IF($AR9=0, 0, ($AK9-$AQ9)/$AR9) -> 1.2072711 | AT9: =AVERAGEIF($E$2:$E$2201, $E9, $AL$2:$AL$2201) -> 0.0057333065 | AU9: {=IFERROR(STDEV(IF($E$2:$E$2201=$E9, $AL$2:$AL$2201)), 0)} -> 0.0067452578 | AV9: =IF($AU9=0, 0, ($AL9-$AT9)/$AU9) -> 1.3556955 | AW9: =AVERAGEIF($E$2:$E$2201, $E9, $AM$2:$AM$2201) -> 0 | AX9: {=IFERROR(STDEV(IF($E$2:$E$2201=$E9, $AM$2:$AM$2201)), 0)} -> 0 | AY9: =IF($AU9=0, 0, ($AL9-$AT9)/$AU9) -> 1.3556955 | AZ9: =INDEX(Model_Assumptions[Values],9)*((INDEX(Model_Scenarios[GR Weight],1)*$AG9)+(INDEX(Model_Scenarios[GP Weight],1)*$AH9)+(INDEX(Model_Scenarios[LTV Weight],1)*$AI9))-(INDEX(Model_Scenarios[LTV Weight],1)*$AP9)-(INDEX(Model_Scenarios[GP Weight],1)*($AS9+$AV9+$AY9)) -> 2.4076989 | BA9: =INDEX(Model_Assumptions[Values],9)*((INDEX(Model_Scenarios[GR Weight],2)*$AG9)+(INDEX(Model_Scenarios[GP Weight],2)*$AH9)+(INDEX(Model_Scenarios[LTV Weight],2)*$AI9))-(INDEX(Model_Scenarios[LTV Weight],2)*$AP9)-(INDEX(Model_Scenarios[GP Weight],2)*($AS9+$AV9+$AY9)) -> 1.7553429 | BB9: =INDEX(Model_Assumptions[Values],9)*((INDEX(Model_Scenarios[GR Weight],3)*$AG9)+(INDEX(Model_Scenarios[GP Weight],3)*$AH9)+(INDEX(Model_Scenarios[LTV Weight],3)*$AI9))-(INDEX(Model_Scenarios[LTV Weight],3)*$AP9)-(INDEX(Model_Scenarios[GP Weight],3)*($AS9+$AV9+$AY9)) -> 0.75874237 | BC9: =INDEX(Model_Assumptions[Values],9)*((INDEX(Model_Scenarios[GR Weight],4)*$AG9)+(INDEX(Model_Scenarios[GP Weight],4)*$AH9)+(INDEX(Model_Scenarios[LTV Weight],4)*$AI9))-(INDEX(Model_Scenarios[LTV Weight],4)*$AP9)-(INDEX(Model_Scenarios[GP Weight],4)*($AS9+$AV9+$AY9)) -> 0.68647659 | BD9: =INDEX(Model_Assumptions[Values],9)*((INDEX(Model_Scenarios[GR Weight],5)*$AG9)+(INDEX(Model_Scenarios[GP Weight],5)*$AH9)+(INDEX(Model_Scenarios[LTV Weight],5)*$AI9))-(INDEX(Model_Scenarios[LTV Weight],5)*$AP9)-(INDEX(Model_Scenarios[GP Weight],5)*($AS9+$AV9+$AY9)) -> -0.43757106
A10: 9 | B10: 1 | C10: 9 | D10: 0.16 | E10: SKU-1000 | F10: Raise | G10: Full | H10: 76.53 | I10: 52.96 | J10: 24 | K10: 1836.72 | L10: 565.68 | M10: 0.3079838 | N10: 80.606323 | O10: 17.225425 | P10: 70.185425 | Q10: 1112.0932 | R10: 895.23502 | S10: 1 | T10: =$H10 + MIN($D10, $S10) * ($N10 - $H10) -> 77.182212 | U10: =IFERROR(($T10-$H10)/$H10, 0) -> 0.0085223005 | V10: =IF($F10="Reduce", INDEX(Model_Assumptions[Values], 2), INDEX(Model_Assumptions[Values], 1)) -> -0.4 | W10: =$J10 * (1 + ($U10 * $V10)) -> 23.918186 | X10: =$W10*$T10 -> 1846.0585 | Y10: =$X10-($W10*$I10) -> 579.35136 | Z10: =$X10-$K10 -> 9.3384877 | AA10: =$Y10-$L10 -> 13.671362 | AB10: =IFERROR($Y10/$X10,0) -> 0.31383153 | AC10: =$AB10-$M10 -> 0.0058477339 | AD10: =IFERROR(($X10-($W10*$I10))/$X10, 0) - IFERROR(($K10-($J10*$I10))/$K10, 0) -> 0.0058477339 | AE10: =IFERROR(($T10-$H10)/($N10-$H10), 0) -> 0.16 | AF10: =$R10 * (1 - $AE10) -> 751.99742 | AG10: =IFERROR($Z10/$O10, 0) -> 0.54213394 | AH10: =IFERROR($AA10/$P10, 0) -> 0.19478918 | AI10: =IFERROR($AF10/$R10, 0) -> 0.84 | AJ10: =MAX(0, $R10 - $AA10) * INDEX(Model_Assumptions[Values], 7) -> 1763.1273 | AK10: =MAX(0, INDEX(Model_Assumptions[Values], 4) - $AD10) -> 0.044152266 | AL10: =MAX(0, INDEX(Model_Assumptions[Values], 5) - $AC10) -> 0.014152266 | AM10: =INDEX(Model_Assumptions[Values], 6) * MAX(0, INDEX(Model_Assumptions[Values], 3) - $AB10)^2 -> 0 | AN10: =AVERAGEIF($E$2:$E$2201, $E10, $AJ$2:$AJ$2201) -> 1707.7543 | AO10: {=IFERROR(STDEV(IF($E$2:$E$2201=$E10, $AJ$2:$AJ$2201)), 0)} -> 48.827543 | AP10: =IF($AO10=0, 0, ($AJ10-$AN10)/$AO10) -> 1.134053 | AQ10: =AVERAGEIF($E$2:$E$2201, $E10, $AK$2:$AK$2201) -> 0.032549534 | AR10: {=IFERROR(STDEV(IF($E$2:$E$2201=$E10, $AK$2:$AK$2201)), 0)} -> 0.010211698 | AS10: =IF($AR10=0, 0, ($AK10-$AQ10)/$AR10) -> 1.1362196 | AT10: =AVERAGEIF($E$2:$E$2201, $E10, $AL$2:$AL$2201) -> 0.0057333065 | AU10: {=IFERROR(STDEV(IF($E$2:$E$2201=$E10, $AL$2:$AL$2201)), 0)} -> 0.0067452578 | AV10: =IF($AU10=0, 0, ($AL10-$AT10)/$AU10) -> 1.2481302 | AW10: =AVERAGEIF($E$2:$E$2201, $E10, $AM$2:$AM$2201) -> 0 | AX10: {=IFERROR(STDEV(IF($E$2:$E$2201=$E10, $AM$2:$AM$2201)), 0)} -> 0 | AY10: =IF($AU10=0, 0, ($AL10-$AT10)/$AU10) -> 1.2481302 | AZ10: =INDEX(Model_Assumptions[Values],9)*((INDEX(Model_Scenarios[GR Weight],1)*$AG10)+(INDEX(Model_Scenarios[GP Weight],1)*$AH10)+(INDEX(Model_Scenarios[LTV Weight],1)*$AI10))-(INDEX(Model_Scenarios[LTV Weight],1)*$AP10)-(INDEX(Model_Scenarios[GP Weight],1)*($AS10+$AV10+$AY10)) -> 2.4579712 | BA10: =INDEX(Model_Assumptions[Values],9)*((INDEX(Model_Scenarios[GR Weight],2)*$AG10)+(INDEX(Model_Scenarios[GP Weight],2)*$AH10)+(INDEX(Model_Scenarios[LTV Weight],2)*$AI10))-(INDEX(Model_Scenarios[LTV Weight],2)*$AP10)-(INDEX(Model_Scenarios[GP Weight],2)*($AS10+$AV10+$AY10)) -> 1.8677592 | BB10: =INDEX(Model_Assumptions[Values],9)*((INDEX(Model_Scenarios[GR Weight],3)*$AG10)+(INDEX(Model_Scenarios[GP Weight],3)*$AH10)+(INDEX(Model_Scenarios[LTV Weight],3)*$AI10))-(INDEX(Model_Scenarios[LTV Weight],3)*$AP10)-(INDEX(Model_Scenarios[GP Weight],3)*($AS10+$AV10+$AY10)) -> 0.97355933 | BC10: =INDEX(Model_Assumptions[Values],9)*((INDEX(Model_Scenarios[GR Weight],4)*$AG10)+(INDEX(Model_Scenarios[GP Weight],4)*$AH10)+(INDEX(Model_Scenarios[LTV Weight],4)*$AI10))-(INDEX(Model_Scenarios[LTV Weight],4)*$AP10)-(INDEX(Model_Scenarios[GP Weight],4)*($AS10+$AV10+$AY10)) -> 0.9380316 | BD10: =INDEX(Model_Assumptions[Values],9)*((INDEX(Model_Scenarios[GR Weight],5)*$AG10)+(INDEX(Model_Scenarios[GP Weight],5)*$AH10)+(INDEX(Model_Scenarios[LTV Weight],5)*$AI10))-(INDEX(Model_Scenarios[LTV Weight],5)*$AP10)-(INDEX(Model_Scenarios[GP Weight],5)*($AS10+$AV10+$AY10)) -> -0.15357301
A11: 10 | B11: 1 | C11: 10 | D11: 0.18 | E11: SKU-1000 | F11: Raise | G11: Full | H11: 76.53 | I11: 52.96 | J11: 24 | K11: 1836.72 | L11: 565.68 | M11: 0.3079838 | N11: 80.606323 | O11: 17.225425 | P11: 70.185425 | Q11: 1112.0932 | R11: 895.23502 | S11: 1 | T11: =$H11 + MIN($D11, $S11) * ($N11 - $H11) -> 77.263738 | U11: =IFERROR(($T11-$H11)/$H11, 0) -> 0.009587588 | V11: =IF($F11="Reduce", INDEX(Model_Assumptions[Values], 2), INDEX(Model_Assumptions[Values], 1)) -> -0.4 | W11: =$J11 * (1 + ($U11 * $V11)) -> 23.907959 | X11: =$W11*$T11 -> 1847.2183 | Y11: =$X11-($W11*$I11) -> 581.05278 | Z11: =$X11-$K11 -> 10.498295 | AA11: =$Y11-$L11 -> 15.372778 | AB11: =IFERROR($Y11/$X11,0) -> 0.31455556 | AC11: =$AB11-$M11 -> 0.0065717589 | AD11: =IFERROR(($X11-($W11*$I11))/$X11, 0) - IFERROR(($K11-($J11*$I11))/$K11, 0) -> 0.0065717589 | AE11: =IFERROR(($T11-$H11)/($N11-$H11), 0) -> 0.18 | AF11: =$R11 * (1 - $AE11) -> 734.09272 | AG11: =IFERROR($Z11/$O11, 0) -> 0.60946506 | AH11: =IFERROR($AA11/$P11, 0) -> 0.21903092 | AI11: =IFERROR($AF11/$R11, 0) -> 0.82 | AJ11: =MAX(0, $R11 - $AA11) * INDEX(Model_Assumptions[Values], 7) -> 1759.7245 | AK11: =MAX(0, INDEX(Model_Assumptions[Values], 4) - $AD11) -> 0.043428241 | AL11: =MAX(0, INDEX(Model_Assumptions[Values], 5) - $AC11) -> 0.013428241 | AM11: =INDEX(Model_Assumptions[Values], 6) * MAX(0, INDEX(Model_Assumptions[Values], 3) - $AB11)^2 -> 0 | AN11: =AVERAGEIF($E$2:$E$2201, $E11, $AJ$2:$AJ$2201) -> 1707.7543 | AO11: {=IFERROR(STDEV(IF($E$2:$E$2201=$E11, $AJ$2:$AJ$2201)), 0)} -> 48.827543 | AP11: =IF($AO11=0, 0, ($AJ11-$AN11)/$AO11) -> 1.0643621 | AQ11: =AVERAGEIF($E$2:$E$2201, $E11, $AK$2:$AK$2201) -> 0.032549534 | AR11: {=IFERROR(STDEV(IF($E$2:$E$2201=$E11, $AK$2:$AK$2201)), 0)} -> 0.010211698 | AS11: =IF($AR11=0, 0, ($AK11-$AQ11)/$AR11) -> 1.0653181 | AT11: =AVERAGEIF($E$2:$E$2201, $E11, $AL$2:$AL$2201) -> 0.0057333065 | AU11: {=IFERROR(STDEV(IF($E$2:$E$2201=$E11, $AL$2:$AL$2201)), 0)} -> 0.0067452578 | AV11: =IF($AU11=0, 0, ($AL11-$AT11)/$AU11) -> 1.1407918 | AW11: =AVERAGEIF($E$2:$E$2201, $E11, $AM$2:$AM$2201) -> 0 | AX11: {=IFERROR(STDEV(IF($E$2:$E$2201=$E11, $AM$2:$AM$2201)), 0)} -> 0 | AY11: =IF($AU11=0, 0, ($AL11-$AT11)/$AU11) -> 1.1407918 | AZ11: =INDEX(Model_Assumptions[Values],9)*((INDEX(Model_Scenarios[GR Weight],1)*$AG11)+(INDEX(Model_Scenarios[GP Weight],1)*$AH11)+(INDEX(Model_Scenarios[LTV Weight],1)*$AI11))-(INDEX(Model_Scenarios[LTV Weight],1)*$AP11)-(INDEX(Model_Scenarios[GP Weight],1)*($AS11+$AV11+$AY11)) -> 2.5080681 | BA11: =INDEX(Model_Assumptions[Values],9)*((INDEX(Model_Scenarios[GR Weight],2)*$AG11)+(INDEX(Model_Scenarios[GP Weight],2)*$AH11)+(INDEX(Model_Scenarios[LTV Weight],2)*$AI11))-(INDEX(Model_Scenarios[LTV Weight],2)*$AP11)-(INDEX(Model_Scenarios[GP Weight],2)*($AS11+$AV11+$AY11)) -> 1.979914 | BB11: =INDEX(Model_Assumptions[Values],9)*((INDEX(Model_Scenarios[GR Weight],3)*$AG11)+(INDEX(Model_Scenarios[GP Weight],3)*$AH11)+(INDEX(Model_Scenarios[LTV Weight],3)*$AI11))-(INDEX(Model_Scenarios[LTV Weight],3)*$AP11)-(INDEX(Model_Scenarios[GP Weight],3)*($AS11+$AV11+$AY11)) -> 1.187975 | BC11: =INDEX(Model_Assumptions[Values],9)*((INDEX(Model_Scenarios[GR Weight],4)*$AG11)+(INDEX(Model_Scenarios[GP Weight],4)*$AH11)+(INDEX(Model_Scenarios[LTV Weight],4)*$AI11))-(INDEX(Model_Scenarios[LTV Weight],4)*$AP11)-(INDEX(Model_Scenarios[GP Weight],4)*($AS11+$AV11+$AY11)) -> 1.1891438 | BD11: =INDEX(Model_Assumptions[Values],9)*((INDEX(Model_Scenarios[GR Weight],5)*$AG11)+(INDEX(Model_Scenarios[GP Weight],5)*$AH11)+(INDEX(Model_Scenarios[LTV Weight],5)*$AI11))-(INDEX(Model_Scenarios[LTV Weight],5)*$AP11)-(INDEX(Model_Scenarios[GP Weight],5)*($AS11+$AV11+$AY11)) -> 0.12991366
A12: 11 | B12: 1 | C12: 11 | D12: 0.2 | E12: SKU-1000 | F12: Raise | G12: Full | H12: 76.53 | I12: 52.96 | J12: 24 | K12: 1836.72 | L12: 565.68 | M12: 0.3079838 | N12: 80.606323 | O12: 17.225425 | P12: 70.185425 | Q12: 1112.0932 | R12: 895.23502 | S12: 1 | T12: =$H12 + MIN($D12, $S12) * ($N12 - $H12) -> 77.345265 | U12: =IFERROR(($T12-$H12)/$H12, 0) -> 0.010652876 | V12: =IF($F12="Reduce", INDEX(Model_Assumptions[Values], 2), INDEX(Model_Assumptions[Values], 1)) -> -0.4 | W12: =$J12 * (1 + ($U12 * $V12)) -> 23.897732 | X12: =$W12*$T12 -> 1848.3764 | Y12: =$X12-($W12*$I12) -> 582.75253 | Z12: =$X12-$K12 -> 11.656435 | AA12: =$Y12-$L12 -> 17.072527 | AB12: =IFERROR($Y12/$X12,0) -> 0.31527805 | AC12: =$AB12-$M12 -> 0.0072942577 | AD12: =IFERROR(($X12-($W12*$I12))/$X12, 0) - IFERROR(($K12-($J12*$I12))/$K12, 0) -> 0.0072942577 | AE12: =IFERROR(($T12-$H12)/($N12-$H12), 0) -> 0.2 | AF12: =$R12 * (1 - $AE12) -> 716.18802 | AG12: =IFERROR($Z12/$O12, 0) -> 0.67669938 | AH12: =IFERROR($AA12/$P12, 0) -> 0.24324889 | AI12: =IFERROR($AF12/$R12, 0) -> 0.8 | AJ12: =MAX(0, $R12 - $AA12) * INDEX(Model_Assumptions[Values], 7) -> 1756.325 | AK12: =MAX(0, INDEX(Model_Assumptions[Values], 4) - $AD12) -> 0.042705742 | AL12: =MAX(0, INDEX(Model_Assumptions[Values], 5) - $AC12) -> 0.012705742 | AM12: =INDEX(Model_Assumptions[Values], 6) * MAX(0, INDEX(Model_Assumptions[Values], 3) - $AB12)^2 -> 0 | AN12: =AVERAGEIF($E$2:$E$2201, $E12, $AJ$2:$AJ$2201) -> 1707.7543 | AO12: {=IFERROR(STDEV(IF($E$2:$E$2201=$E12, $AJ$2:$AJ$2201)), 0)} -> 48.827543 | AP12: =IF($AO12=0, 0, ($AJ12-$AN12)/$AO12) -> 0.99473958 | AQ12: =AVERAGEIF($E$2:$E$2201, $E12, $AK$2:$AK$2201) -> 0.032549534 | AR12: {=IFERROR(STDEV(IF($E$2:$E$2201=$E12, $AK$2:$AK$2201)), 0)} -> 0.010211698 | AS12: =IF($AR12=0, 0, ($AK12-$AQ12)/$AR12) -> 0.99456602 | AT12: =AVERAGEIF($E$2:$E$2201, $E12, $AL$2:$AL$2201) -> 0.0057333065 | AU12: {=IFERROR(STDEV(IF($E$2:$E$2201=$E12, $AL$2:$AL$2201)), 0)} -> 0.0067452578 | AV12: =IF($AU12=0, 0, ($AL12-$AT12)/$AU12) -> 1.0336797 | AW12: =AVERAGEIF($E$2:$E$2201, $E12, $AM$2:$AM$2201) -> 0 | AX12: {=IFERROR(STDEV(IF($E$2:$E$2201=$E12, $AM$2:$AM$2201)), 0)} -> 0 | AY12: =IF($AU12=0, 0, ($AL12-$AT12)/$AU12) -> 1.0336797 | AZ12: =INDEX(Model_Assumptions[Values],9)*((INDEX(Model_Scenarios[GR Weight],1)*$AG12)+(INDEX(Model_Scenarios[GP Weight],1)*$AH12)+(INDEX(Model_Scenarios[LTV Weight],1)*$AI12))-(INDEX(Model_Scenarios[LTV Weight],1)*$AP12)-(INDEX(Model_Scenarios[GP Weight],1)*($AS12+$AV12+$AY12)) -> 2.5579899 | BA12: =INDEX(Model_Assumptions[Values],9)*((INDEX(Model_Scenarios[GR Weight],2)*$AG12)+(INDEX(Model_Scenarios[GP Weight],2)*$AH12)+(INDEX(Model_Scenarios[LTV Weight],2)*$AI12))-(INDEX(Model_Scenarios[LTV Weight],2)*$AP12)-(INDEX(Model_Scenarios[GP Weight],2)*($AS12+$AV12+$AY12)) -> 2.0918076 | BB12: =INDEX(Model_Assumptions[Values],9)*((INDEX(Model_Scenarios[GR Weight],3)*$AG12)+(INDEX(Model_Scenarios[GP Weight],3)*$AH12)+(INDEX(Model_Scenarios[LTV Weight],3)*$AI12))-(INDEX(Model_Scenarios[LTV Weight],3)*$AP12)-(INDEX(Model_Scenarios[GP Weight],3)*($AS12+$AV12+$AY12)) -> 1.4019901 | BC12: =INDEX(Model_Assumptions[Values],9)*((INDEX(Model_Scenarios[GR Weight],4)*$AG12)+(INDEX(Model_Scenarios[GP Weight],4)*$AH12)+(INDEX(Model_Scenarios[LTV Weight],4)*$AI12))-(INDEX(Model_Scenarios[LTV Weight],4)*$AP12)-(INDEX(Model_Scenarios[GP Weight],4)*($AS12+$AV12+$AY12)) -> 1.4398137 | BD12: =INDEX(Model_Assumptions[Values],9)*((INDEX(Model_Scenarios[GR Weight],5)*$AG12)+(INDEX(Model_Scenarios[GP Weight],5)*$AH12)+(INDEX(Model_Scenarios[LTV Weight],5)*$AI12))-(INDEX(Model_Scenarios[LTV Weight],5)*$AP12)-(INDEX(Model_Scenarios[GP Weight],5)*($AS12+$AV12+$AY12)) -> 0.41289
A13: 12 | B13: 1 | C13: 12 | D13: 0.22 | E13: SKU-1000 | F13: Raise | G13: Full | H13: 76.53 | I13: 52.96 | J13: 24 | K13: 1836.72 | L13: 565.68 | M13: 0.3079838 | N13: 80.606323 | O13: 17.225425 | P13: 70.185425 | Q13: 1112.0932 | R13: 895.23502 | S13: 1 | T13: =$H13 + MIN($D13, $S13) * ($N13 - $H13) -> 77.426791 | U13: =IFERROR(($T13-$H13)/$H13, 0) -> 0.011718163 | V13: =IF($F13="Reduce", INDEX(Model_Assumptions[Values], 2), INDEX(Model_Assumptions[Values], 1)) -> -0.4 | W13: =$J13 * (1 + ($U13 * $V13)) -> 23.887506 | X13: =$W13*$T13 -> 1849.5329 | Y13: =$X13-($W13*$I13) -> 584.45061 | Z13: =$X13-$K13 -> 12.812907 | AA13: =$Y13-$L13 -> 18.770608 | AB13: =IFERROR($Y13/$X13,0) -> 0.31599903 | AC13: =$AB13-$M13 -> 0.0080152349 | AD13: =IFERROR(($X13-($W13*$I13))/$X13, 0) - IFERROR(($K13-($J13*$I13))/$K13, 0) -> 0.0080152349 | AE13: =IFERROR(($T13-$H13)/($N13-$H13), 0) -> 0.22 | AF13: =$R13 * (1 - $AE13) -> 698.28332 | AG13: =IFERROR($Z13/$O13, 0) -> 0.74383689 | AH13: =IFERROR($AA13/$P13, 0) -> 0.26744311 | AI13: =IFERROR($AF13/$R13, 0) -> 0.78 | AJ13: =MAX(0, $R13 - $AA13) * INDEX(Model_Assumptions[Values], 7) -> 1752.9288 | AK13: =MAX(0, INDEX(Model_Assumptions[Values], 4) - $AD13) -> 0.041984765 | AL13: =MAX(0, INDEX(Model_Assumptions[Values], 5) - $AC13) -> 0.011984765 | AM13: =INDEX(Model_Assumptions[Values], 6) * MAX(0, INDEX(Model_Assumptions[Values], 3) - $AB13)^2 -> 0 | AN13: =AVERAGEIF($E$2:$E$2201, $E13, $AJ$2:$AJ$2201) -> 1707.7543 | AO13: {=IFERROR(STDEV(IF($E$2:$E$2201=$E13, $AJ$2:$AJ$2201)), 0)} -> 48.827543 | AP13: =IF($AO13=0, 0, ($AJ13-$AN13)/$AO13) -> 0.92518534 | AQ13: =AVERAGEIF($E$2:$E$2201, $E13, $AK$2:$AK$2201) -> 0.032549534 | AR13: {=IFERROR(STDEV(IF($E$2:$E$2201=$E13, $AK$2:$AK$2201)), 0)} -> 0.010211698 | AS13: =IF($AR13=0, 0, ($AK13-$AQ13)/$AR13) -> 0.92396295 | AT13: =AVERAGEIF($E$2:$E$2201, $E13, $AL$2:$AL$2201) -> 0.0057333065 | AU13: {=IFERROR(STDEV(IF($E$2:$E$2201=$E13, $AL$2:$AL$2201)), 0)} -> 0.0067452578 | AV13: =IF($AU13=0, 0, ($AL13-$AT13)/$AU13) -> 0.92679313 | AW13: =AVERAGEIF($E$2:$E$2201, $E13, $AM$2:$AM$2201) -> 0 | AX13: {=IFERROR(STDEV(IF($E$2:$E$2201=$E13, $AM$2:$AM$2201)), 0)} -> 0 | AY13: =IF($AU13=0, 0, ($AL13-$AT13)/$AU13) -> 0.92679313 | AZ13: =INDEX(Model_Assumptions[Values],9)*((INDEX(Model_Scenarios[GR Weight],1)*$AG13)+(INDEX(Model_Scenarios[GP Weight],1)*$AH13)+(INDEX(Model_Scenarios[LTV Weight],1)*$AI13))-(INDEX(Model_Scenarios[LTV Weight],1)*$AP13)-(INDEX(Model_Scenarios[GP Weight],1)*($AS13+$AV13+$AY13)) -> 2.6077368 | BA13: =INDEX(Model_Assumptions[Values],9)*((INDEX(Model_Scenarios[GR Weight],2)*$AG13)+(INDEX(Model_Scenarios[GP Weight],2)*$AH13)+(INDEX(Model_Scenarios[LTV Weight],2)*$AI13))-(INDEX(Model_Scenarios[LTV Weight],2)*$AP13)-(INDEX(Model_Scenarios[GP Weight],2)*($AS13+$AV13+$AY13)) -> 2.2034405 | BB13: =INDEX(Model_Assumptions[Values],9)*((INDEX(Model_Scenarios[GR Weight],3)*$AG13)+(INDEX(Model_Scenarios[GP Weight],3)*$AH13)+(INDEX(Model_Scenarios[LTV Weight],3)*$AI13))-(INDEX(Model_Scenarios[LTV Weight],3)*$AP13)-(INDEX(Model_Scenarios[GP Weight],3)*($AS13+$AV13+$AY13)) -> 1.6156052 | BC13: =INDEX(Model_Assumptions[Values],9)*((INDEX(Model_Scenarios[GR Weight],4)*$AG13)+(INDEX(Model_Scenarios[GP Weight],4)*$AH13)+(INDEX(Model_Scenarios[LTV Weight],4)*$AI13))-(INDEX(Model_Scenarios[LTV Weight],4)*$AP13)-(INDEX(Model_Scenarios[GP Weight],4)*($AS13+$AV13+$AY13)) -> 1.6900422 | BD13: =INDEX(Model_Assumptions[Values],9)*((INDEX(Model_Scenarios[GR Weight],5)*$AG13)+(INDEX(Model_Scenarios[GP Weight],5)*$AH13)+(INDEX(Model_Scenarios[LTV Weight],5)*$AI13))-(INDEX(Model_Scenarios[LTV Weight],5)*$AP13)-(INDEX(Model_Scenarios[GP Weight],5)*($AS13+$AV13+$AY13)) -> 0.69535704
A14: 13 | B14: 1 | C14: 13 | D14: 0.24 | E14: SKU-1000 | F14: Raise | G14: Full | H14: 76.53 | I14: 52.96 | J14: 24 | K14: 1836.72 | L14: 565.68 | M14: 0.3079838 | N14: 80.606323 | O14: 17.225425 | P14: 70.185425 | Q14: 1112.0932 | R14: 895.23502 | S14: 1 | T14: =$H14 + MIN($D14, $S14) * ($N14 - $H14) -> 77.508317 | U14: =IFERROR(($T14-$H14)/$H14, 0) -> 0.012783451 | V14: =IF($F14="Reduce", INDEX(Model_Assumptions[Values], 2), INDEX(Model_Assumptions[Values], 1)) -> -0.4 | W14: =$J14 * (1 + ($U14 * $V14)) -> 23.877279 | X14: =$W14*$T14 -> 1850.6877 | Y14: =$X14-($W14*$I14) -> 586.14702 | Z14: =$X14-$K14 -> 13.967712 | AA14: =$Y14-$L14 -> 20.467022 | AB14: =IFERROR($Y14/$X14,0) -> 0.31671849 | AC14: =$AB14-$M14 -> 0.0087346955 | AD14: =IFERROR(($X14-($W14*$I14))/$X14, 0) - IFERROR(($K14-($J14*$I14))/$K14, 0) -> 0.0087346955 | AE14: =IFERROR(($T14-$H14)/($N14-$H14), 0) -> 0.24 | AF14: =$R14 * (1 - $AE14) -> 680.37862 | AG14: =IFERROR($Z14/$O14, 0) -> 0.8108776 | AH14: =IFERROR($AA14/$P14, 0) -> 0.29161357 | AI14: =IFERROR($AF14/$R14, 0) -> 0.76 | AJ14: =MAX(0, $R14 - $AA14) * INDEX(Model_Assumptions[Values], 7) -> 1749.536 | AK14: =MAX(0, INDEX(Model_Assumptions[Values], 4) - $AD14) -> 0.041265305 | AL14: =MAX(0, INDEX(Model_Assumptions[Values], 5) - $AC14) -> 0.011265305 | AM14: =INDEX(Model_Assumptions[Values], 6) * MAX(0, INDEX(Model_Assumptions[Values], 3) - $AB14)^2 -> 0 | AN14: =AVERAGEIF($E$2:$E$2201, $E14, $AJ$2:$AJ$2201) -> 1707.7543 | AO14: {=IFERROR(STDEV(IF($E$2:$E$2201=$E14, $AJ$2:$AJ$2201)), 0)} -> 48.827543 | AP14: =IF($AO14=0, 0, ($AJ14-$AN14)/$AO14) -> 0.8556994 | AQ14: =AVERAGEIF($E$2:$E$2201, $E14, $AK$2:$AK$2201) -> 0.032549534 | AR14: {=IFERROR(STDEV(IF($E$2:$E$2201=$E14, $AK$2:$AK$2201)), 0)} -> 0.010211698 | AS14: =IF($AR14=0, 0, ($AK14-$AQ14)/$AR14) -> 0.85350841 | AT14: =AVERAGEIF($E$2:$E$2201, $E14, $AL$2:$AL$2201) -> 0.0057333065 | AU14: {=IFERROR(STDEV(IF($E$2:$E$2201=$E14, $AL$2:$AL$2201)), 0)} -> 0.0067452578 | AV14: =IF($AU14=0, 0, ($AL14-$AT14)/$AU14) -> 0.82013145 | AW14: =AVERAGEIF($E$2:$E$2201, $E14, $AM$2:$AM$2201) -> 0 | AX14: {=IFERROR(STDEV(IF($E$2:$E$2201=$E14, $AM$2:$AM$2201)), 0)} -> 0 | AY14: =IF($AU14=0, 0, ($AL14-$AT14)/$AU14) -> 0.82013145 | AZ14: =INDEX(Model_Assumptions[Values],9)*((INDEX(Model_Scenarios[GR Weight],1)*$AG14)+(INDEX(Model_Scenarios[GP Weight],1)*$AH14)+(INDEX(Model_Scenarios[LTV Weight],1)*$AI14))-(INDEX(Model_Scenarios[LTV Weight],1)*$AP14)-(INDEX(Model_Scenarios[GP Weight],1)*($AS14+$AV14+$AY14)) -> 2.6573089 | BA14: =INDEX(Model_Assumptions[Values],9)*((INDEX(Model_Scenarios[GR Weight],2)*$AG14)+(INDEX(Model_Scenarios[GP Weight],2)*$AH14)+(INDEX(Model_Scenarios[LTV Weight],2)*$AI14))-(INDEX(Model_Scenarios[LTV Weight],2)*$AP14)-(INDEX(Model_Scenarios[GP Weight],2)*($AS14+$AV14+$AY14)) -> 2.3148129 | BB14: =INDEX(Model_Assumptions[Values],9)*((INDEX(Model_Scenarios[GR Weight],3)*$AG14)+(INDEX(Model_Scenarios[GP Weight],3)*$AH14)+(INDEX(Model_Scenarios[LTV Weight],3)*$AI14))-(INDEX(Model_Scenarios[LTV Weight],3)*$AP14)-(INDEX(Model_Scenarios[GP Weight],3)*($AS14+$AV14+$AY14)) -> 1.828821 | BC14: =INDEX(Model_Assumptions[Values],9)*((INDEX(Model_Scenarios[GR Weight],4)*$AG14)+(INDEX(Model_Scenarios[GP Weight],4)*$AH14)+(INDEX(Model_Scenarios[LTV Weight],4)*$AI14))-(INDEX(Model_Scenarios[LTV Weight],4)*$AP14)-(INDEX(Model_Scenarios[GP Weight],4)*($AS14+$AV14+$AY14)) -> 1.9398298 | BD14: =INDEX(Model_Assumptions[Values],9)*((INDEX(Model_Scenarios[GR Weight],5)*$AG14)+(INDEX(Model_Scenarios[GP Weight],5)*$AH14)+(INDEX(Model_Scenarios[LTV Weight],5)*$AI14))-(INDEX(Model_Scenarios[LTV Weight],5)*$AP14)-(INDEX(Model_Scenarios[GP Weight],5)*($AS14+$AV14+$AY14)) -> 0.97731584
... A2101: 2100 | B2101: 42 | C2101: 50 | D2101: 0.98 | E2101: SKU-1049 | F2101: Raise | G2101: Full | H2101: 99.75 | I2101: 38.13 | J2101: 34 | K2101: 3391.5 | L2101: 2095.08 | M2101: 0.61774436 | N2101: 110.43409 | O2101: 597.24501 | P2101: 635.37501 | Q2101: 1533.9834 | R2101: 1185.8872 | S2101: 1 | T2101: =$H2101 + MIN($D2101, $S2101) * ($N2101 - $H2101) -> 110.22041 | U2101: =IFERROR(($T2101-$H2101)/$H2101, 0) -> 0.10496651 | V2101: =IF($F2101="Reduce", INDEX(Model_Assumptions[Values], 2), INDEX(Model_Assumptions[Values], 1)) -> -0.4 | W2101: =$J2101 * (1 + ($U2101 * $V2101)) -> 32.572455 | X2101: =$W2101*$T2101 -> 3590.1494 | Y2101: =$X2101-($W2101*$I2101) -> 2348.1616 | Z2101: =$X2101-$K2101 -> 198.64938 | AA2101: =$Y2101-$L2101 -> 253.08165 | AB2101: =IFERROR($Y2101/$X2101,0) -> 0.65405681 | AC2101: =$AB2101-$M2101 -> 0.036312449 | AD2101: =IFERROR(($X2101-($W2101*$I2101))/$X2101, 0) - IFERROR(($K2101-($J2101*$I2101))/$K2101, 0) -> 0.036312449 | AE2101: =IFERROR(($T2101-$H2101)/($N2101-$H2101), 0) -> 0.98 | AF2101: =$R2101 * (1 - $AE2101) -> 23.717744 | AG2101: =IFERROR($Z2101/$O2101, 0) -> 0.33260952 | AH2101: =IFERROR($AA2101/$P2101, 0) -> 0.39831854 | AI2101: =IFERROR($AF2101/$R2101, 0) -> 0.02 | AJ2101: =MAX(0, $R2101 - $AA2101) * INDEX(Model_Assumptions[Values], 7) -> 1865.6111 | AK2101: =MAX(0, INDEX(Model_Assumptions[Values], 4) - $AD2101) -> 0.013687551 | AL2101: =MAX(0, INDEX(Model_Assumptions[Values], 5) - $AC2101) -> 0 | AM2101: =INDEX(Model_Assumptions[Values], 6) * MAX(0, INDEX(Model_Assumptions[Values], 3) - $AB2101)^2 -> 0 | AN2101: =AVERAGEIF($E$2:$E$2201, $E2101, $AJ$2:$AJ$2201) -> 2113.8121 | AO2101: {=IFERROR(STDEV(IF($E$2:$E$2201=$E2101, $AJ$2:$AJ$2201)), 0)} -> 150.60054 | AP2101: =IF($AO2101=0, 0, ($AJ2101-$AN2101)/$AO2101) -> -1.6480751 | AQ2101: =AVERAGEIF($E$2:$E$2201, $E2101, $AK$2:$AK$2201) -> 0.031252213 | AR2101: {=IFERROR(STDEV(IF($E$2:$E$2201=$E2101, $AK$2:$AK$2201)), 0)} -> 0.010796484 | AS2101: =IF($AR2101=0, 0, ($AK2101-$AQ2101)/$AR2101) -> -1.6268872 | AT2101: =AVERAGEIF($E$2:$E$2201, $E2101, $AL$2:$AL$2201) -> 0.0052636488 | AU2101: {=IFERROR(STDEV(IF($E$2:$E$2201=$E2101, $AL$2:$AL$2201)), 0)} -> 0.0066424286 | AV2101: =IF($AU2101=0, 0, ($AL2101-$AT2101)/$AU2101) -> -0.79242836 | AW2101: =AVERAGEIF($E$2:$E$2201, $E2101, $AM$2:$AM$2201) -> 0 | AX2101: {=IFERROR(STDEV(IF($E$2:$E$2201=$E2101, $AM$2:$AM$2201)), 0)} -> 0 | AY2101: =IF($AU2101=0, 0, ($AL2101-$AT2101)/$AU2101) -> -0.79242836 | AZ2101: =INDEX(Model_Assumptions[Values],9)*((INDEX(Model_Scenarios[GR Weight],1)*$AG2101)+(INDEX(Model_Scenarios[GP Weight],1)*$AH2101)+(INDEX(Model_Scenarios[LTV Weight],1)*$AI2101))-(INDEX(Model_Scenarios[LTV Weight],1)*$AP2101)-(INDEX(Model_Scenarios[GP Weight],1)*($AS2101+$AV2101+$AY2101)) -> 2.0850985 | BA2101: =INDEX(Model_Assumptions[Values],9)*((INDEX(Model_Scenarios[GR Weight],2)*$AG2101)+(INDEX(Model_Scenarios[GP Weight],2)*$AH2101)+(INDEX(Model_Scenarios[LTV Weight],2)*$AI2101))-(INDEX(Model_Scenarios[LTV Weight],2)*$AP2101)-(INDEX(Model_Scenarios[GP Weight],2)*($AS2101+$AV2101+$AY2101)) -> 2.4263733 | BB2101: =INDEX(Model_Assumptions[Values],9)*((INDEX(Model_Scenarios[GR Weight],3)*$AG2101)+(INDEX(Model_Scenarios[GP Weight],3)*$AH2101)+(INDEX(Model_Scenarios[LTV Weight],3)*$AI2101))-(INDEX(Model_Scenarios[LTV Weight],3)*$AP2101)-(INDEX(Model_Scenarios[GP Weight],3)*($AS2101+$AV2101+$AY2101)) -> 2.9361598 | BC2101: =INDEX(Model_Assumptions[Values],9)*((INDEX(Model_Scenarios[GR Weight],4)*$AG2101)+(INDEX(Model_Scenarios[GP Weight],4)*$AH2101)+(INDEX(Model_Scenarios[LTV Weight],4)*$AI2101))-(INDEX(Model_Scenarios[LTV Weight],4)*$AP2101)-(INDEX(Model_Scenarios[GP Weight],4)*($AS2101+$AV2101+$AY2101)) -> 2.927657 | BD2101: =INDEX(Model_Assumptions[Values],9)*((INDEX(Model_Scenarios[GR Weight],5)*$AG2101)+(INDEX(Model_Scenarios[GP Weight],5)*$AH2101)+(INDEX(Model_Scenarios[LTV Weight],5)*$AI2101))-(INDEX(Model_Scenarios[LTV Weight],5)*$AP2101)-(INDEX(Model_Scenarios[GP Weight],5)*($AS2101+$AV2101+$AY2101)) -> 3.6314634

Sheet Model Assumptions
A1: MONTE CARLO MODEL ASSUMPTIONS | B1: Values
A2: Raise Elasticity | B2: -0.4
A3: Reduce Elasticity | B3: -0.8
A4: Margin Floor | B4: 0.2
A5: Minimum Gross Revenue Lift % | B5: 0.05
A6: Minimum Gross Profit Margin Lift % | B6: 0.02
A7: Quadratic Margin Penalty | B7: 50
A8: LTV Recovery Penalty Multiplier | B8: 2
A9: Grid Step Size % | B9: 0.02
A10: Reward Multiplier | B10: 5
A11: Penalty Dampner | B11: 4

Sheet Model Input
A1: SKU | B1: Tie-Breaking Recommendation | C1: Candidate Type | D1: Current Price | E1: Current Cost Per Unit | F1: Current Volume | G1: Current Gross Revenue | H1: Current Gross Profit | I1: Current Gross Profit Margin % | J1: V1 Suggested Price | K1: V1 Gross Revenue Impact | L1: V1 Gross Profit Impact $ | M1: Total LTV at Risk | N1: % Critical | O1: % High | P1: % Medium | Q1: %Low
A2: SKU-1000 | B2: Raise | C2: Full | D2: 76.53 | E2: 52.96 | F2: 24 | G2: 1836.72 | H2: 565.68 | I2: 0.3079838 | J2: 80.606323 | K2: 17.225425 | L2: 70.185425 | M2: 1112.0932 | N2: 0.5 | O2: 0.3 | P2: 0.2 | Q2: 0
A3: SKU-1001 | B3: Raise | C3: Full | D3: 53.26 | E3: 36.64 | F3: 21 | G3: 1118.46 | H3: 349.02 | I3: 0.31205407 | J3: 57.563992 | K3: 32.819836 | L3: 69.459836 | M3: 1487.03 | N3: 0.33333333 | O3: 0.44444444 | P3: 0.22222222 | Q3: 0
A4: SKU-1004 | B4: Hold | C4: Full | D4: 18.39 | E4: 8.26 | F4: 17 | G4: 312.63 | H4: 172.21 | I4: 0.55084285 | J4: 20.325622 | K4: 12.579946 | L4: 20.839946 | M4: 1216.0707 | N4: 0.55555556 | O4: 0.11111111 | P4: 0.33333333 | Q4: 0
A5: SKU-1005 | B5: Raise | C5: Full | D5: 29.62 | E5: 19.42 | F5: 46 | G5: 1362.52 | H5: 469.2 | I5: 0.34436192 | J5: 28.258195 | K5: 110.97518 | L5: 91.555177 | M5: 1171.8239 | N5: 0.41176471 | O5: 0.41176471 | P5: 0.17647059 | Q5: 0
A6: SKU-1006 | B6: Hold | C6: Full | D6: 113.18 | E6: 39.01 | F6: 24 | G6: 2716.32 | H6: 1780.08 | I6: 0.6553278 | J6: 122.07351 | K6: 91.370781 | L6: 130.38078 | M6: 1378.1368 | N6: 0.4 | O6: 0.3 | P6: 0.2 | Q6: 0.1
A7: SKU-1009 | B7: Raise | C7: Full | D7: 177.91 | E7: 73.49 | F7: 36 | G7: 6404.76 | H7: 3759.12 | I7: 0.58692597 | J7: 210.36242 | K7: 2118.3199 | L7: 2338.7899 | M7: 1987.1738 | N7: 0.58333333 | O7: 0.33333333 | P7: 0.083333333 | Q7: 0
A8: SKU-1010 | B8: Raise | C8: Full | D8: 45.86 | E8: 24.87 | F8: 42 | G8: 1926.12 | H8: 881.58 | I8: 0.45769734 | J8: 57.591702 | K8: 713.86466 | L8: 813.34466 | M8: 1838.4437 | N8: 0.70588235 | O8: 0.23529412 | P8: 0.058823529 | Q8: 0
A9: SKU-1011 | B9: Raise | C9: Full | D9: 67.56 | E9: 43.21 | F9: 22 | G9: 1486.32 | H9: 535.7 | I9: 0.36042037 | J9: 74.848492 | K9: 85.498342 | L9: 128.70834 | M9: 1511.5432 | N9: 0.4 | O9: 0.2 | P9: 0.4 | Q9: 0
A10: SKU-1012 | B10: Raise | C10: Full | D10: 20.37 | E10: 9.76 | F10: 15 | G10: 305.55 | H10: 159.15 | I10: 0.52086402 | J10: 20.226862 | K10: 49.152923 | L10: 49.152923 | M10: 464.13364 | N10: 0.42857143 | O10: 0.14285714 | P10: 0.28571429 | Q10: 0.14285714
A11: SKU-1013 | B11: Raise | C11: Constrained | D11: 84.95 | E11: 53.07 | F11: 36 | G11: 3058.2 | H11: 1147.68 | I11: 0.37527958 | J11: 84.95 | K11: 0 | L11: 0 | M11: 1153.7475 | N11: 0.57142857 | O11: 0.14285714 | P11: 0.21428571 | Q11: 0.071428571
A12: SKU-1014 | B12: Raise | C12: Full | D12: 143.8 | E12: 62.15 | F12: 29 | G12: 4170.2 | H12: 2367.85 | I12: 0.5678025 | J12: 176.09453 | K12: 408.25774 | L12: 594.70774 | M12: 1207.1798 | N12: 0.5 | O12: 0.5 | P12: 0 | Q12: 0
A13: SKU-1017 | B13: Raise | C13: Full | D13: 63.19 | E13: 41.45 | F13: 19 | G13: 1200.61 | H13: 413.06 | I13: 0.34404178 | J13: 64.147136 | K13: 148.52558 | L13: 148.52558 | M13: 1170.2078 | N13: 0.55555556 | O13: 0 | P13: 0.44444444 | Q13: 0
... A43: SKU-1049 | B43: Raise | C43: Full | D43: 99.75 | E43: 38.13 | F43: 34 | G43: 3391.5 | H43: 2095.08 | I43: 0.61774436 | J43: 110.43409 | K43: 597.24501 | L43: 635.37501 | M43: 1533.9834 | N43: 0.30769231 | O43: 0.53846154 | P43: 0.15384615 | Q43: 0

Sheet Model Scenarios
A1: SCENARIOS | B1: GR Weight | C1: GP Weight | D1: LTV Weight
A2: Aggressive Conservative | B2: 0.1 | C2: 0.1 | D2: 0.8
A3: Conservative | B3: 0.15 | C3: 0.2 | D3: 0.65
A4: Balanced | B4: 0.25 | C4: 0.35 | D4: 0.4
A5: Growth | B5: 0.35 | C5: 0.35 | D5: 0.3
A6: Aggressive Growth | B6: 0.2 | C6: 0.55 | D6: 0.25

Sheet FilePath
A1: FilePath
A2: {=LEFT(CELL("filename",A1),SEARCH("[",CELL("filename",A1))-1)} -> C:\Users\Shamel\Documents\Projects\pricing_analysis\
