Workbook

Sheet Final Candidate Output
A1: Criteria for selection: Gross Profit Lift % > 5% LTV Protection Ratio >40% | E1: AVERAGE GR LIFT % | F1: =AVERAGE($AH$10:$AH$33) -> 0.049460573
E2: AERAGE GP LIFT % | F2: =AVERAGE($AN$10:$AN$33) -> 0.12326403
E3: AVERAGE PRICE LIFT % | F3: =AVERAGE($AC$10:$AC$33) -> 0.08875811
A9: SKU | B9: Product Name | C9: Category | D9: Recommendation | E9: Current Price | F9: Current Cost Per Unit | G9: Current Volume | H9: Current Gross Revenue | I9: Current COGS | J9: Current Gross Profit | K9: Current Gross Profit Margin % | L9: V1 Suggested Price | M9: V1 Difference $ | N9: V1 Difference % | O9: V1 Gross Revenue Impact | P9: V1 Gross Profit Impact $ | Q9: Total Buyers | R9: Average Churn Score | S9: Average Projected Churn Rate | T9: Total Buyer LTV | U9: Total LTV at Risk | V9: % Critical | W9: % High | X9: % Medium | Y9: %Low | Z9: Dominant Tier | AA9: Adjusted Price | AB9: Adjusted Difference $ | AC9: Adjusted Difference % | AD9: Adjusted Volume Change % | AE9: Adjusted Volume | AF9: Adjusted Projected Gross Revenue | AG9: Adjusted Gross Revenue Impact | AH9: Adjusted Gross Revenue Lift | AI9: Adjusted COGS | AJ9: Adjusted COGS Impact | AK9: Adjusted COGS Lift | AL9: Adjusted Gross Profit | AM9: Projected Gross Profit Impact $ | AN9: Projected Gross Profit Lift % | AO9: Projected Gross Profit Margin % | AP9: Project Gross Profit Margin Impact % | AQ9: Projected Gross Profit Margin Lift | AR9: LTV Protected | AS9: LTV Sacrificed | AT9: LTV Protection-Adjusted Risk Ratio
A10: {=_xlfn._xlws.FILTER(_xlfn.ANCHORARRAY('Monte Carlo IO (4)'!$A$12),('Monte Carlo IO (4)'!$AO$12:$AO$53>0.05),('Monte Carlo IO (4)'!$AU$12:$AU$53>0.4))} -> SKU-1000 | B10: {=_xlfn.XLOOKUP($A10,_xlfn.ANCHORARRAY('Monte Carlo IO (4)'!$A$12), 'Monte Carlo IO (4)'!$B$12:$D$53,,0)} -> Wireless Earbuds | C10: Electronics | D10: Raise | E10: {=_xlfn.XLOOKUP($A10,_xlfn.ANCHORARRAY('Monte Carlo IO (4)'!$A$12), 'Monte Carlo IO (4)'!$F$12:$L$53)} -> 76.53 | F10: 52.96 | G10: 24 | H10: 1836.72 | I10: 1271.04 | J10: 565.68 | K10: 0.3079838 | L10: {=_xlfn.XLOOKUP($A10,_xlfn.ANCHORARRAY('Monte Carlo IO (4)'!$A$12), 'Monte Carlo IO (4)'!$M$12:$AU$53)} -> 80.606323 | M10: 4.0763228 | N10: 0.053264378 | O10: 17.225425 | P10: 70.185425 | Q10: 10 | R10: 70.505262 | S10: 0.3181247 | T10: 3841.99 | U10: 1112.0932 | V10: 0.5 | W10: 0.3 | X10: 0.2 | Y10: 0 | Z10: Critical | AA10: 78.975794 | AB10: 2.4457937 | AC10: 0.031958627 | AD10: -0.012783451 | AE10: 24.012783 | AF10: 1871.1891 | AG10: 34.469053 | AH10: 0.018766635 | AI10: 1271.717 | AJ10: 0.67701155 | AK10: 0.00053264378 | AL10: 616.39733 | AM10: 50.71733 | AN10: 0.08965728 | AO10: 0.32941478 | AP10: 0.021430983 | AQ10: 0.021430983 | AR10: 358.09401 | AS10: 537.14101 | AT10: 0.66666667
A11: SKU-1001 | B11: {=_xlfn.XLOOKUP($A11,_xlfn.ANCHORARRAY('Monte Carlo IO (4)'!$A$12), 'Monte Carlo IO (4)'!$B$12:$D$53,,0)} -> Bluetooth Speaker | C11: Electronics | D11: Raise | E11: {=_xlfn.XLOOKUP($A11,_xlfn.ANCHORARRAY('Monte Carlo IO (4)'!$A$12), 'Monte Carlo IO (4)'!$F$12:$L$53)} -> 53.26 | F11: 36.64 | G11: 21 | H11: 1118.46 | I11: 769.44 | J11: 349.02 | K11: 0.31205407 | L11: {=_xlfn.XLOOKUP($A11,_xlfn.ANCHORARRAY('Monte Carlo IO (4)'!$A$12), 'Monte Carlo IO (4)'!$M$12:$AU$53)} -> 57.563992 | M11: 4.3039918 | N11: 0.080810961 | O11: 32.819836 | P11: 69.459836 | Q11: 9 | R11: 66.806056 | S11: 0.26336465 | T11: 5045.98 | U11: 1487.03 | V11: 0.33333333 | W11: 0.44444444 | X11: 0.22222222 | Y11: 0 | Z11: High | AA11: 55.842395 | AB11: 2.5823951 | AC11: 0.048486577 | AD11: -0.019394631 | AE11: 21.019395 | AF11: 1149.9464 | AG11: 31.486401 | AH11: 0.028151567 | AI11: 1113.1871 | AJ11: 343.74714 | AK11: 0.44674977 | AL11: 395.42941 | AM11: 46.409406 | AN11: 0.13297062 | AO11: 0.34386768 | AP11: 0.03181361 | AQ11: 0.03181361 | AR11: 449.41351 | AS11: 674.12027 | AT11: 0.66666667
A12: SKU-1004 | B12: {=_xlfn.XLOOKUP($A12,_xlfn.ANCHORARRAY('Monte Carlo IO (4)'!$A$12), 'Monte Carlo IO (4)'!$B$12:$D$53,,0)} -> USB-C Hub | C12: Electronics | D12: Hold | E12: {=_xlfn.XLOOKUP($A12,_xlfn.ANCHORARRAY('Monte Carlo IO (4)'!$A$12), 'Monte Carlo IO (4)'!$F$12:$L$53)} -> 18.39 | F12: 8.26 | G12: 17 | H12: 312.63 | I12: 140.42 | J12: 172.21 | K12: 0.55084285 | L12: {=_xlfn.XLOOKUP($A12,_xlfn.ANCHORARRAY('Monte Carlo IO (4)'!$A$12), 'Monte Carlo IO (4)'!$M$12:$AU$53)} -> 20.325622 | M12: 1.9356217 | N12: 0.10525403 | O12: 12.579946 | P12: 20.839946 | Q12: 9 | R12: 68.467577 | S12: 0.2519532 | T12: 6058.75 | U12: 1216.0707 | V12: 0.55555556 | W12: 0.11111111 | X12: 0.33333333 | Y12: 0 | Z12: Critical | AA12: 19.551373 | AB12: 1.161373 | AC12: 0.063152419 | AD12: -0.025260968 | AE12: 17.025261 | AF12: 323.97727 | AG12: 11.347269 | AH12: 0.03629616 | AI12: 901.65782 | AJ12: 761.23782 | AK12: 5.4211496 | AL12: 187.10441 | AM12: 14.894414 | AN12: 0.086489831 | AO12: 0.57752328 | AP12: 0.026680427 | AQ12: 0.026680427 | AR12: 375.63072 | AS12: 563.44608 | AT12: 0.66666667
A13: SKU-1006 | B13: {=_xlfn.XLOOKUP($A13,_xlfn.ANCHORARRAY('Monte Carlo IO (4)'!$A$12), 'Monte Carlo IO (4)'!$B$12:$D$53,,0)} -> Mechanical Keyboard | C13: Electronics | D13: Hold | E13: {=_xlfn.XLOOKUP($A13,_xlfn.ANCHORARRAY('Monte Carlo IO (4)'!$A$12), 'Monte Carlo IO (4)'!$F$12:$L$53)} -> 113.18 | F13: 39.01 | G13: 24 | H13: 2716.32 | I13: 936.24 | J13: 1780.08 | K13: 0.6553278 | L13: {=_xlfn.XLOOKUP($A13,_xlfn.ANCHORARRAY('Monte Carlo IO (4)'!$A$12), 'Monte Carlo IO (4)'!$M$12:$AU$53)} -> 122.07351 | M13: 8.8935122 | N13: 0.078578479 | O13: 91.370781 | P13: 130.38078 | Q13: 10 | R13: 63.379342 | S13: 0.1953265 | T13: 8331.72 | U13: 1378.1368 | V13: 0.4 | W13: 0.3 | X13: 0.2 | Y13: 0.1 | Z13: Critical | AA13: 118.51611 | AB13: 5.3361073 | AC13: 0.047147087 | AD13: -0.018858835 | AE13: 24.018859 | AF13: 2790.7448 | AG13: 74.424759 | AH13: 0.027399113 | AI13: 1272.0388 | AJ13: 335.79876 | AK13: 0.3586674 | AL13: 1872.1612 | AM13: 92.081155 | AN13: 0.051728661 | AO13: 0.67084643 | AP13: 0.015518632 | AQ13: 0.015518632 | AR13: 396.9034 | AS13: 595.3551 | AT13: 0.66666667
A14: SKU-1009 | B14: {=_xlfn.XLOOKUP($A14,_xlfn.ANCHORARRAY('Monte Carlo IO (4)'!$A$12), 'Monte Carlo IO (4)'!$B$12:$D$53,,0)} -> Phone Stand | C14: Electronics | D14: Raise | E14: {=_xlfn.XLOOKUP($A14,_xlfn.ANCHORARRAY('Monte Carlo IO (4)'!$A$12), 'Monte Carlo IO (4)'!$F$12:$L$53)} -> 177.91 | F14: 73.49 | G14: 36 | H14: 6404.76 | I14: 2645.64 | J14: 3759.12 | K14: 0.58692597 | L14: {=_xlfn.XLOOKUP($A14,_xlfn.ANCHORARRAY('Monte Carlo IO (4)'!$A$12), 'Monte Carlo IO (4)'!$M$12:$AU$53)} -> 210.36242 | M14: 32.452421 | N14: 0.1824092 | O14: 2118.3199 | P14: 2338.7899 | Q14: 12 | R14: 72.583716 | S14: 0.2476082 | T14: 9553.98 | U14: 1987.1738 | V14: 0.58333333 | W14: 0.33333333 | X14: 0.083333333 | Y14: 0 | Z14: Critical | AA14: 197.38145 | AB14: 19.471452 | AC14: 0.10944552 | AD14: -0.043778208 | AE14: 36.043778 | AF14: 6794.6561 | AG14: 389.89606 | AH14: 0.060875983 | AI14: 1908.8785 | AJ14: -736.76151 | AK14: -0.27848139 | AL14: 4264.8374 | AM14: 505.71744 | AN14: 0.1345308 | AO14: 0.62767525 | AP14: 0.040749276 | AQ14: 0.040749276 | AR14: 688.8869 | AS14: 1033.3304 | AT14: 0.66666667
A15: SKU-1010 | B15: {=_xlfn.XLOOKUP($A15,_xlfn.ANCHORARRAY('Monte Carlo IO (4)'!$A$12), 'Monte Carlo IO (4)'!$B$12:$D$53,,0)} -> Slim Fit Jeans | C15: Apparel | D15: Raise | E15: {=_xlfn.XLOOKUP($A15,_xlfn.ANCHORARRAY('Monte Carlo IO (4)'!$A$12), 'Monte Carlo IO (4)'!$F$12:$L$53)} -> 45.86 | F15: 24.87 | G15: 42 | H15: 1926.12 | I15: 1044.54 | J15: 881.58 | K15: 0.45769734 | L15: {=_xlfn.XLOOKUP($A15,_xlfn.ANCHORARRAY('Monte Carlo IO (4)'!$A$12), 'Monte Carlo IO (4)'!$M$12:$AU$53)} -> 57.591702 | M15: 11.731702 | N15: 0.25581556 | O15: 713.86466 | P15: 813.34466 | Q15: 17 | R15: 81.368043 | S15: 0.36473224 | T15: 5696.89 | U15: 1838.4437 | V15: 0.70588235 | W15: 0.23529412 | X15: 0.058823529 | Y15: 0 | Z15: Critical | AA15: 52.899021 | AB15: 7.0390209 | AC15: 0.15348934 | AD15: -0.061395734 | AE15: 42.061396 | AF15: 2085.3524 | AG15: 159.23236 | AH15: 0.082670011 | AI15: 2227.5715 | AJ15: 1183.0315 | AK15: 1.1325861 | AL15: 1104.9427 | AM15: 223.36266 | AN15: 0.2533663 | AO15: 0.52985897 | AP15: 0.072161634 | AQ15: 0.072161634 | AR15: 666.16547 | AS15: 999.2482 | AT15: 0.66666667
A16: SKU-1011 | B16: {=_xlfn.XLOOKUP($A16,_xlfn.ANCHORARRAY('Monte Carlo IO (4)'!$A$12), 'Monte Carlo IO (4)'!$B$12:$D$53,,0)} -> Graphic Tee | C16: Apparel | D16: Raise | E16: {=_xlfn.XLOOKUP($A16,_xlfn.ANCHORARRAY('Monte Carlo IO (4)'!$A$12), 'Monte Carlo IO (4)'!$F$12:$L$53)} -> 67.56 | F16: 43.21 | G16: 22 | H16: 1486.32 | I16: 950.62 | J16: 535.7 | K16: 0.36042037 | L16: {=_xlfn.XLOOKUP($A16,_xlfn.ANCHORARRAY('Monte Carlo IO (4)'!$A$12), 'Monte Carlo IO (4)'!$M$12:$AU$53)} -> 74.848492 | M16: 7.2884925 | N16: 0.10788177 | O16: 85.498342 | P16: 128.70834 | Q16: 10 | R16: 66.15144 | S16: 0.25273448 | T16: 5893.09 | U16: 1511.5432 | V16: 0.4 | W16: 0.2 | X16: 0.4 | Y16: 0 | Z16: Critical | AA16: 71.933095 | AB16: 4.3730955 | AC16: 0.064729063 | AD16: -0.025891625 | AE16: 22.025892 | AF16: 1541.5539 | AG16: 55.233876 | AH16: 0.037161497 | AI16: 1166.4912 | AJ16: 215.87122 | AK16: 0.22708466 | AL16: 615.54697 | AM16: 79.846973 | AN16: 0.14905166 | AO16: 0.39930293 | AP16: 0.038882559 | AQ16: 0.038882559 | AR16: 429.27827 | AS16: 643.91741 | AT16: 0.66666667
A17: SKU-1014 | B17: {=_xlfn.XLOOKUP($A17,_xlfn.ANCHORARRAY('Monte Carlo IO (4)'!$A$12), 'Monte Carlo IO (4)'!$B$12:$D$53,,0)} -> Wool Sweater | C17: Apparel | D17: Raise | E17: {=_xlfn.XLOOKUP($A17,_xlfn.ANCHORARRAY('Monte Carlo IO (4)'!$A$12), 'Monte Carlo IO (4)'!$F$12:$L$53)} -> 143.8 | F17: 62.15 | G17: 29 | H17: 4170.2 | I17: 1802.35 | J17: 2367.85 | K17: 0.5678025 | L17: {=_xlfn.XLOOKUP($A17,_xlfn.ANCHORARRAY('Monte Carlo IO (4)'!$A$12), 'Monte Carlo IO (4)'!$M$12:$AU$53)} -> 176.09453 | M17: 32.294528 | N17: 0.22457947 | O17: 408.25774 | P17: 594.70774 | Q17: 10 | R17: 75.767552 | S17: 0.28614482 | T17: 4045.53 | U17: 1207.1798 | V17: 0.5 | W17: 0.5 | X17: 0 | Y17: 0 | Z17: Critical | AA17: 163.17672 | AB17: 19.376717 | AC17: 0.13474768 | AD17: -0.053899074 | AE17: 29.053899 | AF17: 4477.0677 | AG17: 306.86765 | AH17: 0.073585836 | AI17: 1538.6945 | AJ17: -263.65551 | AK17: -0.1462843 | AL17: 2771.8626 | AM17: 404.01265 | AN17: 0.17062426 | AO17: 0.61912458 | AP17: 0.051322081 | AQ17: 0.051322081 | AR17: 422.51294 | AS17: 633.76941 | AT17: 0.66666667
A18: SKU-1019 | B18: {=_xlfn.XLOOKUP($A18,_xlfn.ANCHORARRAY('Monte Carlo IO (4)'!$A$12), 'Monte Carlo IO (4)'!$B$12:$D$53,,0)} -> Canvas Tote Bag | C18: Apparel | D18: Raise | E18: {=_xlfn.XLOOKUP($A18,_xlfn.ANCHORARRAY('Monte Carlo IO (4)'!$A$12), 'Monte Carlo IO (4)'!$F$12:$L$53)} -> 160.35 | F18: 72.47 | G18: 36 | H18: 5772.6 | I18: 2608.92 | J18: 3163.68 | K18: 0.54805114 | L18: {=_xlfn.XLOOKUP($A18,_xlfn.ANCHORARRAY('Monte Carlo IO (4)'!$A$12), 'Monte Carlo IO (4)'!$M$12:$AU$53)} -> 182.28731 | M18: 21.937309 | N18: 0.13680891 | O18: 425.16851 | P18: 570.10851 | Q18: 12 | R18: 69.769541 | S18: 0.28227914 | T18: 5455.85 | U18: 1437.421 | V18: 0.41666667 | W18: 0.41666667 | X18: 0.16666667 | Y18: 0 | Z18: Critical | AA18: 173.51239 | AB18: 13.162385 | AC18: 0.082085347 | AD18: -0.032834139 | AE18: 36.032834 | AF18: 6041.3492 | AG18: 268.7492 | AH18: 0.046556007 | AI18: 1908.2989 | AJ18: -700.6211 | AK18: -0.26854833 | AL18: 3518.0908 | AM18: 354.41085 | AN18: 0.11202487 | AO18: 0.58233529 | AP18: 0.034284153 | AQ18: 0.034284153 | AR18: 457.57901 | AS18: 686.36852 | AT18: 0.66666667
A19: SKU-1021 | B19: {=_xlfn.XLOOKUP($A19,_xlfn.ANCHORARRAY('Monte Carlo IO (4)'!$A$12), 'Monte Carlo IO (4)'!$B$12:$D$53,,0)} -> Air Fryer | C19: Home & Kitchen | D19: Raise | E19: {=_xlfn.XLOOKUP($A19,_xlfn.ANCHORARRAY('Monte Carlo IO (4)'!$A$12), 'Monte Carlo IO (4)'!$F$12:$L$53)} -> 98.51 | F19: 55.17 | G19: 34 | H19: 3349.34 | I19: 1875.78 | J19: 1473.56 | K19: 0.43995533 | L19: {=_xlfn.XLOOKUP($A19,_xlfn.ANCHORARRAY('Monte Carlo IO (4)'!$A$12), 'Monte Carlo IO (4)'!$M$12:$AU$53)} -> 115.63152 | M19: 17.12152 | N19: 0.17380489 | O19: 350.86864 | P19: 461.20864 | Q19: 13 | R19: 67.896641 | S19: 0.2190319 | T19: 7864.87 | U19: 1821.0804 | V19: 0.46153846 | W19: 0.38461538 | X19: 0.15384615 | Y19: 0 | Z19: Critical | AA19: 108.78291 | AB19: 10.272912 | AC19: 0.10428294 | AD19: -0.041713175 | AE19: 34.041713 | AF19: 3544.3379 | AG19: 194.99787 | AH19: 0.05821979 | AI19: 1802.8491 | AJ19: -72.93087 | AK19: -0.03888029 | AL19: 1746.8026 | AM19: 273.24261 | AN19: 0.18543026 | AO19: 0.49284314 | AP19: 0.052887807 | AQ19: 0.052887807 | AR19: 591.15071 | AS19: 886.72606 | AT19: 0.66666667
A20: SKU-1026 | B20: {=_xlfn.XLOOKUP($A20,_xlfn.ANCHORARRAY('Monte Carlo IO (4)'!$A$12), 'Monte Carlo IO (4)'!$B$12:$D$53,,0)} -> Dish Rack | C20: Home & Kitchen | D20: Raise | E20: {=_xlfn.XLOOKUP($A20,_xlfn.ANCHORARRAY('Monte Carlo IO (4)'!$A$12), 'Monte Carlo IO (4)'!$F$12:$L$53)} -> 106.06 | F20: 33.42 | G20: 39 | H20: 4136.34 | I20: 1303.38 | J20: 2832.96 | K20: 0.68489534 | L20: {=_xlfn.XLOOKUP($A20,_xlfn.ANCHORARRAY('Monte Carlo IO (4)'!$A$12), 'Monte Carlo IO (4)'!$M$12:$AU$53)} -> 125.95982 | M20: 19.899821 | N20: 0.18762795 | O20: 398.21354 | P20: 498.47354 | Q20: 12 | R20: 83.640694 | S20: 0.39945616 | T20: 3203.34 | U20: 1061.3752 | V20: 0.75 | W20: 0.16666667 | X20: 0.083333333 | Y20: 0 | Z20: Critical | AA20: 117.99989 | AB20: 11.939892 | AC20: 0.11257677 | AD20: -0.045030708 | AE20: 39.045031 | AF20: 4394.7647 | AG20: 258.42467 | AH20: 0.062476651 | AI20: 2067.8248 | AJ20: 764.44483 | AK20: 0.58650956 | AL20: 3150.0768 | AM20: 317.1168 | AN20: 0.11193832 | AO20: 0.7167794 | AP20: 0.03188406 | AQ20: 0.03188406 | AR20: 385.63297 | AS20: 578.44946 | AT20: 0.66666667
A21: SKU-1027 | B21: {=_xlfn.XLOOKUP($A21,_xlfn.ANCHORARRAY('Monte Carlo IO (4)'!$A$12), 'Monte Carlo IO (4)'!$B$12:$D$53,,0)} -> Storage Bins | C21: Home & Kitchen | D21: Raise | E21: {=_xlfn.XLOOKUP($A21,_xlfn.ANCHORARRAY('Monte Carlo IO (4)'!$A$12), 'Monte Carlo IO (4)'!$F$12:$L$53)} -> 34.48 | F21: 19.24 | G21: 19 | H21: 655.12 | I21: 365.56 | J21: 289.56 | K21: 0.44199536 | L21: {=_xlfn.XLOOKUP($A21,_xlfn.ANCHORARRAY('Monte Carlo IO (4)'!$A$12), 'Monte Carlo IO (4)'!$M$12:$AU$53)} -> 36.908162 | M21: 2.4281619 | N21: 0.070422329 | O21: 9.2269146 | P21: 28.466915 | Q21: 7 | R21: 73.558325 | S21: 0.22727842 | T21: 2703.13 | U21: 804.52718 | V21: 0.57142857 | W21: 0.14285714 | X21: 0.28571429 | Y21: 0 | Z21: Critical | AA21: 35.936897 | AB21: 1.4568972 | AC21: 0.042253398 | AD21: -0.016901359 | AE21: 19.016901 | AF21: 671.26078 | AG21: 16.14078 | AH21: 0.024637899 | AI21: 1007.1351 | AJ21: 641.5751 | AK21: 1.7550473 | AL21: 311.87924 | AM21: 22.319241 | AN21: 0.077079849 | AO21: 0.46461711 | AP21: 0.022621746 | AQ21: 0.022621746 | AR21: 255.15005 | AS21: 382.72507 | AT21: 0.66666667
A22: SKU-1029 | B22: {=_xlfn.XLOOKUP($A22,_xlfn.ANCHORARRAY('Monte Carlo IO (4)'!$A$12), 'Monte Carlo IO (4)'!$B$12:$D$53,,0)} -> Scented Candle | C22: Home & Kitchen | D22: Raise | E22: {=_xlfn.XLOOKUP($A22,_xlfn.ANCHORARRAY('Monte Carlo IO (4)'!$A$12), 'Monte Carlo IO (4)'!$F$12:$L$53)} -> 148.11 | F22: 69.64 | G22: 27 | H22: 3998.97 | I22: 1880.28 | J22: 2118.69 | K22: 0.52980893 | L22: {=_xlfn.XLOOKUP($A22,_xlfn.ANCHORARRAY('Monte Carlo IO (4)'!$A$12), 'Monte Carlo IO (4)'!$M$12:$AU$53)} -> 164.85972 | M22: 16.749716 | N22: 0.1130897 | O22: 917.56261 | P22: 987.20261 | Q22: 12 | R22: 67.01174 | S22: 0.25894827 | T22: 7071.97 | U22: 1774.9244 | V22: 0.5 | W22: 0.083333333 | X22: 0.41666667 | Y22: 0 | Z22: Critical | AA22: 157.82484 | AB22: 9.7148351 | AC22: 0.065592027 | AD22: -0.026236811 | AE22: 27.026237 | AF22: 4149.4684 | AG22: 150.4984 | AH22: 0.037634291 | AI22: 1431.3095 | AJ22: -448.9705 | AK22: -0.23877853 | AL22: 2318.5209 | AM22: 199.83095 | AN22: 0.094318164 | AO22: 0.55875132 | AP22: 0.028942395 | AQ22: 0.028942395 | AR22: 543.57058 | AS22: 750.64509 | AT22: 0.72413793
... A33: SKU-1049 | B33: {=_xlfn.XLOOKUP($A33,_xlfn.ANCHORARRAY('Monte Carlo IO (4)'!$A$12), 'Monte Carlo IO (4)'!$B$12:$D$53,,0)} -> Protein Shaker | C33: Sports & Outdoors | D33: Raise | E33: {=_xlfn.XLOOKUP($A33,_xlfn.ANCHORARRAY('Monte Carlo IO (4)'!$A$12), 'Monte Carlo IO (4)'!$F$12:$L$53)} -> 99.75 | F33: 38.13 | G33: 34 | H33: 3391.5 | I33: 1296.42 | J33: 2095.08 | K33: 0.61774436 | L33: {=_xlfn.XLOOKUP($A33,_xlfn.ANCHORARRAY('Monte Carlo IO (4)'!$A$12), 'Monte Carlo IO (4)'!$M$12:$AU$53)} -> 110.43409 | M33: 10.684091 | N33: 0.10710868 | O33: 597.24501 | P33: 635.37501 | Q33: 13 | R33: 62.63275 | S33: 0.23171703 | T33: 6043.77 | U33: 1533.9834 | V33: 0.30769231 | W33: 0.53846154 | X33: 0.15384615 | Y33: 0 | Z33: High | AA33: 106.16045 | AB33: 6.4104547 | AC33: 0.06426521 | AD33: -0.025706084 | AE33: 34.025706 | AF33: 3516.6705 | AG33: 125.1705 | AH33: 0.036907119 | AI33: 1802.0014 | AJ33: 505.58139 | AK33: 0.38998272 | AL33: 2253.5764 | AM33: 158.49638 | AN33: 0.075651706 | AO33: 0.64082671 | AP33: 0.023082347 | AQ33: 0.023082347 | AR33: 474.35487 | AS33: 711.53231 | AT33: 0.66666667

Sheet Competitive Analysis (Step 1)
A1: COMPETITIVE MODEL ASSUMPTIONS | B1: Values
A2: Tolerance Band | B2: 0.1
A3: Tie Break Rule | B3: Raise
A4: Raise Elasticity | B4: -0.4
A5: Reduce Elasticity | B5: -0.8
A6: Raise Premium | B6: 0.05
A7: Rating Price Adjustment | B7: $2 per 0.1 delta
A9: {=_4_competitor_pricing_[#All]} -> SKU | B9: Product Name | C9: Competitor | D9: Competitor Price | E9: Comp Rating | F9: Comp Review Count | G9: Observation Date | H9: Average Competitor Price | I9: Price Delta | J9: Category | K9: Our Price | L9: Our Cost | M9: Our Gross Margin (%) | N9: Our Rating | O9: Our Review Count | P9: Our Stock Units | Q9: Total Units Sold | R9: Gross Revenue | S9: Total COGS | T9: Total Gross Profit | U9: Discounts Applied $ | V9: Total Revenue Less Discounts | W9: Total Net Profit $ | X9: Net Profit Margin % | Y9: Order Count | Z9: Avg Discount % | AA9: % Discount Sensitive (High) | AB9: % Loyal High-Value Buyers | AC9: %At-Risk Churner | AD9: %Dormant | AE9: % Deal Hunter Buyers | AF9: Avg Days Since Last Order | AG9: Return Rate % | AH9: Cancellation Rate % | AI9: Signal
A10: SKU-1000 | B10: Wireless Earbuds | C10: RivalMart | D10: 63.06 | E10: 4.3 | F10: 1109 | G10: 45321 | H10: {=AVERAGEIF($A10:$A209, $A10:$A209, $D10:$D209)} -> 71.835 | I10: =($K10 - $D10) / $D10 -> 0.21360609 | J10: {=_xlfn.XLOOKUP($A10:$A209, _1_product_catalog_pricing[SKU], _1_product_catalog_pricing[Category], , 0)} -> Electronics | K10: {=_xlfn.XLOOKUP($A10:$A209, _1_product_catalog_pricing[SKU], _1_product_catalog_pricing[Retail Price ($)], , 0)} -> 76.53 | L10: {=_xlfn.XLOOKUP($A10:$A209, _1_product_catalog_pricing[SKU], _1_product_catalog_pricing[Cost Price ($)], ,0)} -> 52.96 | M10: {=(_xlfn.ANCHORARRAY($K10)-_xlfn.ANCHORARRAY($L10))/_xlfn.ANCHORARRAY($K10)} -> 0.3079838 | N10: {=_xlfn.XLOOKUP($A10:$A209, _1_product_catalog_pricing[SKU], _1_product_catalog_pricing[Rating (1-5)],,0)} -> 4.5 | O10: {=_xlfn.XLOOKUP($A10:$A209, _1_product_catalog_pricing[SKU], _1_product_catalog_pricing[Review Count],,0)} -> 2781 | P10: {=_xlfn.XLOOKUP($A10:$A209, _1_product_catalog_pricing[SKU], _1_product_catalog_pricing[Stock Units],,0)} -> 71 | Q10: {=SUMIFS(_2_sales_transactions[Quantity], _2_sales_transactions[SKU], 'Competitive Analysis (Step 1)'!$A10:$A209, _2_sales_transactions[Order Status], "Completed")} -> 24 | R10: {=SUMIFS(Transactions_and_Customer_Information_Joined[Gross Revenue], Transactions_and_Customer_Information_Joined[SKU], 'Competitive Analysis (Step 1)'!A10:A209, Transactions_and_Customer_Information_Joined[Order Status], "Completed")} -> 1836.72 | S10: {=SUMIFS(_2_sales_transactions[COGS ($)], _2_sales_transactions[SKU], 'Competitive Analysis (Step 1)'!$A10:$A209, _2_sales_transactions[Order Status], "Completed")} -> 1271.04 | T10: {=_xlfn.ANCHORARRAY($R10)-_xlfn.ANCHORARRAY($S10)} -> 565.68 | U10: {=SUMIFS(Transactions_and_Customer_Information_Joined[Discount Amount ($)], Transactions_and_Customer_Information_Joined[SKU], 'Competitive Analysis (Step 1)'!A10:A209, Transactions_and_Customer_Information_Joined[Order Status], "Completed")} -> 91.83 | V10: {=SUMIFS(_2_sales_transactions[Revenue Less Discount ($)], _2_sales_transactions[SKU], 'Competitive Analysis (Step 1)'!$A10:$A209, _2_sales_transactions[Order Status], "Completed")} -> 1744.89 | W10: =SUMIFS(Transactions_and_Customer_Information_Joined[Gross Profit ($)], Transactions_and_Customer_Information_Joined[SKU], 'Competitive Analysis (Step 1)'!$A10, Transactions_and_Customer_Information_Joined[Order Status], "Completed") -> 473.85 | X10: {=_xlfn.ANCHORARRAY($W10)/_xlfn.ANCHORARRAY($V10)} -> 0.2715644 | Y10: {=COUNTIFS(_2_sales_transactions[SKU], 'Competitive Analysis (Step 1)'!$A10:$A209, _2_sales_transactions[Order Status], "Completed")} -> 10 | Z10: {=AVERAGEIFS(_2_sales_transactions[Discount (%)], _2_sales_transactions[SKU], 'Competitive Analysis (Step 1)'!$A10:$A209, _2_sales_transactions[Order Status], "Completed")} -> 5 | AA10: {=COUNTIFS(Transactions_and_Customer_Information_Joined[SKU], 'Competitive Analysis (Step 1)'!$A10:$A209, Transactions_and_Customer_Information_Joined[Order Status], "Completed", Transactions_and_Customer_Information_Joined[3_customer_segments.Discount Sensitivity], "High") /_xlfn.ANCHORARRAY($Y10)} -> 0.3 | AB10: {=COUNTIFS(Transactions_and_Customer_Information_Joined[SKU], 'Competitive Analysis (Step 1)'!$A10:$A209, Transactions_and_Customer_Information_Joined[3_customer_segments.Segment], "Loyal High-Value", Transactions_and_Customer_Information_Joined[Order Status], "Completed") /_xlfn.ANCHORARRAY($Y10)} -> 0.1 | AC10: {=COUNTIFS(Transactions_and_Customer_Information_Joined[SKU], 'Competitive Analysis (Step 1)'!$A10:$A209, Transactions_and_Customer_Information_Joined[3_customer_segments.Segment], "At-Risk Churner", Transactions_and_Customer_Information_Joined[Order Status], "Completed") /_xlfn.ANCHORARRAY($Y10)} -> 0.1 | AD10: {=COUNTIFS(Transactions_and_Customer_Information_Joined[SKU], 'Competitive Analysis (Step 1)'!$A10:$A209, Transactions_and_Customer_Information_Joined[3_customer_segments.Segment], "Dormant", Transactions_and_Customer_Information_Joined[Order Status], "Completed") /_xlfn.ANCHORARRAY($Y10)} -> 0.3 | AE10: {=COUNTIFS(Transactions_and_Customer_Information_Joined[SKU], 'Competitive Analysis (Step 1)'!$A10:$A209, Transactions_and_Customer_Information_Joined[3_customer_segments.Segment], "Deal Hunter", Transactions_and_Customer_Information_Joined[Order Status], "Completed") /_xlfn.ANCHORARRAY($Y10)} -> 0.1 | AF10: {=AVERAGEIFS(Transactions_and_Customer_Information_Joined[3_customer_segments.Days Since Last Order], Transactions_and_Customer_Information_Joined[Order Status], "Completed", Transactions_and_Customer_Information_Joined[SKU], 'Competitive Analysis (Step 1)'!$A10:$A209)} -> 165.5 | AG10: {=COUNTIFS(Transactions_and_Customer_Information_Joined[SKU], 'Competitive Analysis (Step 1)'!$A10:$A209, Transactions_and_Customer_Information_Joined[Order Status], "Returned") / ('Competitive Analysis (Step 1)'!$Y10 + COUNTIFS(Transactions_and_Customer_Information_Joined[SKU], 'Competitive Analysis (Step 1)'!$A10:$A209, Transactions_and_Customer_Information_Joined[Order Status], "Returned"))} -> 0.33333333 | AH10: {=COUNTIFS(Transactions_and_Customer_Information_Joined[SKU], 'Competitive Analysis (Step 1)'!$A10:$A209, Transactions_and_Customer_Information_Joined[Order Status], "Cancelled") / ('Competitive Analysis (Step 1)'!$Y10 + COUNTIFS(Transactions_and_Customer_Information_Joined[SKU], 'Competitive Analysis (Step 1)'!$A10:$A209, Transactions_and_Customer_Information_Joined[Order Status], "Cancelled"))} -> 0.090909091 | AI10: {=_xlfn.IFS($I10:$I209 >$B$2, "Reduce", $I10:$I209 < - $B$2, "Raise", OR($I10:$I209 > -$B$2, $I10:$I209 < $B$2), "Hold")} -> Reduce
A11: SKU-1000 | B11: Wireless Earbuds | C11: ShopNow | D11: 76.06 | E11: 3.2 | F11: 1664 | G11: 45314 | H11: 71.835 | I11: =($K11 - $D11) / $D11 -> 0.0061793321 | J11: Electronics | K11: 76.53 | L11: 52.96 | M11: 0.3079838 | N11: 4.5 | O11: 2781 | P11: 71 | Q11: 24 | R11: 1836.72 | S11: 1271.04 | T11: 565.68 | U11: 91.83 | V11: 1744.89 | W11: =SUMIFS(Transactions_and_Customer_Information_Joined[Gross Profit ($)], Transactions_and_Customer_Information_Joined[SKU], 'Competitive Analysis (Step 1)'!$A11, Transactions_and_Customer_Information_Joined[Order Status], "Completed") -> 473.85 | X11: 0.2715644 | Y11: 10 | Z11: 5 | AA11: 0.3 | AB11: 0.1 | AC11: 0.1 | AD11: 0.3 | AE11: 0.1 | AF11: 165.5 | AG11: 0.33333333 | AH11: 0.090909091 | AI11: Hold
A12: SKU-1000 | B12: Wireless Earbuds | C12: BestDeals | D12: 76.63 | E12: 3 | F12: 479 | G12: 45347 | H12: 71.835 | I12: =($K12 - $D12) / $D12 -> -0.0013049719 | J12: Electronics | K12: 76.53 | L12: 52.96 | M12: 0.3079838 | N12: 4.5 | O12: 2781 | P12: 71 | Q12: 24 | R12: 1836.72 | S12: 1271.04 | T12: 565.68 | U12: 91.83 | V12: 1744.89 | W12: =SUMIFS(Transactions_and_Customer_Information_Joined[Gross Profit ($)], Transactions_and_Customer_Information_Joined[SKU], 'Competitive Analysis (Step 1)'!$A12, Transactions_and_Customer_Information_Joined[Order Status], "Completed") -> 473.85 | X12: 0.2715644 | Y12: 10 | Z12: 5 | AA12: 0.3 | AB12: 0.1 | AC12: 0.1 | AD12: 0.3 | AE12: 0.1 | AF12: 165.5 | AG12: 0.33333333 | AH12: 0.090909091 | AI12: Hold
A13: SKU-1000 | B13: Wireless Earbuds | C13: QuickCart | D13: 71.59 | E13: 4.8 | F13: 1407 | G13: 45368 | H13: 71.835 | I13: =($K13 - $D13) / $D13 -> 0.069004051 | J13: Electronics | K13: 76.53 | L13: 52.96 | M13: 0.3079838 | N13: 4.5 | O13: 2781 | P13: 71 | Q13: 24 | R13: 1836.72 | S13: 1271.04 | T13: 565.68 | U13: 91.83 | V13: 1744.89 | W13: =SUMIFS(Transactions_and_Customer_Information_Joined[Gross Profit ($)], Transactions_and_Customer_Information_Joined[SKU], 'Competitive Analysis (Step 1)'!$A13, Transactions_and_Customer_Information_Joined[Order Status], "Completed") -> 473.85 | X13: 0.2715644 | Y13: 10 | Z13: 5 | AA13: 0.3 | AB13: 0.1 | AC13: 0.1 | AD13: 0.3 | AE13: 0.1 | AF13: 165.5 | AG13: 0.33333333 | AH13: 0.090909091 | AI13: Hold
A14: SKU-1001 | B14: Bluetooth Speaker | C14: RivalMart | D14: 60.11 | E14: 4.9 | F14: 2485 | G14: 45326 | H14: 56.81 | I14: =($K14 - $D14) / $D14 -> -0.11395774 | J14: Electronics | K14: 53.26 | L14: 36.64 | M14: 0.31205407 | N14: 3.4 | O14: 2671 | P14: 287 | Q14: 21 | R14: 1118.46 | S14: 769.44 | T14: 349.02 | U14: 101.2 | V14: 1017.26 | W14: =SUMIFS(Transactions_and_Customer_Information_Joined[Gross Profit ($)], Transactions_and_Customer_Information_Joined[SKU], 'Competitive Analysis (Step 1)'!$A14, Transactions_and_Customer_Information_Joined[Order Status], "Completed") -> 247.82 | X14: 0.46581012 | Y14: 9 | Z14: 8.8888889 | AA14: 0.33333333 | AB14: 0.11111111 | AC14: 0.11111111 | AD14: 0.22222222 | AE14: 0.11111111 | AF14: 214.22222 | AG14: 0.16666667 | AH14: 0.33333333 | AI14: Raise
A15: SKU-1001 | B15: Bluetooth Speaker | C15: ShopNow | D15: 64.58 | E15: 3.7 | F15: 2332 | G15: 45358 | H15: 56.81 | I15: =($K15 - $D15) / $D15 -> -0.17528647 | J15: Electronics | K15: 53.26 | L15: 36.64 | M15: 0.31205407 | N15: 3.4 | O15: 2671 | P15: 287 | Q15: 21 | R15: 1118.46 | S15: 769.44 | T15: 349.02 | U15: 101.2 | V15: 1017.26 | W15: =SUMIFS(Transactions_and_Customer_Information_Joined[Gross Profit ($)], Transactions_and_Customer_Information_Joined[SKU], 'Competitive Analysis (Step 1)'!$A15, Transactions_and_Customer_Information_Joined[Order Status], "Completed") -> 247.82 | X15: 0.46581012 | Y15: 9 | Z15: 8.8888889 | AA15: 0.33333333 | AB15: 0.11111111 | AC15: 0.11111111 | AD15: 0.22222222 | AE15: 0.11111111 | AF15: 214.22222 | AG15: 0.16666667 | AH15: 0.33333333 | AI15: Raise
A16: SKU-1001 | B16: Bluetooth Speaker | C16: BestDeals | D16: 56.33 | E16: 4.1 | F16: 2209 | G16: 45344 | H16: 56.81 | I16: =($K16 - $D16) / $D16 -> -0.054500266 | J16: Electronics | K16: 53.26 | L16: 36.64 | M16: 0.31205407 | N16: 3.4 | O16: 2671 | P16: 287 | Q16: 21 | R16: 1118.46 | S16: 769.44 | T16: 349.02 | U16: 101.2 | V16: 1017.26 | W16: =SUMIFS(Transactions_and_Customer_Information_Joined[Gross Profit ($)], Transactions_and_Customer_Information_Joined[SKU], 'Competitive Analysis (Step 1)'!$A16, Transactions_and_Customer_Information_Joined[Order Status], "Completed") -> 247.82 | X16: 0.46581012 | Y16: 9 | Z16: 8.8888889 | AA16: 0.33333333 | AB16: 0.11111111 | AC16: 0.11111111 | AD16: 0.22222222 | AE16: 0.11111111 | AF16: 214.22222 | AG16: 0.16666667 | AH16: 0.33333333 | AI16: Hold
A17: SKU-1001 | B17: Bluetooth Speaker | C17: QuickCart | D17: 46.22 | E17: 4.1 | F17: 1896 | G17: 45382 | H17: 56.81 | I17: =($K17 - $D17) / $D17 -> 0.15231502 | J17: Electronics | K17: 53.26 | L17: 36.64 | M17: 0.31205407 | N17: 3.4 | O17: 2671 | P17: 287 | Q17: 21 | R17: 1118.46 | S17: 769.44 | T17: 349.02 | U17: 101.2 | V17: 1017.26 | W17: =SUMIFS(Transactions_and_Customer_Information_Joined[Gross Profit ($)], Transactions_and_Customer_Information_Joined[SKU], 'Competitive Analysis (Step 1)'!$A17, Transactions_and_Customer_Information_Joined[Order Status], "Completed") -> 247.82 | X17: 0.46581012 | Y17: 9 | Z17: 8.8888889 | AA17: 0.33333333 | AB17: 0.11111111 | AC17: 0.11111111 | AD17: 0.22222222 | AE17: 0.11111111 | AF17: 214.22222 | AG17: 0.16666667 | AH17: 0.33333333 | AI17: Reduce
A18: SKU-1002 | B18: Smart Watch | C18: RivalMart | D18: 60.69 | E18: 3.5 | F18: 1138 | G18: 45307 | H18: 63.75 | I18: =($K18 - $D18) / $D18 -> 0.21173175 | J18: Electronics | K18: 73.54 | L18: 38.69 | M18: 0.47389176 | N18: 3.8 | O18: 1148 | P18: 357 | Q18: 35 | R18: 2290.05 | S18: 1354.15 | T18: 935.9 | U18: 137.41 | V18: 2152.64 | W18: =SUMIFS(Transactions_and_Customer_Information_Joined[Gross Profit ($)], Transactions_and_Customer_Information_Joined[SKU], 'Competitive Analysis (Step 1)'!$A18, Transactions_and_Customer_Information_Joined[Order Status], "Completed") -> 798.49 | X18: 0.22012506 | Y18: 15 | Z18: 5.6666667 | AA18: 0.53333333 | AB18: 0.33333333 | AC18: 0.2 | AD18: 0.066666667 | AE18: 0.066666667 | AF18: 183.33333 | AG18: 0.23076923 | AH18: 0.52380952 | AI18: Reduce
A19: SKU-1002 | B19: Smart Watch | C19: ShopNow | D19: 71.58 | E19: 4.3 | F19: 1230 | G19: 45320 | H19: 63.75 | I19: =($K19 - $D19) / $D19 -> 0.02738195 | J19: Electronics | K19: 73.54 | L19: 38.69 | M19: 0.47389176 | N19: 3.8 | O19: 1148 | P19: 357 | Q19: 35 | R19: 2290.05 | S19: 1354.15 | T19: 935.9 | U19: 137.41 | V19: 2152.64 | W19: =SUMIFS(Transactions_and_Customer_Information_Joined[Gross Profit ($)], Transactions_and_Customer_Information_Joined[SKU], 'Competitive Analysis (Step 1)'!$A19, Transactions_and_Customer_Information_Joined[Order Status], "Completed") -> 798.49 | X19: 0.22012506 | Y19: 15 | Z19: 5.6666667 | AA19: 0.53333333 | AB19: 0.33333333 | AC19: 0.2 | AD19: 0.066666667 | AE19: 0.066666667 | AF19: 183.33333 | AG19: 0.23076923 | AH19: 0.52380952 | AI19: Hold
A20: SKU-1002 | B20: Smart Watch | C20: BestDeals | D20: 58.29 | E20: 3.4 | F20: 296 | G20: 45337 | H20: 63.75 | I20: =($K20 - $D20) / $D20 -> 0.26162292 | J20: Electronics | K20: 73.54 | L20: 38.69 | M20: 0.47389176 | N20: 3.8 | O20: 1148 | P20: 357 | Q20: 35 | R20: 2290.05 | S20: 1354.15 | T20: 935.9 | U20: 137.41 | V20: 2152.64 | W20: =SUMIFS(Transactions_and_Customer_Information_Joined[Gross Profit ($)], Transactions_and_Customer_Information_Joined[SKU], 'Competitive Analysis (Step 1)'!$A20, Transactions_and_Customer_Information_Joined[Order Status], "Completed") -> 798.49 | X20: 0.22012506 | Y20: 15 | Z20: 5.6666667 | AA20: 0.53333333 | AB20: 0.33333333 | AC20: 0.2 | AD20: 0.066666667 | AE20: 0.066666667 | AF20: 183.33333 | AG20: 0.23076923 | AH20: 0.52380952 | AI20: Reduce
A21: SKU-1002 | B21: Smart Watch | C21: QuickCart | D21: 64.44 | E21: 4 | F21: 1899 | G21: 45341 | H21: 63.75 | I21: =($K21 - $D21) / $D21 -> 0.14121664 | J21: Electronics | K21: 73.54 | L21: 38.69 | M21: 0.47389176 | N21: 3.8 | O21: 1148 | P21: 357 | Q21: 35 | R21: 2290.05 | S21: 1354.15 | T21: 935.9 | U21: 137.41 | V21: 2152.64 | W21: =SUMIFS(Transactions_and_Customer_Information_Joined[Gross Profit ($)], Transactions_and_Customer_Information_Joined[SKU], 'Competitive Analysis (Step 1)'!$A21, Transactions_and_Customer_Information_Joined[Order Status], "Completed") -> 798.49 | X21: 0.22012506 | Y21: 15 | Z21: 5.6666667 | AA21: 0.53333333 | AB21: 0.33333333 | AC21: 0.2 | AD21: 0.066666667 | AE21: 0.066666667 | AF21: 183.33333 | AG21: 0.23076923 | AH21: 0.52380952 | AI21: Reduce
A22: SKU-1003 | B22: Portable Charger | C22: RivalMart | D22: 126.85 | E22: 4 | F22: 1482 | G22: 45355 | H22: 141.6025 | I22: =($K22 - $D22) / $D22 -> 0.21426882 | J22: Electronics | K22: 154.03 | L22: 76.79 | M22: 0.50146075 | N22: 4.7 | O22: 2482 | P22: 183 | Q22: 23 | R22: 3542.69 | S22: 1766.17 | T22: 1776.52 | U22: 269.55 | V22: 3273.14 | W22: =SUMIFS(Transactions_and_Customer_Information_Joined[Gross Profit ($)], Transactions_and_Customer_Information_Joined[SKU], 'Competitive Analysis (Step 1)'!$A22, Transactions_and_Customer_Information_Joined[Order Status], "Completed") -> 1506.97 | X22: 0.14476924 | Y22: 10 | Z22: 7 | AA22: 0.5 | AB22: 0 | AC22: 0.1 | AD22: 0.3 | AE22: 0.2 | AF22: 140.4 | AG22: 0.28571429 | AH22: 0.41176471 | AI22: Reduce
... A209: SKU-1049 | B209: Protein Shaker | C209: QuickCart | D209: 102.76 | E209: 3.1 | F209: 13 | G209: 45344 | H209: 107.1925 | I209: =($K209 - $D209) / $D209 -> -0.029291553 | J209: Sports & Outdoors | K209: 99.75 | L209: 38.13 | M209: 0.61774436 | N209: 3.2 | O209: 2121 | P209: 337 | Q209: 34 | R209: 3047.08 | S209: 1296.42 | T209: 1750.66 | U209: 295.75 | V209: 2751.33 | W209: =SUMIFS(Transactions_and_Customer_Information_Joined[Gross Profit ($)], Transactions_and_Customer_Information_Joined[SKU], 'Competitive Analysis (Step 1)'!$A209, Transactions_and_Customer_Information_Joined[Order Status], "Completed") -> 1454.91 | X209: 0.1722258 | Y209: 13 | Z209: 9.6153846 | AA209: 0.23076923 | AB209: 0.15384615 | AC209: 0.15384615 | AD209: 0.076923077 | AE209: 0.076923077 | AF209: 122.53846 | AG209: 0.23076923 | AH209: 0.33333333 | AI209: Hold

Sheet V1 Pricing Model (Step 2)
A1: PRICING MODEL ASSUMPTIONS | B1: Values
A2: Analysis Reference Date (Assumed) | B2: 45382
A3: Tolerance Band | B3: 0.08
A4: Tie-Break Rule | B4: Raise
A5: Raise Premium | B5: 0.05
A6: Rating Price Adjustment | B6: 0.03
A7: Reduce - Weak | B7: 0.95
A8: Rating Threshold for Reduce - Weak | B8: -0.3
A9: Reduce - Neutral | B9: 0.98
A10: Hold - Strong rating nudge | B10: 1.01
A11: Rating Threshold for Hold - Strong | B11: 0.3
A12: Raise Elasticity | B12: -0.4
A13: Reduce Elasticity | B13: -0.8
A14: Margin Floor | B14: 0.2
A15: Hold - Max Price Movement | B15: 0.08
A16: Signal Score Threshold | B16: 0.05
... A19: Inventory Sensitivity | B19: -0.02
A21: SKU | B21: Product Name | C21: Category | D21: Our Price (Retail) | E21: Our COGS | F21: Stock Units | G21: Average Monthly Volume | H21: Stock Ratio | I21: Gross Margin % | J21: Avg Competitor Price | K21: Price Gap $ | L21: Price Gap % | M21: Our Rating | N21: Avg Competitor Rating | O21: Rating Delta | P21: Category Median Margin | Q21: Inventory Modifier | R21: Weighted Signal Score | S21: Recommendation | T21: Tie Breaker Recommendation | U21: Suggested Price | V21: Difference from Current $ | W21: Difference from Current % | X21: Difference from Avg Competitor $ | Y21: Difference from Average Competitor % | Z21: Volume Change % | AA21: New Volume | AB21: Projected Gross Revenue | AC21: Gross Revenue Impact | AD21: Projected Gross Revenue Lift | AE21: Projected COGS | AF21: Projected COGS Impact | AG21: Projected COGS Lift | AH21: Projected Gross Profit | AI21: Projected Gross Profit Impact | AJ21: Projected Gross Profit Margin % | AK21: Projected Gross Profit Margin Lift | AL21: Final Candidate for Churn Input
A22: {=_xlfn.UNIQUE(_1_product_catalog_pricing[SKU])} -> SKU-1000 | B22: {=_xlfn.XLOOKUP(_xlfn.ANCHORARRAY($A22), 'Competitive Analysis (Step 1)'!$A10:$A209, 'Competitive Analysis (Step 1)'!$B10:$B209, ,0)} -> Wireless Earbuds | C22: {=_xlfn.XLOOKUP(_xlfn.ANCHORARRAY($A22), 'Competitive Analysis (Step 1)'!$A10:$A209,_xlfn.ANCHORARRAY( 'Competitive Analysis (Step 1)'!J10),,0)} -> Electronics | D22: {=_xlfn.XLOOKUP(_xlfn.ANCHORARRAY($A22), 'Competitive Analysis (Step 1)'!$A10:$A209,_xlfn.ANCHORARRAY( 'Competitive Analysis (Step 1)'!$K10))} -> 76.53 | E22: {=_xlfn.XLOOKUP(_xlfn.ANCHORARRAY($A22), 'Competitive Analysis (Step 1)'!$A10:$A209,_xlfn.ANCHORARRAY( 'Competitive Analysis (Step 1)'!$L10),,0)} -> 52.96 | F22: {=_xlfn.XLOOKUP($A22,'Competitive Analysis (Step 1)'!$A$10:$A$209,_xlfn.ANCHORARRAY( 'Competitive Analysis (Step 1)'!$P$10),,0)} -> 71 | G22: {=SUMPRODUCT((Transactions_and_Customer_Information_Joined[SKU]='V1 Pricing Model (Step 2)'!$A22) * (Transactions_and_Customer_Information_Joined[Order Status]="Completed") * (Transactions_and_Customer_Information_Joined[Quantity])) / 12} -> 2 | H22: =IF($G22=0, 99, $F22/$G22) -> 35.5 | I22: =($D22-$E22)/$D22 -> 0.3079838 | J22: {=(SMALL(IF('Competitive Analysis (Step 1)'!$A$10:$A$209=$A22,'Competitive Analysis (Step 1)'!$D$10:$D$209),2)+SMALL(IF('Competitive Analysis (Step 1)'!$A$10:$A$209=$A22,'Competitive Analysis (Step 1)'!$D$10:$D$209),3))/2} -> 73.825 | K22: =$J22-$D22 -> -2.705 | L22: =$K22/$D22 -> -0.035345616 | M22: {=_xlfn.XLOOKUP(_xlfn.ANCHORARRAY($A22), 'Competitive Analysis (Step 1)'!$A10:$A209,_xlfn.ANCHORARRAY( 'Competitive Analysis (Step 1)'!$N10))} -> 4.5 | N22: {=AVERAGEIF('Competitive Analysis (Step 1)'!$A10:$A209,_xlfn.ANCHORARRAY( 'V1 Pricing Model (Step 2)'!$A22), 'Competitive Analysis (Step 1)'!$E10:$E209)} -> 3.825 | O22: {=_xlfn.ANCHORARRAY($M22) -_xlfn.ANCHORARRAY($N22)} -> 0.675 | P22: {=MEDIAN(IF($C$22:$C$71=$C22, $I$22:$I$71))} -> 0.5261518 | Q22: {=_xlfn.LET( _xlpm.stock, $F22, _xlpm.stock_ratio, $H22, _xlpm.cat_ratios, IF($C$22:$C$71=$C22, $H$22:$H$71), _xlpm.cat_median, MEDIAN(_xlpm.cat_ratios), _xlpm.cat_stdev, STDEV(IF($C$22:$C$71=$C22, $H$22:$H$71)), _xlpm.z_score, IF(_xlpm.cat_stdev = 0, 0, (_xlpm.stock_ratio - _xlpm.cat_median) / _xlpm.cat_stdev), _xlpm.capped_z, MIN(MAX(_xlpm.z_score, -2), 2), IF(_xlpm.stock < $B$18, 0, 1 + $B$19 * _xlpm.capped_z) )} -> 1.0201885 | R22: {=_xlfn.LET( _xlpm.sku, $A22, _xlpm.tol, $B$3, _xlpm.sku_range, 'Competitive Analysis (Step 1)'!$A$10:$A$209, _xlpm.comp_prices, 'Competitive Analysis (Step 1)'!$D$10:$D$209, _xlpm.comp_reviews, 'Competitive Analysis (Step 1)'!$F$10:$F$209, _xlpm.obs_dates, 'Competitive Analysis (Step 1)'!$G$10:$G$209, _xlpm.our_price, $D22, _xlpm.matches, (_xlpm.sku_range=_xlpm.sku), _xlpm.deltas, IF(_xlpm.matches, (_xlpm.our_price - _xlpm.comp_prices) / _xlpm.comp_prices, 0), _xlpm.review_wt, IF(_xlpm.matches, LN(_xlpm.comp_reviews + 1), 0), _xlpm.decay_wt, IFERROR(IF(_xlpm.matches, EXP(-$B$17 * ($B$2 - _xlpm.obs_dates)), 0), 0), _xlpm.weights, _xlpm.review_wt * _xlpm.decay_wt, _xlpm.outside_band, IF(ABS(_xlpm.deltas) > _xlpm.tol, 1, 0), _xlpm.total_weight, SUMPRODUCT(_xlpm.weights * _xlpm.matches), _xlpm.weighted_signal, SUMPRODUCT(_xlpm.weights * _xlpm.deltas * _xlpm.outside_band), IF(_xlpm.total_weight = 0, 0, _xlpm.weighted_signal / _xlpm.total_weight) )} -> 0.03532219 | S22: =IF($R22 < -$B$16, "Raise", IF($R22 > $B$16, "Reduce", "Hold")) -> Hold | T22: {=IF($S22="Hold", IF(0.5 * ($P22-$I22) / $P22 + 0.5 * ($R22 / MAX(ABS($R22:$R71))) > 0, "Raise", "Hold"), $S22)} -> Raise | U22: =IF($Q22=0, $D22, _xlfn.LET( _xlpm.raw_price, $Q22 * IF($T22="Raise", ($J22*(1+$B$5)) + ($J22 * MIN($B$6*ABS($O22), $B$5) * SIGN($O22)), IF($T22="Reduce", $J22 * ($B$7 + ($B$9-$B$7) / (1+EXP(-20*($O22-$B$8)))), IF($T22="Hold", IF($O22>$B$11, MIN(MAX($D22, ($J22*$B$10)+($J22 * MIN($B$6*ABS($O22), $B$5) * SIGN($O22))), $D22*(1+$B$15)), $D22)))), IF(AND(OR($T22="Hold", $T22="Reduce"), _xlpm.raw_price < $D22, _xlpm.raw_price >= $D22 * 0.95), $D22, _xlpm.raw_price) )) -> 80.606323 | V22: =$U22-$D22 -> 4.0763228 | W22: =$V22/$D22 -> 0.053264378 | X22: =$U22-$J22 -> 6.7813228 | Y22: =$X22/$J22 -> 0.091856727 | Z22: =IF($V22 = 0, 0, IF($S22="Reduce", $W22*$B$13, $W22*$B$12)) -> -0.021305751 | AA22: {=ROUND(_xlfn.XLOOKUP($A22, 'Competitive Analysis (Step 1)'!$A$10:$A$209,_xlfn.ANCHORARRAY( 'Competitive Analysis (Step 1)'!$Q$10), , 0) * (1+$Z22), 0)} -> 23 | AB22: =$AA22*$U22 -> 1853.9454 | AC22: {=$AB22 - _xlfn.XLOOKUP($A22, 'Competitive Analysis (Step 1)'!$A$10:$A$209,_xlfn.ANCHORARRAY( 'Competitive Analysis (Step 1)'!$R$10), ,0)} -> 17.225425 | AD22: {=$AC22 / _xlfn.XLOOKUP($A22, 'Competitive Analysis (Step 1)'!$A$10:$A$209,_xlfn.ANCHORARRAY( 'Competitive Analysis (Step 1)'!$V$10), ,0)} -> 0.0098719262 | AE22: =$AA22 * _xlfn.XLOOKUP($A22, _1_product_catalog_pricing[SKU], _1_product_catalog_pricing[Cost Price ($)], , 0) -> 1218.08 | AF22: {=$AE22 - _xlfn.XLOOKUP($A22, 'Competitive Analysis (Step 1)'!$A$10:$A$209,_xlfn.ANCHORARRAY( 'Competitive Analysis (Step 1)'!$S$10),,0)} -> -52.96 | AG22: {=$AF22 / _xlfn.XLOOKUP($A22, 'Competitive Analysis (Step 1)'!$A$10:$A$209,_xlfn.ANCHORARRAY( 'Competitive Analysis (Step 1)'!$S$10),,0)} -> -0.041666667 | AH22: =$AB22-$AE22 -> 635.86543 | AI22: {=$AH22 - _xlfn.XLOOKUP($A22, 'Competitive Analysis (Step 1)'!$A$10:$A$209,_xlfn.ANCHORARRAY( 'Competitive Analysis (Step 1)'!$T$10),,0)} -> 70.185425 | AJ22: =IFERROR($AH22 / $AB22, 0) -> 0.34297958 | AK22: {=$AI22 / _xlfn.XLOOKUP($A22, 'Competitive Analysis (Step 1)'!$A$10:$A$209,_xlfn.ANCHORARRAY( 'Competitive Analysis (Step 1)'!$T$10),,0)} -> 0.12407267 | AL22: =IF($AK22 > 0, "Full", IF($AK22 >= $B$20, "Constrained", "Exclude")) -> Full
A23: SKU-1001 | B23: Bluetooth Speaker | C23: Electronics | D23: 53.26 | E23: 36.64 | F23: {=_xlfn.XLOOKUP($A23,'Competitive Analysis (Step 1)'!$A$10:$A$209,_xlfn.ANCHORARRAY( 'Competitive Analysis (Step 1)'!$P$10),,0)} -> 287 | G23: {=SUMPRODUCT((Transactions_and_Customer_Information_Joined[SKU]='V1 Pricing Model (Step 2)'!$A23) * (Transactions_and_Customer_Information_Joined[Order Status]="Completed") * (Transactions_and_Customer_Information_Joined[Quantity])) / 12} -> 1.75 | H23: =IF($G23=0, 99, $F23/$G23) -> 164 | I23: =($D23-$E23)/$D23 -> 0.31205407 | J23: {=(SMALL(IF('Competitive Analysis (Step 1)'!$A$10:$A$209=$A23,'Competitive Analysis (Step 1)'!$D$10:$D$209),2)+SMALL(IF('Competitive Analysis (Step 1)'!$A$10:$A$209=$A23,'Competitive Analysis (Step 1)'!$D$10:$D$209),3))/2} -> 58.22 | K23: =$J23-$D23 -> 4.96 | L23: =$K23/$D23 -> 0.093128051 | M23: 3.4 | N23: 4.2 | O23: -0.8 | P23: {=MEDIAN(IF($C$22:$C$71=$C23, $I$22:$I$71))} -> 0.5261518 | Q23: {=_xlfn.LET( _xlpm.stock, $F23, _xlpm.stock_ratio, $H23, _xlpm.cat_ratios, IF($C$22:$C$71=$C23, $H$22:$H$71), _xlpm.cat_median, MEDIAN(_xlpm.cat_ratios), _xlpm.cat_stdev, STDEV(IF($C$22:$C$71=$C23, $H$22:$H$71)), _xlpm.z_score, IF(_xlpm.cat_stdev = 0, 0, (_xlpm.stock_ratio - _xlpm.cat_median) / _xlpm.cat_stdev), _xlpm.capped_z, MIN(MAX(_xlpm.z_score, -2), 2), IF(_xlpm.stock < $B$18, 0, 1 + $B$19 * _xlpm.capped_z) )} -> 0.96367666 | R23: {=_xlfn.LET( _xlpm.sku, $A23, _xlpm.tol, $B$3, _xlpm.sku_range, 'Competitive Analysis (Step 1)'!$A$10:$A$209, _xlpm.comp_prices, 'Competitive Analysis (Step 1)'!$D$10:$D$209, _xlpm.comp_reviews, 'Competitive Analysis (Step 1)'!$F$10:$F$209, _xlpm.obs_dates, 'Competitive Analysis (Step 1)'!$G$10:$G$209, _xlpm.our_price, $D23, _xlpm.matches, (_xlpm.sku_range=_xlpm.sku), _xlpm.deltas, IF(_xlpm.matches, (_xlpm.our_price - _xlpm.comp_prices) / _xlpm.comp_prices, 0), _xlpm.review_wt, IF(_xlpm.matches, LN(_xlpm.comp_reviews + 1), 0), _xlpm.decay_wt, IFERROR(IF(_xlpm.matches, EXP(-$B$17 * ($B$2 - _xlpm.obs_dates)), 0), 0), _xlpm.weights, _xlpm.review_wt * _xlpm.decay_wt, _xlpm.outside_band, IF(ABS(_xlpm.deltas) > _xlpm.tol, 1, 0), _xlpm.total_weight, SUMPRODUCT(_xlpm.weights * _xlpm.matches), _xlpm.weighted_signal, SUMPRODUCT(_xlpm.weights * _xlpm.deltas * _xlpm.outside_band), IF(_xlpm.total_weight = 0, 0, _xlpm.weighted_signal / _xlpm.total_weight) )} -> 0.00096443417 | S23: =IF($R23 < -$B$16, "Raise", IF($R23 > $B$16, "Reduce", "Hold")) -> Hold | T23: {=IF($S23="Hold", IF(0.5 * ($P23-$I23) / $P23 + 0.5 * ($R23 / MAX(ABS($R23:$R72))) > 0, "Raise", "Hold"), $S23)} -> Raise | U23: =IF($Q23=0, $D23, _xlfn.LET( _xlpm.raw_price, $Q23 * IF($T23="Raise", ($J23*(1+$B$5)) + ($J23 * MIN($B$6*ABS($O23), $B$5) * SIGN($O23)), IF($T23="Reduce", $J23 * ($B$7 + ($B$9-$B$7) / (1+EXP(-20*($O23-$B$8)))), IF($T23="Hold", IF($O23>$B$11, MIN(MAX($D23, ($J23*$B$10)+($J23 * MIN($B$6*ABS($O23), $B$5) * SIGN($O23))), $D23*(1+$B$15)), $D23)))), IF(AND(OR($T23="Hold", $T23="Reduce"), _xlpm.raw_price < $D23, _xlpm.raw_price >= $D23 * 0.95), $D23, _xlpm.raw_price) )) -> 57.563992 | V23: =$U23-$D23 -> 4.3039918 | W23: =$V23/$D23 -> 0.080810961 | X23: =$U23-$J23 -> -0.65600821 | Y23: =$X23/$J23 -> -0.011267747 | Z23: =IF($V23 = 0, 0, IF($S23="Reduce", $W23*$B$13, $W23*$B$12)) -> -0.032324384 | AA23: {=ROUND(_xlfn.XLOOKUP($A23, 'Competitive Analysis (Step 1)'!$A$10:$A$209,_xlfn.ANCHORARRAY( 'Competitive Analysis (Step 1)'!$Q$10), , 0) * (1+$Z23), 0)} -> 20 | AB23: =$AA23*$U23 -> 1151.2798 | AC23: {=$AB23 - _xlfn.XLOOKUP($A23, 'Competitive Analysis (Step 1)'!$A$10:$A$209,_xlfn.ANCHORARRAY( 'Competitive Analysis (Step 1)'!$R$10), ,0)} -> 32.819836 | AD23: {=$AC23 / _xlfn.XLOOKUP($A23, 'Competitive Analysis (Step 1)'!$A$10:$A$209,_xlfn.ANCHORARRAY( 'Competitive Analysis (Step 1)'!$V$10), ,0)} -> 0.032262977 | AE23: =$AA23 * _xlfn.XLOOKUP($A23, _1_product_catalog_pricing[SKU], _1_product_catalog_pricing[Cost Price ($)], , 0) -> 732.8 | AF23: {=$AE23 - _xlfn.XLOOKUP($A23, 'Competitive Analysis (Step 1)'!$A$10:$A$209,_xlfn.ANCHORARRAY( 'Competitive Analysis (Step 1)'!$S$10),,0)} -> -36.64 | AG23: {=$AF23 / _xlfn.XLOOKUP($A23, 'Competitive Analysis (Step 1)'!$A$10:$A$209,_xlfn.ANCHORARRAY( 'Competitive Analysis (Step 1)'!$S$10),,0)} -> -0.047619048 | AH23: =$AB23-$AE23 -> 418.47984 | AI23: {=$AH23 - _xlfn.XLOOKUP($A23, 'Competitive Analysis (Step 1)'!$A$10:$A$209,_xlfn.ANCHORARRAY( 'Competitive Analysis (Step 1)'!$T$10),,0)} -> 69.459836 | AJ23: =IFERROR($AH23 / $AB23, 0) -> 0.36349098 | AK23: {=$AI23 / _xlfn.XLOOKUP($A23, 'Competitive Analysis (Step 1)'!$A$10:$A$209,_xlfn.ANCHORARRAY( 'Competitive Analysis (Step 1)'!$T$10),,0)} -> 0.19901391 | AL23: =IF($AK23 > 0, "Full", IF($AK23 >= $B$20, "Constrained", "Exclude")) -> Full
A24: SKU-1002 | B24: Smart Watch | C24: Electronics | D24: 73.54 | E24: 38.69 | F24: {=_xlfn.XLOOKUP($A24,'Competitive Analysis (Step 1)'!$A$10:$A$209,_xlfn.ANCHORARRAY( 'Competitive Analysis (Step 1)'!$P$10),,0)} -> 357 | G24: {=SUMPRODUCT((Transactions_and_Customer_Information_Joined[SKU]='V1 Pricing Model (Step 2)'!$A24) * (Transactions_and_Customer_Information_Joined[Order Status]="Completed") * (Transactions_and_Customer_Information_Joined[Quantity])) / 12} -> 2.9166667 | H24: =IF($G24=0, 99, $F24/$G24) -> 122.4 | I24: =($D24-$E24)/$D24 -> 0.47389176 | J24: {=(SMALL(IF('Competitive Analysis (Step 1)'!$A$10:$A$209=$A24,'Competitive Analysis (Step 1)'!$D$10:$D$209),2)+SMALL(IF('Competitive Analysis (Step 1)'!$A$10:$A$209=$A24,'Competitive Analysis (Step 1)'!$D$10:$D$209),3))/2} -> 62.565 | K24: =$J24-$D24 -> -10.975 | L24: =$K24/$D24 -> -0.14923851 | M24: 3.8 | N24: 3.8 | O24: 0 | P24: {=MEDIAN(IF($C$22:$C$71=$C24, $I$22:$I$71))} -> 0.5261518 | Q24: {=_xlfn.LET( _xlpm.stock, $F24, _xlpm.stock_ratio, $H24, _xlpm.cat_ratios, IF($C$22:$C$71=$C24, $H$22:$H$71), _xlpm.cat_median, MEDIAN(_xlpm.cat_ratios), _xlpm.cat_stdev, STDEV(IF($C$22:$C$71=$C24, $H$22:$H$71)), _xlpm.z_score, IF(_xlpm.cat_stdev = 0, 0, (_xlpm.stock_ratio - _xlpm.cat_median) / _xlpm.cat_stdev), _xlpm.capped_z, MIN(MAX(_xlpm.z_score, -2), 2), IF(_xlpm.stock < $B$18, 0, 1 + $B$19 * _xlpm.capped_z) )} -> 0.98197154 | R24: {=_xlfn.LET( _xlpm.sku, $A24, _xlpm.tol, $B$3, _xlpm.sku_range, 'Competitive Analysis (Step 1)'!$A$10:$A$209, _xlpm.comp_prices, 'Competitive Analysis (Step 1)'!$D$10:$D$209, _xlpm.comp_reviews, 'Competitive Analysis (Step 1)'!$F$10:$F$209, _xlpm.obs_dates, 'Competitive Analysis (Step 1)'!$G$10:$G$209, _xlpm.our_price, $D24, _xlpm.matches, (_xlpm.sku_range=_xlpm.sku), _xlpm.deltas, IF(_xlpm.matches, (_xlpm.our_price - _xlpm.comp_prices) / _xlpm.comp_prices, 0), _xlpm.review_wt, IF(_xlpm.matches, LN(_xlpm.comp_reviews + 1), 0), _xlpm.decay_wt, IFERROR(IF(_xlpm.matches, EXP(-$B$17 * ($B$2 - _xlpm.obs_dates)), 0), 0), _xlpm.weights, _xlpm.review_wt * _xlpm.decay_wt, _xlpm.outside_band, IF(ABS(_xlpm.deltas) > _xlpm.tol, 1, 0), _xlpm.total_weight, SUMPRODUCT(_xlpm.weights * _xlpm.matches), _xlpm.weighted_signal, SUMPRODUCT(_xlpm.weights * _xlpm.deltas * _xlpm.outside_band), IF(_xlpm.total_weight = 0, 0, _xlpm.weighted_signal / _xlpm.total_weight) )} -> 0.15186217 | S24: =IF($R24 < -$B$16, "Raise", IF($R24 > $B$16, "Reduce", "Hold")) -> Reduce | T24: {=IF($S24="Hold", IF(0.5 * ($P24-$I24) / $P24 + 0.5 * ($R24 / MAX(ABS($R24:$R73))) > 0, "Raise", "Hold"), $S24)} -> Reduce | U24: =IF($Q24=0, $D24, _xlfn.LET( _xlpm.raw_price, $Q24 * IF($T24="Raise", ($J24*(1+$B$5)) + ($J24 * MIN($B$6*ABS($O24), $B$5) * SIGN($O24)), IF($T24="Reduce", $J24 * ($B$7 + ($B$9-$B$7) / (1+EXP(-20*($O24-$B$8)))), IF($T24="Hold", IF($O24>$B$11, MIN(MAX($D24, ($J24*$B$10)+($J24 * MIN($B$6*ABS($O24), $B$5) * SIGN($O24))), $D24*(1+$B$15)), $D24)))), IF(AND(OR($T24="Hold", $T24="Reduce"), _xlpm.raw_price < $D24, _xlpm.raw_price >= $D24 * 0.95), $D24, _xlpm.raw_price) )) -> 60.203751 | V24: =$U24-$D24 -> -13.336249 | W24: =$V24/$D24 -> -0.18134687 | X24: =$U24-$J24 -> -2.361249 | Y24: =$X24/$J24 -> -0.037740733 | Z24: =IF($V24 = 0, 0, IF($S24="Reduce", $W24*$B$13, $W24*$B$12)) -> 0.1450775 | AA24: {=ROUND(_xlfn.XLOOKUP($A24, 'Competitive Analysis (Step 1)'!$A$10:$A$209,_xlfn.ANCHORARRAY( 'Competitive Analysis (Step 1)'!$Q$10), , 0) * (1+$Z24), 0)} -> 40 | AB24: =$AA24*$U24 -> 2408.15 | AC24: {=$AB24 - _xlfn.XLOOKUP($A24, 'Competitive Analysis (Step 1)'!$A$10:$A$209,_xlfn.ANCHORARRAY( 'Competitive Analysis (Step 1)'!$R$10), ,0)} -> 118.10004 | AD24: {=$AC24 / _xlfn.XLOOKUP($A24, 'Competitive Analysis (Step 1)'!$A$10:$A$209,_xlfn.ANCHORARRAY( 'Competitive Analysis (Step 1)'!$V$10), ,0)} -> 0.054862885 | AE24: =$AA24 * _xlfn.XLOOKUP($A24, _1_product_catalog_pricing[SKU], _1_product_catalog_pricing[Cost Price ($)], , 0) -> 1547.6 | AF24: {=$AE24 - _xlfn.XLOOKUP($A24, 'Competitive Analysis (Step 1)'!$A$10:$A$209,_xlfn.ANCHORARRAY( 'Competitive Analysis (Step 1)'!$S$10),,0)} -> 193.45 | AG24: {=$AF24 / _xlfn.XLOOKUP($A24, 'Competitive Analysis (Step 1)'!$A$10:$A$209,_xlfn.ANCHORARRAY( 'Competitive Analysis (Step 1)'!$S$10),,0)} -> 0.14285714 | AH24: =$AB24-$AE24 -> 860.55004 | AI24: {=$AH24 - _xlfn.XLOOKUP($A24, 'Competitive Analysis (Step 1)'!$A$10:$A$209,_xlfn.ANCHORARRAY( 'Competitive Analysis (Step 1)'!$T$10),,0)} -> -75.349959 | AJ24: =IFERROR($AH24 / $AB24, 0) -> 0.35734901 | AK24: {=$AI24 / _xlfn.XLOOKUP($A24, 'Competitive Analysis (Step 1)'!$A$10:$A$209,_xlfn.ANCHORARRAY( 'Competitive Analysis (Step 1)'!$T$10),,0)} -> -0.080510694 | AL24: =IF($AK24 > 0, "Full", IF($AK24 >= $B$20, "Constrained", "Exclude")) -> Exclude
A25: SKU-1003 | B25: Portable Charger | C25: Electronics | D25: 154.03 | E25: 76.79 | F25: {=_xlfn.XLOOKUP($A25,'Competitive Analysis (Step 1)'!$A$10:$A$209,_xlfn.ANCHORARRAY( 'Competitive Analysis (Step 1)'!$P$10),,0)} -> 183 | G25: {=SUMPRODUCT((Transactions_and_Customer_Information_Joined[SKU]='V1 Pricing Model (Step 2)'!$A25) * (Transactions_and_Customer_Information_Joined[Order Status]="Completed") * (Transactions_and_Customer_Information_Joined[Quantity])) / 12} -> 1.9166667 | H25: =IF($G25=0, 99, $F25/$G25) -> 95.478261 | I25: =($D25-$E25)/$D25 -> 0.50146075 | J25: {=(SMALL(IF('Competitive Analysis (Step 1)'!$A$10:$A$209=$A25,'Competitive Analysis (Step 1)'!$D$10:$D$209),2)+SMALL(IF('Competitive Analysis (Step 1)'!$A$10:$A$209=$A25,'Competitive Analysis (Step 1)'!$D$10:$D$209),3))/2} -> 133.345 | K25: =$J25-$D25 -> -20.685 | L25: =$K25/$D25 -> -0.13429202 | M25: 4.7 | N25: 3.9 | O25: 0.8 | P25: {=MEDIAN(IF($C$22:$C$71=$C25, $I$22:$I$71))} -> 0.5261518 | Q25: {=_xlfn.LET( _xlpm.stock, $F25, _xlpm.stock_ratio, $H25, _xlpm.cat_ratios, IF($C$22:$C$71=$C25, $H$22:$H$71), _xlpm.cat_median, MEDIAN(_xlpm.cat_ratios), _xlpm.cat_stdev, STDEV(IF($C$22:$C$71=$C25, $H$22:$H$71)), _xlpm.z_score, IF(_xlpm.cat_stdev = 0, 0, (_xlpm.stock_ratio - _xlpm.cat_median) / _xlpm.cat_stdev), _xlpm.capped_z, MIN(MAX(_xlpm.z_score, -2), 2), IF(_xlpm.stock < $B$18, 0, 1 + $B$19 * _xlpm.capped_z) )} -> 0.9938112 | R25: {=_xlfn.LET( _xlpm.sku, $A25, _xlpm.tol, $B$3, _xlpm.sku_range, 'Competitive Analysis (Step 1)'!$A$10:$A$209, _xlpm.comp_prices, 'Competitive Analysis (Step 1)'!$D$10:$D$209, _xlpm.comp_reviews, 'Competitive Analysis (Step 1)'!$F$10:$F$209, _xlpm.obs_dates, 'Competitive Analysis (Step 1)'!$G$10:$G$209, _xlpm.our_price, $D25, _xlpm.matches, (_xlpm.sku_range=_xlpm.sku), _xlpm.deltas, IF(_xlpm.matches, (_xlpm.our_price - _xlpm.comp_prices) / _xlpm.comp_prices, 0), _xlpm.review_wt, IF(_xlpm.matches, LN(_xlpm.comp_reviews + 1), 0), _xlpm.decay_wt, IFERROR(IF(_xlpm.matches, EXP(-$B$17 * ($B$2 - _xlpm.obs_dates)), 0), 0), _xlpm.weights, _xlpm.review_wt * _xlpm.decay_wt, _xlpm.outside_band, IF(ABS(_xlpm.deltas) > _xlpm.tol, 1, 0), _xlpm.total_weight, SUMPRODUCT(_xlpm.weights * _xlpm.matches), _xlpm.weighted_signal, SUMPRODUCT(_xlpm.weights * _xlpm.deltas * _xlpm.outside_band), IF(_xlpm.total_weight = 0, 0, _xlpm.weighted_signal / _xlpm.total_weight) )} -> 0.14935681 | S25: =IF($R25 < -$B$16, "Raise", IF($R25 > $B$16, "Reduce", "Hold")) -> Reduce | T25: {=IF($S25="Hold", IF(0.5 * ($P25-$I25) / $P25 + 0.5 * ($R25 / MAX(ABS($R25:$R74))) > 0, "Raise", "Hold"), $S25)} -> Reduce | U25: =IF($Q25=0, $D25, _xlfn.LET( _xlpm.raw_price, $Q25 * IF($T25="Raise", ($J25*(1+$B$5)) + ($J25 * MIN($B$6*ABS($O25), $B$5) * SIGN($O25)), IF($T25="Reduce", $J25 * ($B$7 + ($B$9-$B$7) / (1+EXP(-20*($O25-$B$8)))), IF($T25="Hold", IF($O25>$B$11, MIN(MAX($D25, ($J25*$B$10)+($J25 * MIN($B$6*ABS($O25), $B$5) * SIGN($O25))), $D25*(1+$B$15)), $D25)))), IF(AND(OR($T25="Hold", $T25="Reduce"), _xlpm.raw_price < $D25, _xlpm.raw_price >= $D25 * 0.95), $D25, _xlpm.raw_price) )) -> 129.86936 | V25: =$U25-$D25 -> -24.16064 | W25: =$V25/$D25 -> -0.15685672 | X25: =$U25-$J25 -> -3.4756404 | Y25: =$X25/$J25 -> -0.026065023 | Z25: =IF($V25 = 0, 0, IF($S25="Reduce", $W25*$B$13, $W25*$B$12)) -> 0.12548538 | AA25: {=ROUND(_xlfn.XLOOKUP($A25, 'Competitive Analysis (Step 1)'!$A$10:$A$209,_xlfn.ANCHORARRAY( 'Competitive Analysis (Step 1)'!$Q$10), , 0) * (1+$Z25), 0)} -> 26 | AB25: =$AA25*$U25 -> 3376.6033 | AC25: {=$AB25 - _xlfn.XLOOKUP($A25, 'Competitive Analysis (Step 1)'!$A$10:$A$209,_xlfn.ANCHORARRAY( 'Competitive Analysis (Step 1)'!$R$10), ,0)} -> -166.08665 | AD25: {=$AC25 / _xlfn.XLOOKUP($A25, 'Competitive Analysis (Step 1)'!$A$10:$A$209,_xlfn.ANCHORARRAY( 'Competitive Analysis (Step 1)'!$V$10), ,0)} -> -0.0507423 | AE25: =$AA25 * _xlfn.XLOOKUP($A25, _1_product_catalog_pricing[SKU], _1_product_catalog_pricing[Cost Price ($)], , 0) -> 1996.54 | AF25: {=$AE25 - _xlfn.XLOOKUP($A25, 'Competitive Analysis (Step 1)'!$A$10:$A$209,_xlfn.ANCHORARRAY( 'Competitive Analysis (Step 1)'!$S$10),,0)} -> 230.37 | AG25: {=$AF25 / _xlfn.XLOOKUP($A25, 'Competitive Analysis (Step 1)'!$A$10:$A$209,_xlfn.ANCHORARRAY( 'Competitive Analysis (Step 1)'!$S$10),,0)} -> 0.13043478 | AH25: =$AB25-$AE25 -> 1380.0633 | AI25: {=$AH25 - _xlfn.XLOOKUP($A25, 'Competitive Analysis (Step 1)'!$A$10:$A$209,_xlfn.ANCHORARRAY( 'Competitive Analysis (Step 1)'!$T$10),,0)} -> -396.45665 | AJ25: =IFERROR($AH25 / $AB25, 0) -> 0.40871349 | AK25: {=$AI25 / _xlfn.XLOOKUP($A25, 'Competitive Analysis (Step 1)'!$A$10:$A$209,_xlfn.ANCHORARRAY( 'Competitive Analysis (Step 1)'!$T$10),,0)} -> -0.22316476 | AL25: =IF($AK25 > 0, "Full", IF($AK25 >= $B$20, "Constrained", "Exclude")) -> Exclude
A26: SKU-1004 | B26: USB-C Hub | C26: Electronics | D26: 18.39 | E26: 8.26 | F26: {=_xlfn.XLOOKUP($A26,'Competitive Analysis (Step 1)'!$A$10:$A$209,_xlfn.ANCHORARRAY( 'Competitive Analysis (Step 1)'!$P$10),,0)} -> 40 | G26: {=SUMPRODUCT((Transactions_and_Customer_Information_Joined[SKU]='V1 Pricing Model (Step 2)'!$A26) * (Transactions_and_Customer_Information_Joined[Order Status]="Completed") * (Transactions_and_Customer_Information_Joined[Quantity])) / 12} -> 1.4166667 | H26: =IF($G26=0, 99, $F26/$G26) -> 28.235294 | I26: =($D26-$E26)/$D26 -> 0.55084285 | J26: {=(SMALL(IF('Competitive Analysis (Step 1)'!$A$10:$A$209=$A26,'Competitive Analysis (Step 1)'!$D$10:$D$209),2)+SMALL(IF('Competitive Analysis (Step 1)'!$A$10:$A$209=$A26,'Competitive Analysis (Step 1)'!$D$10:$D$209),3))/2} -> 21.76 | K26: =$J26-$D26 -> 3.37 | L26: =$K26/$D26 -> 0.18325177 | M26: 4.1 | N26: 3.65 | O26: 0.45 | P26: {=MEDIAN(IF($C$22:$C$71=$C26, $I$22:$I$71))} -> 0.5261518 | Q26: {=_xlfn.LET( _xlpm.stock, $F26, _xlpm.stock_ratio, $H26, _xlpm.cat_ratios, IF($C$22:$C$71=$C26, $H$22:$H$71), _xlpm.cat_median, MEDIAN(_xlpm.cat_ratios), _xlpm.cat_stdev, STDEV(IF($C$22:$C$71=$C26, $H$22:$H$71)), _xlpm.z_score, IF(_xlpm.cat_stdev = 0, 0, (_xlpm.stock_ratio - _xlpm.cat_median) / _xlpm.cat_stdev), _xlpm.capped_z, MIN(MAX(_xlpm.z_score, -2), 2), IF(_xlpm.stock < $B$18, 0, 1 + $B$19 * _xlpm.capped_z) )} -> 1.0233834 | R26: {=_xlfn.LET( _xlpm.sku, $A26, _xlpm.tol, $B$3, _xlpm.sku_range, 'Competitive Analysis (Step 1)'!$A$10:$A$209, _xlpm.comp_prices, 'Competitive Analysis (Step 1)'!$D$10:$D$209, _xlpm.comp_reviews, 'Competitive Analysis (Step 1)'!$F$10:$F$209, _xlpm.obs_dates, 'Competitive Analysis (Step 1)'!$G$10:$G$209, _xlpm.our_price, $D26, _xlpm.matches, (_xlpm.sku_range=_xlpm.sku), _xlpm.deltas, IF(_xlpm.matches, (_xlpm.our_price - _xlpm.comp_prices) / _xlpm.comp_prices, 0), _xlpm.review_wt, IF(_xlpm.matches, LN(_xlpm.comp_reviews + 1), 0), _xlpm.decay_wt, IFERROR(IF(_xlpm.matches, EXP(-$B$17 * ($B$2 - _xlpm.obs_dates)), 0), 0), _xlpm.weights, _xlpm.review_wt * _xlpm.decay_wt, _xlpm.outside_band, IF(ABS(_xlpm.deltas) > _xlpm.tol, 1, 0), _xlpm.total_weight, SUMPRODUCT(_xlpm.weights * _xlpm.matches), _xlpm.weighted_signal, SUMPRODUCT(_xlpm.weights * _xlpm.deltas * _xlpm.outside_band), IF(_xlpm.total_weight = 0, 0, _xlpm.weighted_signal / _xlpm.total_weight) )} -> -0.017545443 | S26: =IF($R26 < -$B$16, "Raise", IF($R26 > $B$16, "Reduce", "Hold")) -> Hold | T26: {=IF($S26="Hold", IF(0.5 * ($P26-$I26) / $P26 + 0.5 * ($R26 / MAX(ABS($R26:$R75))) > 0, "Raise", "Hold"), $S26)} -> Hold | U26: =IF($Q26=0, $D26, _xlfn.LET( _xlpm.raw_price, $Q26 * IF($T26="Raise", ($J26*(1+$B$5)) + ($J26 * MIN($B$6*ABS($O26), $B$5) * SIGN($O26)), IF($T26="Reduce", $J26 * ($B$7 + ($B$9-$B$7) / (1+EXP(-20*($O26-$B$8)))), IF($T26="Hold", IF($O26>$B$11, MIN(MAX($D26, ($J26*$B$10)+($J26 * MIN($B$6*ABS($O26), $B$5) * SIGN($O26))), $D26*(1+$B$15)), $D26)))), IF(AND(OR($T26="Hold", $T26="Reduce"), _xlpm.raw_price < $D26, _xlpm.raw_price >= $D26 * 0.95), $D26, _xlpm.raw_price) )) -> 20.325622 | V26: =$U26-$D26 -> 1.9356217 | W26: =$V26/$D26 -> 0.10525403 | X26: =$U26-$J26 -> -1.4343783 | Y26: =$X26/$J26 -> -0.065918123 | Z26: =IF($V26 = 0, 0, IF($S26="Reduce", $W26*$B$13, $W26*$B$12)) -> -0.042101613 | AA26: {=ROUND(_xlfn.XLOOKUP($A26, 'Competitive Analysis (Step 1)'!$A$10:$A$209,_xlfn.ANCHORARRAY( 'Competitive Analysis (Step 1)'!$Q$10), , 0) * (1+$Z26), 0)} -> 16 | AB26: =$AA26*$U26 -> 325.20995 | AC26: {=$AB26 - _xlfn.XLOOKUP($A26, 'Competitive Analysis (Step 1)'!$A$10:$A$209,_xlfn.ANCHORARRAY( 'Competitive Analysis (Step 1)'!$R$10), ,0)} -> 12.579946 | AD26: {=$AC26 / _xlfn.XLOOKUP($A26, 'Competitive Analysis (Step 1)'!$A$10:$A$209,_xlfn.ANCHORARRAY( 'Competitive Analysis (Step 1)'!$V$10), ,0)} -> 0.044133969 | AE26: =$AA26 * _xlfn.XLOOKUP($A26, _1_product_catalog_pricing[SKU], _1_product_catalog_pricing[Cost Price ($)], , 0) -> 132.16 | AF26: {=$AE26 - _xlfn.XLOOKUP($A26, 'Competitive Analysis (Step 1)'!$A$10:$A$209,_xlfn.ANCHORARRAY( 'Competitive Analysis (Step 1)'!$S$10),,0)} -> -8.26 | AG26: {=$AF26 / _xlfn.XLOOKUP($A26, 'Competitive Analysis (Step 1)'!$A$10:$A$209,_xlfn.ANCHORARRAY( 'Competitive Analysis (Step 1)'!$S$10),,0)} -> -0.058823529 | AH26: =$AB26-$AE26 -> 193.04995 | AI26: {=$AH26 - _xlfn.XLOOKUP($A26, 'Competitive Analysis (Step 1)'!$A$10:$A$209,_xlfn.ANCHORARRAY( 'Competitive Analysis (Step 1)'!$T$10),,0)} -> 20.839946 | AJ26: =IFERROR($AH26 / $AB26, 0) -> 0.59361637 | AK26: {=$AI26 / _xlfn.XLOOKUP($A26, 'Competitive Analysis (Step 1)'!$A$10:$A$209,_xlfn.ANCHORARRAY( 'Competitive Analysis (Step 1)'!$T$10),,0)} -> 0.12101473 | AL26: =IF($AK26 > 0, "Full", IF($AK26 >= $B$20, "Constrained", "Exclude")) -> Full
A27: SKU-1005 | B27: Webcam | C27: Electronics | D27: 29.62 | E27: 19.42 | F27: {=_xlfn.XLOOKUP($A27,'Competitive Analysis (Step 1)'!$A$10:$A$209,_xlfn.ANCHORARRAY( 'Competitive Analysis (Step 1)'!$P$10),,0)} -> 437 | G27: {=SUMPRODUCT((Transactions_and_Customer_Information_Joined[SKU]='V1 Pricing Model (Step 2)'!$A27) * (Transactions_and_Customer_Information_Joined[Order Status]="Completed") * (Transactions_and_Customer_Information_Joined[Quantity])) / 12} -> 3.8333333 | H27: =IF($G27=0, 99, $F27/$G27) -> 114 | I27: =($D27-$E27)/$D27 -> 0.34436192 | J27: {=(SMALL(IF('Competitive Analysis (Step 1)'!$A$10:$A$209=$A27,'Competitive Analysis (Step 1)'!$D$10:$D$209),2)+SMALL(IF('Competitive Analysis (Step 1)'!$A$10:$A$209=$A27,'Competitive Analysis (Step 1)'!$D$10:$D$209),3))/2} -> 27.265 | K27: =$J27-$D27 -> -2.355 | L27: =$K27/$D27 -> -0.07950709 | M27: 3.5 | N27: 3.45 | O27: 0.05 | P27: {=MEDIAN(IF($C$22:$C$71=$C27, $I$22:$I$71))} -> 0.5261518 | Q27: {=_xlfn.LET( _xlpm.stock, $F27, _xlpm.stock_ratio, $H27, _xlpm.cat_ratios, IF($C$22:$C$71=$C27, $H$22:$H$71), _xlpm.cat_median, MEDIAN(_xlpm.cat_ratios), _xlpm.cat_stdev, STDEV(IF($C$22:$C$71=$C27, $H$22:$H$71)), _xlpm.z_score, IF(_xlpm.cat_stdev = 0, 0, (_xlpm.stock_ratio - _xlpm.cat_median) / _xlpm.cat_stdev), _xlpm.capped_z, MIN(MAX(_xlpm.z_score, -2), 2), IF(_xlpm.stock < $B$18, 0, 1 + $B$19 * _xlpm.capped_z) )} -> 0.9856657 | R27: {=_xlfn.LET( _xlpm.sku, $A27, _xlpm.tol, $B$3, _xlpm.sku_range, 'Competitive Analysis (Step 1)'!$A$10:$A$209, _xlpm.comp_prices, 'Competitive Analysis (Step 1)'!$D$10:$D$209, _xlpm.comp_reviews, 'Competitive Analysis (Step 1)'!$F$10:$F$209, _xlpm.obs_dates, 'Competitive Analysis (Step 1)'!$G$10:$G$209, _xlpm.our_price, $D27, _xlpm.matches, (_xlpm.sku_range=_xlpm.sku), _xlpm.deltas, IF(_xlpm.matches, (_xlpm.our_price - _xlpm.comp_prices) / _xlpm.comp_prices, 0), _xlpm.review_wt, IF(_xlpm.matches, LN(_xlpm.comp_reviews + 1), 0), _xlpm.decay_wt, IFERROR(IF(_xlpm.matches, EXP(-$B$17 * ($B$2 - _xlpm.obs_dates)), 0), 0), _xlpm.weights, _xlpm.review_wt * _xlpm.decay_wt, _xlpm.outside_band, IF(ABS(_xlpm.deltas) > _xlpm.tol, 1, 0), _xlpm.total_weight, SUMPRODUCT(_xlpm.weights * _xlpm.matches), _xlpm.weighted_signal, SUMPRODUCT(_xlpm.weights * _xlpm.deltas * _xlpm.outside_band), IF(_xlpm.total_weight = 0, 0, _xlpm.weighted_signal / _xlpm.total_weight) )} -> 0.049960291 | S27: =IF($R27 < -$B$16, "Raise", IF($R27 > $B$16, "Reduce", "Hold")) -> Hold | T27: {=IF($S27="Hold", IF(0.5 * ($P27-$I27) / $P27 + 0.5 * ($R27 / MAX(ABS($R27:$R76))) > 0, "Raise", "Hold"), $S27)} -> Raise | U27: =IF($Q27=0, $D27, _xlfn.LET( _xlpm.raw_price, $Q27 * IF($T27="Raise", ($J27*(1+$B$5)) + ($J27 * MIN($B$6*ABS($O27), $B$5) * SIGN($O27)), IF($T27="Reduce", $J27 * ($B$7 + ($B$9-$B$7) / (1+EXP(-20*($O27-$B$8)))), IF($T27="Hold", IF($O27>$B$11, MIN(MAX($D27, ($J27*$B$10)+($J27 * MIN($B$6*ABS($O27), $B$5) * SIGN($O27))), $D27*(1+$B$15)), $D27)))), IF(AND(OR($T27="Hold", $T27="Reduce"), _xlpm.raw_price < $D27, _xlpm.raw_price >= $D27 * 0.95), $D27, _xlpm.raw_price) )) -> 28.258195 | V27: =$U27-$D27 -> -1.3618047 | W27: =$V27/$D27 -> -0.045975852 | X27: =$U27-$J27 -> 0.99319526 | Y27: =$X27/$J27 -> 0.036427481 | Z27: =IF($V27 = 0, 0, IF($S27="Reduce", $W27*$B$13, $W27*$B$12)) -> 0.018390341 | AA27: {=ROUND(_xlfn.XLOOKUP($A27, 'Competitive Analysis (Step 1)'!$A$10:$A$209,_xlfn.ANCHORARRAY( 'Competitive Analysis (Step 1)'!$Q$10), , 0) * (1+$Z27), 0)} -> 47 | AB27: =$AA27*$U27 -> 1328.1352 | AC27: {=$AB27 - _xlfn.XLOOKUP($A27, 'Competitive Analysis (Step 1)'!$A$10:$A$209,_xlfn.ANCHORARRAY( 'Competitive Analysis (Step 1)'!$R$10), ,0)} -> 110.97518 | AD27: {=$AC27 / _xlfn.XLOOKUP($A27, 'Competitive Analysis (Step 1)'!$A$10:$A$209,_xlfn.ANCHORARRAY( 'Competitive Analysis (Step 1)'!$V$10), ,0)} -> 0.099621334 | AE27: =$AA27 * _xlfn.XLOOKUP($A27, _1_product_catalog_pricing[SKU], _1_product_catalog_pricing[Cost Price ($)], , 0) -> 912.74 | AF27: {=$AE27 - _xlfn.XLOOKUP($A27, 'Competitive Analysis (Step 1)'!$A$10:$A$209,_xlfn.ANCHORARRAY( 'Competitive Analysis (Step 1)'!$S$10),,0)} -> 19.42 | AG27: {=$AF27 / _xlfn.XLOOKUP($A27, 'Competitive Analysis (Step 1)'!$A$10:$A$209,_xlfn.ANCHORARRAY( 'Competitive Analysis (Step 1)'!$S$10),,0)} -> 0.02173913 | AH27: =$AB27-$AE27 -> 415.39518 | AI27: {=$AH27 - _xlfn.XLOOKUP($A27, 'Competitive Analysis (Step 1)'!$A$10:$A$209,_xlfn.ANCHORARRAY( 'Competitive Analysis (Step 1)'!$T$10),,0)} -> 91.555177 | AJ27: =IFERROR($AH27 / $AB27, 0) -> 0.31276574 | AK27: {=$AI27 / _xlfn.XLOOKUP($A27, 'Competitive Analysis (Step 1)'!$A$10:$A$209,_xlfn.ANCHORARRAY( 'Competitive Analysis (Step 1)'!$T$10),,0)} -> 0.28271732 | AL27: =IF($AK27 > 0, "Full", IF($AK27 >= $B$20, "Constrained", "Exclude")) -> Full
A28: SKU-1006 | B28: Mechanical Keyboard | C28: Electronics | D28: 113.18 | E28: 39.01 | F28: {=_xlfn.XLOOKUP($A28,'Competitive Analysis (Step 1)'!$A$10:$A$209,_xlfn.ANCHORARRAY( 'Competitive Analysis (Step 1)'!$P$10),,0)} -> 107 | G28: {=SUMPRODUCT((Transactions_and_Customer_Information_Joined[SKU]='V1 Pricing Model (Step 2)'!$A28) * (Transactions_and_Customer_Information_Joined[Order Status]="Completed") * (Transactions_and_Customer_Information_Joined[Quantity])) / 12} -> 2 | H28: =IF($G28=0, 99, $F28/$G28) -> 53.5 | I28: =($D28-$E28)/$D28 -> 0.6553278 | J28: {=(SMALL(IF('Competitive Analysis (Step 1)'!$A$10:$A$209=$A28,'Competitive Analysis (Step 1)'!$D$10:$D$209),2)+SMALL(IF('Competitive Analysis (Step 1)'!$A$10:$A$209=$A28,'Competitive Analysis (Step 1)'!$D$10:$D$209),3))/2} -> 115.705 | K28: =$J28-$D28 -> 2.525 | L28: =$K28/$D28 -> 0.022309595 | M28: 4.3 | N28: 3.225 | O28: 1.075 | P28: {=MEDIAN(IF($C$22:$C$71=$C28, $I$22:$I$71))} -> 0.5261518 | Q28: {=_xlfn.LET( _xlpm.stock, $F28, _xlpm.stock_ratio, $H28, _xlpm.cat_ratios, IF($C$22:$C$71=$C28, $H$22:$H$71), _xlpm.cat_median, MEDIAN(_xlpm.cat_ratios), _xlpm.cat_stdev, STDEV(IF($C$22:$C$71=$C28, $H$22:$H$71)), _xlpm.z_score, IF(_xlpm.cat_stdev = 0, 0, (_xlpm.stock_ratio - _xlpm.cat_median) / _xlpm.cat_stdev), _xlpm.capped_z, MIN(MAX(_xlpm.z_score, -2), 2), IF(_xlpm.stock < $B$18, 0, 1 + $B$19 * _xlpm.capped_z) )} -> 1.0122724 | R28: {=_xlfn.LET( _xlpm.sku, $A28, _xlpm.tol, $B$3, _xlpm.sku_range, 'Competitive Analysis (Step 1)'!$A$10:$A$209, _xlpm.comp_prices, 'Competitive Analysis (Step 1)'!$D$10:$D$209, _xlpm.comp_reviews, 'Competitive Analysis (Step 1)'!$F$10:$F$209, _xlpm.obs_dates, 'Competitive Analysis (Step 1)'!$G$10:$G$209, _xlpm.our_price, $D28, _xlpm.matches, (_xlpm.sku_range=_xlpm.sku), _xlpm.deltas, IF(_xlpm.matches, (_xlpm.our_price - _xlpm.comp_prices) / _xlpm.comp_prices, 0), _xlpm.review_wt, IF(_xlpm.matches, LN(_xlpm.comp_reviews + 1), 0), _xlpm.decay_wt, IFERROR(IF(_xlpm.matches, EXP(-$B$17 * ($B$2 - _xlpm.obs_dates)), 0), 0), _xlpm.weights, _xlpm.review_wt * _xlpm.decay_wt, _xlpm.outside_band, IF(ABS(_xlpm.deltas) > _xlpm.tol, 1, 0), _xlpm.total_weight, SUMPRODUCT(_xlpm.weights * _xlpm.matches), _xlpm.weighted_signal, SUMPRODUCT(_xlpm.weights * _xlpm.deltas * _xlpm.outside_band), IF(_xlpm.total_weight = 0, 0, _xlpm.weighted_signal / _xlpm.total_weight) )} -> -0.034766652 | S28: =IF($R28 < -$B$16, "Raise", IF($R28 > $B$16, "Reduce", "Hold")) -> Hold | T28: {=IF($S28="Hold", IF(0.5 * ($P28-$I28) / $P28 + 0.5 * ($R28 / MAX(ABS($R28:$R77))) > 0, "Raise", "Hold"), $S28)} -> Hold | U28: =IF($Q28=0, $D28, _xlfn.LET( _xlpm.raw_price, $Q28 * IF($T28="Raise", ($J28*(1+$B$5)) + ($J28 * MIN($B$6*ABS($O28), $B$5) * SIGN($O28)), IF($T28="Reduce", $J28 * ($B$7 + ($B$9-$B$7) / (1+EXP(-20*($O28-$B$8)))), IF($T28="Hold", IF($O28>$B$11, MIN(MAX($D28, ($J28*$B$10)+($J28 * MIN($B$6*ABS($O28), $B$5) * SIGN($O28))), $D28*(1+$B$15)), $D28)))), IF(AND(OR($T28="Hold", $T28="Reduce"), _xlpm.raw_price < $D28, _xlpm.raw_price >= $D28 * 0.95), $D28, _xlpm.raw_price) )) -> 122.07351 | V28: =$U28-$D28 -> 8.8935122 | W28: =$V28/$D28 -> 0.078578479 | X28: =$U28-$J28 -> 6.3685122 | Y28: =$X28/$J28 -> 0.055040942 | Z28: =IF($V28 = 0, 0, IF($S28="Reduce", $W28*$B$13, $W28*$B$12)) -> -0.031431392 | AA28: {=ROUND(_xlfn.XLOOKUP($A28, 'Competitive Analysis (Step 1)'!$A$10:$A$209,_xlfn.ANCHORARRAY( 'Competitive Analysis (Step 1)'!$Q$10), , 0) * (1+$Z28), 0)} -> 23 | AB28: =$AA28*$U28 -> 2807.6908 | AC28: {=$AB28 - _xlfn.XLOOKUP($A28, 'Competitive Analysis (Step 1)'!$A$10:$A$209,_xlfn.ANCHORARRAY( 'Competitive Analysis (Step 1)'!$R$10), ,0)} -> 91.370781 | AD28: {=$AC28 / _xlfn.XLOOKUP($A28, 'Competitive Analysis (Step 1)'!$A$10:$A$209,_xlfn.ANCHORARRAY( 'Competitive Analysis (Step 1)'!$V$10), ,0)} -> 0.03728887 | AE28: =$AA28 * _xlfn.XLOOKUP($A28, _1_product_catalog_pricing[SKU], _1_product_catalog_pricing[Cost Price ($)], , 0) -> 897.23 | AF28: {=$AE28 - _xlfn.XLOOKUP($A28, 'Competitive Analysis (Step 1)'!$A$10:$A$209,_xlfn.ANCHORARRAY( 'Competitive Analysis (Step 1)'!$S$10),,0)} -> -39.01 | AG28: {=$AF28 / _xlfn.XLOOKUP($A28, 'Competitive Analysis (Step 1)'!$A$10:$A$209,_xlfn.ANCHORARRAY( 'Competitive Analysis (Step 1)'!$S$10),,0)} -> -0.041666667 | AH28: =$AB28-$AE28 -> 1910.4608 | AI28: {=$AH28 - _xlfn.XLOOKUP($A28, 'Competitive Analysis (Step 1)'!$A$10:$A$209,_xlfn.ANCHORARRAY( 'Competitive Analysis (Step 1)'!$T$10),,0)} -> 130.38078 | AJ28: =IFERROR($AH28 / $AB28, 0) -> 0.68043846 | AK28: {=$AI28 / _xlfn.XLOOKUP($A28, 'Competitive Analysis (Step 1)'!$A$10:$A$209,_xlfn.ANCHORARRAY( 'Competitive Analysis (Step 1)'!$T$10),,0)} -> 0.073244338 | AL28: =IF($AK28 > 0, "Full", IF($AK28 >= $B$20, "Constrained", "Exclude")) -> Full
A29: SKU-1007 | B29: Gaming Mouse | C29: Electronics | D29: 124.26 | E29: 52.62 | F29: {=_xlfn.XLOOKUP($A29,'Competitive Analysis (Step 1)'!$A$10:$A$209,_xlfn.ANCHORARRAY( 'Competitive Analysis (Step 1)'!$P$10),,0)} -> 194 | G29: {=SUMPRODUCT((Transactions_and_Customer_Information_Joined[SKU]='V1 Pricing Model (Step 2)'!$A29) * (Transactions_and_Customer_Information_Joined[Order Status]="Completed") * (Transactions_and_Customer_Information_Joined[Quantity])) / 12} -> 3.6666667 | H29: =IF($G29=0, 99, $F29/$G29) -> 52.909091 | I29: =($D29-$E29)/$D29 -> 0.57653308 | J29: {=(SMALL(IF('Competitive Analysis (Step 1)'!$A$10:$A$209=$A29,'Competitive Analysis (Step 1)'!$D$10:$D$209),2)+SMALL(IF('Competitive Analysis (Step 1)'!$A$10:$A$209=$A29,'Competitive Analysis (Step 1)'!$D$10:$D$209),3))/2} -> 116.915 | K29: =$J29-$D29 -> -7.345 | L29: =$K29/$D29 -> -0.059109931 | M29: 3.5 | N29: 3.675 | O29: -0.175 | P29: {=MEDIAN(IF($C$22:$C$71=$C29, $I$22:$I$71))} -> 0.5261518 | Q29: {=_xlfn.LET( _xlpm.stock, $F29, _xlpm.stock_ratio, $H29, _xlpm.cat_ratios, IF($C$22:$C$71=$C29, $H$22:$H$71), _xlpm.cat_median, MEDIAN(_xlpm.cat_ratios), _xlpm.cat_stdev, STDEV(IF($C$22:$C$71=$C29, $H$22:$H$71)), _xlpm.z_score, IF(_xlpm.cat_stdev = 0, 0, (_xlpm.stock_ratio - _xlpm.cat_median) / _xlpm.cat_stdev), _xlpm.capped_z, MIN(MAX(_xlpm.z_score, -2), 2), IF(_xlpm.stock < $B$18, 0, 1 + $B$19 * _xlpm.capped_z) )} -> 1.0125323 | R29: {=_xlfn.LET( _xlpm.sku, $A29, _xlpm.tol, $B$3, _xlpm.sku_range, 'Competitive Analysis (Step 1)'!$A$10:$A$209, _xlpm.comp_prices, 'Competitive Analysis (Step 1)'!$D$10:$D$209, _xlpm.comp_reviews, 'Competitive Analysis (Step 1)'!$F$10:$F$209, _xlpm.obs_dates, 'Competitive Analysis (Step 1)'!$G$10:$G$209, _xlpm.our_price, $D29, _xlpm.matches, (_xlpm.sku_range=_xlpm.sku), _xlpm.deltas, IF(_xlpm.matches, (_xlpm.our_price - _xlpm.comp_prices) / _xlpm.comp_prices, 0), _xlpm.review_wt, IF(_xlpm.matches, LN(_xlpm.comp_reviews + 1), 0), _xlpm.decay_wt, IFERROR(IF(_xlpm.matches, EXP(-$B$17 * ($B$2 - _xlpm.obs_dates)), 0), 0), _xlpm.weights, _xlpm.review_wt * _xlpm.decay_wt, _xlpm.outside_band, IF(ABS(_xlpm.deltas) > _xlpm.tol, 1, 0), _xlpm.total_weight, SUMPRODUCT(_xlpm.weights * _xlpm.matches), _xlpm.weighted_signal, SUMPRODUCT(_xlpm.weights * _xlpm.deltas * _xlpm.outside_band), IF(_xlpm.total_weight = 0, 0, _xlpm.weighted_signal / _xlpm.total_weight) )} -> 0.099696987 | S29: =IF($R29 < -$B$16, "Raise", IF($R29 > $B$16, "Reduce", "Hold")) -> Reduce | T29: {=IF($S29="Hold", IF(0.5 * ($P29-$I29) / $P29 + 0.5 * ($R29 / MAX(ABS($R29:$R78))) > 0, "Raise", "Hold"), $S29)} -> Reduce | U29: =IF($Q29=0, $D29, _xlfn.LET( _xlpm.raw_price, $Q29 * IF($T29="Raise", ($J29*(1+$B$5)) + ($J29 * MIN($B$6*ABS($O29), $B$5) * SIGN($O29)), IF($T29="Reduce", $J29 * ($B$7 + ($B$9-$B$7) / (1+EXP(-20*($O29-$B$8)))), IF($T29="Hold", IF($O29>$B$11, MIN(MAX($D29, ($J29*$B$10)+($J29 * MIN($B$6*ABS($O29), $B$5) * SIGN($O29))), $D29*(1+$B$15)), $D29)))), IF(AND(OR($T29="Hold", $T29="Reduce"), _xlpm.raw_price < $D29, _xlpm.raw_price >= $D29 * 0.95), $D29, _xlpm.raw_price) )) -> 115.74321 | V29: =$U29-$D29 -> -8.5167934 | W29: =$V29/$D29 -> -0.068540104 | X29: =$U29-$J29 -> -1.1717934 | Y29: =$X29/$J29 -> -0.010022609 | Z29: =IF($V29 = 0, 0, IF($S29="Reduce", $W29*$B$13, $W29*$B$12)) -> 0.054832083 | AA29: {=ROUND(_xlfn.XLOOKUP($A29, 'Competitive Analysis (Step 1)'!$A$10:$A$209,_xlfn.ANCHORARRAY( 'Competitive Analysis (Step 1)'!$Q$10), , 0) * (1+$Z29), 0)} -> 46 | AB29: =$AA29*$U29 -> 5324.1875 | AC29: {=$AB29 - _xlfn.XLOOKUP($A29, 'Competitive Analysis (Step 1)'!$A$10:$A$209,_xlfn.ANCHORARRAY( 'Competitive Analysis (Step 1)'!$R$10), ,0)} -> -143.25249 | AD29: {=$AC29 / _xlfn.XLOOKUP($A29, 'Competitive Analysis (Step 1)'!$A$10:$A$209,_xlfn.ANCHORARRAY( 'Competitive Analysis (Step 1)'!$V$10), ,0)} -> -0.027580062 | AE29: =$AA29 * _xlfn.XLOOKUP($A29, _1_product_catalog_pricing[SKU], _1_product_catalog_pricing[Cost Price ($)], , 0) -> 2420.52 | AF29: {=$AE29 - _xlfn.XLOOKUP($A29, 'Competitive Analysis (Step 1)'!$A$10:$A$209,_xlfn.ANCHORARRAY( 'Competitive Analysis (Step 1)'!$S$10),,0)} -> 105.24 | AG29: {=$AF29 / _xlfn.XLOOKUP($A29, 'Competitive Analysis (Step 1)'!$A$10:$A$209,_xlfn.ANCHORARRAY( 'Competitive Analysis (Step 1)'!$S$10),,0)} -> 0.045454545 | AH29: =$AB29-$AE29 -> 2903.6675 | AI29: {=$AH29 - _xlfn.XLOOKUP($A29, 'Competitive Analysis (Step 1)'!$A$10:$A$209,_xlfn.ANCHORARRAY( 'Competitive Analysis (Step 1)'!$T$10),,0)} -> -248.49249 | AJ29: =IFERROR($AH29 / $AB29, 0) -> 0.54537289 | AK29: {=$AI29 / _xlfn.XLOOKUP($A29, 'Competitive Analysis (Step 1)'!$A$10:$A$209,_xlfn.ANCHORARRAY( 'Competitive Analysis (Step 1)'!$T$10),,0)} -> -0.07883245 | AL29: =IF($AK29 > 0, "Full", IF($AK29 >= $B$20, "Constrained", "Exclude")) -> Exclude
A30: SKU-1008 | B30: LED Desk Lamp | C30: Electronics | D30: 81.6 | E30: 29.32 | F30: {=_xlfn.XLOOKUP($A30,'Competitive Analysis (Step 1)'!$A$10:$A$209,_xlfn.ANCHORARRAY( 'Competitive Analysis (Step 1)'!$P$10),,0)} -> 412 | G30: {=SUMPRODUCT((Transactions_and_Customer_Information_Joined[SKU]='V1 Pricing Model (Step 2)'!$A30) * (Transactions_and_Customer_Information_Joined[Order Status]="Completed") * (Transactions_and_Customer_Information_Joined[Quantity])) / 12} -> 3.1666667 | H30: =IF($G30=0, 99, $F30/$G30) -> 130.10526 | I30: =($D30-$E30)/$D30 -> 0.64068627 | J30: {=(SMALL(IF('Competitive Analysis (Step 1)'!$A$10:$A$209=$A30,'Competitive Analysis (Step 1)'!$D$10:$D$209),2)+SMALL(IF('Competitive Analysis (Step 1)'!$A$10:$A$209=$A30,'Competitive Analysis (Step 1)'!$D$10:$D$209),3))/2} -> 69.525 | K30: =$J30-$D30 -> -12.075 | L30: =$K30/$D30 -> -0.14797794 | M30: 3.6 | N30: 4 | O30: -0.4 | P30: {=MEDIAN(IF($C$22:$C$71=$C30, $I$22:$I$71))} -> 0.5261518 | Q30: {=_xlfn.LET( _xlpm.stock, $F30, _xlpm.stock_ratio, $H30, _xlpm.cat_ratios, IF($C$22:$C$71=$C30, $H$22:$H$71), _xlpm.cat_median, MEDIAN(_xlpm.cat_ratios), _xlpm.cat_stdev, STDEV(IF($C$22:$C$71=$C30, $H$22:$H$71)), _xlpm.z_score, IF(_xlpm.cat_stdev = 0, 0, (_xlpm.stock_ratio - _xlpm.cat_median) / _xlpm.cat_stdev), _xlpm.capped_z, MIN(MAX(_xlpm.z_score, -2), 2), IF(_xlpm.stock < $B$18, 0, 1 + $B$19 * _xlpm.capped_z) )} -> 0.97858291 | R30: {=_xlfn.LET( _xlpm.sku, $A30, _xlpm.tol, $B$3, _xlpm.sku_range, 'Competitive Analysis (Step 1)'!$A$10:$A$209, _xlpm.comp_prices, 'Competitive Analysis (Step 1)'!$D$10:$D$209, _xlpm.comp_reviews, 'Competitive Analysis (Step 1)'!$F$10:$F$209, _xlpm.obs_dates, 'Competitive Analysis (Step 1)'!$G$10:$G$209, _xlpm.our_price, $D30, _xlpm.matches, (_xlpm.sku_range=_xlpm.sku), _xlpm.deltas, IF(_xlpm.matches, (_xlpm.our_price - _xlpm.comp_prices) / _xlpm.comp_prices, 0), _xlpm.review_wt, IF(_xlpm.matches, LN(_xlpm.comp_reviews + 1), 0), _xlpm.decay_wt, IFERROR(IF(_xlpm.matches, EXP(-$B$17 * ($B$2 - _xlpm.obs_dates)), 0), 0), _xlpm.weights, _xlpm.review_wt * _xlpm.decay_wt, _xlpm.outside_band, IF(ABS(_xlpm.deltas) > _xlpm.tol, 1, 0), _xlpm.total_weight, SUMPRODUCT(_xlpm.weights * _xlpm.matches), _xlpm.weighted_signal, SUMPRODUCT(_xlpm.weights * _xlpm.deltas * _xlpm.outside_band), IF(_xlpm.total_weight = 0, 0, _xlpm.weighted_signal / _xlpm.total_weight) )} -> 0.12190219 | S30: =IF($R30 < -$B$16, "Raise", IF($R30 > $B$16, "Reduce", "Hold")) -> Reduce | T30: {=IF($S30="Hold", IF(0.5 * ($P30-$I30) / $P30 + 0.5 * ($R30 / MAX(ABS($R30:$R79))) > 0, "Raise", "Hold"), $S30)} -> Reduce | U30: =IF($Q30=0, $D30, _xlfn.LET( _xlpm.raw_price, $Q30 * IF($T30="Raise", ($J30*(1+$B$5)) + ($J30 * MIN($B$6*ABS($O30), $B$5) * SIGN($O30)), IF($T30="Reduce", $J30 * ($B$7 + ($B$9-$B$7) / (1+EXP(-20*($O30-$B$8)))), IF($T30="Hold", IF($O30>$B$11, MIN(MAX($D30, ($J30*$B$10)+($J30 * MIN($B$6*ABS($O30), $B$5) * SIGN($O30))), $D30*(1+$B$15)), $D30)))), IF(AND(OR($T30="Hold", $T30="Reduce"), _xlpm.raw_price < $D30, _xlpm.raw_price >= $D30 * 0.95), $D30, _xlpm.raw_price) )) -> 64.877481 | V30: =$U30-$D30 -> -16.722519 | W30: =$V30/$D30 -> -0.20493283 | X30: =$U30-$J30 -> -4.6475192 | Y30: =$X30/$J30 -> -0.066846735 | Z30: =IF($V30 = 0, 0, IF($S30="Reduce", $W30*$B$13, $W30*$B$12)) -> 0.16394627 | AA30: {=ROUND(_xlfn.XLOOKUP($A30, 'Competitive Analysis (Step 1)'!$A$10:$A$209,_xlfn.ANCHORARRAY( 'Competitive Analysis (Step 1)'!$Q$10), , 0) * (1+$Z30), 0)} -> 44 | AB30: =$AA30*$U30 -> 2854.6092 | AC30: {=$AB30 - _xlfn.XLOOKUP($A30, 'Competitive Analysis (Step 1)'!$A$10:$A$209,_xlfn.ANCHORARRAY( 'Competitive Analysis (Step 1)'!$R$10), ,0)} -> -246.19085 | AD30: {=$AC30 / _xlfn.XLOOKUP($A30, 'Competitive Analysis (Step 1)'!$A$10:$A$209,_xlfn.ANCHORARRAY( 'Competitive Analysis (Step 1)'!$V$10), ,0)} -> -0.085468688 | AE30: =$AA30 * _xlfn.XLOOKUP($A30, _1_product_catalog_pricing[SKU], _1_product_catalog_pricing[Cost Price ($)], , 0) -> 1290.08 | AF30: {=$AE30 - _xlfn.XLOOKUP($A30, 'Competitive Analysis (Step 1)'!$A$10:$A$209,_xlfn.ANCHORARRAY( 'Competitive Analysis (Step 1)'!$S$10),,0)} -> 175.92 | AG30: {=$AF30 / _xlfn.XLOOKUP($A30, 'Competitive Analysis (Step 1)'!$A$10:$A$209,_xlfn.ANCHORARRAY( 'Competitive Analysis (Step 1)'!$S$10),,0)} -> 0.15789474 | AH30: =$AB30-$AE30 -> 1564.5292 | AI30: {=$AH30 - _xlfn.XLOOKUP($A30, 'Competitive Analysis (Step 1)'!$A$10:$A$209,_xlfn.ANCHORARRAY( 'Competitive Analysis (Step 1)'!$T$10),,0)} -> -422.11085 | AJ30: =IFERROR($AH30 / $AB30, 0) -> 0.54807123 | AK30: {=$AI30 / _xlfn.XLOOKUP($A30, 'Competitive Analysis (Step 1)'!$A$10:$A$209,_xlfn.ANCHORARRAY( 'Competitive Analysis (Step 1)'!$T$10),,0)} -> -0.21247475 | AL30: =IF($AK30 > 0, "Full", IF($AK30 >= $B$20, "Constrained", "Exclude")) -> Exclude
A31: SKU-1009 | B31: Phone Stand | C31: Electronics | D31: 177.91 | E31: 73.49 | F31: {=_xlfn.XLOOKUP($A31,'Competitive Analysis (Step 1)'!$A$10:$A$209,_xlfn.ANCHORARRAY( 'Competitive Analysis (Step 1)'!$P$10),,0)} -> 202 | G31: {=SUMPRODUCT((Transactions_and_Customer_Information_Joined[SKU]='V1 Pricing Model (Step 2)'!$A31) * (Transactions_and_Customer_Information_Joined[Order Status]="Completed") * (Transactions_and_Customer_Information_Joined[Quantity])) / 12} -> 3 | H31: =IF($G31=0, 99, $F31/$G31) -> 67.333333 | I31: =($D31-$E31)/$D31 -> 0.58692597 | J31: {=(SMALL(IF('Competitive Analysis (Step 1)'!$A$10:$A$209=$A31,'Competitive Analysis (Step 1)'!$D$10:$D$209),2)+SMALL(IF('Competitive Analysis (Step 1)'!$A$10:$A$209=$A31,'Competitive Analysis (Step 1)'!$D$10:$D$209),3))/2} -> 191.85 | K31: =$J31-$D31 -> 13.94 | L31: =$K31/$D31 -> 0.078354224 | M31: 4.8 | N31: 3.475 | O31: 1.325 | P31: {=MEDIAN(IF($C$22:$C$71=$C31, $I$22:$I$71))} -> 0.5261518 | Q31: {=_xlfn.LET( _xlpm.stock, $F31, _xlpm.stock_ratio, $H31, _xlpm.cat_ratios, IF($C$22:$C$71=$C31, $H$22:$H$71), _xlpm.cat_median, MEDIAN(_xlpm.cat_ratios), _xlpm.cat_stdev, STDEV(IF($C$22:$C$71=$C31, $H$22:$H$71)), _xlpm.z_score, IF(_xlpm.cat_stdev = 0, 0, (_xlpm.stock_ratio - _xlpm.cat_median) / _xlpm.cat_stdev), _xlpm.capped_z, MIN(MAX(_xlpm.z_score, -2), 2), IF(_xlpm.stock < $B$18, 0, 1 + $B$19 * _xlpm.capped_z) )} -> 1.0061888 | R31: {=_xlfn.LET( _xlpm.sku, $A31, _xlpm.tol, $B$3, _xlpm.sku_range, 'Competitive Analysis (Step 1)'!$A$10:$A$209, _xlpm.comp_prices, 'Competitive Analysis (Step 1)'!$D$10:$D$209, _xlpm.comp_reviews, 'Competitive Analysis (Step 1)'!$F$10:$F$209, _xlpm.obs_dates, 'Competitive Analysis (Step 1)'!$G$10:$G$209, _xlpm.our_price, $D31, _xlpm.matches, (_xlpm.sku_range=_xlpm.sku), _xlpm.deltas, IF(_xlpm.matches, (_xlpm.our_price - _xlpm.comp_prices) / _xlpm.comp_prices, 0), _xlpm.review_wt, IF(_xlpm.matches, LN(_xlpm.comp_reviews + 1), 0), _xlpm.decay_wt, IFERROR(IF(_xlpm.matches, EXP(-$B$17 * ($B$2 - _xlpm.obs_dates)), 0), 0), _xlpm.weights, _xlpm.review_wt * _xlpm.decay_wt, _xlpm.outside_band, IF(ABS(_xlpm.deltas) > _xlpm.tol, 1, 0), _xlpm.total_weight, SUMPRODUCT(_xlpm.weights * _xlpm.matches), _xlpm.weighted_signal, SUMPRODUCT(_xlpm.weights * _xlpm.deltas * _xlpm.outside_band), IF(_xlpm.total_weight = 0, 0, _xlpm.weighted_signal / _xlpm.total_weight) )} -> -0.061545503 | S31: =IF($R31 < -$B$16, "Raise", IF($R31 > $B$16, "Reduce", "Hold")) -> Raise | T31: {=IF($S31="Hold", IF(0.5 * ($P31-$I31) / $P31 + 0.5 * ($R31 / MAX(ABS($R31:$R80))) > 0, "Raise", "Hold"), $S31)} -> Raise | U31: =IF($Q31=0, $D31, _xlfn.LET( _xlpm.raw_price, $Q31 * IF($T31="Raise", ($J31*(1+$B$5)) + ($J31 * MIN($B$6*ABS($O31), $B$5) * SIGN($O31)), IF($T31="Reduce", $J31 * ($B$7 + ($B$9-$B$7) / (1+EXP(-20*($O31-$B$8)))), IF($T31="Hold", IF($O31>$B$11, MIN(MAX($D31, ($J31*$B$10)+($J31 * MIN($B$6*ABS($O31), $B$5) * SIGN($O31))), $D31*(1+$B$15)), $D31)))), IF(AND(OR($T31="Hold", $T31="Reduce"), _xlpm.raw_price < $D31, _xlpm.raw_price >= $D31 * 0.95), $D31, _xlpm.raw_price) )) -> 210.36242 | V31: =$U31-$D31 -> 32.452421 | W31: =$V31/$D31 -> 0.1824092 | X31: =$U31-$J31 -> 18.512421 | Y31: =$X31/$J31 -> 0.096494243 | Z31: =IF($V31 = 0, 0, IF($S31="Reduce", $W31*$B$13, $W31*$B$12)) -> -0.07296368 | AA31: {=ROUND(_xlfn.XLOOKUP($A31, 'Competitive Analysis (Step 1)'!$A$10:$A$209,_xlfn.ANCHORARRAY( 'Competitive Analysis (Step 1)'!$Q$10), , 0) * (1+$Z31), 0)} -> 33 | AB31: =$AA31*$U31 -> 6941.9599 | AC31: {=$AB31 - _xlfn.XLOOKUP($A31, 'Competitive Analysis (Step 1)'!$A$10:$A$209,_xlfn.ANCHORARRAY( 'Competitive Analysis (Step 1)'!$R$10), ,0)} -> 2118.3199 | AD31: {=$AC31 / _xlfn.XLOOKUP($A31, 'Competitive Analysis (Step 1)'!$A$10:$A$209,_xlfn.ANCHORARRAY( 'Competitive Analysis (Step 1)'!$V$10), ,0)} -> 0.46498639 | AE31: =$AA31 * _xlfn.XLOOKUP($A31, _1_product_catalog_pricing[SKU], _1_product_catalog_pricing[Cost Price ($)], , 0) -> 2425.17 | AF31: {=$AE31 - _xlfn.XLOOKUP($A31, 'Competitive Analysis (Step 1)'!$A$10:$A$209,_xlfn.ANCHORARRAY( 'Competitive Analysis (Step 1)'!$S$10),,0)} -> -220.47 | AG31: {=$AF31 / _xlfn.XLOOKUP($A31, 'Competitive Analysis (Step 1)'!$A$10:$A$209,_xlfn.ANCHORARRAY( 'Competitive Analysis (Step 1)'!$S$10),,0)} -> -0.083333333 | AH31: =$AB31-$AE31 -> 4516.7899 | AI31: {=$AH31 - _xlfn.XLOOKUP($A31, 'Competitive Analysis (Step 1)'!$A$10:$A$209,_xlfn.ANCHORARRAY( 'Competitive Analysis (Step 1)'!$T$10),,0)} -> 2338.7899 | AJ31: =IFERROR($AH31 / $AB31, 0) -> 0.65065053 | AK31: {=$AI31 / _xlfn.XLOOKUP($A31, 'Competitive Analysis (Step 1)'!$A$10:$A$209,_xlfn.ANCHORARRAY( 'Competitive Analysis (Step 1)'!$T$10),,0)} -> 1.0738246 | AL31: =IF($AK31 > 0, "Full", IF($AK31 >= $B$20, "Constrained", "Exclude")) -> Full
A32: SKU-1010 | B32: Slim Fit Jeans | C32: Apparel | D32: 45.86 | E32: 24.87 | F32: {=_xlfn.XLOOKUP($A32,'Competitive Analysis (Step 1)'!$A$10:$A$209,_xlfn.ANCHORARRAY( 'Competitive Analysis (Step 1)'!$P$10),,0)} -> 459 | G32: {=SUMPRODUCT((Transactions_and_Customer_Information_Joined[SKU]='V1 Pricing Model (Step 2)'!$A32) * (Transactions_and_Customer_Information_Joined[Order Status]="Completed") * (Transactions_and_Customer_Information_Joined[Quantity])) / 12} -> 3.5 | H32: =IF($G32=0, 99, $F32/$G32) -> 131.14286 | I32: =($D32-$E32)/$D32 -> 0.45769734 | J32: {=(SMALL(IF('Competitive Analysis (Step 1)'!$A$10:$A$209=$A32,'Competitive Analysis (Step 1)'!$D$10:$D$209),2)+SMALL(IF('Competitive Analysis (Step 1)'!$A$10:$A$209=$A32,'Competitive Analysis (Step 1)'!$D$10:$D$209),3))/2} -> 54.615 | K32: =$J32-$D32 -> 8.755 | L32: =$K32/$D32 -> 0.19090711 | M32: 4.2 | N32: 3.85 | O32: 0.35 | P32: {=MEDIAN(IF($C$22:$C$71=$C32, $I$22:$I$71))} -> 0.48928068 | Q32: {=_xlfn.LET( _xlpm.stock, $F32, _xlpm.stock_ratio, $H32, _xlpm.cat_ratios, IF($C$22:$C$71=$C32, $H$22:$H$71), _xlpm.cat_median, MEDIAN(_xlpm.cat_ratios), _xlpm.cat_stdev, STDEV(IF($C$22:$C$71=$C32, $H$22:$H$71)), _xlpm.z_score, IF(_xlpm.cat_stdev = 0, 0, (_xlpm.stock_ratio - _xlpm.cat_median) / _xlpm.cat_stdev), _xlpm.capped_z, MIN(MAX(_xlpm.z_score, -2), 2), IF(_xlpm.stock < $B$18, 0, 1 + $B$19 * _xlpm.capped_z) )} -> 0.99434547 | R32: {=_xlfn.LET( _xlpm.sku, $A32, _xlpm.tol, $B$3, _xlpm.sku_range, 'Competitive Analysis (Step 1)'!$A$10:$A$209, _xlpm.comp_prices, 'Competitive Analysis (Step 1)'!$D$10:$D$209, _xlpm.comp_reviews, 'Competitive Analysis (Step 1)'!$F$10:$F$209, _xlpm.obs_dates, 'Competitive Analysis (Step 1)'!$G$10:$G$209, _xlpm.our_price, $D32, _xlpm.matches, (_xlpm.sku_range=_xlpm.sku), _xlpm.deltas, IF(_xlpm.matches, (_xlpm.our_price - _xlpm.comp_prices) / _xlpm.comp_prices, 0), _xlpm.review_wt, IF(_xlpm.matches, LN(_xlpm.comp_reviews + 1), 0), _xlpm.decay_wt, IFERROR(IF(_xlpm.matches, EXP(-$B$17 * ($B$2 - _xlpm.obs_dates)), 0), 0), _xlpm.weights, _xlpm.review_wt * _xlpm.decay_wt, _xlpm.outside_band, IF(ABS(_xlpm.deltas) > _xlpm.tol, 1, 0), _xlpm.total_weight, SUMPRODUCT(_xlpm.weights * _xlpm.matches), _xlpm.weighted_signal, SUMPRODUCT(_xlpm.weights * _xlpm.deltas * _xlpm.outside_band), IF(_xlpm.total_weight = 0, 0, _xlpm.weighted_signal / _xlpm.total_weight) )} -> -0.098110316 | S32: =IF($R32 < -$B$16, "Raise", IF($R32 > $B$16, "Reduce", "Hold")) -> Raise | T32: {=IF($S32="Hold", IF(0.5 * ($P32-$I32) / $P32 + 0.5 * ($R32 / MAX(ABS($R32:$R81))) > 0, "Raise", "Hold"), $S32)} -> Raise | U32: =IF($Q32=0, $D32, _xlfn.LET( _xlpm.raw_price, $Q32 * IF($T32="Raise", ($J32*(1+$B$5)) + ($J32 * MIN($B$6*ABS($O32), $B$5) * SIGN($O32)), IF($T32="Reduce", $J32 * ($B$7 + ($B$9-$B$7) / (1+EXP(-20*($O32-$B$8)))), IF($T32="Hold", IF($O32>$B$11, MIN(MAX($D32, ($J32*$B$10)+($J32 * MIN($B$6*ABS($O32), $B$5) * SIGN($O32))), $D32*(1+$B$15)), $D32)))), IF(AND(OR($T32="Hold", $T32="Reduce"), _xlpm.raw_price < $D32, _xlpm.raw_price >= $D32 * 0.95), $D32, _xlpm.raw_price) )) -> 57.591702 | V32: =$U32-$D32 -> 11.731702 | W32: =$V32/$D32 -> 0.25581556 | X32: =$U32-$J32 -> 2.9767016 | Y32: =$X32/$J32 -> 0.05450337 | Z32: =IF($V32 = 0, 0, IF($S32="Reduce", $W32*$B$13, $W32*$B$12)) -> -0.10232622 | AA32: {=ROUND(_xlfn.XLOOKUP($A32, 'Competitive Analysis (Step 1)'!$A$10:$A$209,_xlfn.ANCHORARRAY( 'Competitive Analysis (Step 1)'!$Q$10), , 0) * (1+$Z32), 0)} -> 38 | AB32: =$AA32*$U32 -> 2188.4847 | AC32: {=$AB32 - _xlfn.XLOOKUP($A32, 'Competitive Analysis (Step 1)'!$A$10:$A$209,_xlfn.ANCHORARRAY( 'Competitive Analysis (Step 1)'!$R$10), ,0)} -> 713.86466 | AD32: {=$AC32 / _xlfn.XLOOKUP($A32, 'Competitive Analysis (Step 1)'!$A$10:$A$209,_xlfn.ANCHORARRAY( 'Competitive Analysis (Step 1)'!$V$10), ,0)} -> 0.52811578 | AE32: =$AA32 * _xlfn.XLOOKUP($A32, _1_product_catalog_pricing[SKU], _1_product_catalog_pricing[Cost Price ($)], , 0) -> 945.06 | AF32: {=$AE32 - _xlfn.XLOOKUP($A32, 'Competitive Analysis (Step 1)'!$A$10:$A$209,_xlfn.ANCHORARRAY( 'Competitive Analysis (Step 1)'!$S$10),,0)} -> -99.48 | AG32: {=$AF32 / _xlfn.XLOOKUP($A32, 'Competitive Analysis (Step 1)'!$A$10:$A$209,_xlfn.ANCHORARRAY( 'Competitive Analysis (Step 1)'!$S$10),,0)} -> -0.095238095 | AH32: =$AB32-$AE32 -> 1243.4247 | AI32: {=$AH32 - _xlfn.XLOOKUP($A32, 'Competitive Analysis (Step 1)'!$A$10:$A$209,_xlfn.ANCHORARRAY( 'Competitive Analysis (Step 1)'!$T$10),,0)} -> 813.34466 | AJ32: =IFERROR($AH32 / $AB32, 0) -> 0.56816695 | AK32: {=$AI32 / _xlfn.XLOOKUP($A32, 'Competitive Analysis (Step 1)'!$A$10:$A$209,_xlfn.ANCHORARRAY( 'Competitive Analysis (Step 1)'!$T$10),,0)} -> 1.8911474 | AL32: =IF($AK32 > 0, "Full", IF($AK32 >= $B$20, "Constrained", "Exclude")) -> Full
A33: SKU-1011 | B33: Graphic Tee | C33: Apparel | D33: 67.56 | E33: 43.21 | F33: {=_xlfn.XLOOKUP($A33,'Competitive Analysis (Step 1)'!$A$10:$A$209,_xlfn.ANCHORARRAY( 'Competitive Analysis (Step 1)'!$P$10),,0)} -> 78 | G33: {=SUMPRODUCT((Transactions_and_Customer_Information_Joined[SKU]='V1 Pricing Model (Step 2)'!$A33) * (Transactions_and_Customer_Information_Joined[Order Status]="Completed") * (Transactions_and_Customer_Information_Joined[Quantity])) / 12} -> 1.8333333 | H33: =IF($G33=0, 99, $F33/$G33) -> 42.545455 | I33: =($D33-$E33)/$D33 -> 0.36042037 | J33: {=(SMALL(IF('Competitive Analysis (Step 1)'!$A$10:$A$209=$A33,'Competitive Analysis (Step 1)'!$D$10:$D$209),2)+SMALL(IF('Competitive Analysis (Step 1)'!$A$10:$A$209=$A33,'Competitive Analysis (Step 1)'!$D$10:$D$209),3))/2} -> 70.35 | K33: =$J33-$D33 -> 2.79 | L33: =$K33/$D33 -> 0.041296625 | M33: 4.3 | N33: 4.35 | O33: -0.05 | P33: {=MEDIAN(IF($C$22:$C$71=$C33, $I$22:$I$71))} -> 0.48928068 | Q33: {=_xlfn.LET( _xlpm.stock, $F33, _xlpm.stock_ratio, $H33, _xlpm.cat_ratios, IF($C$22:$C$71=$C33, $H$22:$H$71), _xlpm.cat_median, MEDIAN(_xlpm.cat_ratios), _xlpm.cat_stdev, STDEV(IF($C$22:$C$71=$C33, $H$22:$H$71)), _xlpm.z_score, IF(_xlpm.cat_stdev = 0, 0, (_xlpm.stock_ratio - _xlpm.cat_median) / _xlpm.cat_stdev), _xlpm.capped_z, MIN(MAX(_xlpm.z_score, -2), 2), IF(_xlpm.stock < $B$18, 0, 1 + $B$19 * _xlpm.capped_z) )} -> 1.01473 | R33: {=_xlfn.LET( _xlpm.sku, $A33, _xlpm.tol, $B$3, _xlpm.sku_range, 'Competitive Analysis (Step 1)'!$A$10:$A$209, _xlpm.comp_prices, 'Competitive Analysis (Step 1)'!$D$10:$D$209, _xlpm.comp_reviews, 'Competitive Analysis (Step 1)'!$F$10:$F$209, _xlpm.obs_dates, 'Competitive Analysis (Step 1)'!$G$10:$G$209, _xlpm.our_price, $D33, _xlpm.matches, (_xlpm.sku_range=_xlpm.sku), _xlpm.deltas, IF(_xlpm.matches, (_xlpm.our_price - _xlpm.comp_prices) / _xlpm.comp_prices, 0), _xlpm.review_wt, IF(_xlpm.matches, LN(_xlpm.comp_reviews + 1), 0), _xlpm.decay_wt, IFERROR(IF(_xlpm.matches, EXP(-$B$17 * ($B$2 - _xlpm.obs_dates)), 0), 0), _xlpm.weights, _xlpm.review_wt * _xlpm.decay_wt, _xlpm.outside_band, IF(ABS(_xlpm.deltas) > _xlpm.tol, 1, 0), _xlpm.total_weight, SUMPRODUCT(_xlpm.weights * _xlpm.matches), _xlpm.weighted_signal, SUMPRODUCT(_xlpm.weights * _xlpm.deltas * _xlpm.outside_band), IF(_xlpm.total_weight = 0, 0, _xlpm.weighted_signal / _xlpm.total_weight) )} -> 0.017342589 | S33: =IF($R33 < -$B$16, "Raise", IF($R33 > $B$16, "Reduce", "Hold")) -> Hold | T33: {=IF($S33="Hold", IF(0.5 * ($P33-$I33) / $P33 + 0.5 * ($R33 / MAX(ABS($R33:$R82))) > 0, "Raise", "Hold"), $S33)} -> Raise | U33: =IF($Q33=0, $D33, _xlfn.LET( _xlpm.raw_price, $Q33 * IF($T33="Raise", ($J33*(1+$B$5)) + ($J33 * MIN($B$6*ABS($O33), $B$5) * SIGN($O33)), IF($T33="Reduce", $J33 * ($B$7 + ($B$9-$B$7) / (1+EXP(-20*($O33-$B$8)))), IF($T33="Hold", IF($O33>$B$11, MIN(MAX($D33, ($J33*$B$10)+($J33 * MIN($B$6*ABS($O33), $B$5) * SIGN($O33))), $D33*(1+$B$15)), $D33)))), IF(AND(OR($T33="Hold", $T33="Reduce"), _xlpm.raw_price < $D33, _xlpm.raw_price >= $D33 * 0.95), $D33, _xlpm.raw_price) )) -> 74.848492 | V33: =$U33-$D33 -> 7.2884925 | W33: =$V33/$D33 -> 0.10788177 | X33: =$U33-$J33 -> 4.4984925 | Y33: =$X33/$J33 -> 0.063944456 | Z33: =IF($V33 = 0, 0, IF($S33="Reduce", $W33*$B$13, $W33*$B$12)) -> -0.043152709 | AA33: {=ROUND(_xlfn.XLOOKUP($A33, 'Competitive Analysis (Step 1)'!$A$10:$A$209,_xlfn.ANCHORARRAY( 'Competitive Analysis (Step 1)'!$Q$10), , 0) * (1+$Z33), 0)} -> 21 | AB33: =$AA33*$U33 -> 1571.8183 | AC33: {=$AB33 - _xlfn.XLOOKUP($A33, 'Competitive Analysis (Step 1)'!$A$10:$A$209,_xlfn.ANCHORARRAY( 'Competitive Analysis (Step 1)'!$R$10), ,0)} -> 85.498342 | AD33: {=$AC33 / _xlfn.XLOOKUP($A33, 'Competitive Analysis (Step 1)'!$A$10:$A$209,_xlfn.ANCHORARRAY( 'Competitive Analysis (Step 1)'!$V$10), ,0)} -> 0.06327586 | AE33: =$AA33 * _xlfn.XLOOKUP($A33, _1_product_catalog_pricing[SKU], _1_product_catalog_pricing[Cost Price ($)], , 0) -> 907.41 | AF33: {=$AE33 - _xlfn.XLOOKUP($A33, 'Competitive Analysis (Step 1)'!$A$10:$A$209,_xlfn.ANCHORARRAY( 'Competitive Analysis (Step 1)'!$S$10),,0)} -> -43.21 | AG33: {=$AF33 / _xlfn.XLOOKUP($A33, 'Competitive Analysis (Step 1)'!$A$10:$A$209,_xlfn.ANCHORARRAY( 'Competitive Analysis (Step 1)'!$S$10),,0)} -> -0.045454545 | AH33: =$AB33-$AE33 -> 664.40834 | AI33: {=$AH33 - _xlfn.XLOOKUP($A33, 'Competitive Analysis (Step 1)'!$A$10:$A$209,_xlfn.ANCHORARRAY( 'Competitive Analysis (Step 1)'!$T$10),,0)} -> 128.70834 | AJ33: =IFERROR($AH33 / $AB33, 0) -> 0.42270046 | AK33: {=$AI33 / _xlfn.XLOOKUP($A33, 'Competitive Analysis (Step 1)'!$A$10:$A$209,_xlfn.ANCHORARRAY( 'Competitive Analysis (Step 1)'!$T$10),,0)} -> 0.24026198 | AL33: =IF($AK33 > 0, "Full", IF($AK33 >= $B$20, "Constrained", "Exclude")) -> Full
A34: SKU-1012 | B34: Hoodie | C34: Apparel | D34: 20.37 | E34: 9.76 | F34: {=_xlfn.XLOOKUP($A34,'Competitive Analysis (Step 1)'!$A$10:$A$209,_xlfn.ANCHORARRAY( 'Competitive Analysis (Step 1)'!$P$10),,0)} -> 348 | G34: {=SUMPRODUCT((Transactions_and_Customer_Information_Joined[SKU]='V1 Pricing Model (Step 2)'!$A34) * (Transactions_and_Customer_Information_Joined[Order Status]="Completed") * (Transactions_and_Customer_Information_Joined[Quantity])) / 12} -> 1.25 | H34: =IF($G34=0, 99, $F34/$G34) -> 278.4 | I34: =($D34-$E34)/$D34 -> 0.52086402 | J34: {=(SMALL(IF('Competitive Analysis (Step 1)'!$A$10:$A$209=$A34,'Competitive Analysis (Step 1)'!$D$10:$D$209),2)+SMALL(IF('Competitive Analysis (Step 1)'!$A$10:$A$209=$A34,'Competitive Analysis (Step 1)'!$D$10:$D$209),3))/2} -> 19.83 | K34: =$J34-$D34 -> -0.54 | L34: =$K34/$D34 -> -0.026509573 | M34: 4.4 | N34: 4 | O34: 0.4 | P34: {=MEDIAN(IF($C$22:$C$71=$C34, $I$22:$I$71))} -> 0.48928068 | Q34: {=_xlfn.LET( _xlpm.stock, $F34, _xlpm.stock_ratio, $H34, _xlpm.cat_ratios, IF($C$22:$C$71=$C34, $H$22:$H$71), _xlpm.cat_median, MEDIAN(_xlpm.cat_ratios), _xlpm.cat_stdev, STDEV(IF($C$22:$C$71=$C34, $H$22:$H$71)), _xlpm.z_score, IF(_xlpm.cat_stdev = 0, 0, (_xlpm.stock_ratio - _xlpm.cat_median) / _xlpm.cat_stdev), _xlpm.capped_z, MIN(MAX(_xlpm.z_score, -2), 2), IF(_xlpm.stock < $B$18, 0, 1 + $B$19 * _xlpm.capped_z) )} -> 0.9604644 | R34: {=_xlfn.LET( _xlpm.sku, $A34, _xlpm.tol, $B$3, _xlpm.sku_range, 'Competitive Analysis (Step 1)'!$A$10:$A$209, _xlpm.comp_prices, 'Competitive Analysis (Step 1)'!$D$10:$D$209, _xlpm.comp_reviews, 'Competitive Analysis (Step 1)'!$F$10:$F$209, _xlpm.obs_dates, 'Competitive Analysis (Step 1)'!$G$10:$G$209, _xlpm.our_price, $D34, _xlpm.matches, (_xlpm.sku_range=_xlpm.sku), _xlpm.deltas, IF(_xlpm.matches, (_xlpm.our_price - _xlpm.comp_prices) / _xlpm.comp_prices, 0), _xlpm.review_wt, IF(_xlpm.matches, LN(_xlpm.comp_reviews + 1), 0), _xlpm.decay_wt, IFERROR(IF(_xlpm.matches, EXP(-$B$17 * ($B$2 - _xlpm.obs_dates)), 0), 0), _xlpm.weights, _xlpm.review_wt * _xlpm.decay_wt, _xlpm.outside_band, IF(ABS(_xlpm.deltas) > _xlpm.tol, 1, 0), _xlpm.total_weight, SUMPRODUCT(_xlpm.weights * _xlpm.matches), _xlpm.weighted_signal, SUMPRODUCT(_xlpm.weights * _xlpm.deltas * _xlpm.outside_band), IF(_xlpm.total_weight = 0, 0, _xlpm.weighted_signal / _xlpm.total_weight) )} -> 0.045625519 | S34: =IF($R34 < -$B$16, "Raise", IF($R34 > $B$16, "Reduce", "Hold")) -> Hold | T34: {=IF($S34="Hold", IF(0.5 * ($P34-$I34) / $P34 + 0.5 * ($R34 / MAX(ABS($R34:$R83))) > 0, "Raise", "Hold"), $S34)} -> Raise | U34: =IF($Q34=0, $D34, _xlfn.LET( _xlpm.raw_price, $Q34 * IF($T34="Raise", ($J34*(1+$B$5)) + ($J34 * MIN($B$6*ABS($O34), $B$5) * SIGN($O34)), IF($T34="Reduce", $J34 * ($B$7 + ($B$9-$B$7) / (1+EXP(-20*($O34-$B$8)))), IF($T34="Hold", IF($O34>$B$11, MIN(MAX($D34, ($J34*$B$10)+($J34 * MIN($B$6*ABS($O34), $B$5) * SIGN($O34))), $D34*(1+$B$15)), $D34)))), IF(AND(OR($T34="Hold", $T34="Reduce"), _xlpm.raw_price < $D34, _xlpm.raw_price >= $D34 * 0.95), $D34, _xlpm.raw_price) )) -> 20.226862 | V34: =$U34-$D34 -> -0.14313844 | W34: =$V34/$D34 -> -0.0070269239 | X34: =$U34-$J34 -> 0.39686156 | Y34: =$X34/$J34 -> 0.02001319 | Z34: =IF($V34 = 0, 0, IF($S34="Reduce", $W34*$B$13, $W34*$B$12)) -> 0.0028107696 | AA34: {=ROUND(_xlfn.XLOOKUP($A34, 'Competitive Analysis (Step 1)'!$A$10:$A$209,_xlfn.ANCHORARRAY( 'Competitive Analysis (Step 1)'!$Q$10), , 0) * (1+$Z34), 0)} -> 15 | AB34: =$AA34*$U34 -> 303.40292 | AC34: {=$AB34 - _xlfn.XLOOKUP($A34, 'Competitive Analysis (Step 1)'!$A$10:$A$209,_xlfn.ANCHORARRAY( 'Competitive Analysis (Step 1)'!$R$10), ,0)} -> 49.152923 | AD34: {=$AC34 / _xlfn.XLOOKUP($A34, 'Competitive Analysis (Step 1)'!$A$10:$A$209,_xlfn.ANCHORARRAY( 'Competitive Analysis (Step 1)'!$V$10), ,0)} -> 0.21640877 | AE34: =$AA34 * _xlfn.XLOOKUP($A34, _1_product_catalog_pricing[SKU], _1_product_catalog_pricing[Cost Price ($)], , 0) -> 146.4 | AF34: {=$AE34 - _xlfn.XLOOKUP($A34, 'Competitive Analysis (Step 1)'!$A$10:$A$209,_xlfn.ANCHORARRAY( 'Competitive Analysis (Step 1)'!$S$10),,0)} -> 0 | AG34: {=$AF34 / _xlfn.XLOOKUP($A34, 'Competitive Analysis (Step 1)'!$A$10:$A$209,_xlfn.ANCHORARRAY( 'Competitive Analysis (Step 1)'!$S$10),,0)} -> 0 | AH34: =$AB34-$AE34 -> 157.00292 | AI34: {=$AH34 - _xlfn.XLOOKUP($A34, 'Competitive Analysis (Step 1)'!$A$10:$A$209,_xlfn.ANCHORARRAY( 'Competitive Analysis (Step 1)'!$T$10),,0)} -> 49.152923 | AJ34: =IFERROR($AH34 / $AB34, 0) -> 0.51747334 | AK34: {=$AI34 / _xlfn.XLOOKUP($A34, 'Competitive Analysis (Step 1)'!$A$10:$A$209,_xlfn.ANCHORARRAY( 'Competitive Analysis (Step 1)'!$T$10),,0)} -> 0.45575265 | AL34: =IF($AK34 > 0, "Full", IF($AK34 >= $B$20, "Constrained", "Exclude")) -> Full
... A71: SKU-1049 | B71: Protein Shaker | C71: Sports & Outdoors | D71: 99.75 | E71: 38.13 | F71: {=_xlfn.XLOOKUP($A71,'Competitive Analysis (Step 1)'!$A$10:$A$209,_xlfn.ANCHORARRAY( 'Competitive Analysis (Step 1)'!$P$10),,0)} -> 337 | G71: {=SUMPRODUCT((Transactions_and_Customer_Information_Joined[SKU]='V1 Pricing Model (Step 2)'!$A71) * (Transactions_and_Customer_Information_Joined[Order Status]="Completed") * (Transactions_and_Customer_Information_Joined[Quantity])) / 12} -> 2.8333333 | H71: =IF($G71=0, 99, $F71/$G71) -> 118.94118 | I71: =($D71-$E71)/$D71 -> 0.61774436 | J71: {=(SMALL(IF('Competitive Analysis (Step 1)'!$A$10:$A$209=$A71,'Competitive Analysis (Step 1)'!$D$10:$D$209),2)+SMALL(IF('Competitive Analysis (Step 1)'!$A$10:$A$209=$A71,'Competitive Analysis (Step 1)'!$D$10:$D$209),3))/2} -> 107.465 | K71: =$J71-$D71 -> 7.715 | L71: =$K71/$D71 -> 0.077343358 | M71: 3.2 | N71: 3.85 | O71: -0.65 | P71: {=MEDIAN(IF($C$22:$C$71=$C71, $I$22:$I$71))} -> 0.52998638 | Q71: {=_xlfn.LET( _xlpm.stock, $F71, _xlpm.stock_ratio, $H71, _xlpm.cat_ratios, IF($C$22:$C$71=$C71, $H$22:$H$71), _xlpm.cat_median, MEDIAN(_xlpm.cat_ratios), _xlpm.cat_stdev, STDEV(IF($C$22:$C$71=$C71, $H$22:$H$71)), _xlpm.z_score, IF(_xlpm.cat_stdev = 0, 0, (_xlpm.stock_ratio - _xlpm.cat_median) / _xlpm.cat_stdev), _xlpm.capped_z, MIN(MAX(_xlpm.z_score, -2), 2), IF(_xlpm.stock < $B$18, 0, 1 + $B$19 * _xlpm.capped_z) )} -> 0.99721344 | R71: {=_xlfn.LET( _xlpm.sku, $A71, _xlpm.tol, $B$3, _xlpm.sku_range, 'Competitive Analysis (Step 1)'!$A$10:$A$209, _xlpm.comp_prices, 'Competitive Analysis (Step 1)'!$D$10:$D$209, _xlpm.comp_reviews, 'Competitive Analysis (Step 1)'!$F$10:$F$209, _xlpm.obs_dates, 'Competitive Analysis (Step 1)'!$G$10:$G$209, _xlpm.our_price, $D71, _xlpm.matches, (_xlpm.sku_range=_xlpm.sku), _xlpm.deltas, IF(_xlpm.matches, (_xlpm.our_price - _xlpm.comp_prices) / _xlpm.comp_prices, 0), _xlpm.review_wt, IF(_xlpm.matches, LN(_xlpm.comp_reviews + 1), 0), _xlpm.decay_wt, IFERROR(IF(_xlpm.matches, EXP(-$B$17 * ($B$2 - _xlpm.obs_dates)), 0), 0), _xlpm.weights, _xlpm.review_wt * _xlpm.decay_wt, _xlpm.outside_band, IF(ABS(_xlpm.deltas) > _xlpm.tol, 1, 0), _xlpm.total_weight, SUMPRODUCT(_xlpm.weights * _xlpm.matches), _xlpm.weighted_signal, SUMPRODUCT(_xlpm.weights * _xlpm.deltas * _xlpm.outside_band), IF(_xlpm.total_weight = 0, 0, _xlpm.weighted_signal / _xlpm.total_weight) )} -> -0.056073809 | S71: =IF($R71 < -$B$16, "Raise", IF($R71 > $B$16, "Reduce", "Hold")) -> Raise | T71: {=IF($S71="Hold", IF(0.5 * ($P71-$I71) / $P71 + 0.5 * ($R71 / MAX(ABS($R71:$R120))) > 0, "Raise", "Hold"), $S71)} -> Raise | U71: =IF($Q71=0, $D71, _xlfn.LET( _xlpm.raw_price, $Q71 * IF($T71="Raise", ($J71*(1+$B$5)) + ($J71 * MIN($B$6*ABS($O71), $B$5) * SIGN($O71)), IF($T71="Reduce", $J71 * ($B$7 + ($B$9-$B$7) / (1+EXP(-20*($O71-$B$8)))), IF($T71="Hold", IF($O71>$B$11, MIN(MAX($D71, ($J71*$B$10)+($J71 * MIN($B$6*ABS($O71), $B$5) * SIGN($O71))), $D71*(1+$B$15)), $D71)))), IF(AND(OR($T71="Hold", $T71="Reduce"), _xlpm.raw_price < $D71, _xlpm.raw_price >= $D71 * 0.95), $D71, _xlpm.raw_price) )) -> 110.43409 | V71: =$U71-$D71 -> 10.684091 | W71: =$V71/$D71 -> 0.10710868 | X71: =$U71-$J71 -> 2.9690912 | Y71: =$X71/$J71 -> 0.027628449 | Z71: =IF($V71 = 0, 0, IF($S71="Reduce", $W71*$B$13, $W71*$B$12)) -> -0.042843474 | AA71: {=ROUND(_xlfn.XLOOKUP($A71, 'Competitive Analysis (Step 1)'!$A$10:$A$209,_xlfn.ANCHORARRAY( 'Competitive Analysis (Step 1)'!$Q$10), , 0) * (1+$Z71), 0)} -> 33 | AB71: =$AA71*$U71 -> 3644.325 | AC71: {=$AB71 - _xlfn.XLOOKUP($A71, 'Competitive Analysis (Step 1)'!$A$10:$A$209,_xlfn.ANCHORARRAY( 'Competitive Analysis (Step 1)'!$R$10), ,0)} -> 597.24501 | AD71: {=$AC71 / _xlfn.XLOOKUP($A71, 'Competitive Analysis (Step 1)'!$A$10:$A$209,_xlfn.ANCHORARRAY( 'Competitive Analysis (Step 1)'!$V$10), ,0)} -> 0.21707502 | AE71: =$AA71 * _xlfn.XLOOKUP($A71, _1_product_catalog_pricing[SKU], _1_product_catalog_pricing[Cost Price ($)], , 0) -> 1258.29 | AF71: {=$AE71 - _xlfn.XLOOKUP($A71, 'Competitive Analysis (Step 1)'!$A$10:$A$209,_xlfn.ANCHORARRAY( 'Competitive Analysis (Step 1)'!$S$10),,0)} -> -38.13 | AG71: {=$AF71 / _xlfn.XLOOKUP($A71, 'Competitive Analysis (Step 1)'!$A$10:$A$209,_xlfn.ANCHORARRAY( 'Competitive Analysis (Step 1)'!$S$10),,0)} -> -0.029411765 | AH71: =$AB71-$AE71 -> 2386.035 | AI71: {=$AH71 - _xlfn.XLOOKUP($A71, 'Competitive Analysis (Step 1)'!$A$10:$A$209,_xlfn.ANCHORARRAY( 'Competitive Analysis (Step 1)'!$T$10),,0)} -> 635.37501 | AJ71: =IFERROR($AH71 / $AB71, 0) -> 0.65472618 | AK71: {=$AI71 / _xlfn.XLOOKUP($A71, 'Competitive Analysis (Step 1)'!$A$10:$A$209,_xlfn.ANCHORARRAY( 'Competitive Analysis (Step 1)'!$T$10),,0)} -> 0.36293456 | AL71: =IF($AK71 > 0, "Full", IF($AK71 >= $B$20, "Constrained", "Exclude")) -> Full

Sheet V1-Based Churn Model (Step 3)
A1: CHURN MODEL ASSUMPTIONS | B1: Values
A2: Segment - At-Risk Churner Base Score | B2: 70
A3: Segment - Dormant Base Score | B3: 65
A4: Segment - Deal Hunter Base Score | B4: 45
A5: Segment - New Customer Base Score | B5: 35
A6: Segment - Occassional Buyer Base Score | B6: 25
A7: Segment - Loyal High-Value Base Score | B7: 15
A8: Segment - At Risk Churner Baseline Churn Rate | B8: 0.45
A9: Segment - Dormat Baseline Churn Rate | B9: 0.6
A10: Segment - Deal Hunter Baseline Churn Rate | B10: 0.25
A11: Segment - New Customer Baseline Churn Rate | B11: 0.35
A12: Segment - Occassional Buyer Baseline Churn Rate | B12: 0.18
A13: Segment - Loyal High Value Baseline Churn Rate | B13: 0.05
... A35: Partial Churn Spend Reduction | B35: 0.4
A38: Customer ID | B38: Segment | C38: Acquisition Channel | D38: Region | E38: Age Group | F38: Discount Sensitivity | G38: NPS Score | H38: Days Since Last Order | I38: Lifetime Value ($) | J38: Sum of Customer's spend on Candidate SKUs | K38: Sum of Customer's total spend | L38: Spend in Price-Increase SKUs % | M38: Max Price Change Faced % | N38: Purchase Frequency on Candidate SKUs | O38: Spend-Weighted Average Price Change % | P38: Segment Base Score | Q38: Segment Base Churn Rate | R38: Discount Adjustment | S38: NPS Adjustment | T38: Recency Adjustment | U38: Price Exposure Adjustment | V38: Combined Burden Adjustment | W38: Churn Score | X38: Churn Tier | Y38: Projected Churn Rate (Logistic Transformation) | Z38: LTV At Risk $
A39: {=_xlfn.UNIQUE(_xlfn._xlws.FILTER(Transactions_and_Customer_Information_Joined[Customer ID], Transactions_and_Customer_Information_Joined[Order Status]="Completed"))} -> CUST-4362 | B39: {=_xlfn.XLOOKUP(_xlfn.ANCHORARRAY($A39), _3_customer_segments[Customer ID], _3_customer_segments[Segment],,0)} -> Occasional Buyer | C39: {=_xlfn.XLOOKUP(_xlfn.ANCHORARRAY($A39), _3_customer_segments[Customer ID], _3_customer_segments[Acquisition Channel],,0)} -> Influencer | D39: {=_xlfn.XLOOKUP(_xlfn.ANCHORARRAY($A39), _3_customer_segments[Customer ID], _3_customer_segments[Region],,0)} -> Canada | E39: {=_xlfn.XLOOKUP(_xlfn.ANCHORARRAY($A39), _3_customer_segments[Customer ID], _3_customer_segments[Age Group],,0)} -> 35-44 | F39: {=_xlfn.XLOOKUP(_xlfn.ANCHORARRAY($A39), _3_customer_segments[Customer ID], _3_customer_segments[Discount Sensitivity],,0)} -> High | G39: {=_xlfn.XLOOKUP(_xlfn.ANCHORARRAY($A39), _3_customer_segments[Customer ID],_3_customer_segments[NPS Score],,0)} -> 5 | H39: {=_xlfn.XLOOKUP(_xlfn.ANCHORARRAY($A39), _3_customer_segments[Customer ID],_3_customer_segments[Days Since Last Order],,0)} -> 230 | I39: {=_xlfn.XLOOKUP(_xlfn.ANCHORARRAY($A39), _3_customer_segments[Customer ID], _3_customer_segments[Lifetime Value ($)],,0)} -> 176.84 | J39: {=SUMPRODUCT( (Transactions_and_Customer_Information_Joined[Customer ID]='V1-Based Churn Model (Step 3)'!$A39) * (IFERROR(_xlfn.XLOOKUP(Transactions_and_Customer_Information_Joined[SKU], 'V1 Pricing Model (Step 2)'!$A$22:$A$71, 'V1 Pricing Model (Step 2)'!$AL$22:$AL$71), "Exclude")<>"Exclude") * Transactions_and_Customer_Information_Joined[Gross Revenue])} -> 169.9 | K39: =SUMIF(Transactions_and_Customer_Information_Joined[Customer ID], 'V1-Based Churn Model (Step 3)'!$A39, Transactions_and_Customer_Information_Joined[Gross Revenue]) -> 169.9 | L39: =IFERROR($J39/$K39, 0) -> 1 | M39: {=IFERROR(_xlfn.MAXIFS(_xlfn.ANCHORARRAY('Helper Ref'!$A$2), Transactions_and_Customer_Information_Joined[Customer ID],_xlfn.ANCHORARRAY( 'V1-Based Churn Model (Step 3)'!$A39)), 0)} -> 0 | N39: {=SUMPRODUCT( (Transactions_and_Customer_Information_Joined[Customer ID]=$A39) * (Transactions_and_Customer_Information_Joined[Order Status]="Completed") * (IFERROR(_xlfn.XLOOKUP(Transactions_and_Customer_Information_Joined[SKU], 'V1 Pricing Model (Step 2)'!$A$22:$A$71, 'V1 Pricing Model (Step 2)'!$AL$22:$AL$71), "Exclude")<>"Exclude"))} -> 1 | O39: {=IFERROR( SUMPRODUCT( (Transactions_and_Customer_Information_Joined[Customer ID]=$A39) * (IFERROR(_xlfn.XLOOKUP(Transactions_and_Customer_Information_Joined[SKU], 'V1 Pricing Model (Step 2)'!$A$22:$A$71, 'V1 Pricing Model (Step 2)'!$AL$22:$AL$71), "Exclude")<>"Exclude") * Transactions_and_Customer_Information_Joined[Gross Revenue] * IFERROR(_xlfn.XLOOKUP(Transactions_and_Customer_Information_Joined[SKU], 'V1 Pricing Model (Step 2)'!$A$22:$A$71, 'V1 Pricing Model (Step 2)'!$W$22:$W$71), 0) ) / $J39, 0)} -> 0 | P39: {=_xlfn.IFS(B39="At-Risk Churner",$B$2,$B39="Dormant",$B$3,$B39="Deal Hunter",$B$4,$B39="New Customer",$B$5,$B39="Occasional Buyer",$B$6,$B39="Loyal High-Value",$B$7)} -> 25 | Q39: {=_xlfn.IFS($B39 = "At-Risk Churner", $B$8, $B39="Dormant",$B$9, $B39="Deal Hunter", $B$10, $B39="New Customer", $B$11, $B39="Occasional Buyer", $B$12, $B39 = "Loyal High-Value",$B$13)} -> 0.18 | R39: {=_xlfn.IFS(_xlfn.ANCHORARRAY($F39) = "High", $B$14,_xlfn.ANCHORARRAY( $F39) = "Medium", $B$15,_xlfn.ANCHORARRAY( $F39) = "Low", $B$16)} -> 15 | S39: {=IF(_xlfn.ANCHORARRAY($G39)<=$B$17,$B$19,IF(_xlfn.ANCHORARRAY($G39)>=$B$18,$B$20,0))} -> 0 | T39: {=IF(_xlfn.ANCHORARRAY($H39)>$B$21,$B$23,IF(_xlfn.ANCHORARRAY($H39)>$B$22,$B$24,IF(_xlfn.ANCHORARRAY($H39)<60,$B$25,0)))} -> 8 | U39: =MIN( $L39 * $B$26 * (1 + $B$28 * LN(MAX($N39, 1))), $B$27 ) -> 15 | V39: =MIN( $B$29 * ABS($O39) + $B$30 * ABS($M39), $B$31 ) -> 0 | W39: =MIN(MAX( $P39 + $R39 + $S39 + $T39 + $U39 + $V39 + $B$32 * ($R39 * $U39) / 100 + $B$33 * ($P39 * $S39) / 100, 0), 100) -> 63.3375 | X39: {=_xlfn.IFS($W39 <= 30, "Low", $W39 <=50, "Medium", $W39 <= 70, "High", $W39 > 70, "Critical")} -> High | Y39: =$Q39 * (1 / (1 + EXP(-($W39 - 50) / $B$34))) -> 0.14246285 | Z39: =_xlfn.LET( _xlpm.full_churn, $Y39 * $I39, _xlpm.partial_rate, IF(OR($X39="Medium", $X39="High"), (1 - $Y39) * 0.5 * $B$35, 0), _xlpm.partial_churn, _xlpm.partial_rate * $I39, _xlpm.full_churn + _xlpm.partial_churn ) -> 55.522504
A40: CUST-2247 | B40: New Customer | C40: Referral | D40: Midwest | E40: 25-34 | F40: Medium | G40: 3 | H40: 33 | I40: 131.18 | J40: {=SUMPRODUCT( (Transactions_and_Customer_Information_Joined[Customer ID]='V1-Based Churn Model (Step 3)'!$A40) * (IFERROR(_xlfn.XLOOKUP(Transactions_and_Customer_Information_Joined[SKU], 'V1 Pricing Model (Step 2)'!$A$22:$A$71, 'V1 Pricing Model (Step 2)'!$AL$22:$AL$71), "Exclude")<>"Exclude") * Transactions_and_Customer_Information_Joined[Gross Revenue])} -> 522.69 | K40: =SUMIF(Transactions_and_Customer_Information_Joined[Customer ID], 'V1-Based Churn Model (Step 3)'!$A40, Transactions_and_Customer_Information_Joined[Gross Revenue]) -> 522.69 | L40: =IFERROR($J40/$K40, 0) -> 1 | M40: 0.05834808 | N40: {=SUMPRODUCT( (Transactions_and_Customer_Information_Joined[Customer ID]=$A40) * (Transactions_and_Customer_Information_Joined[Order Status]="Completed") * (IFERROR(_xlfn.XLOOKUP(Transactions_and_Customer_Information_Joined[SKU], 'V1 Pricing Model (Step 2)'!$A$22:$A$71, 'V1 Pricing Model (Step 2)'!$AL$22:$AL$71), "Exclude")<>"Exclude"))} -> 1 | O40: {=IFERROR( SUMPRODUCT( (Transactions_and_Customer_Information_Joined[Customer ID]=$A40) * (IFERROR(_xlfn.XLOOKUP(Transactions_and_Customer_Information_Joined[SKU], 'V1 Pricing Model (Step 2)'!$A$22:$A$71, 'V1 Pricing Model (Step 2)'!$AL$22:$AL$71), "Exclude")<>"Exclude") * Transactions_and_Customer_Information_Joined[Gross Revenue] * IFERROR(_xlfn.XLOOKUP(Transactions_and_Customer_Information_Joined[SKU], 'V1 Pricing Model (Step 2)'!$A$22:$A$71, 'V1 Pricing Model (Step 2)'!$W$22:$W$71), 0) ) / $J40, 0)} -> 0.05834808 | P40: {=_xlfn.IFS(B40="At-Risk Churner",$B$2,$B40="Dormant",$B$3,$B40="Deal Hunter",$B$4,$B40="New Customer",$B$5,$B40="Occasional Buyer",$B$6,$B40="Loyal High-Value",$B$7)} -> 35 | Q40: {=_xlfn.IFS($B40 = "At-Risk Churner", $B$8, $B40="Dormant",$B$9, $B40="Deal Hunter", $B$10, $B40="New Customer", $B$11, $B40="Occasional Buyer", $B$12, $B40 = "Loyal High-Value",$B$13)} -> 0.35 | R40: 5 | S40: 10 | T40: -5 | U40: =MIN( $L40 * $B$26 * (1 + $B$28 * LN(MAX($N40, 1))), $B$27 ) -> 15 | V40: =MIN( $B$29 * ABS($O40) + $B$30 * ABS($M40), $B$31 ) -> 2.3339232 | W40: =MIN(MAX( $P40 + $R40 + $S40 + $T40 + $U40 + $V40 + $B$32 * ($R40 * $U40) / 100 + $B$33 * ($P40 * $S40) / 100, 0), 100) -> 62.796423 | X40: {=_xlfn.IFS($W40 <= 30, "Low", $W40 <=50, "Medium", $W40 <= 70, "High", $W40 > 70, "Critical")} -> High | Y40: =$Q40 * (1 / (1 + EXP(-($W40 - 50) / $B$34))) -> 0.27383611 | Z40: =_xlfn.LET( _xlpm.full_churn, $Y40 * $I40, _xlpm.partial_rate, IF(OR($X40="Medium", $X40="High"), (1 - $Y40) * 0.5 * $B$35, 0), _xlpm.partial_churn, _xlpm.partial_rate * $I40, _xlpm.full_churn + _xlpm.partial_churn ) -> 54.973457
A41: CUST-3499 | B41: Loyal High-Value | C41: Referral | D41: West | E41: 55+ | F41: High | G41: 1 | H41: 40 | I41: 2272.04 | J41: {=SUMPRODUCT( (Transactions_and_Customer_Information_Joined[Customer ID]='V1-Based Churn Model (Step 3)'!$A41) * (IFERROR(_xlfn.XLOOKUP(Transactions_and_Customer_Information_Joined[SKU], 'V1 Pricing Model (Step 2)'!$A$22:$A$71, 'V1 Pricing Model (Step 2)'!$AL$22:$AL$71), "Exclude")<>"Exclude") * Transactions_and_Customer_Information_Joined[Gross Revenue])} -> 174.23 | K41: =SUMIF(Transactions_and_Customer_Information_Joined[Customer ID], 'V1-Based Churn Model (Step 3)'!$A41, Transactions_and_Customer_Information_Joined[Gross Revenue]) -> 401.3 | L41: =IFERROR($J41/$K41, 0) -> 0.43416397 | M41: 0.05834808 | N41: {=SUMPRODUCT( (Transactions_and_Customer_Information_Joined[Customer ID]=$A41) * (Transactions_and_Customer_Information_Joined[Order Status]="Completed") * (IFERROR(_xlfn.XLOOKUP(Transactions_and_Customer_Information_Joined[SKU], 'V1 Pricing Model (Step 2)'!$A$22:$A$71, 'V1 Pricing Model (Step 2)'!$AL$22:$AL$71), "Exclude")<>"Exclude"))} -> 1 | O41: {=IFERROR( SUMPRODUCT( (Transactions_and_Customer_Information_Joined[Customer ID]=$A41) * (IFERROR(_xlfn.XLOOKUP(Transactions_and_Customer_Information_Joined[SKU], 'V1 Pricing Model (Step 2)'!$A$22:$A$71, 'V1 Pricing Model (Step 2)'!$AL$22:$AL$71), "Exclude")<>"Exclude") * Transactions_and_Customer_Information_Joined[Gross Revenue] * IFERROR(_xlfn.XLOOKUP(Transactions_and_Customer_Information_Joined[SKU], 'V1 Pricing Model (Step 2)'!$A$22:$A$71, 'V1 Pricing Model (Step 2)'!$W$22:$W$71), 0) ) / $J41, 0)} -> 0.05834808 | P41: {=_xlfn.IFS(B41="At-Risk Churner",$B$2,$B41="Dormant",$B$3,$B41="Deal Hunter",$B$4,$B41="New Customer",$B$5,$B41="Occasional Buyer",$B$6,$B41="Loyal High-Value",$B$7)} -> 15 | Q41: {=_xlfn.IFS($B41 = "At-Risk Churner", $B$8, $B41="Dormant",$B$9, $B41="Deal Hunter", $B$10, $B41="New Customer", $B$11, $B41="Occasional Buyer", $B$12, $B41 = "Loyal High-Value",$B$13)} -> 0.05 | R41: 15 | S41: 10 | T41: -5 | U41: =MIN( $L41 * $B$26 * (1 + $B$28 * LN(MAX($N41, 1))), $B$27 ) -> 10.854099 | V41: =MIN( $B$29 * ABS($O41) + $B$30 * ABS($M41), $B$31 ) -> 2.3339232 | W41: =MIN(MAX( $P41 + $R41 + $S41 + $T41 + $U41 + $V41 + $B$32 * ($R41 * $U41) / 100 + $B$33 * ($P41 * $S41) / 100, 0), 100) -> 48.58224 | X41: {=_xlfn.IFS($W41 <= 30, "Low", $W41 <=50, "Medium", $W41 <= 70, "High", $W41 > 70, "Critical")} -> Medium | Y41: =$Q41 * (1 / (1 + EXP(-($W41 - 50) / $B$34))) -> 0.023230762 | Z41: =_xlfn.LET( _xlpm.full_churn, $Y41 * $I41, _xlpm.partial_rate, IF(OR($X41="Medium", $X41="High"), (1 - $Y41) * 0.5 * $B$35, 0), _xlpm.partial_churn, _xlpm.partial_rate * $I41, _xlpm.full_churn + _xlpm.partial_churn ) -> 496.63298
A42: CUST-2301 | B42: Loyal High-Value | C42: Direct | D42: Southwest | E42: 35-44 | F42: Medium | G42: 6 | H42: 93 | I42: 997.06 | J42: {=SUMPRODUCT( (Transactions_and_Customer_Information_Joined[Customer ID]='V1-Based Churn Model (Step 3)'!$A42) * (IFERROR(_xlfn.XLOOKUP(Transactions_and_Customer_Information_Joined[SKU], 'V1 Pricing Model (Step 2)'!$A$22:$A$71, 'V1 Pricing Model (Step 2)'!$AL$22:$AL$71), "Exclude")<>"Exclude") * Transactions_and_Customer_Information_Joined[Gross Revenue])} -> 26.7 | K42: =SUMIF(Transactions_and_Customer_Information_Joined[Customer ID], 'V1-Based Churn Model (Step 3)'!$A42, Transactions_and_Customer_Information_Joined[Gross Revenue]) -> 26.7 | L42: =IFERROR($J42/$K42, 0) -> 1 | M42: 0.0075818801 | N42: {=SUMPRODUCT( (Transactions_and_Customer_Information_Joined[Customer ID]=$A42) * (Transactions_and_Customer_Information_Joined[Order Status]="Completed") * (IFERROR(_xlfn.XLOOKUP(Transactions_and_Customer_Information_Joined[SKU], 'V1 Pricing Model (Step 2)'!$A$22:$A$71, 'V1 Pricing Model (Step 2)'!$AL$22:$AL$71), "Exclude")<>"Exclude"))} -> 1 | O42: {=IFERROR( SUMPRODUCT( (Transactions_and_Customer_Information_Joined[Customer ID]=$A42) * (IFERROR(_xlfn.XLOOKUP(Transactions_and_Customer_Information_Joined[SKU], 'V1 Pricing Model (Step 2)'!$A$22:$A$71, 'V1 Pricing Model (Step 2)'!$AL$22:$AL$71), "Exclude")<>"Exclude") * Transactions_and_Customer_Information_Joined[Gross Revenue] * IFERROR(_xlfn.XLOOKUP(Transactions_and_Customer_Information_Joined[SKU], 'V1 Pricing Model (Step 2)'!$A$22:$A$71, 'V1 Pricing Model (Step 2)'!$W$22:$W$71), 0) ) / $J42, 0)} -> 0.0075818801 | P42: {=_xlfn.IFS(B42="At-Risk Churner",$B$2,$B42="Dormant",$B$3,$B42="Deal Hunter",$B$4,$B42="New Customer",$B$5,$B42="Occasional Buyer",$B$6,$B42="Loyal High-Value",$B$7)} -> 15 | Q42: {=_xlfn.IFS($B42 = "At-Risk Churner", $B$8, $B42="Dormant",$B$9, $B42="Deal Hunter", $B$10, $B42="New Customer", $B$11, $B42="Occasional Buyer", $B$12, $B42 = "Loyal High-Value",$B$13)} -> 0.05 | R42: 5 | S42: 0 | T42: 0 | U42: =MIN( $L42 * $B$26 * (1 + $B$28 * LN(MAX($N42, 1))), $B$27 ) -> 15 | V42: =MIN( $B$29 * ABS($O42) + $B$30 * ABS($M42), $B$31 ) -> 0.3032752 | W42: =MIN(MAX( $P42 + $R42 + $S42 + $T42 + $U42 + $V42 + $B$32 * ($R42 * $U42) / 100 + $B$33 * ($P42 * $S42) / 100, 0), 100) -> 35.415775 | X42: {=_xlfn.IFS($W42 <= 30, "Low", $W42 <=50, "Medium", $W42 <= 70, "High", $W42 > 70, "Critical")} -> Medium | Y42: =$Q42 * (1 / (1 + EXP(-($W42 - 50) / $B$34))) -> 0.0094354361 | Z42: =_xlfn.LET( _xlpm.full_churn, $Y42 * $I42, _xlpm.partial_rate, IF(OR($X42="Medium", $X42="High"), (1 - $Y42) * 0.5 * $B$35, 0), _xlpm.partial_churn, _xlpm.partial_rate * $I42, _xlpm.full_churn + _xlpm.partial_churn ) -> 206.93816
A43: CUST-3837 | B43: Dormant | C43: Referral | D43: Midwest | E43: 55+ | F43: Low | G43: 9 | H43: 285 | I43: 166.92 | J43: {=SUMPRODUCT( (Transactions_and_Customer_Information_Joined[Customer ID]='V1-Based Churn Model (Step 3)'!$A43) * (IFERROR(_xlfn.XLOOKUP(Transactions_and_Customer_Information_Joined[SKU], 'V1 Pricing Model (Step 2)'!$A$22:$A$71, 'V1 Pricing Model (Step 2)'!$AL$22:$AL$71), "Exclude")<>"Exclude") * Transactions_and_Customer_Information_Joined[Gross Revenue])} -> 436.71 | K43: =SUMIF(Transactions_and_Customer_Information_Joined[Customer ID], 'V1-Based Churn Model (Step 3)'!$A43, Transactions_and_Customer_Information_Joined[Gross Revenue]) -> 436.71 | L43: =IFERROR($J43/$K43, 0) -> 1 | M43: 0.053264378 | N43: {=SUMPRODUCT( (Transactions_and_Customer_Information_Joined[Customer ID]=$A43) * (Transactions_and_Customer_Information_Joined[Order Status]="Completed") * (IFERROR(_xlfn.XLOOKUP(Transactions_and_Customer_Information_Joined[SKU], 'V1 Pricing Model (Step 2)'!$A$22:$A$71, 'V1 Pricing Model (Step 2)'!$AL$22:$AL$71), "Exclude")<>"Exclude"))} -> 1 | O43: {=IFERROR( SUMPRODUCT( (Transactions_and_Customer_Information_Joined[Customer ID]=$A43) * (IFERROR(_xlfn.XLOOKUP(Transactions_and_Customer_Information_Joined[SKU], 'V1 Pricing Model (Step 2)'!$A$22:$A$71, 'V1 Pricing Model (Step 2)'!$AL$22:$AL$71), "Exclude")<>"Exclude") * Transactions_and_Customer_Information_Joined[Gross Revenue] * IFERROR(_xlfn.XLOOKUP(Transactions_and_Customer_Information_Joined[SKU], 'V1 Pricing Model (Step 2)'!$A$22:$A$71, 'V1 Pricing Model (Step 2)'!$W$22:$W$71), 0) ) / $J43, 0)} -> 0.028516032 | P43: {=_xlfn.IFS(B43="At-Risk Churner",$B$2,$B43="Dormant",$B$3,$B43="Deal Hunter",$B$4,$B43="New Customer",$B$5,$B43="Occasional Buyer",$B$6,$B43="Loyal High-Value",$B$7)} -> 65 | Q43: {=_xlfn.IFS($B43 = "At-Risk Churner", $B$8, $B43="Dormant",$B$9, $B43="Deal Hunter", $B$10, $B43="New Customer", $B$11, $B43="Occasional Buyer", $B$12, $B43 = "Loyal High-Value",$B$13)} -> 0.6 | R43: -5 | S43: -8 | T43: 8 | U43: =MIN( $L43 * $B$26 * (1 + $B$28 * LN(MAX($N43, 1))), $B$27 ) -> 15 | V43: =MIN( $B$29 * ABS($O43) + $B$30 * ABS($M43), $B$31 ) -> 1.6356082 | W43: =MIN(MAX( $P43 + $R43 + $S43 + $T43 + $U43 + $V43 + $B$32 * ($R43 * $U43) / 100 + $B$33 * ($P43 * $S43) / 100, 0), 100) -> 76.003108 | X43: {=_xlfn.IFS($W43 <= 30, "Low", $W43 <=50, "Medium", $W43 <= 70, "High", $W43 > 70, "Critical")} -> Critical | Y43: =$Q43 * (1 / (1 + EXP(-($W43 - 50) / $B$34))) -> 0.55852895 | Z43: =_xlfn.LET( _xlpm.full_churn, $Y43 * $I43, _xlpm.partial_rate, IF(OR($X43="Medium", $X43="High"), (1 - $Y43) * 0.5 * $B$35, 0), _xlpm.partial_churn, _xlpm.partial_rate * $I43, _xlpm.full_churn + _xlpm.partial_churn ) -> 93.229652
A44: CUST-2481 | B44: Deal Hunter | C44: Influencer | D44: Northeast | E44: 25-34 | F44: Low | G44: 2 | H44: 255 | I44: 411.92 | J44: {=SUMPRODUCT( (Transactions_and_Customer_Information_Joined[Customer ID]='V1-Based Churn Model (Step 3)'!$A44) * (IFERROR(_xlfn.XLOOKUP(Transactions_and_Customer_Information_Joined[SKU], 'V1 Pricing Model (Step 2)'!$A$22:$A$71, 'V1 Pricing Model (Step 2)'!$AL$22:$AL$71), "Exclude")<>"Exclude") * Transactions_and_Customer_Information_Joined[Gross Revenue])} -> 105.84 | K44: =SUMIF(Transactions_and_Customer_Information_Joined[Customer ID], 'V1-Based Churn Model (Step 3)'!$A44, Transactions_and_Customer_Information_Joined[Gross Revenue]) -> 105.84 | L44: =IFERROR($J44/$K44, 0) -> 1 | M44: -0.045975852 | N44: {=SUMPRODUCT( (Transactions_and_Customer_Information_Joined[Customer ID]=$A44) * (Transactions_and_Customer_Information_Joined[Order Status]="Completed") * (IFERROR(_xlfn.XLOOKUP(Transactions_and_Customer_Information_Joined[SKU], 'V1 Pricing Model (Step 2)'!$A$22:$A$71, 'V1 Pricing Model (Step 2)'!$AL$22:$AL$71), "Exclude")<>"Exclude"))} -> 1 | O44: {=IFERROR( SUMPRODUCT( (Transactions_and_Customer_Information_Joined[Customer ID]=$A44) * (IFERROR(_xlfn.XLOOKUP(Transactions_and_Customer_Information_Joined[SKU], 'V1 Pricing Model (Step 2)'!$A$22:$A$71, 'V1 Pricing Model (Step 2)'!$AL$22:$AL$71), "Exclude")<>"Exclude") * Transactions_and_Customer_Information_Joined[Gross Revenue] * IFERROR(_xlfn.XLOOKUP(Transactions_and_Customer_Information_Joined[SKU], 'V1 Pricing Model (Step 2)'!$A$22:$A$71, 'V1 Pricing Model (Step 2)'!$W$22:$W$71), 0) ) / $J44, 0)} -> -0.045975852 | P44: {=_xlfn.IFS(B44="At-Risk Churner",$B$2,$B44="Dormant",$B$3,$B44="Deal Hunter",$B$4,$B44="New Customer",$B$5,$B44="Occasional Buyer",$B$6,$B44="Loyal High-Value",$B$7)} -> 45 | Q44: {=_xlfn.IFS($B44 = "At-Risk Churner", $B$8, $B44="Dormant",$B$9, $B44="Deal Hunter", $B$10, $B44="New Customer", $B$11, $B44="Occasional Buyer", $B$12, $B44 = "Loyal High-Value",$B$13)} -> 0.25 | R44: -5 | S44: 10 | T44: 8 | U44: =MIN( $L44 * $B$26 * (1 + $B$28 * LN(MAX($N44, 1))), $B$27 ) -> 15 | V44: =MIN( $B$29 * ABS($O44) + $B$30 * ABS($M44), $B$31 ) -> 1.8390341 | W44: =MIN(MAX( $P44 + $R44 + $S44 + $T44 + $U44 + $V44 + $B$32 * ($R44 * $U44) / 100 + $B$33 * ($P44 * $S44) / 100, 0), 100) -> 75.176534 | X44: {=_xlfn.IFS($W44 <= 30, "Low", $W44 <=50, "Medium", $W44 <= 70, "High", $W44 > 70, "Critical")} -> Critical | Y44: =$Q44 * (1 / (1 + EXP(-($W44 - 50) / $B$34))) -> 0.23134254 | Z44: =_xlfn.LET( _xlpm.full_churn, $Y44 * $I44, _xlpm.partial_rate, IF(OR($X44="Medium", $X44="High"), (1 - $Y44) * 0.5 * $B$35, 0), _xlpm.partial_churn, _xlpm.partial_rate * $I44, _xlpm.full_churn + _xlpm.partial_churn ) -> 95.294619
A45: CUST-3854 | B45: Dormant | C45: Organic Search | D45: Canada | E45: 35-44 | F45: High | G45: 3 | H45: 285 | I45: 81.97 | J45: {=SUMPRODUCT( (Transactions_and_Customer_Information_Joined[Customer ID]='V1-Based Churn Model (Step 3)'!$A45) * (IFERROR(_xlfn.XLOOKUP(Transactions_and_Customer_Information_Joined[SKU], 'V1 Pricing Model (Step 2)'!$A$22:$A$71, 'V1 Pricing Model (Step 2)'!$AL$22:$AL$71), "Exclude")<>"Exclude") * Transactions_and_Customer_Information_Joined[Gross Revenue])} -> 105.33 | K45: =SUMIF(Transactions_and_Customer_Information_Joined[Customer ID], 'V1-Based Churn Model (Step 3)'!$A45, Transactions_and_Customer_Information_Joined[Gross Revenue]) -> 105.33 | L45: =IFERROR($J45/$K45, 0) -> 1 | M45: 0.25581556 | N45: {=SUMPRODUCT( (Transactions_and_Customer_Information_Joined[Customer ID]=$A45) * (Transactions_and_Customer_Information_Joined[Order Status]="Completed") * (IFERROR(_xlfn.XLOOKUP(Transactions_and_Customer_Information_Joined[SKU], 'V1 Pricing Model (Step 2)'!$A$22:$A$71, 'V1 Pricing Model (Step 2)'!$AL$22:$AL$71), "Exclude")<>"Exclude"))} -> 1 | O45: {=IFERROR( SUMPRODUCT( (Transactions_and_Customer_Information_Joined[Customer ID]=$A45) * (IFERROR(_xlfn.XLOOKUP(Transactions_and_Customer_Information_Joined[SKU], 'V1 Pricing Model (Step 2)'!$A$22:$A$71, 'V1 Pricing Model (Step 2)'!$AL$22:$AL$71), "Exclude")<>"Exclude") * Transactions_and_Customer_Information_Joined[Gross Revenue] * IFERROR(_xlfn.XLOOKUP(Transactions_and_Customer_Information_Joined[SKU], 'V1 Pricing Model (Step 2)'!$A$22:$A$71, 'V1 Pricing Model (Step 2)'!$W$22:$W$71), 0) ) / $J45, 0)} -> 0.25581556 | P45: {=_xlfn.IFS(B45="At-Risk Churner",$B$2,$B45="Dormant",$B$3,$B45="Deal Hunter",$B$4,$B45="New Customer",$B$5,$B45="Occasional Buyer",$B$6,$B45="Loyal High-Value",$B$7)} -> 65 | Q45: {=_xlfn.IFS($B45 = "At-Risk Churner", $B$8, $B45="Dormant",$B$9, $B45="Deal Hunter", $B$10, $B45="New Customer", $B$11, $B45="Occasional Buyer", $B$12, $B45 = "Loyal High-Value",$B$13)} -> 0.6 | R45: 15 | S45: 10 | T45: 8 | U45: =MIN( $L45 * $B$26 * (1 + $B$28 * LN(MAX($N45, 1))), $B$27 ) -> 15 | V45: =MIN( $B$29 * ABS($O45) + $B$30 * ABS($M45), $B$31 ) -> 10.232622 | W45: =MIN(MAX( $P45 + $R45 + $S45 + $T45 + $U45 + $V45 + $B$32 * ($R45 * $U45) / 100 + $B$33 * ($P45 * $S45) / 100, 0), 100) -> 100 | X45: {=_xlfn.IFS($W45 <= 30, "Low", $W45 <=50, "Medium", $W45 <= 70, "High", $W45 > 70, "Critical")} -> Critical | Y45: =$Q45 * (1 / (1 + EXP(-($W45 - 50) / $B$34))) -> 0.59598429 | Z45: =_xlfn.LET( _xlpm.full_churn, $Y45 * $I45, _xlpm.partial_rate, IF(OR($X45="Medium", $X45="High"), (1 - $Y45) * 0.5 * $B$35, 0), _xlpm.partial_churn, _xlpm.partial_rate * $I45, _xlpm.full_churn + _xlpm.partial_churn ) -> 48.852832
A46: CUST-1942 | B46: Loyal High-Value | C46: Paid Social | D46: UK | E46: 25-34 | F46: Medium | G46: 0 | H46: 89 | I46: 1827.99 | J46: {=SUMPRODUCT( (Transactions_and_Customer_Information_Joined[Customer ID]='V1-Based Churn Model (Step 3)'!$A46) * (IFERROR(_xlfn.XLOOKUP(Transactions_and_Customer_Information_Joined[SKU], 'V1 Pricing Model (Step 2)'!$A$22:$A$71, 'V1 Pricing Model (Step 2)'!$AL$22:$AL$71), "Exclude")<>"Exclude") * Transactions_and_Customer_Information_Joined[Gross Revenue])} -> 0 | K46: =SUMIF(Transactions_and_Customer_Information_Joined[Customer ID], 'V1-Based Churn Model (Step 3)'!$A46, Transactions_and_Customer_Information_Joined[Gross Revenue]) -> 326.4 | L46: =IFERROR($J46/$K46, 0) -> 0 | M46: 0 | N46: {=SUMPRODUCT( (Transactions_and_Customer_Information_Joined[Customer ID]=$A46) * (Transactions_and_Customer_Information_Joined[Order Status]="Completed") * (IFERROR(_xlfn.XLOOKUP(Transactions_and_Customer_Information_Joined[SKU], 'V1 Pricing Model (Step 2)'!$A$22:$A$71, 'V1 Pricing Model (Step 2)'!$AL$22:$AL$71), "Exclude")<>"Exclude"))} -> 0 | O46: {=IFERROR( SUMPRODUCT( (Transactions_and_Customer_Information_Joined[Customer ID]=$A46) * (IFERROR(_xlfn.XLOOKUP(Transactions_and_Customer_Information_Joined[SKU], 'V1 Pricing Model (Step 2)'!$A$22:$A$71, 'V1 Pricing Model (Step 2)'!$AL$22:$AL$71), "Exclude")<>"Exclude") * Transactions_and_Customer_Information_Joined[Gross Revenue] * IFERROR(_xlfn.XLOOKUP(Transactions_and_Customer_Information_Joined[SKU], 'V1 Pricing Model (Step 2)'!$A$22:$A$71, 'V1 Pricing Model (Step 2)'!$W$22:$W$71), 0) ) / $J46, 0)} -> 0 | P46: {=_xlfn.IFS(B46="At-Risk Churner",$B$2,$B46="Dormant",$B$3,$B46="Deal Hunter",$B$4,$B46="New Customer",$B$5,$B46="Occasional Buyer",$B$6,$B46="Loyal High-Value",$B$7)} -> 15 | Q46: {=_xlfn.IFS($B46 = "At-Risk Churner", $B$8, $B46="Dormant",$B$9, $B46="Deal Hunter", $B$10, $B46="New Customer", $B$11, $B46="Occasional Buyer", $B$12, $B46 = "Loyal High-Value",$B$13)} -> 0.05 | R46: 5 | S46: 10 | T46: 0 | U46: =MIN( $L46 * $B$26 * (1 + $B$28 * LN(MAX($N46, 1))), $B$27 ) -> 0 | V46: =MIN( $B$29 * ABS($O46) + $B$30 * ABS($M46), $B$31 ) -> 0 | W46: =MIN(MAX( $P46 + $R46 + $S46 + $T46 + $U46 + $V46 + $B$32 * ($R46 * $U46) / 100 + $B$33 * ($P46 * $S46) / 100, 0), 100) -> 30.15 | X46: {=_xlfn.IFS($W46 <= 30, "Low", $W46 <=50, "Medium", $W46 <= 70, "High", $W46 > 70, "Critical")} -> Medium | Y46: =$Q46 * (1 / (1 + EXP(-($W46 - 50) / $B$34))) -> 0.0060393422 | Z46: =_xlfn.LET( _xlpm.full_churn, $Y46 * $I46, _xlpm.partial_rate, IF(OR($X46="Medium", $X46="High"), (1 - $Y46) * 0.5 * $B$35, 0), _xlpm.partial_churn, _xlpm.partial_rate * $I46, _xlpm.full_churn + _xlpm.partial_churn ) -> 374.42989
A47: CUST-4858 | B47: New Customer | C47: Paid Social | D47: Southeast | E47: 55+ | F47: Medium | G47: 5 | H47: 306 | I47: 146.77 | J47: {=SUMPRODUCT( (Transactions_and_Customer_Information_Joined[Customer ID]='V1-Based Churn Model (Step 3)'!$A47) * (IFERROR(_xlfn.XLOOKUP(Transactions_and_Customer_Information_Joined[SKU], 'V1 Pricing Model (Step 2)'!$A$22:$A$71, 'V1 Pricing Model (Step 2)'!$AL$22:$AL$71), "Exclude")<>"Exclude") * Transactions_and_Customer_Information_Joined[Gross Revenue])} -> 53.95 | K47: =SUMIF(Transactions_and_Customer_Information_Joined[Customer ID], 'V1-Based Churn Model (Step 3)'!$A47, Transactions_and_Customer_Information_Joined[Gross Revenue]) -> 53.95 | L47: =IFERROR($J47/$K47, 0) -> 1 | M47: -0.0063633335 | N47: {=SUMPRODUCT( (Transactions_and_Customer_Information_Joined[Customer ID]=$A47) * (Transactions_and_Customer_Information_Joined[Order Status]="Completed") * (IFERROR(_xlfn.XLOOKUP(Transactions_and_Customer_Information_Joined[SKU], 'V1 Pricing Model (Step 2)'!$A$22:$A$71, 'V1 Pricing Model (Step 2)'!$AL$22:$AL$71), "Exclude")<>"Exclude"))} -> 1 | O47: {=IFERROR( SUMPRODUCT( (Transactions_and_Customer_Information_Joined[Customer ID]=$A47) * (IFERROR(_xlfn.XLOOKUP(Transactions_and_Customer_Information_Joined[SKU], 'V1 Pricing Model (Step 2)'!$A$22:$A$71, 'V1 Pricing Model (Step 2)'!$AL$22:$AL$71), "Exclude")<>"Exclude") * Transactions_and_Customer_Information_Joined[Gross Revenue] * IFERROR(_xlfn.XLOOKUP(Transactions_and_Customer_Information_Joined[SKU], 'V1 Pricing Model (Step 2)'!$A$22:$A$71, 'V1 Pricing Model (Step 2)'!$W$22:$W$71), 0) ) / $J47, 0)} -> -0.0063633335 | P47: {=_xlfn.IFS(B47="At-Risk Churner",$B$2,$B47="Dormant",$B$3,$B47="Deal Hunter",$B$4,$B47="New Customer",$B$5,$B47="Occasional Buyer",$B$6,$B47="Loyal High-Value",$B$7)} -> 35 | Q47: {=_xlfn.IFS($B47 = "At-Risk Churner", $B$8, $B47="Dormant",$B$9, $B47="Deal Hunter", $B$10, $B47="New Customer", $B$11, $B47="Occasional Buyer", $B$12, $B47 = "Loyal High-Value",$B$13)} -> 0.35 | R47: 5 | S47: 0 | T47: 15 | U47: =MIN( $L47 * $B$26 * (1 + $B$28 * LN(MAX($N47, 1))), $B$27 ) -> 15 | V47: =MIN( $B$29 * ABS($O47) + $B$30 * ABS($M47), $B$31 ) -> 0.25453334 | W47: =MIN(MAX( $P47 + $R47 + $S47 + $T47 + $U47 + $V47 + $B$32 * ($R47 * $U47) / 100 + $B$33 * ($P47 * $S47) / 100, 0), 100) -> 70.367033 | X47: {=_xlfn.IFS($W47 <= 30, "Low", $W47 <=50, "Medium", $W47 <= 70, "High", $W47 > 70, "Critical")} -> Critical | Y47: =$Q47 * (1 / (1 + EXP(-($W47 - 50) / $B$34))) -> 0.309609 | Z47: =_xlfn.LET( _xlpm.full_churn, $Y47 * $I47, _xlpm.partial_rate, IF(OR($X47="Medium", $X47="High"), (1 - $Y47) * 0.5 * $B$35, 0), _xlpm.partial_churn, _xlpm.partial_rate * $I47, _xlpm.full_churn + _xlpm.partial_churn ) -> 45.441314
A48: CUST-1468 | B48: Occasional Buyer | C48: Email Campaign | D48: UK | E48: 25-34 | F48: Low | G48: 1 | H48: 139 | I48: 644.28 | J48: {=SUMPRODUCT( (Transactions_and_Customer_Information_Joined[Customer ID]='V1-Based Churn Model (Step 3)'!$A48) * (IFERROR(_xlfn.XLOOKUP(Transactions_and_Customer_Information_Joined[SKU], 'V1 Pricing Model (Step 2)'!$A$22:$A$71, 'V1 Pricing Model (Step 2)'!$AL$22:$AL$71), "Exclude")<>"Exclude") * Transactions_and_Customer_Information_Joined[Gross Revenue])} -> 34.48 | K48: =SUMIF(Transactions_and_Customer_Information_Joined[Customer ID], 'V1-Based Churn Model (Step 3)'!$A48, Transactions_and_Customer_Information_Joined[Gross Revenue]) -> 34.48 | L48: =IFERROR($J48/$K48, 0) -> 1 | M48: 0.070422329 | N48: {=SUMPRODUCT( (Transactions_and_Customer_Information_Joined[Customer ID]=$A48) * (Transactions_and_Customer_Information_Joined[Order Status]="Completed") * (IFERROR(_xlfn.XLOOKUP(Transactions_and_Customer_Information_Joined[SKU], 'V1 Pricing Model (Step 2)'!$A$22:$A$71, 'V1 Pricing Model (Step 2)'!$AL$22:$AL$71), "Exclude")<>"Exclude"))} -> 1 | O48: {=IFERROR( SUMPRODUCT( (Transactions_and_Customer_Information_Joined[Customer ID]=$A48) * (IFERROR(_xlfn.XLOOKUP(Transactions_and_Customer_Information_Joined[SKU], 'V1 Pricing Model (Step 2)'!$A$22:$A$71, 'V1 Pricing Model (Step 2)'!$AL$22:$AL$71), "Exclude")<>"Exclude") * Transactions_and_Customer_Information_Joined[Gross Revenue] * IFERROR(_xlfn.XLOOKUP(Transactions_and_Customer_Information_Joined[SKU], 'V1 Pricing Model (Step 2)'!$A$22:$A$71, 'V1 Pricing Model (Step 2)'!$W$22:$W$71), 0) ) / $J48, 0)} -> 0.070422329 | P48: {=_xlfn.IFS(B48="At-Risk Churner",$B$2,$B48="Dormant",$B$3,$B48="Deal Hunter",$B$4,$B48="New Customer",$B$5,$B48="Occasional Buyer",$B$6,$B48="Loyal High-Value",$B$7)} -> 25 | Q48: {=_xlfn.IFS($B48 = "At-Risk Churner", $B$8, $B48="Dormant",$B$9, $B48="Deal Hunter", $B$10, $B48="New Customer", $B$11, $B48="Occasional Buyer", $B$12, $B48 = "Loyal High-Value",$B$13)} -> 0.18 | R48: -5 | S48: 10 | T48: 0 | U48: =MIN( $L48 * $B$26 * (1 + $B$28 * LN(MAX($N48, 1))), $B$27 ) -> 15 | V48: =MIN( $B$29 * ABS($O48) + $B$30 * ABS($M48), $B$31 ) -> 2.8168932 | W48: =MIN(MAX( $P48 + $R48 + $S48 + $T48 + $U48 + $V48 + $B$32 * ($R48 * $U48) / 100 + $B$33 * ($P48 * $S48) / 100, 0), 100) -> 47.954393 | X48: {=_xlfn.IFS($W48 <= 30, "Low", $W48 <=50, "Medium", $W48 <= 70, "High", $W48 > 70, "Critical")} -> Medium | Y48: =$Q48 * (1 / (1 + EXP(-($W48 - 50) / $B$34))) -> 0.080826735 | Z48: =_xlfn.LET( _xlpm.full_churn, $Y48 * $I48, _xlpm.partial_rate, IF(OR($X48="Medium", $X48="High"), (1 - $Y48) * 0.5 * $B$35, 0), _xlpm.partial_churn, _xlpm.partial_rate * $I48, _xlpm.full_churn + _xlpm.partial_churn ) -> 170.51604
A49: CUST-1627 | B49: Occasional Buyer | C49: Email Campaign | D49: Southwest | E49: 25-34 | F49: Medium | G49: 8 | H49: 47 | I49: 288.31 | J49: {=SUMPRODUCT( (Transactions_and_Customer_Information_Joined[Customer ID]='V1-Based Churn Model (Step 3)'!$A49) * (IFERROR(_xlfn.XLOOKUP(Transactions_and_Customer_Information_Joined[SKU], 'V1 Pricing Model (Step 2)'!$A$22:$A$71, 'V1 Pricing Model (Step 2)'!$AL$22:$AL$71), "Exclude")<>"Exclude") * Transactions_and_Customer_Information_Joined[Gross Revenue])} -> 295.74 | K49: =SUMIF(Transactions_and_Customer_Information_Joined[Customer ID], 'V1-Based Churn Model (Step 3)'!$A49, Transactions_and_Customer_Information_Joined[Gross Revenue]) -> 295.74 | L49: =IFERROR($J49/$K49, 0) -> 1 | M49: 0 | N49: {=SUMPRODUCT( (Transactions_and_Customer_Information_Joined[Customer ID]=$A49) * (Transactions_and_Customer_Information_Joined[Order Status]="Completed") * (IFERROR(_xlfn.XLOOKUP(Transactions_and_Customer_Information_Joined[SKU], 'V1 Pricing Model (Step 2)'!$A$22:$A$71, 'V1 Pricing Model (Step 2)'!$AL$22:$AL$71), "Exclude")<>"Exclude"))} -> 1 | O49: {=IFERROR( SUMPRODUCT( (Transactions_and_Customer_Information_Joined[Customer ID]=$A49) * (IFERROR(_xlfn.XLOOKUP(Transactions_and_Customer_Information_Joined[SKU], 'V1 Pricing Model (Step 2)'!$A$22:$A$71, 'V1 Pricing Model (Step 2)'!$AL$22:$AL$71), "Exclude")<>"Exclude") * Transactions_and_Customer_Information_Joined[Gross Revenue] * IFERROR(_xlfn.XLOOKUP(Transactions_and_Customer_Information_Joined[SKU], 'V1 Pricing Model (Step 2)'!$A$22:$A$71, 'V1 Pricing Model (Step 2)'!$W$22:$W$71), 0) ) / $J49, 0)} -> 0 | P49: {=_xlfn.IFS(B49="At-Risk Churner",$B$2,$B49="Dormant",$B$3,$B49="Deal Hunter",$B$4,$B49="New Customer",$B$5,$B49="Occasional Buyer",$B$6,$B49="Loyal High-Value",$B$7)} -> 25 | Q49: {=_xlfn.IFS($B49 = "At-Risk Churner", $B$8, $B49="Dormant",$B$9, $B49="Deal Hunter", $B$10, $B49="New Customer", $B$11, $B49="Occasional Buyer", $B$12, $B49 = "Loyal High-Value",$B$13)} -> 0.18 | R49: 5 | S49: -8 | T49: -5 | U49: =MIN( $L49 * $B$26 * (1 + $B$28 * LN(MAX($N49, 1))), $B$27 ) -> 15 | V49: =MIN( $B$29 * ABS($O49) + $B$30 * ABS($M49), $B$31 ) -> 0 | W49: =MIN(MAX( $P49 + $R49 + $S49 + $T49 + $U49 + $V49 + $B$32 * ($R49 * $U49) / 100 + $B$33 * ($P49 * $S49) / 100, 0), 100) -> 31.9125 | X49: {=_xlfn.IFS($W49 <= 30, "Low", $W49 <=50, "Medium", $W49 <= 70, "High", $W49 > 70, "Critical")} -> Medium | Y49: =$Q49 * (1 / (1 + EXP(-($W49 - 50) / $B$34))) -> 0.025342068 | Z49: =_xlfn.LET( _xlpm.full_churn, $Y49 * $I49, _xlpm.partial_rate, IF(OR($X49="Medium", $X49="High"), (1 - $Y49) * 0.5 * $B$35, 0), _xlpm.partial_churn, _xlpm.partial_rate * $I49, _xlpm.full_churn + _xlpm.partial_churn ) -> 63.507097
A50: CUST-3267 | B50: At-Risk Churner | C50: Referral | D50: UK | E50: 25-34 | F50: Low | G50: 2 | H50: 221 | I50: 266.56 | J50: {=SUMPRODUCT( (Transactions_and_Customer_Information_Joined[Customer ID]='V1-Based Churn Model (Step 3)'!$A50) * (IFERROR(_xlfn.XLOOKUP(Transactions_and_Customer_Information_Joined[SKU], 'V1 Pricing Model (Step 2)'!$A$22:$A$71, 'V1 Pricing Model (Step 2)'!$AL$22:$AL$71), "Exclude")<>"Exclude") * Transactions_and_Customer_Information_Joined[Gross Revenue])} -> 424.24 | K50: =SUMIF(Transactions_and_Customer_Information_Joined[Customer ID], 'V1-Based Churn Model (Step 3)'!$A50, Transactions_and_Customer_Information_Joined[Gross Revenue]) -> 424.24 | L50: =IFERROR($J50/$K50, 0) -> 1 | M50: 0.18762795 | N50: {=SUMPRODUCT( (Transactions_and_Customer_Information_Joined[Customer ID]=$A50) * (Transactions_and_Customer_Information_Joined[Order Status]="Completed") * (IFERROR(_xlfn.XLOOKUP(Transactions_and_Customer_Information_Joined[SKU], 'V1 Pricing Model (Step 2)'!$A$22:$A$71, 'V1 Pricing Model (Step 2)'!$AL$22:$AL$71), "Exclude")<>"Exclude"))} -> 1 | O50: {=IFERROR( SUMPRODUCT( (Transactions_and_Customer_Information_Joined[Customer ID]=$A50) * (IFERROR(_xlfn.XLOOKUP(Transactions_and_Customer_Information_Joined[SKU], 'V1 Pricing Model (Step 2)'!$A$22:$A$71, 'V1 Pricing Model (Step 2)'!$AL$22:$AL$71), "Exclude")<>"Exclude") * Transactions_and_Customer_Information_Joined[Gross Revenue] * IFERROR(_xlfn.XLOOKUP(Transactions_and_Customer_Information_Joined[SKU], 'V1 Pricing Model (Step 2)'!$A$22:$A$71, 'V1 Pricing Model (Step 2)'!$W$22:$W$71), 0) ) / $J50, 0)} -> 0.18762795 | P50: {=_xlfn.IFS(B50="At-Risk Churner",$B$2,$B50="Dormant",$B$3,$B50="Deal Hunter",$B$4,$B50="New Customer",$B$5,$B50="Occasional Buyer",$B$6,$B50="Loyal High-Value",$B$7)} -> 70 | Q50: {=_xlfn.IFS($B50 = "At-Risk Churner", $B$8, $B50="Dormant",$B$9, $B50="Deal Hunter", $B$10, $B50="New Customer", $B$11, $B50="Occasional Buyer", $B$12, $B50 = "Loyal High-Value",$B$13)} -> 0.45 | R50: -5 | S50: 10 | T50: 8 | U50: =MIN( $L50 * $B$26 * (1 + $B$28 * LN(MAX($N50, 1))), $B$27 ) -> 15 | V50: =MIN( $B$29 * ABS($O50) + $B$30 * ABS($M50), $B$31 ) -> 7.5051181 | W50: =MIN(MAX( $P50 + $R50 + $S50 + $T50 + $U50 + $V50 + $B$32 * ($R50 * $U50) / 100 + $B$33 * ($P50 * $S50) / 100, 0), 100) -> 100 | X50: {=_xlfn.IFS($W50 <= 30, "Low", $W50 <=50, "Medium", $W50 <= 70, "High", $W50 > 70, "Critical")} -> Critical | Y50: =$Q50 * (1 / (1 + EXP(-($W50 - 50) / $B$34))) -> 0.44698822 | Z50: =_xlfn.LET( _xlpm.full_churn, $Y50 * $I50, _xlpm.partial_rate, IF(OR($X50="Medium", $X50="High"), (1 - $Y50) * 0.5 * $B$35, 0), _xlpm.partial_churn, _xlpm.partial_rate * $I50, _xlpm.full_churn + _xlpm.partial_churn ) -> 119.14918
A51: CUST-2786 | B51: Dormant | C51: Organic Search | D51: UK | E51: 35-44 | F51: Low | G51: 6 | H51: 66 | I51: 84.52 | J51: {=SUMPRODUCT( (Transactions_and_Customer_Information_Joined[Customer ID]='V1-Based Churn Model (Step 3)'!$A51) * (IFERROR(_xlfn.XLOOKUP(Transactions_and_Customer_Information_Joined[SKU], 'V1 Pricing Model (Step 2)'!$A$22:$A$71, 'V1 Pricing Model (Step 2)'!$AL$22:$AL$71), "Exclude")<>"Exclude") * Transactions_and_Customer_Information_Joined[Gross Revenue])} -> 921.63 | K51: =SUMIF(Transactions_and_Customer_Information_Joined[Customer ID], 'V1-Based Churn Model (Step 3)'!$A51, Transactions_and_Customer_Information_Joined[Gross Revenue]) -> 1025.59 | L51: =IFERROR($J51/$K51, 0) -> 0.89863396 | M51: 0.13680891 | N51: {=SUMPRODUCT( (Transactions_and_Customer_Information_Joined[Customer ID]=$A51) * (Transactions_and_Customer_Information_Joined[Order Status]="Completed") * (IFERROR(_xlfn.XLOOKUP(Transactions_and_Customer_Information_Joined[SKU], 'V1 Pricing Model (Step 2)'!$A$22:$A$71, 'V1 Pricing Model (Step 2)'!$AL$22:$AL$71), "Exclude")<>"Exclude"))} -> 2 | O51: {=IFERROR( SUMPRODUCT( (Transactions_and_Customer_Information_Joined[Customer ID]=$A51) * (IFERROR(_xlfn.XLOOKUP(Transactions_and_Customer_Information_Joined[SKU], 'V1 Pricing Model (Step 2)'!$A$22:$A$71, 'V1 Pricing Model (Step 2)'!$AL$22:$AL$71), "Exclude")<>"Exclude") * Transactions_and_Customer_Information_Joined[Gross Revenue] * IFERROR(_xlfn.XLOOKUP(Transactions_and_Customer_Information_Joined[SKU], 'V1 Pricing Model (Step 2)'!$A$22:$A$71, 'V1 Pricing Model (Step 2)'!$W$22:$W$71), 0) ) / $J51, 0)} -> 0.076380921 | P51: {=_xlfn.IFS(B51="At-Risk Churner",$B$2,$B51="Dormant",$B$3,$B51="Deal Hunter",$B$4,$B51="New Customer",$B$5,$B51="Occasional Buyer",$B$6,$B51="Loyal High-Value",$B$7)} -> 65 | Q51: {=_xlfn.IFS($B51 = "At-Risk Churner", $B$8, $B51="Dormant",$B$9, $B51="Deal Hunter", $B$10, $B51="New Customer", $B$11, $B51="Occasional Buyer", $B$12, $B51 = "Loyal High-Value",$B$13)} -> 0.6 | R51: -5 | S51: 0 | T51: 0 | U51: =MIN( $L51 * $B$26 * (1 + $B$28 * LN(MAX($N51, 1))), $B$27 ) -> 15 | V51: =MIN( $B$29 * ABS($O51) + $B$30 * ABS($M51), $B$31 ) -> 4.2637967 | W51: =MIN(MAX( $P51 + $R51 + $S51 + $T51 + $U51 + $V51 + $B$32 * ($R51 * $U51) / 100 + $B$33 * ($P51 * $S51) / 100, 0), 100) -> 79.151297 | X51: {=_xlfn.IFS($W51 <= 30, "Low", $W51 <=50, "Medium", $W51 <= 70, "High", $W51 > 70, "Critical")} -> Critical | Y51: =$Q51 * (1 / (1 + EXP(-($W51 - 50) / $B$34))) -> 0.56915358 | Z51: =_xlfn.LET( _xlpm.full_churn, $Y51 * $I51, _xlpm.partial_rate, IF(OR($X51="Medium", $X51="High"), (1 - $Y51) * 0.5 * $B$35, 0), _xlpm.partial_churn, _xlpm.partial_rate * $I51, _xlpm.full_churn + _xlpm.partial_churn ) -> 48.104861
... A590: CUST-4886 | B590: Occasional Buyer | C590: Referral | D590: West | E590: 35-44 | F590: High | G590: 4 | H590: 81 | I590: 249.71 | J590: {=SUMPRODUCT( (Transactions_and_Customer_Information_Joined[Customer ID]='V1-Based Churn Model (Step 3)'!$A590) * (IFERROR(_xlfn.XLOOKUP(Transactions_and_Customer_Information_Joined[SKU], 'V1 Pricing Model (Step 2)'!$A$22:$A$71, 'V1 Pricing Model (Step 2)'!$AL$22:$AL$71), "Exclude")<>"Exclude") * Transactions_and_Customer_Information_Joined[Gross Revenue])} -> 0 | K590: =SUMIF(Transactions_and_Customer_Information_Joined[Customer ID], 'V1-Based Churn Model (Step 3)'!$A590, Transactions_and_Customer_Information_Joined[Gross Revenue]) -> 163.2 | L590: =IFERROR($J590/$K590, 0) -> 0 | M590: 0 | N590: {=SUMPRODUCT( (Transactions_and_Customer_Information_Joined[Customer ID]=$A590) * (Transactions_and_Customer_Information_Joined[Order Status]="Completed") * (IFERROR(_xlfn.XLOOKUP(Transactions_and_Customer_Information_Joined[SKU], 'V1 Pricing Model (Step 2)'!$A$22:$A$71, 'V1 Pricing Model (Step 2)'!$AL$22:$AL$71), "Exclude")<>"Exclude"))} -> 0 | O590: {=IFERROR( SUMPRODUCT( (Transactions_and_Customer_Information_Joined[Customer ID]=$A590) * (IFERROR(_xlfn.XLOOKUP(Transactions_and_Customer_Information_Joined[SKU], 'V1 Pricing Model (Step 2)'!$A$22:$A$71, 'V1 Pricing Model (Step 2)'!$AL$22:$AL$71), "Exclude")<>"Exclude") * Transactions_and_Customer_Information_Joined[Gross Revenue] * IFERROR(_xlfn.XLOOKUP(Transactions_and_Customer_Information_Joined[SKU], 'V1 Pricing Model (Step 2)'!$A$22:$A$71, 'V1 Pricing Model (Step 2)'!$W$22:$W$71), 0) ) / $J590, 0)} -> 0 | P590: {=_xlfn.IFS(B590="At-Risk Churner",$B$2,$B590="Dormant",$B$3,$B590="Deal Hunter",$B$4,$B590="New Customer",$B$5,$B590="Occasional Buyer",$B$6,$B590="Loyal High-Value",$B$7)} -> 25 | Q590: {=_xlfn.IFS($B590 = "At-Risk Churner", $B$8, $B590="Dormant",$B$9, $B590="Deal Hunter", $B$10, $B590="New Customer", $B$11, $B590="Occasional Buyer", $B$12, $B590 = "Loyal High-Value",$B$13)} -> 0.18 | R590: 15 | S590: 0 | T590: 0 | U590: =MIN( $L590 * $B$26 * (1 + $B$28 * LN(MAX($N590, 1))), $B$27 ) -> 0 | V590: =MIN( $B$29 * ABS($O590) + $B$30 * ABS($M590), $B$31 ) -> 0 | W590: =MIN(MAX( $P590 + $R590 + $S590 + $T590 + $U590 + $V590 + $B$32 * ($R590 * $U590) / 100 + $B$33 * ($P590 * $S590) / 100, 0), 100) -> 40 | X590: {=_xlfn.IFS($W590 <= 30, "Low", $W590 <=50, "Medium", $W590 <= 70, "High", $W590 > 70, "Critical")} -> Medium | Y590: =$Q590 * (1 / (1 + EXP(-($W590 - 50) / $B$34))) -> 0.048409456 | Z590: =_xlfn.LET( _xlpm.full_churn, $Y590 * $I590, _xlpm.partial_rate, IF(OR($X590="Medium", $X590="High"), (1 - $Y590) * 0.5 * $B$35, 0), _xlpm.partial_churn, _xlpm.partial_rate * $I590, _xlpm.full_churn + _xlpm.partial_churn ) -> 59.61266
I4040: =SUM(_xlfn.ANCHORARRAY(I39)) -> 285316.04

Sheet Monte Carlo IO (4)
A1: MONTE CARLO MODEL ASSUMPTIONS | B1: Values | D1: SCENARIOS | E1: GR Weight | F1: GP Weight | G1: LTV Weight
A2: Raise Elasticity | B2: -0.4 | D2: Aggressive Conservative | E2: 0.1 | F2: 0.1 | G2: 0.8
A3: Reduce Elasticity | B3: -0.8 | D3: Conservative | E3: 0.15 | F3: 0.2 | G3: 0.65
A4: Margin Floor | B4: 0.2 | D4: Balanced | E4: 0.25 | F4: 0.35 | G4: 0.4
A5: Minimum Gross Revenue Lift % | B5: 0.05 | D5: Growth | E5: 0.35 | F5: 0.35 | G5: 0.3
A6: Minimum Gross Profit Margin Lift % | B6: 0.02 | D6: Aggressive Growth | E6: 0.2 | F6: 0.55 | G6: 0.25
A7: Quadratic Margin Penalty | B7: 50
A8: LTV Recovery Penalty Multiplier | B8: 2
A9: Grid Step Size % | B9: 0.02
A11: SKU | B11: Product Name | C11: Category | D11: Tie-Breaking Recommendation | E11: Candidate Type | F11: Current Price | G11: Current Cost Per Unit | H11: Current Volume | I11: Current Gross Revenue | J11: Current COGS | K11: Current Gross Profit | L11: Current Gross Profit Margin % | M11: V1 Suggested Price | N11: V1 Difference $ | O11: V1 Difference % | P11: V1 Gross Revenue Impact | Q11: V1 Gross Profit Impact $ | R11: Total Buyers | S11: V1-based Average Churn Score | T11: Average Logistic Churn Rate | U11: Total Buyer LTV | V11: Total LTV at Risk | W11: % Critical | X11: % High | Y11: % Medium | Z11: %Low | AA11: Dominant Tier | AB11: Adjusted Price | AC11: Adjusted Difference $ | AD11: Adjusted Difference % | AE11: Adjusted Volume Change % | AF11: Adjusted Volume | AG11: Adjusted Projected Gross Revenue | AH11: Adjusted Gross Revenue Impact | AI11: Adjusted Gross Revenue Lift | AJ11: Adjusted COGS | AK11: Adjusted COGS Impact | AL11: Adjusted COGS Lift | AM11: Adjusted Gross Profit | AN11: Projected Gross Profit Impact $ | AO11: Projected Gross Profit Lift % | AP11: Projected Gross Profit Margin % | AQ11: Project Gross Profit Margin Impact % | AR11: Projected Gross Profit Margin Lift | AS11: LTV Protected | AT11: LTV Sacrificed | AU11: LTV Protection-Risk Ratio
A12: {=_xlfn._xlws.FILTER(_xlfn.ANCHORARRAY('V1 Pricing Model (Step 2)'!$A$22), 'V1 Pricing Model (Step 2)'!$AL$22:$AL$71<>"Exclude")} -> SKU-1000 | B12: =_xlfn.XLOOKUP($A12,_1_product_catalog_pricing[SKU], _1_product_catalog_pricing[Product Name],,0) -> Wireless Earbuds | C12: =_xlfn.XLOOKUP($A12, _1_product_catalog_pricing[SKU], _1_product_catalog_pricing[Category],,0) -> Electronics | D12: {=_xlfn.XLOOKUP($A12,_xlfn.ANCHORARRAY('V1 Pricing Model (Step 2)'!$A$22), 'V1 Pricing Model (Step 2)'!$T$22:$T$71,,0)} -> Raise | E12: {=_xlfn.XLOOKUP($A12,_xlfn.ANCHORARRAY('V1 Pricing Model (Step 2)'!$A$22), 'V1 Pricing Model (Step 2)'!$AL$22:$AL$71,,0)} -> Full | F12: {=_xlfn.XLOOKUP($A12,_xlfn.ANCHORARRAY('V1 Pricing Model (Step 2)'!$A$22),_xlfn.ANCHORARRAY( 'V1 Pricing Model (Step 2)'!$D$22),,0)} -> 76.53 | G12: {=_xlfn.XLOOKUP($A12,_xlfn.ANCHORARRAY('V1 Pricing Model (Step 2)'!$A$22),_xlfn.ANCHORARRAY( 'V1 Pricing Model (Step 2)'!$E$22),,0)} -> 52.96 | H12: {=_xlfn.XLOOKUP($A12, 'Competitive Analysis (Step 1)'!$A$10:$A$209,_xlfn.ANCHORARRAY( 'Competitive Analysis (Step 1)'!$Q$10),,0)} -> 24 | I12: =$F12*$H12 -> 1836.72 | J12: =$G12*$H12 -> 1271.04 | K12: =$I12-$J12 -> 565.68 | L12: =$K12/$I12 -> 0.3079838 | M12: {=_xlfn.XLOOKUP($A12,_xlfn.ANCHORARRAY('V1 Pricing Model (Step 2)'!$A$22),'V1 Pricing Model (Step 2)'!$U$22:$W$71,,0)} -> 80.606323 | N12: 4.0763228 | O12: 0.053264378 | P12: {=_xlfn.XLOOKUP($A12,_xlfn.ANCHORARRAY( 'V1 Pricing Model (Step 2)'!$A$22), 'V1 Pricing Model (Step 2)'!$AC$22:$AC$71)} -> 17.225425 | Q12: {=_xlfn.XLOOKUP($A12,_xlfn.ANCHORARRAY('V1 Pricing Model (Step 2)'!$A$22),'V1 Pricing Model (Step 2)'!$AI$22:$AI$71,,0)} -> 70.185425 | R12: {=COUNTA(_xlfn.UNIQUE(_xlfn._xlws.FILTER(Transactions_and_Customer_Information_Joined[Customer ID], (Transactions_and_Customer_Information_Joined[SKU]='Monte Carlo IO (4)'!$A12) * (Transactions_and_Customer_Information_Joined[Order Status] = "Completed"), "")))} -> 10 | S12: {=AVERAGE(_xlfn._xlws.FILTER('V1-Based Churn Model (Step 3)'!$W$39:$W$590, ISNUMBER(MATCH('V1-Based Churn Model (Step 3)'!$A$39:$A$590, _xlfn.UNIQUE(_xlfn._xlws.FILTER(Transactions_and_Customer_Information_Joined[Customer ID], (Transactions_and_Customer_Information_Joined[SKU]='Monte Carlo IO (4)'!$A12)* (Transactions_and_Customer_Information_Joined[Order Status]="Completed"))),0))))} -> 70.505262 | T12: {=AVERAGE(_xlfn._xlws.FILTER('V1-Based Churn Model (Step 3)'!$Y$39:$Y$590, ISNUMBER(MATCH('V1-Based Churn Model (Step 3)'!$A$39:$A$590, _xlfn.UNIQUE(_xlfn._xlws.FILTER(Transactions_and_Customer_Information_Joined[Customer ID], (Transactions_and_Customer_Information_Joined[SKU]='Monte Carlo IO (4)'!$A12)* (Transactions_and_Customer_Information_Joined[Order Status]="Completed"))),0))))} -> 0.3181247 | U12: {=SUM(_xlfn._xlws.FILTER('V1-Based Churn Model (Step 3)'!$I$39:$I$590, ISNUMBER(MATCH('V1-Based Churn Model (Step 3)'!$A$39:$A$590, _xlfn.UNIQUE(_xlfn._xlws.FILTER(Transactions_and_Customer_Information_Joined[Customer ID], (Transactions_and_Customer_Information_Joined[SKU]='Monte Carlo IO (4)'!$A12)* (Transactions_and_Customer_Information_Joined[Order Status]="Completed"))),0))))} -> 3841.99 | V12: {=SUM(_xlfn._xlws.FILTER('V1-Based Churn Model (Step 3)'!$Z$39:$Z$590, ISNUMBER(MATCH('V1-Based Churn Model (Step 3)'!$A$39:$A$590, _xlfn.UNIQUE(_xlfn._xlws.FILTER(Transactions_and_Customer_Information_Joined[Customer ID], (Transactions_and_Customer_Information_Joined[SKU]='Monte Carlo IO (4)'!$A12)* (Transactions_and_Customer_Information_Joined[Order Status]="Completed"))),0))))} -> 1112.0932 | W12: {=IFERROR(SUM(_xlfn._xlws.FILTER(('V1-Based Churn Model (Step 3)'!$X$39:$X$4039="Critical")*1, ISNUMBER(MATCH('V1-Based Churn Model (Step 3)'!$A$39:$A$4039, _xlfn.UNIQUE(_xlfn._xlws.FILTER(Transactions_and_Customer_Information_Joined[Customer ID], (Transactions_and_Customer_Information_Joined[SKU]='Monte Carlo IO (4)'!$A12)* (Transactions_and_Customer_Information_Joined[Order Status]="Completed"))),0)))) / $R12, 0)} -> 0.5 | X12: {=IFERROR(SUM(_xlfn._xlws.FILTER(('V1-Based Churn Model (Step 3)'!$X$39:$X$4039="High")*1, ISNUMBER(MATCH('V1-Based Churn Model (Step 3)'!$A$39:$A$4039, _xlfn.UNIQUE(_xlfn._xlws.FILTER(Transactions_and_Customer_Information_Joined[Customer ID], (Transactions_and_Customer_Information_Joined[SKU]='Monte Carlo IO (4)'!$A12)* (Transactions_and_Customer_Information_Joined[Order Status]="Completed"))),0)))) / $R12, 0)} -> 0.3 | Y12: {=IFERROR(SUM(_xlfn._xlws.FILTER(('V1-Based Churn Model (Step 3)'!$X$39:$X$4039="Medium")*1, ISNUMBER(MATCH('V1-Based Churn Model (Step 3)'!$A$39:$A$4039, _xlfn.UNIQUE(_xlfn._xlws.FILTER(Transactions_and_Customer_Information_Joined[Customer ID], (Transactions_and_Customer_Information_Joined[SKU]='Monte Carlo IO (4)'!$A12)* (Transactions_and_Customer_Information_Joined[Order Status]="Completed"))),0)))) / $R12, 0)} -> 0.2 | Z12: {=IFERROR(SUM(_xlfn._xlws.FILTER(('V1-Based Churn Model (Step 3)'!$X$39:$X$4039="Low")*1, ISNUMBER(MATCH('V1-Based Churn Model (Step 3)'!$A$39:$A$4039, _xlfn.UNIQUE(_xlfn._xlws.FILTER(Transactions_and_Customer_Information_Joined[Customer ID], (Transactions_and_Customer_Information_Joined[SKU]='Monte Carlo IO (4)'!$A12)* (Transactions_and_Customer_Information_Joined[Order Status]="Completed"))),0)))) / $R12, 0)} -> 0 | AA12: {=_xlfn.IFS($W12 = MAX($W12:$Z12), "Critical", $X12 = MAX($W12:$Z12), "High", $Y12 = MAX($W12:$Z12), "Medium", $Z12 = MAX($W12:$Z12), "Low")} -> Critical | AB12: {=_xlfn.XLOOKUP($A12, Best_Outcomes[SKU], Best_Outcomes[[Adjusted Price]:[Adjusted Difference %]],,0)} -> 78.975794 | AC12: 2.4457937 | AD12: 0.031958627 | AE12: =$AD12 * IF($D12="Reduce", $B$3, $B$2) -> -0.012783451 | AF12: =$H12-$AE12 -> 24.012783 | AG12: {=_xlfn.XLOOKUP($A12,Best_Outcomes[SKU], Best_Outcomes[[Adjusted Gross Revenue]:[Gross Revenue Lift %]])} -> 1871.1891 | AH12: 34.469053 | AI12: 0.018766635 | AJ12: =$AF12*G$12 -> 1271.717 | AK12: =$AJ12-$J12 -> 0.67701155 | AL12: =$AK12/$J12 -> 0.00053264378 | AM12: {=_xlfn.XLOOKUP($A12,Best_Outcomes[SKU], Best_Outcomes[[Adjusted Gross Profit]:[Gross Profit Margin %]])} -> 616.39733 | AN12: 50.71733 | AO12: 0.08965728 | AP12: 0.32941478 | AQ12: =$AP12-$L12 -> 0.021430983 | AR12: {=_xlfn.XLOOKUP($A12,Best_Outcomes[SKU], Best_Outcomes[[Gross Profit Margin Lift %]:[LTV Protection-Risk Ratio]])} -> 0.021430983 | AS12: 358.09401 | AT12: 537.14101 | AU12: 0.66666667
A13: SKU-1001 | B13: =_xlfn.XLOOKUP($A13,_1_product_catalog_pricing[SKU], _1_product_catalog_pricing[Product Name],,0) -> Bluetooth Speaker | C13: =_xlfn.XLOOKUP($A13, _1_product_catalog_pricing[SKU], _1_product_catalog_pricing[Category],,0) -> Electronics | D13: {=_xlfn.XLOOKUP($A13,_xlfn.ANCHORARRAY('V1 Pricing Model (Step 2)'!$A$22), 'V1 Pricing Model (Step 2)'!$T$22:$T$71,,0)} -> Raise | E13: {=_xlfn.XLOOKUP($A13,_xlfn.ANCHORARRAY('V1 Pricing Model (Step 2)'!$A$22), 'V1 Pricing Model (Step 2)'!$AL$22:$AL$71,,0)} -> Full | F13: {=_xlfn.XLOOKUP($A13,_xlfn.ANCHORARRAY('V1 Pricing Model (Step 2)'!$A$22),_xlfn.ANCHORARRAY( 'V1 Pricing Model (Step 2)'!$D$22),,0)} -> 53.26 | G13: {=_xlfn.XLOOKUP($A13,_xlfn.ANCHORARRAY('V1 Pricing Model (Step 2)'!$A$22),_xlfn.ANCHORARRAY( 'V1 Pricing Model (Step 2)'!$E$22),,0)} -> 36.64 | H13: {=_xlfn.XLOOKUP($A13, 'Competitive Analysis (Step 1)'!$A$10:$A$209,_xlfn.ANCHORARRAY( 'Competitive Analysis (Step 1)'!$Q$10),,0)} -> 21 | I13: =$F13*$H13 -> 1118.46 | J13: =$G13*$H13 -> 769.44 | K13: =$I13-$J13 -> 349.02 | L13: =$K13/$I13 -> 0.31205407 | M13: {=_xlfn.XLOOKUP($A13,_xlfn.ANCHORARRAY('V1 Pricing Model (Step 2)'!$A$22),'V1 Pricing Model (Step 2)'!$U$22:$W$71,,0)} -> 57.563992 | N13: 4.3039918 | O13: 0.080810961 | P13: {=_xlfn.XLOOKUP($A13,_xlfn.ANCHORARRAY( 'V1 Pricing Model (Step 2)'!$A$22), 'V1 Pricing Model (Step 2)'!$AC$22:$AC$71)} -> 32.819836 | Q13: {=_xlfn.XLOOKUP($A13,_xlfn.ANCHORARRAY('V1 Pricing Model (Step 2)'!$A$22),'V1 Pricing Model (Step 2)'!$AI$22:$AI$71,,0)} -> 69.459836 | R13: {=COUNTA(_xlfn.UNIQUE(_xlfn._xlws.FILTER(Transactions_and_Customer_Information_Joined[Customer ID], (Transactions_and_Customer_Information_Joined[SKU]='Monte Carlo IO (4)'!$A13) * (Transactions_and_Customer_Information_Joined[Order Status] = "Completed"), "")))} -> 9 | S13: {=AVERAGE(_xlfn._xlws.FILTER('V1-Based Churn Model (Step 3)'!$W$39:$W$590, ISNUMBER(MATCH('V1-Based Churn Model (Step 3)'!$A$39:$A$590, _xlfn.UNIQUE(_xlfn._xlws.FILTER(Transactions_and_Customer_Information_Joined[Customer ID], (Transactions_and_Customer_Information_Joined[SKU]='Monte Carlo IO (4)'!$A13)* (Transactions_and_Customer_Information_Joined[Order Status]="Completed"))),0))))} -> 66.806056 | T13: {=AVERAGE(_xlfn._xlws.FILTER('V1-Based Churn Model (Step 3)'!$Y$39:$Y$590, ISNUMBER(MATCH('V1-Based Churn Model (Step 3)'!$A$39:$A$590, _xlfn.UNIQUE(_xlfn._xlws.FILTER(Transactions_and_Customer_Information_Joined[Customer ID], (Transactions_and_Customer_Information_Joined[SKU]='Monte Carlo IO (4)'!$A13)* (Transactions_and_Customer_Information_Joined[Order Status]="Completed"))),0))))} -> 0.26336465 | U13: {=SUM(_xlfn._xlws.FILTER('V1-Based Churn Model (Step 3)'!$I$39:$I$590, ISNUMBER(MATCH('V1-Based Churn Model (Step 3)'!$A$39:$A$590, _xlfn.UNIQUE(_xlfn._xlws.FILTER(Transactions_and_Customer_Information_Joined[Customer ID], (Transactions_and_Customer_Information_Joined[SKU]='Monte Carlo IO (4)'!$A13)* (Transactions_and_Customer_Information_Joined[Order Status]="Completed"))),0))))} -> 5045.98 | V13: {=SUM(_xlfn._xlws.FILTER('V1-Based Churn Model (Step 3)'!$Z$39:$Z$590, ISNUMBER(MATCH('V1-Based Churn Model (Step 3)'!$A$39:$A$590, _xlfn.UNIQUE(_xlfn._xlws.FILTER(Transactions_and_Customer_Information_Joined[Customer ID], (Transactions_and_Customer_Information_Joined[SKU]='Monte Carlo IO (4)'!$A13)* (Transactions_and_Customer_Information_Joined[Order Status]="Completed"))),0))))} -> 1487.03 | W13: {=IFERROR(SUM(_xlfn._xlws.FILTER(('V1-Based Churn Model (Step 3)'!$X$39:$X$4039="Critical")*1, ISNUMBER(MATCH('V1-Based Churn Model (Step 3)'!$A$39:$A$4039, _xlfn.UNIQUE(_xlfn._xlws.FILTER(Transactions_and_Customer_Information_Joined[Customer ID], (Transactions_and_Customer_Information_Joined[SKU]='Monte Carlo IO (4)'!$A13)* (Transactions_and_Customer_Information_Joined[Order Status]="Completed"))),0)))) / $R13, 0)} -> 0.33333333 | X13: {=IFERROR(SUM(_xlfn._xlws.FILTER(('V1-Based Churn Model (Step 3)'!$X$39:$X$4039="High")*1, ISNUMBER(MATCH('V1-Based Churn Model (Step 3)'!$A$39:$A$4039, _xlfn.UNIQUE(_xlfn._xlws.FILTER(Transactions_and_Customer_Information_Joined[Customer ID], (Transactions_and_Customer_Information_Joined[SKU]='Monte Carlo IO (4)'!$A13)* (Transactions_and_Customer_Information_Joined[Order Status]="Completed"))),0)))) / $R13, 0)} -> 0.44444444 | Y13: {=IFERROR(SUM(_xlfn._xlws.FILTER(('V1-Based Churn Model (Step 3)'!$X$39:$X$4039="Medium")*1, ISNUMBER(MATCH('V1-Based Churn Model (Step 3)'!$A$39:$A$4039, _xlfn.UNIQUE(_xlfn._xlws.FILTER(Transactions_and_Customer_Information_Joined[Customer ID], (Transactions_and_Customer_Information_Joined[SKU]='Monte Carlo IO (4)'!$A13)* (Transactions_and_Customer_Information_Joined[Order Status]="Completed"))),0)))) / $R13, 0)} -> 0.22222222 | Z13: {=IFERROR(SUM(_xlfn._xlws.FILTER(('V1-Based Churn Model (Step 3)'!$X$39:$X$4039="Low")*1, ISNUMBER(MATCH('V1-Based Churn Model (Step 3)'!$A$39:$A$4039, _xlfn.UNIQUE(_xlfn._xlws.FILTER(Transactions_and_Customer_Information_Joined[Customer ID], (Transactions_and_Customer_Information_Joined[SKU]='Monte Carlo IO (4)'!$A13)* (Transactions_and_Customer_Information_Joined[Order Status]="Completed"))),0)))) / $R13, 0)} -> 0 | AA13: {=_xlfn.IFS($W13 = MAX($W13:$Z13), "Critical", $X13 = MAX($W13:$Z13), "High", $Y13 = MAX($W13:$Z13), "Medium", $Z13 = MAX($W13:$Z13), "Low")} -> High | AB13: {=_xlfn.XLOOKUP($A13, Best_Outcomes[SKU], Best_Outcomes[[Adjusted Price]:[Adjusted Difference %]],,0)} -> 55.842395 | AC13: 2.5823951 | AD13: 0.048486577 | AE13: =$AD13 * IF($D13="Reduce", $B$3, $B$2) -> -0.019394631 | AF13: =$H13-$AE13 -> 21.019395 | AG13: {=_xlfn.XLOOKUP($A13,Best_Outcomes[SKU], Best_Outcomes[[Adjusted Gross Revenue]:[Gross Revenue Lift %]])} -> 1149.9464 | AH13: 31.486401 | AI13: 0.028151567 | AJ13: =$AF13*G$12 -> 1113.1871 | AK13: =$AJ13-$J13 -> 343.74714 | AL13: =$AK13/$J13 -> 0.44674977 | AM13: {=_xlfn.XLOOKUP($A13,Best_Outcomes[SKU], Best_Outcomes[[Adjusted Gross Profit]:[Gross Profit Margin %]])} -> 395.42941 | AN13: 46.409406 | AO13: 0.13297062 | AP13: 0.34386768 | AQ13: =$AP13-$L13 -> 0.03181361 | AR13: {=_xlfn.XLOOKUP($A13,Best_Outcomes[SKU], Best_Outcomes[[Gross Profit Margin Lift %]:[LTV Protection-Risk Ratio]])} -> 0.03181361 | AS13: 449.41351 | AT13: 674.12027 | AU13: 0.66666667
A14: SKU-1004 | B14: =_xlfn.XLOOKUP($A14,_1_product_catalog_pricing[SKU], _1_product_catalog_pricing[Product Name],,0) -> USB-C Hub | C14: =_xlfn.XLOOKUP($A14, _1_product_catalog_pricing[SKU], _1_product_catalog_pricing[Category],,0) -> Electronics | D14: {=_xlfn.XLOOKUP($A14,_xlfn.ANCHORARRAY('V1 Pricing Model (Step 2)'!$A$22), 'V1 Pricing Model (Step 2)'!$T$22:$T$71,,0)} -> Hold | E14: {=_xlfn.XLOOKUP($A14,_xlfn.ANCHORARRAY('V1 Pricing Model (Step 2)'!$A$22), 'V1 Pricing Model (Step 2)'!$AL$22:$AL$71,,0)} -> Full | F14: {=_xlfn.XLOOKUP($A14,_xlfn.ANCHORARRAY('V1 Pricing Model (Step 2)'!$A$22),_xlfn.ANCHORARRAY( 'V1 Pricing Model (Step 2)'!$D$22),,0)} -> 18.39 | G14: {=_xlfn.XLOOKUP($A14,_xlfn.ANCHORARRAY('V1 Pricing Model (Step 2)'!$A$22),_xlfn.ANCHORARRAY( 'V1 Pricing Model (Step 2)'!$E$22),,0)} -> 8.26 | H14: {=_xlfn.XLOOKUP($A14, 'Competitive Analysis (Step 1)'!$A$10:$A$209,_xlfn.ANCHORARRAY( 'Competitive Analysis (Step 1)'!$Q$10),,0)} -> 17 | I14: =$F14*$H14 -> 312.63 | J14: =$G14*$H14 -> 140.42 | K14: =$I14-$J14 -> 172.21 | L14: =$K14/$I14 -> 0.55084285 | M14: {=_xlfn.XLOOKUP($A14,_xlfn.ANCHORARRAY('V1 Pricing Model (Step 2)'!$A$22),'V1 Pricing Model (Step 2)'!$U$22:$W$71,,0)} -> 20.325622 | N14: 1.9356217 | O14: 0.10525403 | P14: {=_xlfn.XLOOKUP($A14,_xlfn.ANCHORARRAY( 'V1 Pricing Model (Step 2)'!$A$22), 'V1 Pricing Model (Step 2)'!$AC$22:$AC$71)} -> 12.579946 | Q14: {=_xlfn.XLOOKUP($A14,_xlfn.ANCHORARRAY('V1 Pricing Model (Step 2)'!$A$22),'V1 Pricing Model (Step 2)'!$AI$22:$AI$71,,0)} -> 20.839946 | R14: {=COUNTA(_xlfn.UNIQUE(_xlfn._xlws.FILTER(Transactions_and_Customer_Information_Joined[Customer ID], (Transactions_and_Customer_Information_Joined[SKU]='Monte Carlo IO (4)'!$A14) * (Transactions_and_Customer_Information_Joined[Order Status] = "Completed"), "")))} -> 9 | S14: {=AVERAGE(_xlfn._xlws.FILTER('V1-Based Churn Model (Step 3)'!$W$39:$W$590, ISNUMBER(MATCH('V1-Based Churn Model (Step 3)'!$A$39:$A$590, _xlfn.UNIQUE(_xlfn._xlws.FILTER(Transactions_and_Customer_Information_Joined[Customer ID], (Transactions_and_Customer_Information_Joined[SKU]='Monte Carlo IO (4)'!$A14)* (Transactions_and_Customer_Information_Joined[Order Status]="Completed"))),0))))} -> 68.467577 | T14: {=AVERAGE(_xlfn._xlws.FILTER('V1-Based Churn Model (Step 3)'!$Y$39:$Y$590, ISNUMBER(MATCH('V1-Based Churn Model (Step 3)'!$A$39:$A$590, _xlfn.UNIQUE(_xlfn._xlws.FILTER(Transactions_and_Customer_Information_Joined[Customer ID], (Transactions_and_Customer_Information_Joined[SKU]='Monte Carlo IO (4)'!$A14)* (Transactions_and_Customer_Information_Joined[Order Status]="Completed"))),0))))} -> 0.2519532 | U14: {=SUM(_xlfn._xlws.FILTER('V1-Based Churn Model (Step 3)'!$I$39:$I$590, ISNUMBER(MATCH('V1-Based Churn Model (Step 3)'!$A$39:$A$590, _xlfn.UNIQUE(_xlfn._xlws.FILTER(Transactions_and_Customer_Information_Joined[Customer ID], (Transactions_and_Customer_Information_Joined[SKU]='Monte Carlo IO (4)'!$A14)* (Transactions_and_Customer_Information_Joined[Order Status]="Completed"))),0))))} -> 6058.75 | V14: {=SUM(_xlfn._xlws.FILTER('V1-Based Churn Model (Step 3)'!$Z$39:$Z$590, ISNUMBER(MATCH('V1-Based Churn Model (Step 3)'!$A$39:$A$590, _xlfn.UNIQUE(_xlfn._xlws.FILTER(Transactions_and_Customer_Information_Joined[Customer ID], (Transactions_and_Customer_Information_Joined[SKU]='Monte Carlo IO (4)'!$A14)* (Transactions_and_Customer_Information_Joined[Order Status]="Completed"))),0))))} -> 1216.0707 | W14: {=IFERROR(SUM(_xlfn._xlws.FILTER(('V1-Based Churn Model (Step 3)'!$X$39:$X$4039="Critical")*1, ISNUMBER(MATCH('V1-Based Churn Model (Step 3)'!$A$39:$A$4039, _xlfn.UNIQUE(_xlfn._xlws.FILTER(Transactions_and_Customer_Information_Joined[Customer ID], (Transactions_and_Customer_Information_Joined[SKU]='Monte Carlo IO (4)'!$A14)* (Transactions_and_Customer_Information_Joined[Order Status]="Completed"))),0)))) / $R14, 0)} -> 0.55555556 | X14: {=IFERROR(SUM(_xlfn._xlws.FILTER(('V1-Based Churn Model (Step 3)'!$X$39:$X$4039="High")*1, ISNUMBER(MATCH('V1-Based Churn Model (Step 3)'!$A$39:$A$4039, _xlfn.UNIQUE(_xlfn._xlws.FILTER(Transactions_and_Customer_Information_Joined[Customer ID], (Transactions_and_Customer_Information_Joined[SKU]='Monte Carlo IO (4)'!$A14)* (Transactions_and_Customer_Information_Joined[Order Status]="Completed"))),0)))) / $R14, 0)} -> 0.11111111 | Y14: {=IFERROR(SUM(_xlfn._xlws.FILTER(('V1-Based Churn Model (Step 3)'!$X$39:$X$4039="Medium")*1, ISNUMBER(MATCH('V1-Based Churn Model (Step 3)'!$A$39:$A$4039, _xlfn.UNIQUE(_xlfn._xlws.FILTER(Transactions_and_Customer_Information_Joined[Customer ID], (Transactions_and_Customer_Information_Joined[SKU]='Monte Carlo IO (4)'!$A14)* (Transactions_and_Customer_Information_Joined[Order Status]="Completed"))),0)))) / $R14, 0)} -> 0.33333333 | Z14: {=IFERROR(SUM(_xlfn._xlws.FILTER(('V1-Based Churn Model (Step 3)'!$X$39:$X$4039="Low")*1, ISNUMBER(MATCH('V1-Based Churn Model (Step 3)'!$A$39:$A$4039, _xlfn.UNIQUE(_xlfn._xlws.FILTER(Transactions_and_Customer_Information_Joined[Customer ID], (Transactions_and_Customer_Information_Joined[SKU]='Monte Carlo IO (4)'!$A14)* (Transactions_and_Customer_Information_Joined[Order Status]="Completed"))),0)))) / $R14, 0)} -> 0 | AA14: {=_xlfn.IFS($W14 = MAX($W14:$Z14), "Critical", $X14 = MAX($W14:$Z14), "High", $Y14 = MAX($W14:$Z14), "Medium", $Z14 = MAX($W14:$Z14), "Low")} -> Critical | AB14: {=_xlfn.XLOOKUP($A14, Best_Outcomes[SKU], Best_Outcomes[[Adjusted Price]:[Adjusted Difference %]],,0)} -> 19.551373 | AC14: 1.161373 | AD14: 0.063152419 | AE14: =$AD14 * IF($D14="Reduce", $B$3, $B$2) -> -0.025260968 | AF14: =$H14-$AE14 -> 17.025261 | AG14: {=_xlfn.XLOOKUP($A14,Best_Outcomes[SKU], Best_Outcomes[[Adjusted Gross Revenue]:[Gross Revenue Lift %]])} -> 323.97727 | AH14: 11.347269 | AI14: 0.03629616 | AJ14: =$AF14*G$12 -> 901.65782 | AK14: =$AJ14-$J14 -> 761.23782 | AL14: =$AK14/$J14 -> 5.4211496 | AM14: {=_xlfn.XLOOKUP($A14,Best_Outcomes[SKU], Best_Outcomes[[Adjusted Gross Profit]:[Gross Profit Margin %]])} -> 187.10441 | AN14: 14.894414 | AO14: 0.086489831 | AP14: 0.57752328 | AQ14: =$AP14-$L14 -> 0.026680427 | AR14: {=_xlfn.XLOOKUP($A14,Best_Outcomes[SKU], Best_Outcomes[[Gross Profit Margin Lift %]:[LTV Protection-Risk Ratio]])} -> 0.026680427 | AS14: 375.63072 | AT14: 563.44608 | AU14: 0.66666667
A15: SKU-1005 | B15: =_xlfn.XLOOKUP($A15,_1_product_catalog_pricing[SKU], _1_product_catalog_pricing[Product Name],,0) -> Webcam | C15: =_xlfn.XLOOKUP($A15, _1_product_catalog_pricing[SKU], _1_product_catalog_pricing[Category],,0) -> Electronics | D15: {=_xlfn.XLOOKUP($A15,_xlfn.ANCHORARRAY('V1 Pricing Model (Step 2)'!$A$22), 'V1 Pricing Model (Step 2)'!$T$22:$T$71,,0)} -> Raise | E15: {=_xlfn.XLOOKUP($A15,_xlfn.ANCHORARRAY('V1 Pricing Model (Step 2)'!$A$22), 'V1 Pricing Model (Step 2)'!$AL$22:$AL$71,,0)} -> Full | F15: {=_xlfn.XLOOKUP($A15,_xlfn.ANCHORARRAY('V1 Pricing Model (Step 2)'!$A$22),_xlfn.ANCHORARRAY( 'V1 Pricing Model (Step 2)'!$D$22),,0)} -> 29.62 | G15: {=_xlfn.XLOOKUP($A15,_xlfn.ANCHORARRAY('V1 Pricing Model (Step 2)'!$A$22),_xlfn.ANCHORARRAY( 'V1 Pricing Model (Step 2)'!$E$22),,0)} -> 19.42 | H15: {=_xlfn.XLOOKUP($A15, 'Competitive Analysis (Step 1)'!$A$10:$A$209,_xlfn.ANCHORARRAY( 'Competitive Analysis (Step 1)'!$Q$10),,0)} -> 46 | I15: =$F15*$H15 -> 1362.52 | J15: =$G15*$H15 -> 893.32 | K15: =$I15-$J15 -> 469.2 | L15: =$K15/$I15 -> 0.34436192 | M15: {=_xlfn.XLOOKUP($A15,_xlfn.ANCHORARRAY('V1 Pricing Model (Step 2)'!$A$22),'V1 Pricing Model (Step 2)'!$U$22:$W$71,,0)} -> 28.258195 | N15: -1.3618047 | O15: -0.045975852 | P15: {=_xlfn.XLOOKUP($A15,_xlfn.ANCHORARRAY( 'V1 Pricing Model (Step 2)'!$A$22), 'V1 Pricing Model (Step 2)'!$AC$22:$AC$71)} -> 110.97518 | Q15: {=_xlfn.XLOOKUP($A15,_xlfn.ANCHORARRAY('V1 Pricing Model (Step 2)'!$A$22),'V1 Pricing Model (Step 2)'!$AI$22:$AI$71,,0)} -> 91.555177 | R15: {=COUNTA(_xlfn.UNIQUE(_xlfn._xlws.FILTER(Transactions_and_Customer_Information_Joined[Customer ID], (Transactions_and_Customer_Information_Joined[SKU]='Monte Carlo IO (4)'!$A15) * (Transactions_and_Customer_Information_Joined[Order Status] = "Completed"), "")))} -> 17 | S15: {=AVERAGE(_xlfn._xlws.FILTER('V1-Based Churn Model (Step 3)'!$W$39:$W$590, ISNUMBER(MATCH('V1-Based Churn Model (Step 3)'!$A$39:$A$590, _xlfn.UNIQUE(_xlfn._xlws.FILTER(Transactions_and_Customer_Information_Joined[Customer ID], (Transactions_and_Customer_Information_Joined[SKU]='Monte Carlo IO (4)'!$A15)* (Transactions_and_Customer_Information_Joined[Order Status]="Completed"))),0))))} -> 67.88689 | T15: {=AVERAGE(_xlfn._xlws.FILTER('V1-Based Churn Model (Step 3)'!$Y$39:$Y$590, ISNUMBER(MATCH('V1-Based Churn Model (Step 3)'!$A$39:$A$590, _xlfn.UNIQUE(_xlfn._xlws.FILTER(Transactions_and_Customer_Information_Joined[Customer ID], (Transactions_and_Customer_Information_Joined[SKU]='Monte Carlo IO (4)'!$A15)* (Transactions_and_Customer_Information_Joined[Order Status]="Completed"))),0))))} -> 0.2662507 | U15: {=SUM(_xlfn._xlws.FILTER('V1-Based Churn Model (Step 3)'!$I$39:$I$590, ISNUMBER(MATCH('V1-Based Churn Model (Step 3)'!$A$39:$A$590, _xlfn.UNIQUE(_xlfn._xlws.FILTER(Transactions_and_Customer_Information_Joined[Customer ID], (Transactions_and_Customer_Information_Joined[SKU]='Monte Carlo IO (4)'!$A15)* (Transactions_and_Customer_Information_Joined[Order Status]="Completed"))),0))))} -> 3551.52 | V15: {=SUM(_xlfn._xlws.FILTER('V1-Based Churn Model (Step 3)'!$Z$39:$Z$590, ISNUMBER(MATCH('V1-Based Churn Model (Step 3)'!$A$39:$A$590, _xlfn.UNIQUE(_xlfn._xlws.FILTER(Transactions_and_Customer_Information_Joined[Customer ID], (Transactions_and_Customer_Information_Joined[SKU]='Monte Carlo IO (4)'!$A15)* (Transactions_and_Customer_Information_Joined[Order Status]="Completed"))),0))))} -> 1171.8239 | W15: {=IFERROR(SUM(_xlfn._xlws.FILTER(('V1-Based Churn Model (Step 3)'!$X$39:$X$4039="Critical")*1, ISNUMBER(MATCH('V1-Based Churn Model (Step 3)'!$A$39:$A$4039, _xlfn.UNIQUE(_xlfn._xlws.FILTER(Transactions_and_Customer_Information_Joined[Customer ID], (Transactions_and_Customer_Information_Joined[SKU]='Monte Carlo IO (4)'!$A15)* (Transactions_and_Customer_Information_Joined[Order Status]="Completed"))),0)))) / $R15, 0)} -> 0.41176471 | X15: {=IFERROR(SUM(_xlfn._xlws.FILTER(('V1-Based Churn Model (Step 3)'!$X$39:$X$4039="High")*1, ISNUMBER(MATCH('V1-Based Churn Model (Step 3)'!$A$39:$A$4039, _xlfn.UNIQUE(_xlfn._xlws.FILTER(Transactions_and_Customer_Information_Joined[Customer ID], (Transactions_and_Customer_Information_Joined[SKU]='Monte Carlo IO (4)'!$A15)* (Transactions_and_Customer_Information_Joined[Order Status]="Completed"))),0)))) / $R15, 0)} -> 0.41176471 | Y15: {=IFERROR(SUM(_xlfn._xlws.FILTER(('V1-Based Churn Model (Step 3)'!$X$39:$X$4039="Medium")*1, ISNUMBER(MATCH('V1-Based Churn Model (Step 3)'!$A$39:$A$4039, _xlfn.UNIQUE(_xlfn._xlws.FILTER(Transactions_and_Customer_Information_Joined[Customer ID], (Transactions_and_Customer_Information_Joined[SKU]='Monte Carlo IO (4)'!$A15)* (Transactions_and_Customer_Information_Joined[Order Status]="Completed"))),0)))) / $R15, 0)} -> 0.17647059 | Z15: {=IFERROR(SUM(_xlfn._xlws.FILTER(('V1-Based Churn Model (Step 3)'!$X$39:$X$4039="Low")*1, ISNUMBER(MATCH('V1-Based Churn Model (Step 3)'!$A$39:$A$4039, _xlfn.UNIQUE(_xlfn._xlws.FILTER(Transactions_and_Customer_Information_Joined[Customer ID], (Transactions_and_Customer_Information_Joined[SKU]='Monte Carlo IO (4)'!$A15)* (Transactions_and_Customer_Information_Joined[Order Status]="Completed"))),0)))) / $R15, 0)} -> 0 | AA15: {=_xlfn.IFS($W15 = MAX($W15:$Z15), "Critical", $X15 = MAX($W15:$Z15), "High", $Y15 = MAX($W15:$Z15), "Medium", $Z15 = MAX($W15:$Z15), "Low")} -> Critical | AB15: {=_xlfn.XLOOKUP($A15, Best_Outcomes[SKU], Best_Outcomes[[Adjusted Price]:[Adjusted Difference %]],,0)} -> 29.62 | AC15: 0 | AD15: 0 | AE15: =$AD15 * IF($D15="Reduce", $B$3, $B$2) -> 0 | AF15: =$H15-$AE15 -> 46 | AG15: {=_xlfn.XLOOKUP($A15,Best_Outcomes[SKU], Best_Outcomes[[Adjusted Gross Revenue]:[Gross Revenue Lift %]])} -> 1362.52 | AH15: 0 | AI15: 0 | AJ15: =$AF15*G$12 -> 2436.16 | AK15: =$AJ15-$J15 -> 1542.84 | AL15: =$AK15/$J15 -> 1.7270855 | AM15: {=_xlfn.XLOOKUP($A15,Best_Outcomes[SKU], Best_Outcomes[[Adjusted Gross Profit]:[Gross Profit Margin %]])} -> 469.2 | AN15: 0 | AO15: 0 | AP15: 0.34436192 | AQ15: =$AP15-$L15 -> 0 | AR15: {=_xlfn.XLOOKUP($A15,Best_Outcomes[SKU], Best_Outcomes[[Gross Profit Margin Lift %]:[LTV Protection-Risk Ratio]])} -> 0 | AS15: 927.1195 | AT15: 0 | AU15: 0
A16: SKU-1006 | B16: =_xlfn.XLOOKUP($A16,_1_product_catalog_pricing[SKU], _1_product_catalog_pricing[Product Name],,0) -> Mechanical Keyboard | C16: =_xlfn.XLOOKUP($A16, _1_product_catalog_pricing[SKU], _1_product_catalog_pricing[Category],,0) -> Electronics | D16: {=_xlfn.XLOOKUP($A16,_xlfn.ANCHORARRAY('V1 Pricing Model (Step 2)'!$A$22), 'V1 Pricing Model (Step 2)'!$T$22:$T$71,,0)} -> Hold | E16: {=_xlfn.XLOOKUP($A16,_xlfn.ANCHORARRAY('V1 Pricing Model (Step 2)'!$A$22), 'V1 Pricing Model (Step 2)'!$AL$22:$AL$71,,0)} -> Full | F16: {=_xlfn.XLOOKUP($A16,_xlfn.ANCHORARRAY('V1 Pricing Model (Step 2)'!$A$22),_xlfn.ANCHORARRAY( 'V1 Pricing Model (Step 2)'!$D$22),,0)} -> 113.18 | G16: {=_xlfn.XLOOKUP($A16,_xlfn.ANCHORARRAY('V1 Pricing Model (Step 2)'!$A$22),_xlfn.ANCHORARRAY( 'V1 Pricing Model (Step 2)'!$E$22),,0)} -> 39.01 | H16: {=_xlfn.XLOOKUP($A16, 'Competitive Analysis (Step 1)'!$A$10:$A$209,_xlfn.ANCHORARRAY( 'Competitive Analysis (Step 1)'!$Q$10),,0)} -> 24 | I16: =$F16*$H16 -> 2716.32 | J16: =$G16*$H16 -> 936.24 | K16: =$I16-$J16 -> 1780.08 | L16: =$K16/$I16 -> 0.6553278 | M16: {=_xlfn.XLOOKUP($A16,_xlfn.ANCHORARRAY('V1 Pricing Model (Step 2)'!$A$22),'V1 Pricing Model (Step 2)'!$U$22:$W$71,,0)} -> 122.07351 | N16: 8.8935122 | O16: 0.078578479 | P16: {=_xlfn.XLOOKUP($A16,_xlfn.ANCHORARRAY( 'V1 Pricing Model (Step 2)'!$A$22), 'V1 Pricing Model (Step 2)'!$AC$22:$AC$71)} -> 91.370781 | Q16: {=_xlfn.XLOOKUP($A16,_xlfn.ANCHORARRAY('V1 Pricing Model (Step 2)'!$A$22),'V1 Pricing Model (Step 2)'!$AI$22:$AI$71,,0)} -> 130.38078 | R16: {=COUNTA(_xlfn.UNIQUE(_xlfn._xlws.FILTER(Transactions_and_Customer_Information_Joined[Customer ID], (Transactions_and_Customer_Information_Joined[SKU]='Monte Carlo IO (4)'!$A16) * (Transactions_and_Customer_Information_Joined[Order Status] = "Completed"), "")))} -> 10 | S16: {=AVERAGE(_xlfn._xlws.FILTER('V1-Based Churn Model (Step 3)'!$W$39:$W$590, ISNUMBER(MATCH('V1-Based Churn Model (Step 3)'!$A$39:$A$590, _xlfn.UNIQUE(_xlfn._xlws.FILTER(Transactions_and_Customer_Information_Joined[Customer ID], (Transactions_and_Customer_Information_Joined[SKU]='Monte Carlo IO (4)'!$A16)* (Transactions_and_Customer_Information_Joined[Order Status]="Completed"))),0))))} -> 63.379342 | T16: {=AVERAGE(_xlfn._xlws.FILTER('V1-Based Churn Model (Step 3)'!$Y$39:$Y$590, ISNUMBER(MATCH('V1-Based Churn Model (Step 3)'!$A$39:$A$590, _xlfn.UNIQUE(_xlfn._xlws.FILTER(Transactions_and_Customer_Information_Joined[Customer ID], (Transactions_and_Customer_Information_Joined[SKU]='Monte Carlo IO (4)'!$A16)* (Transactions_and_Customer_Information_Joined[Order Status]="Completed"))),0))))} -> 0.1953265 | U16: {=SUM(_xlfn._xlws.FILTER('V1-Based Churn Model (Step 3)'!$I$39:$I$590, ISNUMBER(MATCH('V1-Based Churn Model (Step 3)'!$A$39:$A$590, _xlfn.UNIQUE(_xlfn._xlws.FILTER(Transactions_and_Customer_Information_Joined[Customer ID], (Transactions_and_Customer_Information_Joined[SKU]='Monte Carlo IO (4)'!$A16)* (Transactions_and_Customer_Information_Joined[Order Status]="Completed"))),0))))} -> 8331.72 | V16: {=SUM(_xlfn._xlws.FILTER('V1-Based Churn Model (Step 3)'!$Z$39:$Z$590, ISNUMBER(MATCH('V1-Based Churn Model (Step 3)'!$A$39:$A$590, _xlfn.UNIQUE(_xlfn._xlws.FILTER(Transactions_and_Customer_Information_Joined[Customer ID], (Transactions_and_Customer_Information_Joined[SKU]='Monte Carlo IO (4)'!$A16)* (Transactions_and_Customer_Information_Joined[Order Status]="Completed"))),0))))} -> 1378.1368 | W16: {=IFERROR(SUM(_xlfn._xlws.FILTER(('V1-Based Churn Model (Step 3)'!$X$39:$X$4039="Critical")*1, ISNUMBER(MATCH('V1-Based Churn Model (Step 3)'!$A$39:$A$4039, _xlfn.UNIQUE(_xlfn._xlws.FILTER(Transactions_and_Customer_Information_Joined[Customer ID], (Transactions_and_Customer_Information_Joined[SKU]='Monte Carlo IO (4)'!$A16)* (Transactions_and_Customer_Information_Joined[Order Status]="Completed"))),0)))) / $R16, 0)} -> 0.4 | X16: {=IFERROR(SUM(_xlfn._xlws.FILTER(('V1-Based Churn Model (Step 3)'!$X$39:$X$4039="High")*1, ISNUMBER(MATCH('V1-Based Churn Model (Step 3)'!$A$39:$A$4039, _xlfn.UNIQUE(_xlfn._xlws.FILTER(Transactions_and_Customer_Information_Joined[Customer ID], (Transactions_and_Customer_Information_Joined[SKU]='Monte Carlo IO (4)'!$A16)* (Transactions_and_Customer_Information_Joined[Order Status]="Completed"))),0)))) / $R16, 0)} -> 0.3 | Y16: {=IFERROR(SUM(_xlfn._xlws.FILTER(('V1-Based Churn Model (Step 3)'!$X$39:$X$4039="Medium")*1, ISNUMBER(MATCH('V1-Based Churn Model (Step 3)'!$A$39:$A$4039, _xlfn.UNIQUE(_xlfn._xlws.FILTER(Transactions_and_Customer_Information_Joined[Customer ID], (Transactions_and_Customer_Information_Joined[SKU]='Monte Carlo IO (4)'!$A16)* (Transactions_and_Customer_Information_Joined[Order Status]="Completed"))),0)))) / $R16, 0)} -> 0.2 | Z16: {=IFERROR(SUM(_xlfn._xlws.FILTER(('V1-Based Churn Model (Step 3)'!$X$39:$X$4039="Low")*1, ISNUMBER(MATCH('V1-Based Churn Model (Step 3)'!$A$39:$A$4039, _xlfn.UNIQUE(_xlfn._xlws.FILTER(Transactions_and_Customer_Information_Joined[Customer ID], (Transactions_and_Customer_Information_Joined[SKU]='Monte Carlo IO (4)'!$A16)* (Transactions_and_Customer_Information_Joined[Order Status]="Completed"))),0)))) / $R16, 0)} -> 0.1 | AA16: {=_xlfn.IFS($W16 = MAX($W16:$Z16), "Critical", $X16 = MAX($W16:$Z16), "High", $Y16 = MAX($W16:$Z16), "Medium", $Z16 = MAX($W16:$Z16), "Low")} -> Critical | AB16: {=_xlfn.XLOOKUP($A16, Best_Outcomes[SKU], Best_Outcomes[[Adjusted Price]:[Adjusted Difference %]],,0)} -> 118.51611 | AC16: 5.3361073 | AD16: 0.047147087 | AE16: =$AD16 * IF($D16="Reduce", $B$3, $B$2) -> -0.018858835 | AF16: =$H16-$AE16 -> 24.018859 | AG16: {=_xlfn.XLOOKUP($A16,Best_Outcomes[SKU], Best_Outcomes[[Adjusted Gross Revenue]:[Gross Revenue Lift %]])} -> 2790.7448 | AH16: 74.424759 | AI16: 0.027399113 | AJ16: =$AF16*G$12 -> 1272.0388 | AK16: =$AJ16-$J16 -> 335.79876 | AL16: =$AK16/$J16 -> 0.3586674 | AM16: {=_xlfn.XLOOKUP($A16,Best_Outcomes[SKU], Best_Outcomes[[Adjusted Gross Profit]:[Gross Profit Margin %]])} -> 1872.1612 | AN16: 92.081155 | AO16: 0.051728661 | AP16: 0.67084643 | AQ16: =$AP16-$L16 -> 0.015518632 | AR16: {=_xlfn.XLOOKUP($A16,Best_Outcomes[SKU], Best_Outcomes[[Gross Profit Margin Lift %]:[LTV Protection-Risk Ratio]])} -> 0.015518632 | AS16: 396.9034 | AT16: 595.3551 | AU16: 0.66666667
A17: SKU-1009 | B17: =_xlfn.XLOOKUP($A17,_1_product_catalog_pricing[SKU], _1_product_catalog_pricing[Product Name],,0) -> Phone Stand | C17: =_xlfn.XLOOKUP($A17, _1_product_catalog_pricing[SKU], _1_product_catalog_pricing[Category],,0) -> Electronics | D17: {=_xlfn.XLOOKUP($A17,_xlfn.ANCHORARRAY('V1 Pricing Model (Step 2)'!$A$22), 'V1 Pricing Model (Step 2)'!$T$22:$T$71,,0)} -> Raise | E17: {=_xlfn.XLOOKUP($A17,_xlfn.ANCHORARRAY('V1 Pricing Model (Step 2)'!$A$22), 'V1 Pricing Model (Step 2)'!$AL$22:$AL$71,,0)} -> Full | F17: {=_xlfn.XLOOKUP($A17,_xlfn.ANCHORARRAY('V1 Pricing Model (Step 2)'!$A$22),_xlfn.ANCHORARRAY( 'V1 Pricing Model (Step 2)'!$D$22),,0)} -> 177.91 | G17: {=_xlfn.XLOOKUP($A17,_xlfn.ANCHORARRAY('V1 Pricing Model (Step 2)'!$A$22),_xlfn.ANCHORARRAY( 'V1 Pricing Model (Step 2)'!$E$22),,0)} -> 73.49 | H17: {=_xlfn.XLOOKUP($A17, 'Competitive Analysis (Step 1)'!$A$10:$A$209,_xlfn.ANCHORARRAY( 'Competitive Analysis (Step 1)'!$Q$10),,0)} -> 36 | I17: =$F17*$H17 -> 6404.76 | J17: =$G17*$H17 -> 2645.64 | K17: =$I17-$J17 -> 3759.12 | L17: =$K17/$I17 -> 0.58692597 | M17: {=_xlfn.XLOOKUP($A17,_xlfn.ANCHORARRAY('V1 Pricing Model (Step 2)'!$A$22),'V1 Pricing Model (Step 2)'!$U$22:$W$71,,0)} -> 210.36242 | N17: 32.452421 | O17: 0.1824092 | P17: {=_xlfn.XLOOKUP($A17,_xlfn.ANCHORARRAY( 'V1 Pricing Model (Step 2)'!$A$22), 'V1 Pricing Model (Step 2)'!$AC$22:$AC$71)} -> 2118.3199 | Q17: {=_xlfn.XLOOKUP($A17,_xlfn.ANCHORARRAY('V1 Pricing Model (Step 2)'!$A$22),'V1 Pricing Model (Step 2)'!$AI$22:$AI$71,,0)} -> 2338.7899 | R17: {=COUNTA(_xlfn.UNIQUE(_xlfn._xlws.FILTER(Transactions_and_Customer_Information_Joined[Customer ID], (Transactions_and_Customer_Information_Joined[SKU]='Monte Carlo IO (4)'!$A17) * (Transactions_and_Customer_Information_Joined[Order Status] = "Completed"), "")))} -> 12 | S17: {=AVERAGE(_xlfn._xlws.FILTER('V1-Based Churn Model (Step 3)'!$W$39:$W$590, ISNUMBER(MATCH('V1-Based Churn Model (Step 3)'!$A$39:$A$590, _xlfn.UNIQUE(_xlfn._xlws.FILTER(Transactions_and_Customer_Information_Joined[Customer ID], (Transactions_and_Customer_Information_Joined[SKU]='Monte Carlo IO (4)'!$A17)* (Transactions_and_Customer_Information_Joined[Order Status]="Completed"))),0))))} -> 72.583716 | T17: {=AVERAGE(_xlfn._xlws.FILTER('V1-Based Churn Model (Step 3)'!$Y$39:$Y$590, ISNUMBER(MATCH('V1-Based Churn Model (Step 3)'!$A$39:$A$590, _xlfn.UNIQUE(_xlfn._xlws.FILTER(Transactions_and_Customer_Information_Joined[Customer ID], (Transactions_and_Customer_Information_Joined[SKU]='Monte Carlo IO (4)'!$A17)* (Transactions_and_Customer_Information_Joined[Order Status]="Completed"))),0))))} -> 0.2476082 | U17: {=SUM(_xlfn._xlws.FILTER('V1-Based Churn Model (Step 3)'!$I$39:$I$590, ISNUMBER(MATCH('V1-Based Churn Model (Step 3)'!$A$39:$A$590, _xlfn.UNIQUE(_xlfn._xlws.FILTER(Transactions_and_Customer_Information_Joined[Customer ID], (Transactions_and_Customer_Information_Joined[SKU]='Monte Carlo IO (4)'!$A17)* (Transactions_and_Customer_Information_Joined[Order Status]="Completed"))),0))))} -> 9553.98 | V17: {=SUM(_xlfn._xlws.FILTER('V1-Based Churn Model (Step 3)'!$Z$39:$Z$590, ISNUMBER(MATCH('V1-Based Churn Model (Step 3)'!$A$39:$A$590, _xlfn.UNIQUE(_xlfn._xlws.FILTER(Transactions_and_Customer_Information_Joined[Customer ID], (Transactions_and_Customer_Information_Joined[SKU]='Monte Carlo IO (4)'!$A17)* (Transactions_and_Customer_Information_Joined[Order Status]="Completed"))),0))))} -> 1987.1738 | W17: {=IFERROR(SUM(_xlfn._xlws.FILTER(('V1-Based Churn Model (Step 3)'!$X$39:$X$4039="Critical")*1, ISNUMBER(MATCH('V1-Based Churn Model (Step 3)'!$A$39:$A$4039, _xlfn.UNIQUE(_xlfn._xlws.FILTER(Transactions_and_Customer_Information_Joined[Customer ID], (Transactions_and_Customer_Information_Joined[SKU]='Monte Carlo IO (4)'!$A17)* (Transactions_and_Customer_Information_Joined[Order Status]="Completed"))),0)))) / $R17, 0)} -> 0.58333333 | X17: {=IFERROR(SUM(_xlfn._xlws.FILTER(('V1-Based Churn Model (Step 3)'!$X$39:$X$4039="High")*1, ISNUMBER(MATCH('V1-Based Churn Model (Step 3)'!$A$39:$A$4039, _xlfn.UNIQUE(_xlfn._xlws.FILTER(Transactions_and_Customer_Information_Joined[Customer ID], (Transactions_and_Customer_Information_Joined[SKU]='Monte Carlo IO (4)'!$A17)* (Transactions_and_Customer_Information_Joined[Order Status]="Completed"))),0)))) / $R17, 0)} -> 0.33333333 | Y17: {=IFERROR(SUM(_xlfn._xlws.FILTER(('V1-Based Churn Model (Step 3)'!$X$39:$X$4039="Medium")*1, ISNUMBER(MATCH('V1-Based Churn Model (Step 3)'!$A$39:$A$4039, _xlfn.UNIQUE(_xlfn._xlws.FILTER(Transactions_and_Customer_Information_Joined[Customer ID], (Transactions_and_Customer_Information_Joined[SKU]='Monte Carlo IO (4)'!$A17)* (Transactions_and_Customer_Information_Joined[Order Status]="Completed"))),0)))) / $R17, 0)} -> 0.083333333 | Z17: {=IFERROR(SUM(_xlfn._xlws.FILTER(('V1-Based Churn Model (Step 3)'!$X$39:$X$4039="Low")*1, ISNUMBER(MATCH('V1-Based Churn Model (Step 3)'!$A$39:$A$4039, _xlfn.UNIQUE(_xlfn._xlws.FILTER(Transactions_and_Customer_Information_Joined[Customer ID], (Transactions_and_Customer_Information_Joined[SKU]='Monte Carlo IO (4)'!$A17)* (Transactions_and_Customer_Information_Joined[Order Status]="Completed"))),0)))) / $R17, 0)} -> 0 | AA17: {=_xlfn.IFS($W17 = MAX($W17:$Z17), "Critical", $X17 = MAX($W17:$Z17), "High", $Y17 = MAX($W17:$Z17), "Medium", $Z17 = MAX($W17:$Z17), "Low")} -> Critical | AB17: {=_xlfn.XLOOKUP($A17, Best_Outcomes[SKU], Best_Outcomes[[Adjusted Price]:[Adjusted Difference %]],,0)} -> 197.38145 | AC17: 19.471452 | AD17: 0.10944552 | AE17: =$AD17 * IF($D17="Reduce", $B$3, $B$2) -> -0.043778208 | AF17: =$H17-$AE17 -> 36.043778 | AG17: {=_xlfn.XLOOKUP($A17,Best_Outcomes[SKU], Best_Outcomes[[Adjusted Gross Revenue]:[Gross Revenue Lift %]])} -> 6794.6561 | AH17: 389.89606 | AI17: 0.060875983 | AJ17: =$AF17*G$12 -> 1908.8785 | AK17: =$AJ17-$J17 -> -736.76151 | AL17: =$AK17/$J17 -> -0.27848139 | AM17: {=_xlfn.XLOOKUP($A17,Best_Outcomes[SKU], Best_Outcomes[[Adjusted Gross Profit]:[Gross Profit Margin %]])} -> 4264.8374 | AN17: 505.71744 | AO17: 0.1345308 | AP17: 0.62767525 | AQ17: =$AP17-$L17 -> 0.040749276 | AR17: {=_xlfn.XLOOKUP($A17,Best_Outcomes[SKU], Best_Outcomes[[Gross Profit Margin Lift %]:[LTV Protection-Risk Ratio]])} -> 0.040749276 | AS17: 688.8869 | AT17: 1033.3304 | AU17: 0.66666667
A18: SKU-1010 | B18: =_xlfn.XLOOKUP($A18,_1_product_catalog_pricing[SKU], _1_product_catalog_pricing[Product Name],,0) -> Slim Fit Jeans | C18: =_xlfn.XLOOKUP($A18, _1_product_catalog_pricing[SKU], _1_product_catalog_pricing[Category],,0) -> Apparel | D18: {=_xlfn.XLOOKUP($A18,_xlfn.ANCHORARRAY('V1 Pricing Model (Step 2)'!$A$22), 'V1 Pricing Model (Step 2)'!$T$22:$T$71,,0)} -> Raise | E18: {=_xlfn.XLOOKUP($A18,_xlfn.ANCHORARRAY('V1 Pricing Model (Step 2)'!$A$22), 'V1 Pricing Model (Step 2)'!$AL$22:$AL$71,,0)} -> Full | F18: {=_xlfn.XLOOKUP($A18,_xlfn.ANCHORARRAY('V1 Pricing Model (Step 2)'!$A$22),_xlfn.ANCHORARRAY( 'V1 Pricing Model (Step 2)'!$D$22),,0)} -> 45.86 | G18: {=_xlfn.XLOOKUP($A18,_xlfn.ANCHORARRAY('V1 Pricing Model (Step 2)'!$A$22),_xlfn.ANCHORARRAY( 'V1 Pricing Model (Step 2)'!$E$22),,0)} -> 24.87 | H18: {=_xlfn.XLOOKUP($A18, 'Competitive Analysis (Step 1)'!$A$10:$A$209,_xlfn.ANCHORARRAY( 'Competitive Analysis (Step 1)'!$Q$10),,0)} -> 42 | I18: =$F18*$H18 -> 1926.12 | J18: =$G18*$H18 -> 1044.54 | K18: =$I18-$J18 -> 881.58 | L18: =$K18/$I18 -> 0.45769734 | M18: {=_xlfn.XLOOKUP($A18,_xlfn.ANCHORARRAY('V1 Pricing Model (Step 2)'!$A$22),'V1 Pricing Model (Step 2)'!$U$22:$W$71,,0)} -> 57.591702 | N18: 11.731702 | O18: 0.25581556 | P18: {=_xlfn.XLOOKUP($A18,_xlfn.ANCHORARRAY( 'V1 Pricing Model (Step 2)'!$A$22), 'V1 Pricing Model (Step 2)'!$AC$22:$AC$71)} -> 713.86466 | Q18: {=_xlfn.XLOOKUP($A18,_xlfn.ANCHORARRAY('V1 Pricing Model (Step 2)'!$A$22),'V1 Pricing Model (Step 2)'!$AI$22:$AI$71,,0)} -> 813.34466 | R18: {=COUNTA(_xlfn.UNIQUE(_xlfn._xlws.FILTER(Transactions_and_Customer_Information_Joined[Customer ID], (Transactions_and_Customer_Information_Joined[SKU]='Monte Carlo IO (4)'!$A18) * (Transactions_and_Customer_Information_Joined[Order Status] = "Completed"), "")))} -> 17 | S18: {=AVERAGE(_xlfn._xlws.FILTER('V1-Based Churn Model (Step 3)'!$W$39:$W$590, ISNUMBER(MATCH('V1-Based Churn Model (Step 3)'!$A$39:$A$590, _xlfn.UNIQUE(_xlfn._xlws.FILTER(Transactions_and_Customer_Information_Joined[Customer ID], (Transactions_and_Customer_Information_Joined[SKU]='Monte Carlo IO (4)'!$A18)* (Transactions_and_Customer_Information_Joined[Order Status]="Completed"))),0))))} -> 81.368043 | T18: {=AVERAGE(_xlfn._xlws.FILTER('V1-Based Churn Model (Step 3)'!$Y$39:$Y$590, ISNUMBER(MATCH('V1-Based Churn Model (Step 3)'!$A$39:$A$590, _xlfn.UNIQUE(_xlfn._xlws.FILTER(Transactions_and_Customer_Information_Joined[Customer ID], (Transactions_and_Customer_Information_Joined[SKU]='Monte Carlo IO (4)'!$A18)* (Transactions_and_Customer_Information_Joined[Order Status]="Completed"))),0))))} -> 0.36473224 | U18: {=SUM(_xlfn._xlws.FILTER('V1-Based Churn Model (Step 3)'!$I$39:$I$590, ISNUMBER(MATCH('V1-Based Churn Model (Step 3)'!$A$39:$A$590, _xlfn.UNIQUE(_xlfn._xlws.FILTER(Transactions_and_Customer_Information_Joined[Customer ID], (Transactions_and_Customer_Information_Joined[SKU]='Monte Carlo IO (4)'!$A18)* (Transactions_and_Customer_Information_Joined[Order Status]="Completed"))),0))))} -> 5696.89 | V18: {=SUM(_xlfn._xlws.FILTER('V1-Based Churn Model (Step 3)'!$Z$39:$Z$590, ISNUMBER(MATCH('V1-Based Churn Model (Step 3)'!$A$39:$A$590, _xlfn.UNIQUE(_xlfn._xlws.FILTER(Transactions_and_Customer_Information_Joined[Customer ID], (Transactions_and_Customer_Information_Joined[SKU]='Monte Carlo IO (4)'!$A18)* (Transactions_and_Customer_Information_Joined[Order Status]="Completed"))),0))))} -> 1838.4437 | W18: {=IFERROR(SUM(_xlfn._xlws.FILTER(('V1-Based Churn Model (Step 3)'!$X$39:$X$4039="Critical")*1, ISNUMBER(MATCH('V1-Based Churn Model (Step 3)'!$A$39:$A$4039, _xlfn.UNIQUE(_xlfn._xlws.FILTER(Transactions_and_Customer_Information_Joined[Customer ID], (Transactions_and_Customer_Information_Joined[SKU]='Monte Carlo IO (4)'!$A18)* (Transactions_and_Customer_Information_Joined[Order Status]="Completed"))),0)))) / $R18, 0)} -> 0.70588235 | X18: {=IFERROR(SUM(_xlfn._xlws.FILTER(('V1-Based Churn Model (Step 3)'!$X$39:$X$4039="High")*1, ISNUMBER(MATCH('V1-Based Churn Model (Step 3)'!$A$39:$A$4039, _xlfn.UNIQUE(_xlfn._xlws.FILTER(Transactions_and_Customer_Information_Joined[Customer ID], (Transactions_and_Customer_Information_Joined[SKU]='Monte Carlo IO (4)'!$A18)* (Transactions_and_Customer_Information_Joined[Order Status]="Completed"))),0)))) / $R18, 0)} -> 0.23529412 | Y18: {=IFERROR(SUM(_xlfn._xlws.FILTER(('V1-Based Churn Model (Step 3)'!$X$39:$X$4039="Medium")*1, ISNUMBER(MATCH('V1-Based Churn Model (Step 3)'!$A$39:$A$4039, _xlfn.UNIQUE(_xlfn._xlws.FILTER(Transactions_and_Customer_Information_Joined[Customer ID], (Transactions_and_Customer_Information_Joined[SKU]='Monte Carlo IO (4)'!$A18)* (Transactions_and_Customer_Information_Joined[Order Status]="Completed"))),0)))) / $R18, 0)} -> 0.058823529 | Z18: {=IFERROR(SUM(_xlfn._xlws.FILTER(('V1-Based Churn Model (Step 3)'!$X$39:$X$4039="Low")*1, ISNUMBER(MATCH('V1-Based Churn Model (Step 3)'!$A$39:$A$4039, _xlfn.UNIQUE(_xlfn._xlws.FILTER(Transactions_and_Customer_Information_Joined[Customer ID], (Transactions_and_Customer_Information_Joined[SKU]='Monte Carlo IO (4)'!$A18)* (Transactions_and_Customer_Information_Joined[Order Status]="Completed"))),0)))) / $R18, 0)} -> 0 | AA18: {=_xlfn.IFS($W18 = MAX($W18:$Z18), "Critical", $X18 = MAX($W18:$Z18), "High", $Y18 = MAX($W18:$Z18), "Medium", $Z18 = MAX($W18:$Z18), "Low")} -> Critical | AB18: {=_xlfn.XLOOKUP($A18, Best_Outcomes[SKU], Best_Outcomes[[Adjusted Price]:[Adjusted Difference %]],,0)} -> 52.899021 | AC18: 7.0390209 | AD18: 0.15348934 | AE18: =$AD18 * IF($D18="Reduce", $B$3, $B$2) -> -0.061395734 | AF18: =$H18-$AE18 -> 42.061396 | AG18: {=_xlfn.XLOOKUP($A18,Best_Outcomes[SKU], Best_Outcomes[[Adjusted Gross Revenue]:[Gross Revenue Lift %]])} -> 2085.3524 | AH18: 159.23236 | AI18: 0.082670011 | AJ18: =$AF18*G$12 -> 2227.5715 | AK18: =$AJ18-$J18 -> 1183.0315 | AL18: =$AK18/$J18 -> 1.1325861 | AM18: {=_xlfn.XLOOKUP($A18,Best_Outcomes[SKU], Best_Outcomes[[Adjusted Gross Profit]:[Gross Profit Margin %]])} -> 1104.9427 | AN18: 223.36266 | AO18: 0.2533663 | AP18: 0.52985897 | AQ18: =$AP18-$L18 -> 0.072161634 | AR18: {=_xlfn.XLOOKUP($A18,Best_Outcomes[SKU], Best_Outcomes[[Gross Profit Margin Lift %]:[LTV Protection-Risk Ratio]])} -> 0.072161634 | AS18: 666.16547 | AT18: 999.2482 | AU18: 0.66666667
A19: SKU-1011 | B19: =_xlfn.XLOOKUP($A19,_1_product_catalog_pricing[SKU], _1_product_catalog_pricing[Product Name],,0) -> Graphic Tee | C19: =_xlfn.XLOOKUP($A19, _1_product_catalog_pricing[SKU], _1_product_catalog_pricing[Category],,0) -> Apparel | D19: {=_xlfn.XLOOKUP($A19,_xlfn.ANCHORARRAY('V1 Pricing Model (Step 2)'!$A$22), 'V1 Pricing Model (Step 2)'!$T$22:$T$71,,0)} -> Raise | E19: {=_xlfn.XLOOKUP($A19,_xlfn.ANCHORARRAY('V1 Pricing Model (Step 2)'!$A$22), 'V1 Pricing Model (Step 2)'!$AL$22:$AL$71,,0)} -> Full | F19: {=_xlfn.XLOOKUP($A19,_xlfn.ANCHORARRAY('V1 Pricing Model (Step 2)'!$A$22),_xlfn.ANCHORARRAY( 'V1 Pricing Model (Step 2)'!$D$22),,0)} -> 67.56 | G19: {=_xlfn.XLOOKUP($A19,_xlfn.ANCHORARRAY('V1 Pricing Model (Step 2)'!$A$22),_xlfn.ANCHORARRAY( 'V1 Pricing Model (Step 2)'!$E$22),,0)} -> 43.21 | H19: {=_xlfn.XLOOKUP($A19, 'Competitive Analysis (Step 1)'!$A$10:$A$209,_xlfn.ANCHORARRAY( 'Competitive Analysis (Step 1)'!$Q$10),,0)} -> 22 | I19: =$F19*$H19 -> 1486.32 | J19: =$G19*$H19 -> 950.62 | K19: =$I19-$J19 -> 535.7 | L19: =$K19/$I19 -> 0.36042037 | M19: {=_xlfn.XLOOKUP($A19,_xlfn.ANCHORARRAY('V1 Pricing Model (Step 2)'!$A$22),'V1 Pricing Model (Step 2)'!$U$22:$W$71,,0)} -> 74.848492 | N19: 7.2884925 | O19: 0.10788177 | P19: {=_xlfn.XLOOKUP($A19,_xlfn.ANCHORARRAY( 'V1 Pricing Model (Step 2)'!$A$22), 'V1 Pricing Model (Step 2)'!$AC$22:$AC$71)} -> 85.498342 | Q19: {=_xlfn.XLOOKUP($A19,_xlfn.ANCHORARRAY('V1 Pricing Model (Step 2)'!$A$22),'V1 Pricing Model (Step 2)'!$AI$22:$AI$71,,0)} -> 128.70834 | R19: {=COUNTA(_xlfn.UNIQUE(_xlfn._xlws.FILTER(Transactions_and_Customer_Information_Joined[Customer ID], (Transactions_and_Customer_Information_Joined[SKU]='Monte Carlo IO (4)'!$A19) * (Transactions_and_Customer_Information_Joined[Order Status] = "Completed"), "")))} -> 10 | S19: {=AVERAGE(_xlfn._xlws.FILTER('V1-Based Churn Model (Step 3)'!$W$39:$W$590, ISNUMBER(MATCH('V1-Based Churn Model (Step 3)'!$A$39:$A$590, _xlfn.UNIQUE(_xlfn._xlws.FILTER(Transactions_and_Customer_Information_Joined[Customer ID], (Transactions_and_Customer_Information_Joined[SKU]='Monte Carlo IO (4)'!$A19)* (Transactions_and_Customer_Information_Joined[Order Status]="Completed"))),0))))} -> 66.15144 | T19: {=AVERAGE(_xlfn._xlws.FILTER('V1-Based Churn Model (Step 3)'!$Y$39:$Y$590, ISNUMBER(MATCH('V1-Based Churn Model (Step 3)'!$A$39:$A$590, _xlfn.UNIQUE(_xlfn._xlws.FILTER(Transactions_and_Customer_Information_Joined[Customer ID], (Transactions_and_Customer_Information_Joined[SKU]='Monte Carlo IO (4)'!$A19)* (Transactions_and_Customer_Information_Joined[Order Status]="Completed"))),0))))} -> 0.25273448 | U19: {=SUM(_xlfn._xlws.FILTER('V1-Based Churn Model (Step 3)'!$I$39:$I$590, ISNUMBER(MATCH('V1-Based Churn Model (Step 3)'!$A$39:$A$590, _xlfn.UNIQUE(_xlfn._xlws.FILTER(Transactions_and_Customer_Information_Joined[Customer ID], (Transactions_and_Customer_Information_Joined[SKU]='Monte Carlo IO (4)'!$A19)* (Transactions_and_Customer_Information_Joined[Order Status]="Completed"))),0))))} -> 5893.09 | V19: {=SUM(_xlfn._xlws.FILTER('V1-Based Churn Model (Step 3)'!$Z$39:$Z$590, ISNUMBER(MATCH('V1-Based Churn Model (Step 3)'!$A$39:$A$590, _xlfn.UNIQUE(_xlfn._xlws.FILTER(Transactions_and_Customer_Information_Joined[Customer ID], (Transactions_and_Customer_Information_Joined[SKU]='Monte Carlo IO (4)'!$A19)* (Transactions_and_Customer_Information_Joined[Order Status]="Completed"))),0))))} -> 1511.5432 | W19: {=IFERROR(SUM(_xlfn._xlws.FILTER(('V1-Based Churn Model (Step 3)'!$X$39:$X$4039="Critical")*1, ISNUMBER(MATCH('V1-Based Churn Model (Step 3)'!$A$39:$A$4039, _xlfn.UNIQUE(_xlfn._xlws.FILTER(Transactions_and_Customer_Information_Joined[Customer ID], (Transactions_and_Customer_Information_Joined[SKU]='Monte Carlo IO (4)'!$A19)* (Transactions_and_Customer_Information_Joined[Order Status]="Completed"))),0)))) / $R19, 0)} -> 0.4 | X19: {=IFERROR(SUM(_xlfn._xlws.FILTER(('V1-Based Churn Model (Step 3)'!$X$39:$X$4039="High")*1, ISNUMBER(MATCH('V1-Based Churn Model (Step 3)'!$A$39:$A$4039, _xlfn.UNIQUE(_xlfn._xlws.FILTER(Transactions_and_Customer_Information_Joined[Customer ID], (Transactions_and_Customer_Information_Joined[SKU]='Monte Carlo IO (4)'!$A19)* (Transactions_and_Customer_Information_Joined[Order Status]="Completed"))),0)))) / $R19, 0)} -> 0.2 | Y19: {=IFERROR(SUM(_xlfn._xlws.FILTER(('V1-Based Churn Model (Step 3)'!$X$39:$X$4039="Medium")*1, ISNUMBER(MATCH('V1-Based Churn Model (Step 3)'!$A$39:$A$4039, _xlfn.UNIQUE(_xlfn._xlws.FILTER(Transactions_and_Customer_Information_Joined[Customer ID], (Transactions_and_Customer_Information_Joined[SKU]='Monte Carlo IO (4)'!$A19)* (Transactions_and_Customer_Information_Joined[Order Status]="Completed"))),0)))) / $R19, 0)} -> 0.4 | Z19: {=IFERROR(SUM(_xlfn._xlws.FILTER(('V1-Based Churn Model (Step 3)'!$X$39:$X$4039="Low")*1, ISNUMBER(MATCH('V1-Based Churn Model (Step 3)'!$A$39:$A$4039, _xlfn.UNIQUE(_xlfn._xlws.FILTER(Transactions_and_Customer_Information_Joined[Customer ID], (Transactions_and_Customer_Information_Joined[SKU]='Monte Carlo IO (4)'!$A19)* (Transactions_and_Customer_Information_Joined[Order Status]="Completed"))),0)))) / $R19, 0)} -> 0 | AA19: {=_xlfn.IFS($W19 = MAX($W19:$Z19), "Critical", $X19 = MAX($W19:$Z19), "High", $Y19 = MAX($W19:$Z19), "Medium", $Z19 = MAX($W19:$Z19), "Low")} -> Critical | AB19: {=_xlfn.XLOOKUP($A19, Best_Outcomes[SKU], Best_Outcomes[[Adjusted Price]:[Adjusted Difference %]],,0)} -> 71.933095 | AC19: 4.3730955 | AD19: 0.064729063 | AE19: =$AD19 * IF($D19="Reduce", $B$3, $B$2) -> -0.025891625 | AF19: =$H19-$AE19 -> 22.025892 | AG19: {=_xlfn.XLOOKUP($A19,Best_Outcomes[SKU], Best_Outcomes[[Adjusted Gross Revenue]:[Gross Revenue Lift %]])} -> 1541.5539 | AH19: 55.233876 | AI19: 0.037161497 | AJ19: =$AF19*G$12 -> 1166.4912 | AK19: =$AJ19-$J19 -> 215.87122 | AL19: =$AK19/$J19 -> 0.22708466 | AM19: {=_xlfn.XLOOKUP($A19,Best_Outcomes[SKU], Best_Outcomes[[Adjusted Gross Profit]:[Gross Profit Margin %]])} -> 615.54697 | AN19: 79.846973 | AO19: 0.14905166 | AP19: 0.39930293 | AQ19: =$AP19-$L19 -> 0.038882559 | AR19: {=_xlfn.XLOOKUP($A19,Best_Outcomes[SKU], Best_Outcomes[[Gross Profit Margin Lift %]:[LTV Protection-Risk Ratio]])} -> 0.038882559 | AS19: 429.27827 | AT19: 643.91741 | AU19: 0.66666667
